Workbook

Sheet Abkürzungen_WG
A1: Abkürzungen nach Artikelarten

Sheet Migrationsartikel
A1: Lf Nr. | B1: PLU-Nr. neu | C1: Stk / kg | D1: PAZ | E1: EAN | F1: Gestellbeschriftung 1 Max. 22 Zeichen (d) | G1: Gestellbeschriftung 2 Max. 22 Zeichen (d) | H1: Gestellbeschriftung 3 Max. 4-8 Zeichen (d) | I1: Kassenbontext Max. 28 Zeichen (d) | J1: Gestellbeschriftung 1 Max. 22 Zeichen (f) | K1: Gestellbeschriftung 2 Max. 22 Zeichen (f) | L1: Gestellbeschriftung 3 Max. 4-8 Zeichen (f) | M1: Kassenbontext Max. 28 Zeichen (f) | N1: Gestellbeschriftung 1 Max. 22 Zeichen (i) | O1: Gestellbeschriftung 2 Max. 22 Zeichen (i) | P1: Gestellbeschriftung 3 Max. 4-8 Zeichen (i) | Q1: Kassenbontext Max. 28 Zeichen (i) | R1: Nettoinhalt | S1: Grundpreismenge Feld 1 | T1: Grundpreismenge Feld 2 | U1: Basismengeneinheit Waage = Kg Verkauf = Stk = Stk Relevant für Berechnungen im MDM/SAP | V1: Warengruppe 1. Feld | W1: Warengruppe 2. Feld | X1: Warengruppe 3. Feld | Y1: Steuerklassifikation | Z1: Altersbegrenzung | AA1: Depot | AB1: Rabatt zugelassen | AC1: Rückgabe zugelassen | AD1: Preisänderung zugelassen | AE1: Etiketten-druck | AF1: Shop-in-Shop | AG1: Fremdartikel | AH1: Qualitätsanforderung geprüft | AI1: Verkaufskonditionen | AJ1: Lieferant
A2: 1 | C2: Stk | D2: Nein | F2: Baguette | G2: aus der Region | H2: 250g | I2: Baguette 250g | J2: Baguette | K2: de la région | L2: 250g | M2: Baguette 250g | N2: Baguette | O2: della regione | P2: 250g | Q2: Baguette 250g | R2: 0.25 | S2: 100 | T2: Gramm | U2: (PCE) Stück | V2: Backwaren & Convenience | W2: Brot und Backwaren | X2: Backwaren andere | AB2: ja | AC2: ja | AD2: ja | AE2: ja | AF2: - | AG2: - | AH2: ja | AI2: 0.05 | AJ2: -
A3: 2 | C3: Stk | D3: Nein | F3: Baslerbrot | G3: aus der Region | H3: 250g | I3: Baslerbrot 250g | J3: Pain bâlois | K3: de la région | L3: 250g | M3: Pain bâlois 250g | N3: Pane di Basilea | O3: della regione | P3: 250g | Q3: Pane di Basilea 250g | R3: 0.25 | S3: 100 | T3: Gramm | U3: (PCE) Stück | V3: Backwaren & Convenience | W3: Brot und Backwaren | X3: Backwaren andere | AB3: ja | AC3: ja | AD3: ja | AE3: ja | AF3: - | AG3: - | AH3: ja | AI3: 0.05 | AJ3: -
A4: 3 | C4: Stk | D4: Nein | F4: Baslerbrot | G4: aus der Region | H4: 500g | I4: Baslerbrot 500g | J4: Pain bâlois | K4: de la région | L4: 500g | M4: Pain bâlois 500g | N4: Pane di Basilea | O4: della regione | P4: 500g | Q4: Pane di Basilea 500g | R4: 0.5 | S4: 100 | T4: Gramm | U4: (PCE) Stück | V4: Backwaren & Convenience | W4: Brot und Backwaren | X4: Backwaren andere | AB4: ja | AC4: ja | AD4: ja | AE4: ja | AF4: - | AG4: - | AH4: ja | AI4: 0.05 | AJ4: -
A5: 4 | C5: Stk | D5: Nein | F5: Berliner | G5: aus der Region | H5: 1Stk | I5: Berliner | J5: Boule de Berlin | K5: de la région | L5: 1pce | M5: Boule de Berlin | N5: Berliner | O5: della regione | P5: 1pz | Q5: Berliner | R5: 1 | S5: 1 | T5: Stück | U5: (PCE) Stück | V5: Backwaren & Convenience | W5: Brot und Backwaren | X5: Backwaren andere | AB5: ja | AC5: ja | AD5: ja | AE5: ja | AF5: - | AG5: - | AH5: ja | AI5: 0.05 | AJ5: -
A6: 5 | C6: Stk | D6: Nein | F6: Birewegge | G6: aus der Region | H6: 1Stk | I6: Birewegge | J6: Birewegge | K6: de la région | L6: 1pce | M6: Birewegge | N6: Birewegge | O6: della regione | P6: 1pz | Q6: Birewegge | R6: 1 | S6: 1 | T6: Stück | U6: (PCE) Stück | V6: Backwaren & Convenience | W6: Brot und Backwaren | X6: Backwaren andere | AB6: ja | AC6: ja | AD6: ja | AE6: ja | AF6: - | AG6: - | AH6: ja | AI6: 0.05 | AJ6: -
A7: 6 | C7: Stk | D7: Nein | F7: Bricelets | G7: aus der Region | H7: 1Stk | I7: Bricelets | J7: Bricelets | K7: de la région | L7: 1pce | M7: Bricelets | N7: Bricelets | O7: della regione | P7: 1pz | Q7: Bricelets | R7: 1 | S7: 1 | T7: Stück | U7: (PCE) Stück | V7: Backwaren & Convenience | W7: Brot und Backwaren | X7: Backwaren andere | AB7: ja | AC7: ja | AD7: ja | AE7: ja | AF7: - | AG7: - | AH7: ja | AI7: 0.05 | AJ7: -
A8: 7 | C8: Stk | D8: Nein | F8: Brioche mit Füllung | G8: aus der Region | H8: 1Stk | I8: Brioche mit Füllung | J8: Brioche fourée | K8: de la région | L8: 1pce | M8: Brioche fourée | N8: Brioche ripiena | O8: della regione | P8: 1pz | Q8: Brioche ripiena | R8: 1 | S8: 1 | T8: Stück | U8: (PCE) Stück | V8: Backwaren & Convenience | W8: Brot und Backwaren | X8: Backwaren andere | AB8: ja | AC8: ja | AD8: ja | AE8: ja | AF8: - | AG8: - | AH8: ja | AI8: 0 | AJ8: -
A9: 8 | C9: Stk | D9: Nein | F9: Brot vom Beck | G9: aus der Region | H9: 1Stk | I9: Brot vom Beck | J9: Pain du boulanger | K9: de la région | L9: 1pce | M9: Pain du boulanger | N9: Pane del panettiere | O9: della regione | P9: 1pz | Q9: Pane del panettiere | R9: 1 | S9: 1 | T9: Stück | U9: (PCE) Stück | V9: Backwaren & Convenience | W9: Brot und Backwaren | X9: Backwaren andere | AB9: ja | AC9: ja | AD9: ja | AE9: ja | AF9: - | AG9: - | AH9: ja | AI9: 0 | AJ9: -
A10: 9 | C10: Stk | D10: Nein | F10: Brottheke | G10: aus der Region | H10: 1Stk | I10: Brottheke | J10: Comptoir à pain | K10: de la région | L10: 1pce | M10: Comptoir à pain | N10: Banco pane | O10: della regione | P10: 1pz | Q10: Banco pane | R10: 1 | S10: 1 | T10: Stück | U10: (PCE) Stück | V10: Backwaren & Convenience | W10: Brot und Backwaren | X10: Backwaren andere | AB10: ja | AC10: ja | AD10: ja | AE10: ja | AF10: - | AG10: - | AH10: ja | AI10: 0 | AJ10: -
A11: 10 | C11: Stk | D11: Nein | F11: Bürli | G11: aus der Region | H11: 1Stk | I11: Bürli | J11: Bürli | K11: de la région | L11: 1pce | M11: Bürli | N11: Bürli | O11: della regione | P11: 1pz | Q11: Bürli | R11: 1 | S11: 1 | T11: Stück | U11: (PCE) Stück | V11: Backwaren & Convenience | W11: Brot und Backwaren | X11: Backwaren andere | AB11: ja | AC11: ja | AD11: ja | AE11: ja | AF11: - | AG11: - | AH11: ja | AI11: 0.05 | AJ11: -
A12: 11 | C12: Stk | D12: Nein | F12: Buttergipfel | G12: aus der Region | H12: 1Stk | I12: Buttergipfel | J12: Croissant au beurre | K12: de la région | L12: 1pce | M12: Croissant au beurre | N12: Cornetto al burro | O12: della regione | P12: 1pz | Q12: Cornetto al burro | R12: 1 | S12: 1 | T12: Stück | U12: (PCE) Stück | V12: Backwaren & Convenience | W12: Brot und Backwaren | X12: Backwaren andere | AB12: ja | AC12: ja | AD12: ja | AE12: ja | AF12: - | AG12: - | AH12: ja | AI12: 0.05 | AJ12: -
A13: 12 | C13: Stk | D13: Nein | F13: Butterzopf | G13: aus der Region | H13: 300g | I13: Butterzopf 300g | J13: Tresse | K13: de la région | L13: 300g | M13: Tresse 300g | N13: Treccia | O13: della regione | P13: 300g | Q13: Treccia 300g | R13: 0.3 | S13: 100 | T13: Gramm | U13: (PCE) Stück | V13: Backwaren & Convenience | W13: Brot und Backwaren | X13: Backwaren andere | AB13: ja | AC13: ja | AD13: ja | AE13: ja | AF13: - | AG13: - | AH13: ja | AI13: 0.05 | AJ13: -
... A78: 100 | C78: Stk | D78: Nein | F78: Wachteleier | G78: aus der Region | H78: 1Stk | I78: Wachteleier 1Stk | J78: Oeufs de caille | K78: de la région | L78: 1pce | M78: Oeufs de caille | N78: Uova di quaglia | O78: della regione | P78: 1pz | Q78: Uova di quaglia | R78: 1 | S78: 1 | T78: Stück | U78: (PCE) Stück | V78: Frische | W78: Molkereiprodukte & Eier | X78: Eier | AB78: ja | AC78: ja | AD78: ja | AE78: ja | AF78: - | AG78: - | AH78: ja | AI78: 0.05 | AJ78: -
A79: 73 | B79: 829 | C79: kg | D79: Nein | F79: Eglifilet | G79: aus der Region | H79: 1Stk | I79: Eglifilet | J79: Filet de perche | K79: de la région | L79: 1pce | M79: Filet de perche | N79: Filetto di persico | O79: della regione | P79: 1pz | Q79: Filetto di persico | R79: 1 | S79: 100 | T79: Gramm | U79: (PCE) Stück | V79: Frische | W79: SB - Fleisch | X79: Fisch | AB79: ja | AC79: ja | AD79: ja | AE79: ja | AF79: - | AG79: - | AH79: ja | AI79: 0.05 | AJ79: -
A80: 98 | B80: 830 | C80: kg | D80: Nein | F80: Rindstartar | G80: aus der Region | H80: 1Stk | I80: Rindstartar | J80: Tartare de boeuf | K80: de la région | L80: 1pce | M80: Tartare de boeuf | N80: Tartare di manzo | O80: della regione | P80: 1pz | Q80: Tartare di manzo | R80: 1 | S80: 100 | T80: Gramm | U80: (PCE) Stück | V80: Frische | W80: SB - Fleisch | X80: Fleisch | AB80: ja | AC80: ja | AD80: ja | AE80: ja | AF80: - | AG80: - | AH80: ja | AI80: 0.05 | AJ80: -
A81: 99 | C81: Stk | D81: Nein | F81: Theke Wurstwaren | G81: aus der Region | H81: 1Stk | I81: Theke Wurstwaren | J81: Comptoir charcuterie | K81: de la région | L81: 1pce | M81: Comptoir charcuterie | N81: Banco salumeria | O81: della regione | P81: 1pz | Q81: Banco salumeria | R81: 1 | S81: 1 | T81: Stück | U81: (PCE) Stück | V81: Frische | W81: Fleisch- und Wurstwaren | X81: Fleisch- und Wurstwaren andere | AB81: ja | AC81: ja | AD81: ja | AE81: ja | AF81: - | AG81: - | AH81: ja | AI81: 0 | AJ81: -
A82: 101 | C82: Stk | D82: Nein | F82: Wurstwaren | G82: aus der Region | H82: 1Stk | I82: Wurstwaren | J82: Charcuterie | K82: de la région | L82: 1pce | M82: Charcuterie | N82: Salumi | O82: della regione | P82: 1pz | Q82: Salumi | R82: 1 | S82: 1 | T82: Stück | U82: (PCE) Stück | V82: Frische | W82: Fleisch- und Wurstwaren | X82: Fleisch- und Wurstwaren andere | AB82: ja | AC82: ja | AD82: ja | AE82: ja | AF82: - | AG82: - | AH82: ja | AI82: 0 | AJ82: -
A83: 66 | C83: Stk | D83: Nein | F83: Büscion | G83: aus der Region | H83: 2Stk | I83: Büscion 2Stk | J83: Büscion 2pces | K83: de la région | L83: 2pces | M83: Büscion | N83: Büscion | O83: della regione | P83: 2pz | Q83: Büscion 2pz | R83: 2 | S83: 1 | T83: Stück | U83: (PCE) Stück | V83: Frische | W83: Käse | X83: Käse | AB83: ja | AC83: ja | AD83: ja | AE83: ja | AF83: - | AG83: - | AH83: ja | AI83: 0.05 | AJ83: -
A84: 79 | C84: Stk | D84: Nein | F84: Fondue | G84: aus der Region | H84: 400g | I84: Fondue 400g | J84: Fondue | K84: de la région | L84: 400g | M84: Fondue 400g | N84: Fondue | O84: della regione | P84: 400g | Q84: Fondue 400g | R84: 0.4 | S84: 100 | T84: Gramm | U84: (PCE) Stück | V84: Frische | W84: Käse | X84: Käse | AB84: ja | AC84: ja | AD84: ja | AE84: ja | AF84: - | AG84: - | AH84: ja | AI84: 0.05 | AJ84: -
A85: 80 | C85: Stk | D85: Nein | F85: Fondue | G85: aus der Region | H85: 600g | I85: Fondue 600g | J85: Fondue | K85: de la région | L85: 600g | M85: Fondue 600g | N85: Fondue | O85: della regione | P85: 600g | Q85: Fondue 600g | R85: 0.6 | S85: 100 | T85: Gramm | U85: (PCE) Stück | V85: Frische | W85: Käse | X85: Käse | AB85: ja | AC85: ja | AD85: ja | AE85: ja | AF85: - | AG85: - | AH85: ja | AI85: 0.05 | AJ85: -
A86: 81 | C86: Stk | D86: Nein | F86: Fondue | G86: aus der Region | H86: 800g | I86: Fondue 800g | J86: Fondue | K86: de la région | L86: 800g | M86: Fondue 800g | N86: Fondue | O86: della regione | P86: 800g | Q86: Fondue 800g | R86: 0.8 | S86: 100 | T86: Gramm | U86: (PCE) Stück | V86: Frische | W86: Käse | X86: Käse | AB86: ja | AC86: ja | AD86: ja | AE86: ja | AF86: - | AG86: - | AH86: ja | AI86: 0.05 | AJ86: -
A87: 82 | B87: 837 | C87: kg | D87: Nein | F87: Frischkäse | G87: aus der Region | H87: 2Stk | I87: Frischkäse 2Stk | J87: Fromage frais | K87: de la région | L87: 2pces | M87: Fromage frais 2pces | N87: Formaggini freschi | O87: della regione | P87: 2pz | Q87: Formaggini freschi 2pz | R87: 2 | S87: 100 | T87: Gramm | U87: (PCE) Stück | V87: Frische | W87: Käse | X87: Käse | AB87: ja | AC87: ja | AD87: ja | AE87: ja | AF87: - | AG87: - | AH87: ja | AI87: 0.05 | AJ87: -
A88: 83 | B88: 838 | C88: kg | D88: Nein | F88: Gruyère | G88: aus der Region | H88: 1Stk | I88: Gruyère | J88: Gruyère | K88: de la région | L88: 1pce | M88: Gruyère | N88: Gruyère | O88: della regione | P88: 1pz | Q88: Gruyère | R88: 1 | S88: 100 | T88: Gramm | U88: (PCE) Stück | V88: Frische | W88: Käse | X88: Käse | AB88: ja | AC88: ja | AD88: ja | AE88: ja | AF88: - | AG88: - | AH88: ja | AI88: 0.05 | AJ88: -
A89: 87 | C89: Stk | D89: Nein | F89: Käse Spezialitäten | G89: aus der Region | H89: 1Stk | I89: Käse Spezialitäten | J89: Spécialités de fromage | K89: de la région | L89: 1pce | M89: Spécialités de fromage | N89: Formaggi | O89: della regione | P89: 1pz | Q89: Formaggi | R89: 1 | S89: 1 | T89: Stück | U89: (PCE) Stück | V89: Frische | W89: Käse | X89: Käse | AB89: ja | AC89: ja | AD89: ja | AE89: ja | AF89: - | AG89: - | AH89: ja | AI89: 0 | AJ89: -
A90: 88 | C90: Stk | D90: Nein | F90: Käsetheke | G90: aus der Region | H90: 1Stk | I90: Käsetheke | J90: Fromagerie | K90: de la région | L90: 1pce | M90: Fromagerie | N90: Banco formaggi | O90: della regione | P90: 1pz | Q90: Banco formaggi | R90: 1 | S90: 1 | T90: Stück | U90: (PCE) Stück | V90: Frische | W90: Käse | X90: Käse | AB90: ja | AC90: ja | AD90: ja | AE90: ja | AF90: - | AG90: - | AH90: ja | AI90: 0 | AJ90: -
A91: 93 | B91: 841 | C91: kg | D91: Nein | F91: Mutschli | G91: aus der Region | H91: 1Stk | I91: Mutschli | J91: Tomme | K91: de la région | L91: 1pce | M91: Tomme | N91: Tomino | O91: della regione | P91: 1pz | Q91: Tomino | R91: 1 | S91: 100 | T91: Gramm | U91: (PCE) Stück | V91: Frische | W91: Käse | X91: Käse | AB91: ja | AC91: ja | AD91: ja | AE91: ja | AF91: - | AG91: - | AH91: ja | AI91: 0.05 | AJ91: -
A92: 96 | B92: 842 | C92: kg | D92: Nein | F92: Raclette | G92: aus der Region | H92: 1Stk | I92: Raclette | J92: Raclette | K92: de la région | L92: 1pce | M92: Raclette | N92: Raclette | O92: della regione | P92: 1pz | Q92: Raclette | R92: 1 | S92: 100 | T92: Gramm | U92: (PCE) Stück | V92: Frische | W92: Käse | X92: Käse | AB92: ja | AC92: ja | AD92: ja | AE92: ja | AF92: - | AG92: - | AH92: ja | AI92: 0.05 | AJ92: -
A93: 102 | C93: Stk | D93: Nein | F93: Zincarlin | G93: aus der Region | H93: 1Stk | I93: Zincarlin | J93: Zincarlin | K93: de la région | L93: 1pce | M93: Zincarlin | N93: Zincarlin | O93: della regione | P93: 1pz | Q93: Zincarlin | R93: 1 | S93: 1 | T93: Stück | U93: (PCE) Stück | V93: Frische | W93: Käse | X93: Käse | AB93: ja | AC93: ja | AD93: ja | AE93: ja | AF93: - | AG93: - | AH93: ja | AI93: 0.05 | AJ93: -
A94: 67 | C94: Stk | D94: Nein | F94: Butter | G94: aus der Region | H94: 100g | I94: Butter 100g | J94: Beurre | K94: de la région | L94: 100g | M94: Beurre 100g | N94: Burro | O94: della regione | P94: 100g | Q94: Burro 100g | R94: 0.1 | S94: 100 | T94: Gramm | U94: (PCE) Stück | V94: Frische | W94: Molkereiprodukte & Eier | X94: Milchprodukte | AB94: ja | AC94: ja | AD94: ja | AE94: ja | AF94: - | AG94: - | AH94: ja | AI94: 0.05 | AJ94: -
A95: 68 | C95: Stk | D95: Nein | F95: Butter | G95: aus der Region | H95: 200g | I95: Butter 200g | J95: Beurre | K95: de la région | L95: 200g | M95: Beurre 200g | N95: Burro | O95: della regione | P95: 200g | Q95: Burro 200g | R95: 0.2 | S95: 100 | T95: Gramm | U95: (PCE) Stück | V95: Frische | W95: Molkereiprodukte & Eier | X95: Milchprodukte | AB95: ja | AC95: ja | AD95: ja | AE95: ja | AF95: - | AG95: - | AH95: ja | AI95: 0.05 | AJ95: -
A96: 69 | C96: Stk | D96: Nein | F96: Butter | G96: aus der Region | H96: 250g | I96: Butter 250g | J96: Beurre | K96: de la région | L96: 250g | M96: Beurre 250g | N96: Burro | O96: della regione | P96: 250g | Q96: Burro 250g | R96: 0.25 | S96: 100 | T96: Gramm | U96: (PCE) Stück | V96: Frische | W96: Molkereiprodukte & Eier | X96: Milchprodukte | AB96: ja | AC96: ja | AD96: ja | AE96: ja | AF96: - | AG96: - | AH96: ja | AI96: 0.05 | AJ96: -
A97: 71 | C97: Stk | D97: Nein | F97: Doppel-Rahm | G97: aus der Region | H97: 200ml | I97: Doppel-Rahm 200ml | J97: Double crème | K97: de la région | L97: 200ml | M97: Double crème 200ml | N97: Panna doppia | O97: della regione | P97: 200ml | Q97: Panna 200ml | R97: 0.2 | S97: 100 | T97: Milliliter | U97: (PCE) Stück | V97: Frische | W97: Molkereiprodukte & Eier | X97: Milchprodukte | AB97: ja | AC97: ja | AD97: ja | AE97: ja | AF97: - | AG97: - | AH97: ja | AI97: 0.05 | AJ97: -
A98: 72 | C98: Stk | D98: Nein | F98: Doppel-Rahm | G98: aus der Region | H98: 250ml | I98: Doppel-Rahm 250ml | J98: Double crème | K98: de la région | L98: 250ml | M98: Double crème 250ml | N98: Panna doppia | O98: della regione | P98: 250ml | Q98: Panna 250ml | R98: 0.25 | S98: 100 | T98: Milliliter | U98: (PCE) Stück | V98: Frische | W98: Molkereiprodukte & Eier | X98: Milchprodukte | AB98: ja | AC98: ja | AD98: ja | AE98: ja | AF98: - | AG98: - | AH98: ja | AI98: 0.05 | AJ98: -
A99: 85 | C99: Stk | D99: Nein | F99: Jogurt | G99: aus der Region | H99: 130g | I99: Jogurt 130g | J99: Yogourt | K99: de la région | L99: 130g | M99: Yogourt 130g | N99: Yogourt | O99: della regione | P99: 130g | Q99: Yogourt 130g | R99: 0.13 | S99: 100 | T99: Gramm | U99: (PCE) Stück | V99: Frische | W99: Molkereiprodukte & Eier | X99: Milchprodukte | AB99: ja | AC99: ja | AD99: ja | AE99: ja | AF99: - | AG99: - | AH99: ja | AI99: 0 | AJ99: -
A100: 85 | C100: Stk | D100: Nein | F100: Jogurt | G100: aus der Region | H100: 150g | I100: Jogurt 150g | J100: Yogourt | K100: de la région | L100: 150g | M100: Yogourt 150g | N100: Yogourt | O100: della regione | P100: 150g | Q100: Yogourt 150g | R100: 0.15 | S100: 100 | T100: Gramm | U100: (PCE) Stück | V100: Frische | W100: Molkereiprodukte & Eier | X100: Milchprodukte | AB100: ja | AC100: ja | AD100: ja | AE100: ja | AF100: - | AG100: - | AH100: ja | AI100: 0 | AJ100: -
A101: 85 | C101: Stk | D101: Nein | F101: Jogurt | G101: aus der Region | H101: 180g | I101: Jogurt 180g | J101: Yogourt | K101: de la région | L101: 180g | M101: Yogourt 180g | N101: Yogourt | O101: della regione | P101: 180g | Q101: Yogourt 180g | R101: 0.18 | S101: 100 | T101: Gramm | U101: (PCE) Stück | V101: Frische | W101: Molkereiprodukte & Eier | X101: Milchprodukte | AB101: ja | AC101: ja | AD101: ja | AE101: ja | AF101: - | AG101: - | AH101: ja | AI101: 0 | AJ101: -
A102: 85 | C102: Stk | D102: Nein | F102: Jogurt | G102: aus der Region | H102: 200g | I102: Jogurt 200g | J102: Yogourt | K102: de la région | L102: 200g | M102: Yogourt 200g | N102: Yogourt | O102: della regione | P102: 200g | Q102: Yogourt 200g | R102: 0.2 | S102: 100 | T102: Gramm | U102: (PCE) Stück | V102: Frische | W102: Molkereiprodukte & Eier | X102: Milchprodukte | AB102: ja | AC102: ja | AD102: ja | AE102: ja | AF102: - | AG102: - | AH102: ja | AI102: 0 | AJ102: -
A103: 85 | C103: Stk | D103: Nein | F103: Jogurt | G103: aus der Region | H103: 250g | I103: Jogurt 250g | J103: Yogourt | K103: de la région | L103: 250g | M103: Yogourt 250g | N103: Yogourt | O103: della regione | P103: 250g | Q103: Yogourt 250g | R103: 0.25 | S103: 100 | T103: Gramm | U103: (PCE) Stück | V103: Frische | W103: Molkereiprodukte & Eier | X103: Milchprodukte | AB103: ja | AC103: ja | AD103: ja | AE103: ja | AF103: - | AG103: - | AH103: ja | AI103: 0 | AJ103: -
A104: 86 | C104: Stk | D104: Nein | F104: Jogurt | G104: aus der Region | H104: 400g | I104: Jogurt 400g | J104: Yogourt | K104: de la région | L104: 400g | M104: Yogourt 400g | N104: Yogourt | O104: della regione | P104: 400g | Q104: Yogourt 400g | R104: 0.4 | S104: 100 | T104: Gramm | U104: (PCE) Stück | V104: Frische | W104: Molkereiprodukte & Eier | X104: Milchprodukte | AB104: ja | AC104: ja | AD104: ja | AE104: ja | AF104: - | AG104: - | AH104: ja | AI104: 0 | AJ104: -
... A110: 78 | C110: Stk | D110: Nein | F110: Fleischtheke | G110: aus der Region | H110: 1Stk | I110: Fleischtheke | J110: Boucherie | K110: de la région | L110: 1pce | M110: Boucherie | N110: Banco carni | O110: della regione | P110: 1pz | Q110: Banco carni | R110: 1 | S110: 1 | T110: Stück | U110: (PCE) Stück | V110: Frische | W110: SB - Fleisch | X110: SB - Fleisch andere | AB110: ja | AC110: ja | AD110: ja | AE110: ja | AF110: - | AG110: - | AH110: ja | AI110: 0 | AJ110: -
A111: 65 | B111: 861 | C111: kg | D111: Nein | F111: Bauernschüblig | G111: aus der Region | H111: 2Stk | I111: Bauernschüblig 2Stk | J111: Schüblig | K111: de la région | L111: 2pces | M111: Schüblig 2pces | N111: Schüblig contadino | O111: della regione | P111: 2pz | Q111: Schüblig contadino 2pz | R111: 2 | S111: 100 | T111: Gramm | U111: (PCE) Stück | V111: Frische | W111: Fleisch- und Wurstwaren | X111: Wurstwaren | AB111: ja | AC111: ja | AD111: ja | AE111: ja | AF111: - | AG111: - | AH111: ja | AI111: 0.05 | AJ111: -
A112: 70 | B112: 862 | C112: kg | D112: Nein | F112: Cervelat | G112: aus der Region | H112: 2Stk | I112: Cervelat 2Stk | J112: Cervelas | K112: de la région | L112: 2pces | M112: Cervelas 2pces | N112: Cervelat | O112: della regione | P112: 2pz | Q112: Cervelat 2pz | R112: 2 | S112: 100 | T112: Gramm | U112: (PCE) Stück | V112: Frische | W112: Fleisch- und Wurstwaren | X112: Wurstwaren | AB112: ja | AC112: ja | AD112: ja | AE112: ja | AF112: - | AG112: - | AH112: ja | AI112: 0.05 | AJ112: -
A113: 84 | B113: 863 | C113: kg | D113: Nein | F113: Hauswurst | G113: aus der Region | H113: 2Stk | I113: Hauswurst 2Stk | J113: Saucisse | K113: de la région | L113: 2pces | M113: Saucisse 2pces | N113: Salsiccia | O113: della regione | P113: 2pz | Q113: Salsiccia 2pz | R113: 2 | S113: 100 | T113: Gramm | U113: (PCE) Stück | V113: Frische | W113: Fleisch- und Wurstwaren | X113: Wurstwaren | AB113: ja | AC113: ja | AD113: ja | AE113: ja | AF113: - | AG113: - | AH113: ja | AI113: 0 | AJ113: -
A114: 90 | B114: 864 | C114: kg | D114: Nein | F114: Landjäger dunkel | G114: aus der Region | H114: 2Stk | I114: Landjäger dunkel 2Stk | J114: Sauc. Landjäger foncée | K114: de la région | L114: 2pces | M114: Sauc. foncée 2pces | N114: Sals. Landjäger scura | O114: della regione | P114: 2pz | Q114: Sals. scura 2pz | R114: 2 | S114: 100 | T114: Gramm | U114: (PCE) Stück | V114: Frische | W114: Fleisch- und Wurstwaren | X114: Wurstwaren | AB114: ja | AC114: ja | AD114: ja | AE114: ja | AF114: - | AG114: - | AH114: ja | AI114: 0.05 | AJ114: -
A115: 91 | B115: 865 | C115: kg | D115: Nein | F115: Landjäger hell | G115: aus der Region | H115: 2Stk | I115: Landjäger hell 2Stk | J115: Sauc. Landjäger claire | K115: de la région | L115: 2pces | M115: Sauc. claire 2pces | N115: Sals. Landjäger chiara | O115: della regione | P115: 2pz | Q115: Sals. chiara 2pz | R115: 2 | S115: 100 | T115: Gramm | U115: (PCE) Stück | V115: Frische | W115: Fleisch- und Wurstwaren | X115: Wurstwaren | AB115: ja | AC115: ja | AD115: ja | AE115: ja | AF115: - | AG115: - | AH115: ja | AI115: 0.05 | AJ115: -
A116: 97 | B116: 866 | C116: kg | D116: Nein | F116: Rauchwurst | G116: aus der Region | H116: 2Stk | I116: Rauchwurst 2Stk | J116: Saucisse fumée | K116: de la région | L116: 2pces | M116: Saucisse fumée 2pces | N116: Salsiccia affumicata | O116: della regione | P116: 2pz | Q116: Salsiccia affumicata 2pz | R116: 2 | S116: 100 | T116: Gramm | U116: (PCE) Stück | V116: Frische | W116: Fleisch- und Wurstwaren | X116: Wurstwaren | AB116: ja | AC116: ja | AD116: ja | AE116: ja | AF116: - | AG116: - | AH116: ja | AI116: 0.05 | AJ116: -
A117: 109 | C117: Stk | D117: Nein | F117: Bier | G117: aus der Region | H117: 6x25cl | I117: Bier 6x25cl | J117: Bière | K117: de la région | L117: 6x25cl | M117: Bière 6x25cl | N117: Birra | O117: della regione | P117: 6x25cl | Q117: Birra 6x25cl | R117: 0.25 | S117: 10 | T117: Centiliter | U117: (PCE) Stück | V117: Getränke | W117: Bier | X117: Bier | AB117: ja | AC117: ja | AD117: ja | AE117: ja | AF117: - | AG117: - | AH117: ja | AI117: 0 | AJ117: -
A118: 109 | C118: Stk | D118: Nein | F118: Bier | G118: aus der Region | H118: 4x25cl | I118: Bier 4x25cl | J118: Bière | K118: de la région | L118: 4x25cl | M118: Bière 4x25cl | N118: Birra | O118: della regione | P118: 4x25cl | Q118: Birra 4x25cl | R118: 0.25 | S118: 10 | T118: Centiliter | U118: (PCE) Stück | V118: Getränke | W118: Bier | X118: Bier | AB118: ja | AC118: ja | AD118: ja | AE118: ja | AF118: - | AG118: - | AH118: ja | AI118: 0 | AJ118: -
A119: 109 | C119: Stk | D119: Nein | F119: Bier | G119: aus der Region | H119: 25cl | I119: Bier 25cl | J119: Bière | K119: de la région | L119: 25cl | M119: Bière 25cl | N119: Birra | O119: della regione | P119: 25cl | Q119: Birra 25cl | R119: 0.25 | S119: 10 | T119: Centiliter | U119: (PCE) Stück | V119: Getränke | W119: Bier | X119: Bier | AB119: ja | AC119: ja | AD119: ja | AE119: ja | AF119: - | AG119: - | AH119: ja | AI119: 0 | AJ119: -
A120: 108 | C120: Stk | D120: Nein | F120: Bier | G120: aus der Region | H120: 10x33cl | I120: Bier 10x33cl | J120: Bière | K120: de la région | L120: 10x33cl | M120: Bière 10x33cl | N120: Birra | O120: della regione | P120: 10x33cl | Q120: Birra 10x33cl | R120: 0.33 | S120: 10 | T120: Centiliter | U120: (PCE) Stück | V120: Getränke | W120: Bier | X120: Bier | AB120: ja | AC120: ja | AD120: ja | AE120: ja | AF120: - | AG120: - | AH120: ja | AI120: 0 | AJ120: -
A121: 108 | C121: Stk | D121: Nein | F121: Bier | G121: aus der Region | H121: 6x33cl | I121: Bier 6x33cl | J121: Bière | K121: de la région | L121: 6x33cl | M121: Bière 6x33cl | N121: Birra | O121: della regione | P121: 6x33cl | Q121: Birra 6x33cl | R121: 0.33 | S121: 10 | T121: Centiliter | U121: (PCE) Stück | V121: Getränke | W121: Bier | X121: Bier | AB121: ja | AC121: ja | AD121: ja | AE121: ja | AF121: - | AG121: - | AH121: ja | AI121: 0 | AJ121: -
A122: 108 | C122: Stk | D122: Nein | F122: Bier | G122: aus der Region | H122: 4x33cl | I122: Bier 4x33cl | J122: Bière | K122: de la région | L122: 4x33cl | M122: Bière 4x33cl | N122: Birra | O122: della regione | P122: 4x33cl | Q122: Birra 4x33cl | R122: 0.33 | S122: 10 | T122: Centiliter | U122: (PCE) Stück | V122: Getränke | W122: Bier | X122: Bier | AB122: ja | AC122: ja | AD122: ja | AE122: ja | AF122: - | AG122: - | AH122: ja | AI122: 0 | AJ122: -
A123: 108 | C123: Stk | D123: Nein | F123: Bier | G123: aus der Region | H123: 3x33cl | I123: Bier 3x33cl | J123: Bière | K123: de la région | L123: 3x33cl | M123: Bière 3x33cl | N123: Birra | O123: della regione | P123: 3x33cl | Q123: Birra 3x33cl | R123: 0.33 | S123: 10 | T123: Centiliter | U123: (PCE) Stück | V123: Getränke | W123: Bier | X123: Bier | AB123: ja | AC123: ja | AD123: ja | AE123: ja | AF123: - | AG123: - | AH123: ja | AI123: 0 | AJ123: -
A124: 108 | C124: Stk | D124: Nein | F124: Bier | G124: aus der Region | H124: 33cl | I124: Bier 33cl | J124: Bière | K124: de la région | L124: 33cl | M124: Bière 33cl | N124: Birra | O124: della regione | P124: 33cl | Q124: Birra 33cl | R124: 0.33 | S124: 10 | T124: Centiliter | U124: (PCE) Stück | V124: Getränke | W124: Bier | X124: Bier | AB124: ja | AC124: ja | AD124: ja | AE124: ja | AF124: - | AG124: - | AH124: ja | AI124: 0 | AJ124: -
A125: 109 | C125: Stk | D125: Nein | F125: Bier | G125: aus der Region | H125: 6x50cl | I125: Bier 6x50cl | J125: Bière | K125: de la région | L125: 6x50cl | M125: Bière 6x50cl | N125: Birra | O125: della regione | P125: 6x50cl | Q125: Birra 6x50cl | R125: 0.5 | S125: 10 | T125: Centiliter | U125: (PCE) Stück | V125: Getränke | W125: Bier | X125: Bier | AB125: ja | AC125: ja | AD125: ja | AE125: ja | AF125: - | AG125: - | AH125: ja | AI125: 0 | AJ125: -
A126: 109 | C126: Stk | D126: Nein | F126: Bier | G126: aus der Region | H126: 4x50cl | I126: Bier 4x50cl | J126: Bière | K126: de la région | L126: 4x50cl | M126: Bière 4x50cl | N126: Birra | O126: della regione | P126: 4x50cl | Q126: Birra 4x50cl | R126: 0.5 | S126: 10 | T126: Centiliter | U126: (PCE) Stück | V126: Getränke | W126: Bier | X126: Bier | AB126: ja | AC126: ja | AD126: ja | AE126: ja | AF126: - | AG126: - | AH126: ja | AI126: 0 | AJ126: -
A127: 109 | C127: Stk | D127: Nein | F127: Bier | G127: aus der Region | H127: 50cl | I127: Bier 50cl | J127: Bière | K127: de la région | L127: 50cl | M127: Bière 50cl | N127: Birra | O127: della regione | P127: 50cl | Q127: Birra 50cl | R127: 0.5 | S127: 10 | T127: Centiliter | U127: (PCE) Stück | V127: Getränke | W127: Bier | X127: Bier | AB127: ja | AC127: ja | AD127: ja | AE127: ja | AF127: - | AG127: - | AH127: ja | AI127: 0 | AJ127: -
A128: 109 | C128: Stk | D128: Nein | F128: Bier | G128: aus der Region | H128: 75cl | I128: Bier 75cl | J128: Bière | K128: de la région | L128: 75cl | M128: Bière 75cl | N128: Birra | O128: della regione | P128: 75cl | Q128: Birra 75cl | R128: 0.75 | S128: 10 | T128: Centiliter | U128: (PCE) Stück | V128: Getränke | W128: Bier | X128: Bier | AB128: ja | AC128: ja | AD128: ja | AE128: ja | AF128: - | AG128: - | AH128: ja | AI128: 0 | AJ128: -
... A165: 123 | C165: Stk | D165: Nein | F165: Tee | G165: aus der Region | H165: 1Stk | I165: Tee | J165: Thé | K165: de la région | L165: 1pce | M165: Thé | N165: Tè | O165: della regione | P165: 1pz | Q165: Tè | R165: 1 | S165: 1 | T165: Stück | U165: (PCE) Stück | V165: Getränke | W165: Kaffee und Tee | X165: Tee | AB165: ja | AC165: ja | AD165: ja | AE165: ja | AF165: - | AG165: - | AH165: ja | AI165: 0 | AJ165: -
A166: 129 | C166: Stk | D166: Nein | F166: Gasflasche | H166: 10.5kg | I166: Gasflasche 10.5kg | J166: Bouteille de gaz | L166: 10.5kg | M166: Bouteille gaz 10.5kg | N166: Bombola di gas | P166: 10.5kg | Q166: Bombola gas 10.5kg | R166: 10.5 | S166: 1 | T166: Kilogramm | U166: (PCE) Stück | V166: Near Food | W166: Gebrauchsartikel | X166: Gebrauchsartikel | AB166: ja | AC166: ja | AD166: ja | AE166: ja | AF166: - | AG166: ja | AH166: ja | AI166: 0.05 | AJ166: -
A167: 130 | C167: Stk | D167: Nein | F167: Gasflasche | H167: 5kg | I167: Gasflasche 5kg | J167: Bouteille de gaz | L167: 5kg | M167: Bouteille gaz 5kg | N167: Bombola di gas | P167: 5kg | Q167: Bombola gas 5kg | R167: 5 | S167: 1 | T167: Kilogramm | U167: (PCE) Stück | V167: Near Food | W167: Gebrauchsartikel | X167: Gebrauchsartikel | AB167: ja | AC167: ja | AD167: ja | AE167: ja | AF167: - | AG167: ja | AH167: ja | AI167: 0.05 | AJ167: -
A168: 131 | C168: Stk | D168: Nein | F168: Gasflasche | H168: 33kg | I168: Gasflasche 33kg | J168: Bouteille de gaz | L168: 33kg | M168: Bouteille gaz 33kg | N168: Bombola di gas | P168: 33kg | Q168: Bombola gas 33kg | R168: 33 | S168: 1 | T168: Kilogramm | U168: (PCE) Stück | V168: Near Food | W168: Gebrauchsartikel | X168: Gebrauchsartikel | AB168: ja | AC168: ja | AD168: ja | AE168: ja | AF168: - | AG168: ja | AH168: ja | AI168: 0.05 | AJ168: -
A169: 132 | C169: Stk | D169: Nein | F169: Gasflasche | H169: 35kg | I169: Gasflasche 35kg | J169: Bouteille de gaz | L169: 35kg | M169: Bouteille gaz 35kg | N169: Bombola di gas | P169: 35kg | Q169: Bombola gas 35kg | R169: 35 | S169: 1 | T169: Kilogramm | U169: (PCE) Stück | V169: Near Food | W169: Gebrauchsartikel | X169: Gebrauchsartikel | AB169: ja | AC169: ja | AD169: ja | AE169: ja | AF169: - | AG169: ja | AH169: ja | AI169: 0.05 | AJ169: -
A170: 133 | C170: Stk | D170: Nein | F170: Gasflasche | H170: 7.5kg | I170: Gasflasche 7.5kg | J170: Bouteille de gaz | L170: 7.5kg | M170: Bouteille gaz 7.5kg | N170: Bombola di gas | P170: 7.5kg | Q170: Bombola gas 7.5kg | R170: 7.5 | S170: 1 | T170: Kilogramm | U170: (PCE) Stück | V170: Near Food | W170: Gebrauchsartikel | X170: Gebrauchsartikel | AB170: ja | AC170: ja | AD170: ja | AE170: ja | AF170: - | AG170: ja | AH170: ja | AI170: 0.05 | AJ170: -
A171: 139 | C171: Stk | D171: Nein | F171: Holz | H171: 1Stk | I171: Holz | J171: Bois de chauffage | L171: 1pce | M171: Bois de chauffage | N171: Legna da ardere | P171: 1pz | Q171: Legna da ardere | R171: 1 | S171: 1 | T171: Stück | U171: (PCE) Stück | V171: Near Food | W171: Gebrauchsartikel | X171: Gebrauchsartikel | AB171: ja | AC171: ja | AD171: ja | AE171: ja | AF171: - | AG171: ja | AH171: ja | AI171: 0.05 | AJ171: -
A172: 140 | C172: Stk | D172: Nein | F172: Holzkohle | H172: 1Stk | I172: Holzkohle | J172: Charbon de bois | L172: 1pce | M172: Charbon de bois | N172: Carbone | P172: 1pz | Q172: Carbone | R172: 1 | S172: 1 | T172: Stück | U172: (PCE) Stück | V172: Near Food | W172: Gebrauchsartikel | X172: Gebrauchsartikel | AB172: ja | AC172: ja | AD172: ja | AE172: ja | AF172: - | AG172: ja | AH172: ja | AI172: 0.05 | AJ172: -
A173: 141 | C173: Stk | D173: Nein | F173: Karten | H173: 1Stk | I173: Karten | J173: Cartes | L173: 1pce | M173: Cartes | N173: Cartoline | P173: 1pz | Q173: Cartoline | R173: 1 | S173: 1 | T173: Stück | U173: (PCE) Stück | V173: Near Food | W173: Gebrauchsartikel | X173: Gebrauchsartikel | AB173: ja | AC173: ja | AD173: ja | AE173: ja | AF173: - | AG173: ja | AH173: ja | AI173: 0.05 | AJ173: -
A174: 142 | C174: Stk | D174: Nein | F174: Pellets | H174: 1Stk | I174: Pellets | J174: Pellets | L174: 1pce | M174: Pellets | N174: Pellet | P174: 1pz | Q174: Pellet | R174: 1 | S174: 1 | T174: Stück | U174: (PCE) Stück | V174: Near Food | W174: Gebrauchsartikel | X174: Gebrauchsartikel | AB174: ja | AC174: ja | AD174: ja | AE174: ja | AF174: - | AG174: ja | AH174: ja | AI174: 0.05 | AJ174: -
A175: 144 | C175: Stk | D175: Nein | F175: Zeitschriften | H175: 1Stk | I175: Zeitschriften | J175: Magazines | L175: 1pce | M175: Magazines | N175: Riviste | P175: 1pz | Q175: Riviste | R175: 1 | S175: 1 | T175: Stück | U175: (PCE) Stück | V175: Near Food | W175: Gebrauchsartikel | X175: Gebrauchsartikel | AB175: ja | AC175: ja | AD175: ja | AE175: ja | AF175: - | AG175: ja | AH175: ja | AI175: 0 | AJ175: -
A176: 124 | C176: Stk | D176: Nein | F176: Bündelmarke | H176: 1Stk | I176: Bündelmarke | J176: Marque de regroupement | L176: 1pce | M176: Marque de regroupement | N176: Tagliando tarif. fasci | P176: 1pz | Q176: Tagliando tarif. fasci | R176: 1 | S176: 1 | T176: Stück | U176: (PCE) Stück | V176: Near Food | W176: Gebrauchsartikel | X176: Gebührensäcke und Marken | AB176: ja | AC176: ja | AD176: ja | AE176: ja | AF176: - | AG176: - | AH176: ja | AI176: 0.05 | AJ176: -
A177: 125 | C177: Stk | D177: Nein | F177: Container Band | H177: 1Stk | I177: Container Band 1Stk | J177: Bande de conteneur | L177: 1pce | M177: Bande conteneur 1pce | N177: Fascia per contenitore | P177: 1pz | Q177: Fascia contenitore 1pz | R177: 1 | S177: 1 | T177: Stück | U177: (PCE) Stück | V177: Near Food | W177: Gebrauchsartikel | X177: Gebührensäcke und Marken | AB177: ja | AC177: ja | AD177: ja | AE177: ja | AF177: - | AG177: - | AH177: ja | AI177: 0.05 | AJ177: -
... A188: 145 | C188: Stk | D188: Nein | F188: Gutschein | H188: 1Stk | I188: Gutschein | J188: Bon cadeau | L188: 1pce | M188: Bon cadeau | N188: Buono regalo | P188: 1pz | Q188: Buono regalo | R188: 1 | S188: 1 | T188: Stück | U188: (PCE) Stück | V188: Nicht-Handelsware | W188: Kasse | X188: Gutschein, Voucher | AB188: ja | AC188: ja | AD188: ja | AE188: ja | AF188: - | AG188: ja | AH188: ja | AI188: 0 | AJ188: -
A189: 147 | C189: Stk | D189: Nein | F189: Vin cuit | G189: aus der Region | H189: 50cl | I189: Vin cuit 50cl | J189: Vin cuit | K189: de la région | L189: 50cl | M189: Vin cuit 50cl | N189: Vin cuit | O189: della regione | P189: 50cl | Q189: Vin cuit 50cl | R189: 0.5 | S189: 1 | T189: Stück | U189: (PCE) Stück | V189: Wein | W189: Weine | X189: Wein andere | AB189: ja | AC189: ja | AD189: ja | AE189: ja | AF189: - | AG189: - | AH189: ja | AI189: 0.05 | AJ189: -
A190: 147 | C190: Stk | D190: Nein | F190: Vin cuit | G190: aus der Region | H190: 75cl | I190: Vin cuit 75cl | J190: Vin cuit | K190: de la région | L190: 75cl | M190: Vin cuit 75cl | N190: Vin cuit | O190: della regione | P190: 75cl | Q190: Vin cuit 75cl | R190: 0.75 | S190: 1 | T190: Stück | U190: (PCE) Stück | V190: Wein | W190: Weine | X190: Wein andere | AB190: ja | AC190: ja | AD190: ja | AE190: ja | AF190: - | AG190: - | AH190: ja | AI190: 0.05 | AJ190: -
A191: 147 | C191: Stk | D191: Nein | F191: Vin cuit | G191: aus der Region | H191: 1l | I191: Vin cuit 1l | J191: Vin cuit | K191: de la région | L191: 1l | M191: Vin cuit 1l | N191: Vin cuit | O191: della regione | P191: 1l | Q191: Vin cuit 1l | R191: 1 | S191: 1 | T191: Stück | U191: (PCE) Stück | V191: Wein | W191: Weine | X191: Wein andere | AB191: ja | AC191: ja | AD191: ja | AE191: ja | AF191: - | AG191: - | AH191: ja | AI191: 0.05 | AJ191: -
A192: 148 | C192: Stk | D192: Nein | F192: Wein | G192: aus der Region | H192: 1l | I192: Wein 1l | J192: Vin | K192: de la région | L192: 1l | M192: Vin 1l | N192: Vino | O192: della regione | P192: 1l | Q192: Vino 1l | R192: 1 | S192: 1 | T192: Stück | U192: (PCE) Stück | V192: Wein | W192: Weine | X192: Wein andere | AB192: ja | AC192: ja | AD192: ja | AE192: ja | AF192: - | AG192: - | AH192: ja | AI192: 0 | AJ192: -
A193: 148 | C193: Stk | D193: Nein | F193: Wein | G193: aus der Region | H193: 25cl | I193: Wein 25cl | J193: Vin | K193: de la région | L193: 25cl | M193: Vin 25cl | N193: Vino | O193: della regione | P193: 25cl | Q193: Vino 25cl | R193: 0.25 | S193: 1 | T193: Stück | U193: (PCE) Stück | V193: Wein | W193: Weine | X193: Wein andere | AB193: ja | AC193: ja | AD193: ja | AE193: ja | AF193: - | AG193: - | AH193: ja | AI193: 0 | AJ193: -
A194: 148 | C194: Stk | D194: Nein | F194: Wein | G194: aus der Region | H194: 50cl | I194: Wein 50cl | J194: Vin | K194: de la région | L194: 50cl | M194: Vin 50cl | N194: Vino | O194: della regione | P194: 50cl | Q194: Vino 50cl | R194: 0.5 | S194: 1 | T194: Stück | U194: (PCE) Stück | V194: Wein | W194: Weine | X194: Wein andere | AB194: ja | AC194: ja | AD194: ja | AE194: ja | AF194: - | AG194: - | AH194: ja | AI194: 0 | AJ194: -
A195: 148 | C195: Stk | D195: Nein | F195: Wein | G195: aus der Region | H195: 75cl | I195: Wein 75cl | J195: Vin | K195: de la région | L195: 75cl | M195: Vin 75cl | N195: Vino | O195: della regione | P195: 75cl | Q195: Vino 75cl | R195: 0.75 | S195: 1 | T195: Stück | U195: (PCE) Stück | V195: Wein | W195: Weine | X195: Wein andere | AB195: ja | AC195: ja | AD195: ja | AE195: ja | AF195: - | AG195: - | AH195: ja | AI195: 0 | AJ195: -
A196: 200 | B196: 135 | C196: kg | D196: Nein | F196: Birnen Büscheli | G196: Offen Kl. 1 | I196: Birnen Büscheli Offen Kl. 1 | J196: Poires Büscheli | K196: En vrac, cl. 1 | M196: Poires Büscheli | N196: Pere Büscheli | O196: Cl. 1 vendita sfusa | Q196: Pere Büscheli Cl. 1 v.s. | R196: 1 | S196: 1 | T196: Kilogramm | U196: (KGM) KG | V196: Früchte und Gemüse | W196: Früchte und Gemüse | X196: Früchte | AB196: ja | AC196: ja | AD196: ja | AE196: ja | AF196: - | AG196: - | AH196: ja | AI196: 0.05 | AJ196: -
A197: 201 | B197: 180 | C197: Stk | D197: Nein | F197: Ananas | G197: Baby | H197: 1Stk | I197: Ananas Baby Stk | J197: Ananas | K197: Baby | L197: 1pce | M197: Ananas Baby | N197: Ananas | O197: Baby | P197: 1pz | Q197: Ananas Baby 1 pz | R197: 1 | S197: 1 | T197: Stück | U197: (PCE) Stück | V197: Früchte und Gemüse | W197: Früchte und Gemüse | X197: Früchte | AB197: ja | AC197: ja | AD197: ja | AE197: ja | AF197: - | AG197: - | AH197: ja | AI197: 0.05 | AJ197: -
A198: 202 | C198: Stk | D198: Nein | E198: 7613399001270 | F198: Ananas | G198: Becher | H198: 200g | I198: Ananas Becher 200g | J198: Ananas | K198: Gobelet | L198: 200g | M198: Ananas gobelet 200g | N198: Ananas | O198: bicchiere | P198: 200g | Q198: Ananas bicchiere 200g | R198: 0.2 | S198: 100 | T198: Gramm | U198: (PCE) Stück | V198: Früchte und Gemüse | W198: Früchte und Gemüse | X198: Früchte | AB198: ja | AC198: ja | AD198: ja | AE198: ja | AF198: - | AG198: - | AH198: ja | AI198: 0.05 | AJ198: -
A199: 203 | C199: Stk | E199: 2008002220011 | F199: Äpfel Granny Smith | G199: gepackt | I199: Äpfel Granny Smith gepackt | J199: Pommes Granny Smith | K199: Emballé | M199: Pommes Granny Smith, emballé | N199: Mele Granny Smith | O199: confezionato | Q199: Mele Granny Smith confez. | R199: 1 | S199: 1 | T199: Kilogramm | U199: (PCE) Stück | V199: Früchte und Gemüse | W199: Früchte und Gemüse | X199: Früchte | AB199: ja | AC199: ja | AD199: ja | AE199: ja | AF199: - | AG199: - | AH199: ja | AI199: 0.05 | AJ199: -
A200: 204 | C200: Stk | D200: Nein | E200: 7613399021476 | F200: Aprikosen | H200: 2kg | I200: Aprikosen 2kg | J200: Abricots | L200: 2kg | M200: Abricots 2kg | N200: Albicocche | P200: 2kg | Q200: Albicocche 2kg | R200: 2 | S200: 1 | T200: Kilogramm | U200: (PCE) Stück | V200: Früchte und Gemüse | W200: Früchte und Gemüse | X200: Früchte | AB200: ja | AC200: ja | AD200: ja | AE200: ja | AF200: - | AG200: - | AH200: ja | AI200: 0.05 | AJ200: -
A201: 205 | B201: 122 | C201: kg | D201: Nein | F201: Aprikosen | G201: Offen AAA | I201: Aprikosen Offen AAA | J201: Abricots | K201: En vrac AAA | M201: Abricosts en vrac AAA | N201: Albicocche | O201: vendita sfusa AAA | Q201: Albicocche vend. sfus. AAA | R201: 1 | S201: 1 | T201: Kilogramm | U201: (KGM) KG | V201: Früchte und Gemüse | W201: Früchte und Gemüse | X201: Früchte | AB201: ja | AC201: ja | AD201: ja | AE201: ja | AF201: - | AG201: - | AH201: ja | AI201: 0.05 | AJ201: -
A202: 206 | C202: kg | D202: Ja | E202: 2203231000000 | F202: Aprikosen | H202: ca. 800g | I202: Aprikosen ca. 800g | J202: Abricots | L202: env. 800g | M202: Abricots env. 800g | N202: Albicocche | P202: ca. 800g | Q202: Albicocche ca. 800g | R202: 0.8 | S202: 1 | T202: Kilogramm | U202: (PCE) Stück | V202: Früchte und Gemüse | W202: Früchte und Gemüse | X202: Früchte | AB202: ja | AC202: ja | AD202: ja | AE202: ja | AF202: - | AG202: - | AH202: ja | AI202: 0.05 | AJ202: -
A203: 207 | B203: 124 | C203: kg | F203: Aprikosen Offen | I203: Aprikosen Offen | J203: Abrivots | K203: En Vrac | M203: Abricots en vrac | N203: Albicocche | O203: vendita sfusa | Q203: Albicocche vend. sfusa | R203: 1 | S203: 1 | T203: Kilogramm | U203: (KGM) KG | V203: Früchte und Gemüse | W203: Früchte und Gemüse | X203: Früchte | AB203: ja | AC203: ja | AD203: ja | AE203: ja | AF203: - | AG203: - | AH203: ja | AI203: 0.05 | AJ203: -
A204: 208 | C204: kg | D204: Ja | E204: 2203231000000 | F204: Aprikosen | G204: Schale | H204: 650g | I204: Aprikosen Schale 650g | J204: Abricots | K204: Barquette | L204: 650g | M204: Abricots barquette 650g | N204: Albicocche | O204: vaschetta | P204: 650g | Q204: Albicocche vasch. 650g | R204: 0.65 | S204: 1 | T204: Kilogramm | U204: (PCE) Stück | V204: Früchte und Gemüse | W204: Früchte und Gemüse | X204: Früchte | AB204: ja | AC204: ja | AD204: ja | AE204: ja | AF204: - | AG204: - | AH204: ja | AI204: 0.05 | AJ204: -
A205: 209 | C205: Stk | D205: Nein | E205: 7613399047834 | F205: Aprikosen getrocknet | H205: 200g | I205: Aprikosen getrocknet 200g | J205: Abricots secs | L205: 200g | M205: Abricots secs 200g | N205: Albicocche secche | P205: 200g | Q205: Albicocche secche 200g | R205: 0.2 | S205: 100 | T205: Gramm | U205: (PCE) Stück | V205: Früchte und Gemüse | W205: Früchte und Gemüse | X205: Früchte | AB205: ja | AC205: ja | AD205: ja | AE205: ja | AF205: - | AG205: - | AH205: ja | AI205: 0.05 | AJ205: -
A206: 210 | B206: 126 | C206: kg | D206: Nein | F206: Bananen Fyffes | G206: Offen | I206: Bananen Fyffes Offen | J206: Bananes Fyffes | K206: En vrac | M206: Bananes Fyffes en vrac | N206: Banane Fyffes | O206: vendita sfusa | Q206: Banane Fyffes vend. sfusa | R206: 1 | S206: 1 | T206: Kilogramm | U206: (KGM) KG | V206: Früchte und Gemüse | W206: Früchte und Gemüse | X206: Früchte | AB206: ja | AC206: ja | AD206: ja | AE206: ja | AF206: - | AG206: - | AH206: ja | AI206: 0.05 | AJ206: -
A207: 211 | C207: kg | D207: Ja | E207: 2201581000000 | F207: Bananen | G207: gepackt | I207: Bananen gepackt | J207: Bananes | K207: Emballé | M207: Bananes emballé | N207: Banane | O207: confezionato | Q207: Banane confezionato | R207: 1 | S207: 1 | T207: Kilogramm | U207: (PCE) Stück | V207: Früchte und Gemüse | W207: Früchte und Gemüse | X207: Früchte | AB207: ja | AC207: ja | AD207: ja | AE207: ja | AF207: - | AG207: - | AH207: ja | AI207: 0.05 | AJ207: -
A208: 212 | C208: Stk | D208: Nein | E208: 7610632050514 | F208: Beerenmischung | G208: Schale | H208: 250g | I208: Beerenmischung Schale 250g | J208: Mélange de baies | K208: Barquette | L208: 250g | M208: Melange de baies 250g | N208: Bacche miste | O208: vaschetta | P208: 250g | Q208: Bacche miste 250g | R208: 0.25 | S208: 100 | T208: Gramm | U208: (PCE) Stück | V208: Früchte und Gemüse | W208: Früchte und Gemüse | X208: Früchte | AB208: ja | AC208: ja | AD208: ja | AE208: ja | AF208: - | AG208: - | AH208: ja | AI208: 0.05 | AJ208: -
A209: 213 | B209: 128 | C209: kg | F209: Bio Bananen Offen | I209: Bio Bananen Offen | J209: Bio Bananes | K209: En vrac | M209: Bio Bananes en vrac | N209: Bio Banane | O209: vendita sfusa | Q209: Bio Banane vendita sfusa | R209: 1 | S209: 1 | T209: Kilogramm | U209: (KGM) KG | V209: Früchte und Gemüse | W209: Früchte und Gemüse | X209: Früchte | AB209: ja | AC209: ja | AD209: ja | AE209: ja | AF209: - | AG209: - | AH209: ja | AI209: 0.05 | AJ209: -
A210: 214 | B210: 171 | C210: kg | F210: Bio Wassermelone Mini | I210: Bio Wassermelone Mini | J210: Bio Pastèques | K210: Mini | M210: Bio Pastèques Mini | N210: Bio Angurie mini | Q210: Bio Angurie mini | R210: 1 | S210: 1 | T210: Kilogramm | U210: (KGM) KG | V210: Früchte und Gemüse | W210: Früchte und Gemüse | X210: Früchte | AB210: ja | AC210: ja | AD210: ja | AE210: ja | AF210: - | AG210: - | AH210: ja | AI210: 0.05 | AJ210: -
A211: 215 | B211: 159 | C211: kg | F211: Bio Orangen Offen | I211: Bio Orangen Offen | J211: Bio Oranges | K211: En vrac | M211: Bio Oranges en vrac | N211: Bio Arance | O211: vendita sfusa | Q211: Bio Arance vendita sfusa | R211: 1 | S211: 1 | T211: Kilogramm | U211: (KGM) KG | V211: Früchte und Gemüse | W211: Früchte und Gemüse | X211: Früchte | AB211: ja | AC211: ja | AD211: ja | AE211: ja | AF211: - | AG211: - | AH211: ja | AI211: 0.05 | AJ211: -
A212: 216 | B212: 137 | C212: kg | F212: Birnen Ercolini | G212: Offen Kl. 1 | I212: Birnen Ercolini Offen Kl. 1 | J212: Poires Ercolini | K212: En vrac, cl. 1 | M212: Poire Ercolini en vrac cl. 1 | N212: Pere Ercolini | O212: Cl. 1 vendita sfusa | Q212: Pere Ercolini cl.1 vend. Sf. | R212: 1 | S212: 1 | T212: Kilogramm | U212: (KGM) KG | V212: Früchte und Gemüse | W212: Früchte und Gemüse | X212: Früchte | AB212: ja | AC212: ja | AD212: ja | AE212: ja | AF212: - | AG212: - | AH212: ja | AI212: 0.05 | AJ212: -
A213: 217 | B213: 142 | C213: kg | F213: Birnen Kaiser | G213: Offen Kl. 1 | I213: Birnen Kaiser Offen Kl.1 | J213: Poires Beurré Bosc | K213: En vrac, cl. 1 | M213: Poire Beurré Bosc en v. cl1 | N213: Pere Kaiser | O213: Cl. 1 vendita sfusa | Q213: Pere Kaiser cl. 1 vendta sf. | R213: 1 | S213: 1 | T213: Kilogramm | U213: (KGM) KG | V213: Früchte und Gemüse | W213: Früchte und Gemüse | X213: Früchte | AB213: ja | AC213: ja | AD213: ja | AE213: ja | AF213: - | AG213: - | AH213: ja | AI213: 0.05 | AJ213: -
A214: 218 | C214: kg | D214: Ja | E214: 2203071000000 | F214: Birnen Abate | G214: Kl. 1 gepackt | I214: Birnen Abate Kl. 1 gepackt | J214: Poires Abate | K214: Cl. 1 emballé | M214: Poires Abate cl. 1 emballé | N214: Pere Abate | O214: Cl. 1 confezionato | Q214: Pere Abate cl.1 confezionato | R214: 1 | S214: 1 | T214: Kilogramm | U214: (PCE) Stück | V214: Früchte und Gemüse | W214: Früchte und Gemüse | X214: Früchte | AB214: ja | AC214: ja | AD214: ja | AE214: ja | AF214: - | AG214: - | AH214: ja | AI214: 0.05 | AJ214: -
A215: 219 | C215: kg | D215: Ja | E215: 2215861000009 | F215: Bio Birnen Abate | G215: Kl. 1 gepackt | I215: Bio Birnen Abate Kl. 1 gep. | J215: Bio Poires Abate | K215: Cl. 1 emballé | M215: Bio Poires Abate cl1 emballé | N215: Bio Pere Abate | O215: Cl. 1 confezionato | Q215: Bio Pere Abate cl. 1 confez. | R215: 1 | S215: 1 | T215: Kilogramm | U215: (PCE) Stück | V215: Früchte und Gemüse | W215: Früchte und Gemüse | X215: Früchte | AB215: ja | AC215: ja | AD215: ja | AE215: ja | AF215: - | AG215: - | AH215: ja | AI215: 0.05 | AJ215: -
...

Sheet Stückartikel_Nat._Bearbeitung
A1: Artikelnr. | B1: PLU | C1: Typ | D1: SAP Nr | E1: Vorschlag Einkauf Text 1 | F1: Vorschlag Einkauf Text 2 | G1: Menge | H1: EAN Code kg 21er | I1: EAN Code 29er | J1: Coli EAN | K1: Vorschlag für Bezeichnung in Deutsch (Kasentext) | L1: Verkaufsmenge gemäss Angaben Lieferant | M1: Kassentext (D) | N1: Gestellbeschriftung 1 (D) | O1: Gestellbeschriftung 2 (D) | P1: Kassentext (D) | Q1: Gestellbeschriftung 1 (F) | R1: Gestellbeschriftung 2 (F) | S1: Kassentext (I) | T1: Gestellbeschriftung 1 (I) | U1: Gestellbeschriftung 2 (I) | V1: Lieferant | W1: Grund- einheit | X1: WG | Y1: MWSt | Z1: VP | AA1: Altersbegrenz. | AB1: Gewichtsartikel | AC1: Barcode ohne Prüfziffer | AD1: Rabatt zugelassen | AE1: Gratis- artikel | AF1: Rückgabe zugelassen | AG1: Preisänder. Kasse erlaub. | AH1: Shop-in-Shop Artikel | AI1: Depot | AJ1: Regio- oder Fremdartikel | AK1: Etiketten- druck | AL1: Artikel gem. LMV
A2: 801722 | B2: 1006097 | C2: F | D2: 1006097 | E2: Bio Zitronen Stück 1 Stück
A3: 801003 | C3: F | D3: 1006284 | E3: Melonen Galia 1 Stück
A4: 800084 | C4: F | D4: 1006007 | E4: Avocado 1 Stück
A5: 800896 | C5: F | D5: 1006180 | E5: Limetten Stück 1 Stück
A6: 800988 | C6: F | D6: 1006035 | E6: Melonen Cantaloupe 1 Stück
A7: 800198 | C7: F | D7: 1006173 | E7: Granatapfel 1 Stück
A8: 800143 | C8: F | D8: 1006213 | E8: Grapefruit 1 Stück
A9: 800885 | C9: F | D9: 1006045 | E9: Kiwis Offenverkauf 1 Stück
A10: 801967 | C10: F | D10: 1006119 | E10: Honigmelone gelb 1 Stück
A11: 800848 | C11: F | D11: 1006086 | E11: Ananas 1 Stück
A12: 800586 | C12: F | D12: 1006059 | E12: Melone Piel de Sapo 1 Stück
A13: 801880 | C13: F | D13: 1100346 | E13: Kiwi Gold Stk
A14: 802608 | C14: F | D14: 1100307 | E14: Avocado Bio Stk
... A23: 800167 | C23: G | D23: 1006232 | E23: Knoblauch 1 Stück

Sheet System-Informationen
A1: Navision (Ist)
A27: MDM (Neu) für nationale Daten
A29: Es stehen folgende Felder zur Verfügung
A30: Gestellbeschriftung 1 | B30: Maximal 22 Zeichen, wenn Markenartikel, so steht dieser Name zuerst
A31: Gestellbeschriftung 2 | B31: Maximal 22 Zeichen, für die restliche Bezeichnung
A32: Gestellbeschriftung 3 | B32: 4-8 Zeichen (für Menge)
A33: Text für Belege | B33: = Text für Kassenzettel, maximal 28 Zeichen. Setzt sicht aus Gestellbeschriftung 1+2+3 zusammen und wird automatisch gekürzt (Anpassungen möglich)
A62: MDM (Neu) Regio App

Sheet Einheiten Nav
A1: Artikelnr. | B1: Code | C1: Einheit aktiv (intern) | D1: Menge pro Basiseinheit | E1: Einheit aktiv (POS) | F1: Gestelletikette drucken | G1: Etiketten-Druck am | H1: Beschreibung | I1: Masterbarcode | J1: Anzahl Barcodes | K1: Einheit Typ | L1: CU Zuweisung | M1: CU BME | N1: CU/TU Verhältnis | O1: Belieferung durch MVN | P1: ProduktNummerWaage | Q1: Netto Gewicht | R1: Brutto Gewicht | S1: OP verfügbar | T1: Colis je Lage OP | U1: Lagen je OP | V1: Colis je OP | W1: Basiseinheiten je OP | X1: HP verfügbar | Y1: Colis per Lage HP | Z1: Lagen je HP | AA1: Colis je HP | AB1: Basiseinheiten je HP | AC1: Länge (mm) | AD1: Breite (mm) | AE1: Höhe (mm) | AF1: Volumen (m3) | AG1: Pfandartikel | AH1: Umgebinde Colis | AI1: Pfandartikel und Umgebinde Colis
A2: 661105 | B2: STK | C2: Ja | D2: 1 | E2: Ja | F2: Ja | H2: Papaya Offenverkauf kg | I2: 2006611050005 | J2: 3 | O2: Nein | P2: 157 | Q2: 1 | R2: 1.05 | AC2: 20 | AD2: 10 | AE2: 10
A3: 661334 | B3: STK | C3: Ja | D3: 1 | E3: Ja | F3: Ja | H3: Maniok kg | I3: 2006613340005 | J3: 3 | O3: Nein | P3: 251 | Q3: 1 | R3: 1.05 | AC3: 100 | AD3: 100 | AE3: 100 | AF3: 0.001
A4: 661455 | B4: STK | C4: Ja | D4: 1 | E4: Ja | F4: Ja | H4: Bio Mini Wassermelone kg | I4: 2006614550007 | J4: 3 | O4: Nein | P4: 158 | Q4: 2 | R4: 2.05 | AC4: 100 | AD4: 100 | AE4: 100 | AF4: 0.001
A5: 790004 | B5: STK | C5: Ja | D5: 1 | E5: Ja | F5: Nein | H5: Test Waage 31. Roger | I5: 2007900040011 | J5: 1 | O5: Nein | P5: 141 | Q5: 0 | R5: 1
A6: 790005 | B6: STK | C6: Ja | D6: 1 | E6: Nein | F6: Nein | H6: Test Waage 11.6. Roger | J6: 1 | O6: Nein | P6: 142 | Q6: 0 | R6: 1
A7: 800269 | B7: STK | C7: Ja | D7: 1 | E7: Ja | F7: Ja | H7: Wassermelonen kg | I7: 2008002690012 | J7: 4 | K7: CU | O7: Nein | P7: 152 | Q7: 1 | R7: 1 | AC7: 100 | AD7: 100 | AE7: 100 | AF7: 0.001
A8: 800471 | B8: STK | C8: Ja | D8: 1 | E8: Ja | F8: Ja | H8: Zwiebeln | I8: 2008004710008 | J8: 2 | O8: Nein | P8: 244 | Q8: 0 | R8: 1 | AC8: 600 | AD8: 400 | AE8: 160 | AF8: 0.038
A9: 800693 | B9: STK | C9: Ja | D9: 1 | E9: Ja | F9: Ja | H9: Pflaumen Offenverkauf kg | I9: 2008006930008 | J9: 3 | K9: CU | O9: Nein | P9: 120 | Q9: 1 | R9: 1 | AC9: 600 | AD9: 400 | AE9: 120 | AF9: 0.029
A10: 800705 | B10: STK | C10: Ja | D10: 1 | E10: Ja | F10: Ja | H10: Tomaten Spezial Offenverk kg | I10: 2008007050002 | J10: 3 | K10: CU | O10: Nein | P10: 207 | Q10: 1 | R10: 1 | AC10: 300 | AD10: 400 | AE10: 120 | AF10: 0.014
A11: 800708 | B11: STK | C11: Ja | D11: 1 | E11: Ja | F11: Ja | H11: Zwetschgen Offenverkauf kg | I11: 2008007080009 | J11: 3 | K11: CU | O11: Nein | P11: 111 | Q11: 1 | R11: 1 | AC11: 100 | AD11: 100 | AE11: 100 | AF11: 0.001
A12: 800709 | B12: STK | C12: Ja | D12: 1 | E12: Ja | F12: Ja | H12: Süss-Kartoffeln Offenver kg | I12: 2008007090008 | J12: 3 | K12: CU | O12: Nein | P12: 208 | Q12: 1 | R12: 1 | AC12: 100 | AD12: 100 | AE12: 100 | AF12: 0.001
A13: 800717 | B13: STK | C13: Ja | D13: 1 | E13: Ja | F13: Ja | H13: Pfirsiche Offenverkauf kg | I13: 2008007170007 | J13: 3 | K13: CU | O13: Nein | P13: 109 | Q13: 1 | R13: 1 | AC13: 600 | AD13: 400 | AE13: 120 | AF13: 0.029
A14: 800719 | B14: STK | C14: Ja | D14: 1 | E14: Ja | F14: Nein | H14: Satsumas Offenverkauf kg | I14: 2008007190005 | J14: 2 | O14: Nein | P14: 124 | Q14: 0 | R14: 0.1
A15: 800753 | B15: STK | C15: Ja | D15: 1 | E15: Ja | F15: Ja | H15: Birnen Abate Fetel | I15: 2008007530009 | J15: 2 | O15: Nein | P15: 114 | Q15: 0 | R15: 1
A16: 800754 | B16: STK | C16: Ja | D16: 1 | E16: Ja | F16: Ja | H16: Äpfel Pink Lady | I16: 2008007540008 | J16: 2 | O16: Nein | P16: 115 | Q16: 0 | R16: 1
A17: 800755 | B17: STK | C17: Ja | D17: 1 | E17: Ja | F17: Ja | H17: Äpfel rot offen Sorte sie kg | I17: 2008007550007 | J17: 3 | K17: CU | O17: Nein | P17: 122 | Q17: 1 | R17: 1 | AC17: 300 | AD17: 400 | AE17: 120 | AF17: 0.014
A18: 800785 | B18: STK | C18: Ja | D18: 1 | E18: Ja | F18: Ja | H18: Satsumas | I18: 2008007850008 | J18: 2 | O18: Nein | P18: 103 | Q18: 0 | R18: 0.1
A19: 800806 | B19: STK | C19: Ja | D19: 1 | E19: Ja | F19: Ja | H19: Zwiebeln Offenverkauf kg | I19: 2008008060000 | J19: 3 | K19: CU | O19: Nein | P19: 213 | Q19: 1 | R19: 1 | AC19: 300 | AD19: 400 | AE19: 120 | AF19: 0.014
A20: 800807 | B20: STK | C20: Ja | D20: 1 | E20: Ja | F20: Ja | H20: Birnen offen Sorte siehe kg | I20: 2008008070009 | J20: 3 | K20: CU | O20: Nein | P20: 119 | Q20: 1 | R20: 1 | AC20: 300 | AD20: 400 | AE20: 120 | AF20: 0.014
A21: 800816 | B21: STK | C21: Ja | D21: 1 | E21: Ja | F21: Nein | H21: Orangen | I21: 2008008160007 | J21: 2 | O21: Nein | P21: 117 | Q21: 0 | R21: 1
A22: 800822 | B22: STK | C22: Ja | D22: 1 | E22: Ja | F22: Ja | H22: Auberginen Offenverkauf kg | I22: 2008008220008 | J22: 3 | K22: CU | O22: Nein | P22: 212 | Q22: 1 | R22: 1 | AC22: 100 | AD22: 100 | AE22: 100 | AF22: 0.001
A23: 800826 | B23: STK | C23: Ja | D23: 1 | E23: Ja | F23: Nein | H23: Spitzpaprika rot Offenverka | I23: 2008008260004 | J23: 2 | O23: Nein | P23: 215 | Q23: 0 | R23: 1
A24: 800827 | B24: STK | C24: Ja | D24: 1 | E24: Ja | F24: Nein | H24: Lollo rot/grün | I24: 2008008270003 | J24: 2 | O24: Nein | P24: 216 | Q24: 0 | R24: 1
A25: 800828 | B25: STK | C25: Ja | D25: 1 | E25: Nein | F25: Nein | H25: Endiviensalat | J25: 2 | O25: Nein | P25: 217 | Q25: 0 | R25: 1
A26: 800834 | B26: STK | C26: Ja | D26: 1 | E26: Ja | F26: Ja | H26: Chiquita Bananen Offenver kg | I26: 2008008340003 | J26: 3 | K26: CU | O26: Nein | P26: 118 | Q26: 1 | R26: 1 | AC26: 600 | AD26: 400 | AE26: 120 | AF26: 0.029
A27: 800855 | B27: STK | C27: Ja | D27: 1 | E27: Ja | F27: Nein | H27: Flachpfirsiche | I27: 2008008550006 | J27: 2 | O27: Nein | P27: 123 | Q27: 0 | R27: 1
A28: 800882 | B28: STK | C28: Ja | D28: 1 | E28: Ja | F28: Ja | H28: Tomaten Peretti Offenver kg | I28: 2008008820000 | J28: 3 | K28: CU | O28: Nein | P28: 214 | Q28: 1 | R28: 1 | AC28: 300 | AD28: 400 | AE28: 120 | AF28: 0.014
A29: 800883 | B29: STK | C29: Ja | D29: 1 | E29: Ja | F29: Ja | H29: Nektarinen flach | I29: 2008008830009 | J29: 2 | O29: Nein | P29: 126 | Q29: 0 | R29: 1
A30: 800884 | B30: STK | C30: Ja | D30: 1 | E30: Ja | F30: Ja | H30: Trauben weiss Offenverka kg | I30: 2008008840008 | J30: 3 | K30: CU | O30: Nein | P30: 127 | Q30: 1 | R30: 1 | AC30: 300 | AD30: 400 | AE30: 120 | AF30: 0.014
A31: 800893 | B31: STK | C31: Ja | D31: 1 | E31: Ja | F31: Ja | H31: Trauben dunkel Offenverk kg | I31: 2008008930006 | J31: 3 | K31: CU | O31: Nein | P31: 132 | Q31: 1 | R31: 1 | AC31: 100 | AD31: 100 | AE31: 100 | AF31: 0.001
A32: 800917 | B32: STK | C32: Ja | D32: 1 | E32: Ja | F32: Ja | H32: Blumenkohl | I32: 2008009170005 | J32: 2 | O32: Nein | P32: 218 | Q32: 0 | R32: 1
A33: 800968 | B33: STK | C33: Ja | D33: 1 | E33: Ja | F33: Ja | H33: Rispentomaten Offenverka kg | I33: 2008009680009 | J33: 3 | K33: CU | O33: Nein | P33: 201 | Q33: 1 | R33: 1 | AC33: 600 | AD33: 400 | AE33: 120 | AF33: 0.029
A34: 800970 | B34: STK | C34: Ja | D34: 1 | E34: Ja | F34: Ja | H34: Äpfel Kl. I | I34: 2008009700004 | J34: 2 | O34: Nein | P34: 100 | Q34: 0 | R34: 0.5
A35: 800971 | B35: STK | C35: Ja | D35: 1 | E35: Ja | F35: Ja | H35: Birnen Kl. I | I35: 2008009710003 | J35: 2 | O35: Nein | P35: 101 | Q35: 0 | R35: 1
A36: 800972 | B36: STK | C36: Ja | D36: 1 | E36: Ja | F36: Ja | H36: Clementinen | I36: 2008009720002 | J36: 2 | O36: Nein | P36: 102 | Q36: 0 | R36: 0.1
A37: 800975 | B37: STK | C37: Ja | D37: 1 | E37: Ja | F37: Ja | H37: Nektarinen Offenverkauf kg | I37: 2008009750009 | J37: 3 | K37: CU | O37: Nein | P37: 107 | Q37: 1 | R37: 1 | AC37: 600 | AD37: 400 | AE37: 120 | AF37: 0.029
A38: 800976 | B38: STK | C38: Ja | D38: 1 | E38: Ja | F38: Ja | H38: Äpfel Kl. I | I38: 2008009760015 | J38: 2 | O38: Nein | P38: 110 | Q38: 0 | R38: 0.5
A39: 800978 | B39: STK | C39: Ja | D39: 1 | E39: Ja | F39: Nein | H39: Lauch grün | I39: 2008009780006 | J39: 2 | O39: Nein | P39: 211 | Q39: 0 | R39: 1
A40: 801071 | B40: STK | C40: Ja | D40: 1 | E40: Ja | F40: Ja | H40: Orangen Blond Offenverka kg | I40: 2008010710009 | J40: 3 | K40: CU | O40: Nein | P40: 106 | Q40: 1 | R40: 1 | AC40: 600 | AD40: 400 | AE40: 120 | AF40: 0.029
A41: 801072 | B41: STK | C41: Ja | D41: 1 | E41: Ja | F41: Ja | H41: Marroni | I41: 2008010720008 | J41: 2 | O41: Nein | P41: 112 | Q41: 0 | R41: 1 | AC41: 600 | AD41: 400
A42: 801073 | B42: STK | C42: Ja | D42: 1 | E42: Ja | F42: Ja | H42: Broccoli Offenverkauf kg | I42: 2008010730007 | J42: 3 | K42: CU | O42: Nein | P42: 209 | Q42: 1 | R42: 1 | AC42: 100 | AD42: 100 | AE42: 100 | AF42: 0.001
A43: 801074 | B43: STK | C43: Ja | D43: 1 | E43: Ja | F43: Ja | H43: Blumenkohl Offenverkauf kg | I43: 2008010740006 | J43: 3 | K43: CU | O43: Nein | P43: 210 | Q43: 1 | R43: 1 | AC43: 100 | AD43: 100 | AE43: 100 | AF43: 0.001
A44: 801075 | B44: STK | C44: Ja | D44: 1 | E44: Ja | F44: Ja | H44: Kaki Persimon | I44: 2008010750005 | J44: 2 | O44: Nein | P44: 113 | Q44: 0 | R44: 1
A45: 801088 | B45: STK | C45: Ja | D45: 1 | E45: Ja | F45: Ja | H45: RAINFOREST Bananen | I45: 2008010880016 | J45: 3 | O45: Nein | P45: 131 | Q45: 0 | R45: 1
A46: 801091 | B46: STK | C46: Ja | D46: 1 | E46: Ja | F46: Ja | H46: Orangen Tarocco | I46: 2008010910003 | J46: 2 | O46: Nein | P46: 116 | Q46: 0 | R46: 1
A47: 801104 | B47: STK | C47: Ja | D47: 1 | E47: Ja | F47: Ja | H47: Fenchel Offenverkauf kg | I47: 2008011040013 | J47: 3 | K47: CU | O47: Nein | P47: 200 | Q47: 1 | R47: 1 | AC47: 100 | AD47: 100 | AE47: 100 | AF47: 0.001
A48: 801105 | B48: STK | C48: Ja | D48: 1 | E48: Ja | F48: Ja | H48: Peperoni rot Offenverkau kg | I48: 2008011050005 | J48: 3 | K48: CU | O48: Nein | P48: 202 | Q48: 1 | R48: 1 | AC48: 100 | AD48: 100 | AE48: 100 | AF48: 0.001
A49: 801106 | B49: STK | C49: Ja | D49: 1 | E49: Ja | F49: Ja | H49: Peperoni gelb | I49: 2008801106004 | J49: 2 | O49: Nein | P49: 203 | Q49: 0 | R49: 1
A50: 801107 | B50: STK | C50: Ja | D50: 1 | E50: Ja | F50: Ja | H50: Fleischtomaten | I50: 2008011070003 | J50: 2 | O50: Nein | P50: 204 | Q50: 0 | R50: 0.5
A51: 801108 | B51: STK | C51: Ja | D51: 1 | E51: Ja | F51: Ja | H51: Karotten | I51: 2008011080002 | J51: 2 | O51: Nein | P51: 205 | Q51: 0 | R51: 1
A52: 801109 | B52: STK | C52: Ja | D52: 1 | E52: Ja | F52: Ja | H52: Äpfel Golden Offenverkauf kg | I52: 2008011090001 | J52: 3 | K52: CU | O52: Nein | P52: 105 | Q52: 1 | R52: 1 | AC52: 100 | AD52: 100 | AE52: 100 | AF52: 0.001
A53: 801110 | B53: STK | C53: Ja | D53: 1 | E53: Ja | F53: Ja | H53: Zucchetti Offenverkauf kg | I53: 2008011100014 | J53: 3 | K53: CU | O53: Nein | P53: 206 | Q53: 1 | R53: 1 | AC53: 300 | AD53: 400 | AE53: 120 | AF53: 0.014
A54: 801111 | B54: STK | C54: Ja | D54: 1 | E54: Ja | F54: Ja | H54: Aprikosen Offenverkauf kg | I54: 2008011110006 | J54: 3 | K54: CU | O54: Nein | P54: 108 | Q54: 1 | R54: 1 | AC54: 100 | AD54: 100 | AE54: 100 | AF54: 0.001
A55: 801292 | B55: STK | C55: Ja | D55: 1 | E55: Ja | F55: Nein | H55: Kohlraben Offenverkauf kg | I55: 2008012920000 | J55: 2 | O55: Nein | P55: 219 | Q55: 0 | R55: 1
A56: 801293 | B56: STK | C56: Ja | D56: 1 | E56: Ja | F56: Nein | H56: Kürbis Hokkaido ca. 1kg | I56: 2008012930009 | J56: 4 | K56: CU | O56: Nein | P56: 239 | Q56: 1 | R56: 1 | AC56: 100 | AD56: 100 | AE56: 100 | AF56: 0.001
A57: 801307 | B57: STK | C57: Ja | D57: 1 | E57: Ja | F57: Ja | H57: Kürbis Butternuss ca.1kg | I57: 2008013070001 | J57: 4 | K57: CU | O57: Nein | P57: 240 | Q57: 1 | R57: 1 | AC57: 100 | AD57: 100 | AE57: 100 | AF57: 0.001
A58: 801365 | B58: STK | C58: Ja | D58: 1 | E58: Ja | F58: Nein | H58: Spanische Erdnüsse Offen kg | I58: 2008013650005 | J58: 2 | O58: Nein | P58: 133 | Q58: 0 | R58: 1
A59: 801366 | B59: STK | C59: Ja | D59: 1 | E59: Ja | F59: Nein | H59: Baumnüsse Offenverkauf kg | I59: 2008013660004 | J59: 2 | O59: Nein | P59: 134 | Q59: 0 | R59: 1
A60: 801546 | B60: STK | C60: Ja | D60: 1 | E60: Ja | F60: Ja | H60: Kabis Offenverkauf kg | I60: 2008015460008 | J60: 3 | K60: CU | O60: Nein | P60: 220 | Q60: 1 | R60: 1 | AC60: 100 | AD60: 100 | AE60: 100 | AF60: 0.001
A61: 801572 | B61: STK | C61: Ja | D61: 1 | E61: Ja | F61: Ja | H61: Bio Ingwer Offenverkau kg | I61: 2008015720003 | J61: 4 | K61: CU | O61: Nein | P61: 237 | Q61: 1 | R61: 1 | AC61: 100 | AD61: 100 | AE61: 100 | AF61: 0.001
A62: 801578 | B62: STK | C62: Ja | D62: 1 | E62: Ja | F62: Ja | H62: Denner Bananen Offenverka kg | I62: 2008015780007 | J62: 3 | K62: CU | O62: Nein | P62: 153 | Q62: 1 | R62: 1 | AC62: 100 | AD62: 100 | AE62: 100 | AF62: 0.001
A63: 801702 | B63: STK | C63: Ja | D63: 1 | E63: Ja | F63: Nein | H63: Kirschen Offenverkauf kg | I63: 2008017020002 | J63: 2 | O63: Nein | P63: 149 | Q63: 0 | R63: 1
A64: 801746 | B64: STK | C64: Ja | D64: 1 | E64: Ja | F64: Ja | H64: IP Suisse Zwiebeln Offenver | I64: 2008017460006 | J64: 2 | O64: Nein | P64: 243 | Q64: 0 | R64: 1
A65: 801766 | B65: STK | C65: Ja | D65: 1 | E65: Ja | F65: Ja | H65: Zucchetti rund Offenverk kg | I65: 2008017660000 | J65: 3 | K65: CU | O65: Nein | P65: 241 | Q65: 1 | R65: 1 | AC65: 300 | AD65: 400 | AE65: 120 | AF65: 0.014
A66: 801773 | B66: STK | C66: Ja | D66: 1 | E66: Ja | F66: Ja | H66: Quitten kg | I66: 2008017730000 | J66: 3 | K66: CU | O66: Nein | P66: 154 | Q66: 1 | R66: 1 | AC66: 600 | AD66: 400 | AE66: 120 | AF66: 0.029
A67: 801793 | B67: STK | C67: Ja | D67: 1 | E67: Ja | F67: Ja | H67: IP-Suisse Zwiebeln Offenv kg | I67: 2008017930004 | J67: 3 | K67: CU | O67: Nein | P67: 245 | Q67: 1 | R67: 1 | AC67: 100 | AD67: 100 | AE67: 100 | AF67: 0.001
A68: 801800 | B68: STK | C68: Ja | D68: 1 | E68: Ja | F68: Ja | H68: Bio Orangen Offenverkauf kg | I68: 2008018000003 | J68: 4 | K68: CU | O68: Nein | P68: 155 | Q68: 1 | R68: 1 | AC68: 600 | AD68: 400 | AE68: 100 | AF68: 0.024
A69: 801806 | B69: STK | C69: Ja | D69: 1 | E69: Ja | F69: Ja | H69: Spitzkabis Offenverkauf kg | I69: 2008018060007 | J69: 3 | K69: CU | O69: Nein | P69: 248 | Q69: 1 | R69: 1 | AC69: 100 | AD69: 100 | AE69: 100 | AF69: 0.001
A70: 801911 | B70: STK | C70: Ja | D70: 1 | E70: Ja | F70: Ja | H70: Bio Bananen Offenverkauf kg | I70: 2008019110008 | J70: 3 | K70: CU | O70: Nein | P70: 156 | Q70: 1 | R70: 1 | AC70: 600 | AD70: 400 | AE70: 120 | AF70: 0.029
A71: 802051 | B71: STK | C71: Ja | D71: 1 | E71: Ja | F71: Ja | H71: Peperoni diverse Offenv | I71: 2008020510002 | J71: 2 | O71: Nein | P71: 230 | Q71: 0 | R71: 1
A72: 802082 | B72: STK | C72: Ja | D72: 1 | E72: Ja | F72: Nein | H72: Spargeln weiss Offenve | I72: 2008020820002 | J72: 2 | O72: Nein | P72: 232 | Q72: 0 | R72: 1
A73: 802083 | B73: STK | C73: Ja | D73: 1 | E73: Ja | F73: Nein | H73: Stangensellerie Offenver kg | I73: 2008020830001 | J73: 3 | K73: CU | O73: Nein | P73: 233 | Q73: 1 | R73: 1 | AC73: 100 | AD73: 100 | AE73: 100 | AF73: 0.001
A74: 802171 | B74: STK | C74: Ja | D74: 1 | E74: Ja | F74: Nein | H74: Mini Bananen Offenverka | I74: 2008021710005 | J74: 2 | O74: Nein | P74: 150 | Q74: 0 | R74: 1
A75: 802173 | B75: STK | C75: Ja | D75: 1 | E75: Ja | F75: Nein | H75: Kartoffeln Offenverkauf kg | I75: 2008021730003 | J75: 2 | O75: Nein | P75: 231 | Q75: 0 | R75: 1
A76: 802175 | B76: STK | C76: Ja | D76: 1 | E76: Ja | F76: Ja | H76: Knoblauch frisch Offenver kg | I76: 2008021750001 | J76: 3 | K76: CU | O76: Nein | P76: 234 | Q76: 1 | R76: 1 | AC76: 100 | AD76: 100 | AE76: 100 | AF76: 0.001
A77: 802189 | B77: STK | C77: Ja | D77: 1 | E77: Ja | F77: Ja | H77: Knollensellerie Offenv kg | I77: 2008021890004 | J77: 4 | K77: CU | O77: Nein | P77: 238 | Q77: 1 | R77: 1 | AC77: 300 | AD77: 400 | AE77: 120 | AF77: 0.014
A78: 802317 | B78: STK | C78: Ja | D78: 1 | E78: Ja | F78: Ja | H78: IP-Suisse Kürbis Butt ca.1kg | I78: 2008023170005 | J78: 4 | K78: CU | O78: Nein | P78: 246 | Q78: 1 | R78: 1 | AC78: 100 | AD78: 100 | AE78: 100 | AF78: 0.001
A79: 802328 | B79: STK | C79: Ja | D79: 1 | E79: Ja | F79: Ja | H79: Bio Kürbis Butternuss ca.1kg | I79: 2008023280001 | J79: 3 | K79: CU | O79: Nein | P79: 249 | Q79: 1 | R79: 1 | AC79: 100 | AD79: 100 | AE79: 100 | AF79: 0.001
A80: 802412 | B80: STK | C80: Ja | D80: 1 | E80: Ja | F80: Ja | H80: IP-Suisse Kürbis Butt ca.1kg | I80: 2008024120009 | J80: 3 | K80: CU | O80: Nein | P80: 250 | Q80: 1 | R80: 1 | AC80: 100 | AD80: 100 | AE80: 100 | AF80: 0.001
A81: 802515 | B81: STK | C81: Ja | D81: 1 | E81: Ja | F81: Ja | H81: IP Suisse Knollenselle Of kg | I81: 2008025150005 | J81: 4 | K81: CU | O81: Nein | P81: 247 | Q81: 1 | R81: 1 | AC81: 300 | AD81: 400 | AE81: 120 | AF81: 0.014
A82: 802780 | B82: STK | C82: Ja | D82: 1 | E82: Ja | F82: Nein | H82: IP-Suisse Lauch Offenverk kg | I82: 2008027800007 | J82: 2 | O82: Nein | P82: 223 | Q82: 0 | R82: 1
A83: 802781 | B83: STK | C83: Ja | D83: 1 | E83: Ja | F83: Nein | H83: IP-Suisse Zucchetti Offen kg | I83: 2008027810006 | J83: 2 | O83: Nein | P83: 224 | Q83: 0 | R83: 1
A84: 802782 | B84: STK | C84: Ja | D84: 1 | E84: Ja | F84: Nein | H84: IP-Suisse Fenchel Offenve kg | I84: 2008027820005 | J84: 2 | O84: Nein | P84: 225 | Q84: 0 | R84: 1
A85: 802783 | B85: STK | C85: Ja | D85: 1 | E85: Ja | F85: Nein | H85: IP-Suisse Kohlraben Offen kg | I85: 2008027830004 | J85: 2 | O85: Nein | P85: 226 | Q85: 0 | R85: 1
A86: 802784 | B86: STK | C86: Ja | D86: 1 | E86: Ja | F86: Nein | H86: IP-Suisse Kürbis Hok ca. 1kg | I86: 2008027840003 | J86: 4 | K86: CU | O86: Nein | P86: 227 | Q86: 1 | R86: 1 | AC86: 300 | AD86: 400 | AE86: 120 | AF86: 0.014
A87: 802806 | B87: STK | C87: Ja | D87: 1 | E87: Ja | F87: Ja | H87: Tomaten Cherry Mix Off | I87: 2008028060004 | J87: 2 | O87: Nein | P87: 229 | Q87: 0 | R87: 1
A88: 802807 | B88: STK | C88: Ja | D88: 1 | E88: Ja | F88: Nein | H88: Tomaten Cherry gelb | I88: 2008028070003 | J88: 2 | O88: Nein | P88: 235 | Q88: 0 | R88: 1
A89: 802808 | B89: STK | C89: Ja | D89: 1 | E89: Ja | F89: Ja | H89: Tomaten Cherry orange Off kg | I89: 2008028080002 | J89: 2 | O89: Nein | P89: 236 | Q89: 0 | R89: 1
A90: 802842 | B90: STK | C90: Ja | D90: 1 | E90: Ja | F90: Ja | H90: IP-Suisse Kabis Offenverk kg | I90: 2008028420006 | J90: 3 | K90: CU | O90: Nein | P90: 228 | Q90: 1 | R90: 1 | AC90: 100 | AD90: 100 | AE90: 100 | AF90: 0.001
A91: 803113 | B91: STK | C91: Ja | D91: 1 | E91: Ja | F91: Ja | H91: Äpfel Gala geschüttet kg | I91: 2008031130008 | J91: 2 | O91: Nein | P91: 135 | Q91: 0 | R91: 1
A92: 803116 | B92: STK | C92: Ja | D92: 1 | E92: Ja | F92: Ja | H92: Äpfel Gala Kl.I | I92: 2008031160005 | J92: 2 | O92: Nein | P92: 136 | Q92: 0 | R92: 1
A93: 803119 | B93: STK | C93: Ja | D93: 1 | E93: Nein | F93: Nein | H93: Champignons weiss offen kg | J93: 2 | O93: Nein | P93: 221 | Q93: 0
A94: 803120 | B94: STK | C94: Ja | D94: 1 | E94: Nein | F94: Nein | H94: Champignons braun offen kg | J94: 2 | O94: Nein | P94: 222 | Q94: 0
A95: 803122 | B95: STK | C95: Ja | D95: 1 | E95: Ja | F95: Nein | H95: Äpfel Golden geschüttet kg | I95: 2008031220006 | J95: 2 | O95: Nein | P95: 138 | Q95: 0 | R95: 1
A96: 803123 | B96: STK | C96: Ja | D96: 1 | E96: Ja | F96: Nein | H96: Äpfel Golden Kl.I geschüt kg | I96: 2008031230005 | J96: 2 | O96: Nein | P96: 139 | Q96: 0 | R96: 1
A97: 803124 | B97: STK | C97: Ja | D97: 1 | E97: Ja | F97: Nein | H97: Äpfel Granny Smith geschü kg | I97: 2008031240004 | J97: 2 | O97: Nein | P97: 140 | Q97: 0 | R97: 1
A98: 803125 | B98: STK | C98: Ja | D98: 1 | E98: Ja | F98: Nein | H98: Äpfel Braeburn Kl 1 gesch kg | I98: 2007031250006 | J98: 2 | O98: Nein | P98: 143 | Q98: 0 | R98: 1
A99: 803126 | B99: STK | C99: Ja | D99: 1 | E99: Ja | F99: Nein | H99: Äpfel Granny Smith Kl.I m kg | I99: 2008031260002 | J99: 2 | O99: Nein | P99: 144 | Q99: 0 | R99: 1
A100: 803127 | B100: STK | C100: Ja | D100: 1 | E100: Ja | F100: Ja | H100: Äpfel Granny Smith Kl.I L kg | I100: 2008031270001 | J100: 2 | O100: Nein | P100: 145 | Q100: 0 | R100: 1
...

Sheet Barcodes Nav
A1: Artikelnr. | B1: Barcode Type | C1: Code | D1: Barocde aktiv (POS) | E1: Master | F1: Warengruppe | G1: Unterwarengruppe | H1: Status | I1: Variantencode | J1: Einheitencode | K1: Menge pro Einheit | L1: Aktiv gesetzt von | M1: Aktiv gesetzt am
A2: 640332 | B2: PLU | C2: 332 | D2: Nein | E2: Nein | F2: 60 | G2: 40 | H2: 96 | J2: STK | K2: 1
A3: 661105 | B3: PLU | C3: 157 | D3: Ja | E3: Nein | F3: 6 | G3: 95 | H3: 7 | J3: STK | K3: 1
A4: 661334 | B4: PLU | C4: 251 | D4: Ja | E4: Nein | F4: 6 | G4: 95 | H4: 0 | J4: STK | K4: 1
A5: 661455 | B5: PLU | C5: 158 | D5: Ja | E5: Nein | F5: 6 | G5: 75 | H5: 7 | J5: STK | K5: 1
A6: 800269 | B6: PLU | C6: 152 | D6: Ja | E6: Nein | F6: 6 | G6: 75 | H6: 0 | J6: STK | K6: 1
A7: 800693 | B7: PLU | C7: 120 | D7: Ja | E7: Nein | F7: 6 | G7: 95 | H7: 0 | J7: STK | K7: 1
A8: 800705 | B8: PLU | C8: 207 | D8: Ja | E8: Nein | F8: 6 | G8: 95 | H8: 0 | J8: STK | K8: 1
A9: 800708 | B9: PLU | C9: 111 | D9: Ja | E9: Nein | F9: 6 | G9: 95 | H9: 7 | J9: STK | K9: 1
A10: 800709 | B10: PLU | C10: 208 | D10: Ja | E10: Nein | F10: 6 | G10: 95 | H10: 0 | J10: STK | K10: 1
A11: 800717 | B11: PLU | C11: 109 | D11: Ja | E11: Nein | F11: 6 | G11: 95 | H11: 0 | J11: STK | K11: 1
A12: 800755 | B12: PLU | C12: 122 | D12: Ja | E12: Nein | F12: 6 | G12: 95 | H12: 0 | J12: STK | K12: 1
A13: 800806 | B13: PLU | C13: 213 | D13: Ja | E13: Nein | F13: 6 | G13: 95 | H13: 7 | J13: STK | K13: 1
... A51: 803456 | B51: PLU | C51: 242 | D51: Ja | E51: Nein | F51: 6 | G51: 20 | H51: 7 | J51: STK | K51: 1
A52: 999892 | B52: PLU | C52: 892 | D52: Ja | E52: Nein | F52: 87 | G52: 10 | H52: 20 | J52: COLIS | K52: 1 | L52: EGLI | M52: 40484.436
A53: 999893 | B53: PLU | C53: 903 | D53: Nein | E53: Ja | F53: 87 | G53: 20 | H53: 90 | J53: STK | K53: 1
A54: 999894 | B54: PLU | C54: 1128 | D54: Nein | E54: Ja | F54: 79 | G54: 999 | H54: 90 | J54: COLIS | K54: 1
A55: 999901 | B55: PLU | C55: 1 | D55: Ja | E55: Nein | F55: 1 | G55: 200 | H55: 7 | J55: COLIS | K55: 1
A56: 999903 | B56: PLU | C56: 3 | D56: Ja | E56: Nein | F56: 3 | G56: 95 | H56: 7 | J56: COLIS | K56: 1
A57: 999904 | B57: PLU | C57: 4 | D57: Ja | E57: Nein | F57: 4 | G57: 40 | H57: 15 | J57: COLIS | K57: 1
A58: 999905 | B58: PLU | C58: 5 | D58: Ja | E58: Nein | F58: 5 | G58: 999 | H58: 7 | J58: COLIS | K58: 1 | L58: TOMASCHETT | M58: 40912.337
A59: 999906 | B59: PLU | C59: 6 | D59: Ja | E59: Nein | F59: 6 | G59: 999 | H59: 15 | J59: COLIS | K59: 1
A60: 999906 | B60: PLU | C60: 80 | D60: Ja | E60: Nein | F60: 6 | G60: 999 | H60: 15 | J60: COLIS | K60: 1
A61: 999907 | B61: PLU | C61: 7 | D61: Ja | E61: Nein | F61: 7 | G61: 240 | H61: 7 | J61: COLIS | K61: 1
A62: 999908 | B62: PLU | C62: 8 | D62: Ja | E62: Nein | F62: 8 | G62: 260 | H62: 7 | J62: COLIS | K62: 1
A63: 999909 | B63: PLU | C63: 9 | D63: Ja | E63: Nein | F63: 9 | G63: 150 | H63: 7 | J63: COLIS | K63: 1
A64: 999910 | B64: PLU | C64: 10 | D64: Ja | E64: Nein | F64: 10 | G64: 900 | H64: 7 | J64: COLIS | K64: 1
A65: 999920 | B65: PLU | C65: 20 | D65: Ja | E65: Nein | F65: 20 | G65: 999 | H65: 7 | J65: COLIS | K65: 1 | L65: EGLI | M65: 43797.515
A66: 999931 | B66: PLU | C66: 31 | D66: Ja | E66: Nein | F66: 31 | G66: 999 | H66: 7 | J66: COLIS | K66: 1
A67: 999935 | B67: PLU | C67: 35 | D67: Ja | E67: Nein | F67: 35 | G67: 190 | H67: 7 | J67: COLIS | K67: 1
A68: 999936 | B68: PLU | C68: 36 | D68: Ja | E68: Nein | F68: 36 | G68: 900 | H68: 7 | J68: COLIS | K68: 1
A69: 999938 | B69: PLU | C69: 38 | D69: Ja | E69: Nein | F69: 38 | G69: 900 | H69: 7 | J69: COLIS | K69: 1
A70: 999940 | B70: PLU | C70: 40 | D70: Ja | E70: Nein | F70: 40 | G70: 900 | H70: 7 | J70: COLIS | K70: 1
A71: 999941 | B71: PLU | C71: 41 | D71: Ja | E71: Nein | F71: 41 | G71: 100 | H71: 7 | J71: COLIS | K71: 1
A72: 999942 | B72: PLU | C72: 42 | D72: Ja | E72: Nein | F72: 42 | G72: 130 | H72: 7 | J72: COLIS | K72: 1
A73: 999943 | B73: PLU | C73: 43 | D73: Ja | E73: Nein | F73: 43 | G73: 900 | H73: 7 | J73: COLIS | K73: 1
A74: 999944 | B74: PLU | C74: 44 | D74: Ja | E74: Nein | F74: 44 | G74: 900 | H74: 7 | J74: COLIS | K74: 1
A75: 999945 | B75: PLU | C75: 45 | D75: Ja | E75: Nein | F75: 45 | G75: 900 | H75: 7 | J75: COLIS | K75: 1
A76: 999948 | B76: PLU | C76: 48 | D76: Ja | E76: Nein | F76: 48 | G76: 900 | H76: 7 | J76: COLIS | K76: 1
A77: 999949 | B77: PLU | C77: 49 | D77: Ja | E77: Nein | F77: 49 | G77: 900 | H77: 7 | J77: COLIS | K77: 1
... A95: 999999 | B95: PLU | C95: 99 | D95: Ja | E95: Nein | F95: 99 | G95: 99 | H95: 7 | J95: COLIS | K95: 1
A97: Artikelnr. | C97: ProduktNummerWaage
A98: 661105 | C98: 157
A99: 661334 | C99: 251
A100: 661455 | C100: 158
A101: 790004 | C101: 141
A102: 790005 | C102: 142
A103: 800269 | C103: 152
A104: 800471 | C104: 244
A105: 800693 | C105: 120
A106: 800705 | C106: 207
A107: 800708 | C107: 111
A108: 800709 | C108: 208
A109: 800717 | C109: 109
... A201: 803456 | C201: 242

Sheet Alle PLU Nav ohne DPB PLU
A1: Artikelnr. | B1: Code PLU | C1: Kassentext | D1: Gestellbeschriftung 1 | E1: Gestellbeschriftung 2 | F1: Kassentext | G1: Gestellbeschriftung 1 | H1: Gestellbeschriftung 2 | I1: Kassentext | J1: Gestellbeschriftung 1 | K1: Gestellbeschriftung 2
A2: 640332 | B2: 332 | C2: =VLOOKUP(A2,Texte!A:G,7,0) -> Ch. Mouton Rothschild 7.5dl | D2: =VLOOKUP(A2,Texte!A:H,8,0) -> Ch. Mouton Rothschild Paulliac | E2: =VLOOKUP(A2,Texte!A:I,9,0) -> 0 | F2: =VLOOKUP(A2,Texte!A:J,10,0) -> Ch. Mouton Rothschild 7.5dl | G2: =VLOOKUP(A2,Texte!A:K,11,0) -> Ch. Mouton Rothschild Paulliac | H2: =VLOOKUP(A2,Texte!A:L,12,0) -> 0 | I2: =VLOOKUP(A2,Texte!A:M,13,0) -> Ch. Mouton Rothschild 7.5dl | J2: =VLOOKUP(A2,Texte!A:N,14,0) -> Ch. Mouton Rothschild Paulliac | K2: =VLOOKUP(A2,Texte!A:O,15,0) -> 0
A3: 661105 | B3: 157 | C3: =VLOOKUP(A3,Texte!A:G,7,0) -> Papaya Offenverkauf kg | D3: =VLOOKUP(A3,Texte!A:H,8,0) -> Papaya | E3: =VLOOKUP(A3,Texte!A:I,9,0) -> 0 | F3: =VLOOKUP(A3,Texte!A:J,10,0) -> Papaye vrac kg | G3: =VLOOKUP(A3,Texte!A:K,11,0) -> Papaye | H3: =VLOOKUP(A3,Texte!A:L,12,0) -> 0 | I3: =VLOOKUP(A3,Texte!A:M,13,0) -> Papaia Vendita sfusa kg | J3: =VLOOKUP(A3,Texte!A:N,14,0) -> Papaia | K3: =VLOOKUP(A3,Texte!A:O,15,0) -> 0
A4: 661334 | B4: 251 | C4: =VLOOKUP(A4,Texte!A:G,7,0) -> Maniok kg | D4: =VLOOKUP(A4,Texte!A:H,8,0) -> Maniok | E4: =VLOOKUP(A4,Texte!A:I,9,0) -> 0 | F4: =VLOOKUP(A4,Texte!A:J,10,0) -> Manioc kg | G4: =VLOOKUP(A4,Texte!A:K,11,0) -> Manioc | H4: =VLOOKUP(A4,Texte!A:L,12,0) -> 0 | I4: =VLOOKUP(A4,Texte!A:M,13,0) -> Manioca kg | J4: =VLOOKUP(A4,Texte!A:N,14,0) -> Manioca | K4: =VLOOKUP(A4,Texte!A:O,15,0) -> 0
A5: 661455 | B5: 158 | C5: =VLOOKUP(A5,Texte!A:G,7,0) -> Bio Mini Wassermelone kg | D5: =VLOOKUP(A5,Texte!A:H,8,0) -> Bio Mini Wassermelone | E5: =VLOOKUP(A5,Texte!A:I,9,0) -> 0 | F5: =VLOOKUP(A5,Texte!A:J,10,0) -> Mini pastèque bio kg | G5: =VLOOKUP(A5,Texte!A:K,11,0) -> Mini pastèque bio | H5: =VLOOKUP(A5,Texte!A:L,12,0) -> 0 | I5: =VLOOKUP(A5,Texte!A:M,13,0) -> Bio Mini Anguria kg | J5: =VLOOKUP(A5,Texte!A:N,14,0) -> Bio Mini Anguria | K5: =VLOOKUP(A5,Texte!A:O,15,0) -> 0
A6: 790004 | B6: 141 | C6: =VLOOKUP(A6,Texte!A:G,7,0) -> Test Waage 31. Roger | D6: =VLOOKUP(A6,Texte!A:H,8,0) -> Test Waage 31. Roger | E6: =VLOOKUP(A6,Texte!A:I,9,0) -> Offenverkauf | F6: =VLOOKUP(A6,Texte!A:J,10,0) -> Test Waage 31. Roger Offen | G6: =VLOOKUP(A6,Texte!A:K,11,0) -> Test Waage 31. Roger | H6: =VLOOKUP(A6,Texte!A:L,12,0) -> Offenverkauf | I6: =VLOOKUP(A6,Texte!A:M,13,0) -> Test Waage 31. Roger Offen | J6: =VLOOKUP(A6,Texte!A:N,14,0) -> Test Waage 31. Roger | K6: =VLOOKUP(A6,Texte!A:O,15,0) -> Offenverkauf
A7: 790005 | B7: 142 | C7: =VLOOKUP(A7,Texte!A:G,7,0) -> Test Waage 11.6. Roger | D7: =VLOOKUP(A7,Texte!A:H,8,0) -> Test Waage 11.6. Roger | E7: =VLOOKUP(A7,Texte!A:I,9,0) -> Offenverkauf | F7: =VLOOKUP(A7,Texte!A:J,10,0) -> Test Waage 11.6. Roger Off | G7: =VLOOKUP(A7,Texte!A:K,11,0) -> Test Waage 11.6. Roger | H7: =VLOOKUP(A7,Texte!A:L,12,0) -> Offenverkauf | I7: =VLOOKUP(A7,Texte!A:M,13,0) -> Test Waage 11.6. Roger Off | J7: =VLOOKUP(A7,Texte!A:N,14,0) -> Test Waage 11.6. Roger | K7: =VLOOKUP(A7,Texte!A:O,15,0) -> Offenverkauf
A8: 800269 | B8: 152 | C8: =VLOOKUP(A8,Texte!A:G,7,0) -> Wassermelonen kg | D8: =VLOOKUP(A8,Texte!A:H,8,0) -> Wassermelonen | E8: =VLOOKUP(A8,Texte!A:I,9,0) -> 0 | F8: =VLOOKUP(A8,Texte!A:J,10,0) -> Pastèques kg | G8: =VLOOKUP(A8,Texte!A:K,11,0) -> Pastèques | H8: =VLOOKUP(A8,Texte!A:L,12,0) -> 0 | I8: =VLOOKUP(A8,Texte!A:M,13,0) -> Anguria kg | J8: =VLOOKUP(A8,Texte!A:N,14,0) -> Anguria | K8: =VLOOKUP(A8,Texte!A:O,15,0) -> 0
A9: 800471 | B9: 244 | C9: =VLOOKUP(A9,Texte!A:G,7,0) -> Zwiebeln | D9: =VLOOKUP(A9,Texte!A:H,8,0) -> IP-Suisse Zwiebeln | E9: =VLOOKUP(A9,Texte!A:I,9,0) -> Offenverkauf | F9: =VLOOKUP(A9,Texte!A:J,10,0) -> IP-Suisse Oingons en vrac | G9: =VLOOKUP(A9,Texte!A:K,11,0) -> IP-Suisse Oignons | H9: =VLOOKUP(A9,Texte!A:L,12,0) -> en vrac | I9: =VLOOKUP(A9,Texte!A:M,13,0) -> Cipolle | J9: =VLOOKUP(A9,Texte!A:N,14,0) -> IP-Suisse Cipolle | K9: =VLOOKUP(A9,Texte!A:O,15,0) -> vendita sfusa
A10: 800693 | B10: 120 | C10: =VLOOKUP(A10,Texte!A:G,7,0) -> Pflaumen Offenverkauf kg | D10: =VLOOKUP(A10,Texte!A:H,8,0) -> Pflaumen | E10: =VLOOKUP(A10,Texte!A:I,9,0) -> 0 | F10: =VLOOKUP(A10,Texte!A:J,10,0) -> Prunes vrac kg | G10: =VLOOKUP(A10,Texte!A:K,11,0) -> Prunes | H10: =VLOOKUP(A10,Texte!A:L,12,0) -> 0 | I10: =VLOOKUP(A10,Texte!A:M,13,0) -> Prugne vendita sfusa kg | J10: =VLOOKUP(A10,Texte!A:N,14,0) -> Prugne | K10: =VLOOKUP(A10,Texte!A:O,15,0) -> 0
A11: 800705 | B11: 207 | C11: =VLOOKUP(A11,Texte!A:G,7,0) -> Tomaten Spezial Offenverk kg | D11: =VLOOKUP(A11,Texte!A:H,8,0) -> Tomaten | E11: =VLOOKUP(A11,Texte!A:I,9,0) -> Spezial | F11: =VLOOKUP(A11,Texte!A:J,10,0) -> Tomates Spécial en vrac kg | G11: =VLOOKUP(A11,Texte!A:K,11,0) -> Tomates | H11: =VLOOKUP(A11,Texte!A:L,12,0) -> Spécial | I11: =VLOOKUP(A11,Texte!A:M,13,0) -> Pomodori Speciale vendita kg | J11: =VLOOKUP(A11,Texte!A:N,14,0) -> Pomodori | K11: =VLOOKUP(A11,Texte!A:O,15,0) -> Speciale
A12: 800708 | B12: 111 | C12: =VLOOKUP(A12,Texte!A:G,7,0) -> Zwetschgen Offenverkauf kg | D12: =VLOOKUP(A12,Texte!A:H,8,0) -> Zwetschgen | E12: =VLOOKUP(A12,Texte!A:I,9,0) -> 0 | F12: =VLOOKUP(A12,Texte!A:J,10,0) -> Pruneaux en vrac kg | G12: =VLOOKUP(A12,Texte!A:K,11,0) -> Pruneaux | H12: =VLOOKUP(A12,Texte!A:L,12,0) -> 0 | I12: =VLOOKUP(A12,Texte!A:M,13,0) -> Prugne vendita di merce kg | J12: =VLOOKUP(A12,Texte!A:N,14,0) -> Prugne | K12: =VLOOKUP(A12,Texte!A:O,15,0) -> 0
A13: 800709 | B13: 208 | C13: =VLOOKUP(A13,Texte!A:G,7,0) -> Süss-Kartoffeln Offenver kg | D13: =VLOOKUP(A13,Texte!A:H,8,0) -> Süss-Kartoffeln | E13: =VLOOKUP(A13,Texte!A:I,9,0) -> 0 | F13: =VLOOKUP(A13,Texte!A:J,10,0) -> Patates douces en vrac kg | G13: =VLOOKUP(A13,Texte!A:K,11,0) -> Patates douces | H13: =VLOOKUP(A13,Texte!A:L,12,0) -> 0 | I13: =VLOOKUP(A13,Texte!A:M,13,0) -> Patate dolci vendita sfu kg | J13: =VLOOKUP(A13,Texte!A:N,14,0) -> Patate dolci | K13: =VLOOKUP(A13,Texte!A:O,15,0) -> 0
... A150: 999999 | B150: 99 | C150: =VLOOKUP(A150,Texte!A:G,7,0) -> Gebinde | D150: =VLOOKUP(A150,Texte!A:H,8,0) -> Gebinde | E150: =VLOOKUP(A150,Texte!A:I,9,0) -> 0 | F150: =VLOOKUP(A150,Texte!A:J,10,0) -> Emballages | G150: =VLOOKUP(A150,Texte!A:K,11,0) -> Emballages | H150: =VLOOKUP(A150,Texte!A:L,12,0) -> 0 | I150: =VLOOKUP(A150,Texte!A:M,13,0) -> Contenitori | J150: =VLOOKUP(A150,Texte!A:N,14,0) -> Contenitori | K150: =VLOOKUP(A150,Texte!A:O,15,0) -> 0

Sheet Texte
A1: Artikel Nr. | B1: Warengruppe | C1: Status | D1: Sprachcode | E1: Einheit | F1: Menge pro Einheit | G1: Kassentext | H1: Gestellbeschriftung 1 | I1: Gestellbeschriftung 2 | J1: Kassentext | K1: Gestellbeschriftung 1 | L1: Gestellbeschriftung 2 | M1: Kassentext | N1: Gestellbeschriftung 1 | O1: Gestellbeschriftung 2
A2: 640332 | B2: 60 | C2: 96 | D2: DEU | E2: STK | F2: 1 | G2: Ch. Mouton Rothschild 7.5dl | H2: Ch. Mouton Rothschild Paulliac | J2: Ch. Mouton Rothschild 7.5dl | K2: Ch. Mouton Rothschild Paulliac | M2: Ch. Mouton Rothschild 7.5dl | N2: Ch. Mouton Rothschild Paulliac
A3: 661105 | B3: 6 | C3: 7 | D3: DEU | E3: STK | F3: 1 | G3: Papaya Offenverkauf kg | H3: Papaya | J3: Papaye vrac kg | K3: Papaye | M3: Papaia Vendita sfusa kg | N3: Papaia
A4: 661334 | B4: 6 | C4: 0 | D4: DEU | E4: STK | F4: 1 | G4: Maniok kg | H4: Maniok | J4: Manioc kg | K4: Manioc | M4: Manioca kg | N4: Manioca
A5: 661455 | B5: 6 | C5: 7 | D5: DEU | E5: STK | F5: 1 | G5: Bio Mini Wassermelone kg | H5: Bio Mini Wassermelone | J5: Mini pastèque bio kg | K5: Mini pastèque bio | M5: Bio Mini Anguria kg | N5: Bio Mini Anguria
A6: 790004 | B6: 6 | C6: 92 | D6: DEU | E6: STK | F6: 1 | G6: Test Waage 31. Roger | H6: Test Waage 31. Roger | I6: Offenverkauf | J6: Test Waage 31. Roger Offen | K6: Test Waage 31. Roger | L6: Offenverkauf | M6: Test Waage 31. Roger Offen | N6: Test Waage 31. Roger | O6: Offenverkauf
A7: 790005 | B7: 6 | C7: 92 | D7: DEU | E7: STK | F7: 1 | G7: Test Waage 11.6. Roger | H7: Test Waage 11.6. Roger | I7: Offenverkauf | J7: Test Waage 11.6. Roger Off | K7: Test Waage 11.6. Roger | L7: Offenverkauf | M7: Test Waage 11.6. Roger Off | N7: Test Waage 11.6. Roger | O7: Offenverkauf
A8: 800269 | B8: 6 | C8: 0 | D8: DEU | E8: STK | F8: 1 | G8: Wassermelonen kg | H8: Wassermelonen | J8: Pastèques kg | K8: Pastèques | M8: Anguria kg | N8: Anguria
A9: 800471 | B9: 6 | C9: 92 | D9: DEU | E9: STK | F9: 1 | G9: Zwiebeln | H9: IP-Suisse Zwiebeln | I9: Offenverkauf | J9: IP-Suisse Oingons en vrac | K9: IP-Suisse Oignons | L9: en vrac | M9: Cipolle | N9: IP-Suisse Cipolle | O9: vendita sfusa
A10: 800693 | B10: 6 | C10: 0 | D10: DEU | E10: STK | F10: 1 | G10: Pflaumen Offenverkauf kg | H10: Pflaumen | J10: Prunes vrac kg | K10: Prunes | M10: Prugne vendita sfusa kg | N10: Prugne
A11: 800705 | B11: 6 | C11: 0 | D11: DEU | E11: STK | F11: 1 | G11: Tomaten Spezial Offenverk kg | H11: Tomaten | I11: Spezial | J11: Tomates Spécial en vrac kg | K11: Tomates | L11: Spécial | M11: Pomodori Speciale vendita kg | N11: Pomodori | O11: Speciale
A12: 800708 | B12: 6 | C12: 7 | D12: DEU | E12: STK | F12: 1 | G12: Zwetschgen Offenverkauf kg | H12: Zwetschgen | J12: Pruneaux en vrac kg | K12: Pruneaux | M12: Prugne vendita di merce kg | N12: Prugne
A13: 800709 | B13: 6 | C13: 0 | D13: DEU | E13: STK | F13: 1 | G13: Süss-Kartoffeln Offenver kg | H13: Süss-Kartoffeln | J13: Patates douces en vrac kg | K13: Patates douces | M13: Patate dolci vendita sfu kg | N13: Patate dolci
A14: 800717 | B14: 6 | C14: 0 | D14: DEU | E14: STK | F14: 1 | G14: Pfirsiche Offenverkauf kg | H14: Pfirsiche | J14: Pêches en vrac kg | K14: Pêches | M14: Pesche vendita sfusa kg | N14: Pesche
A15: 800719 | B15: 6 | C15: 15 | D15: DEU | E15: STK | F15: 1 | G15: Satsumas Offenverkauf kg | H15: Satsumas | I15: Offenverkauf | J15: Satsumas Offenverkauf kg | K15: Satsumas | L15: Offenverkauf | M15: Satsumas Offenverkauf kg | N15: Satsumas | O15: Offenverkauf
A16: 800753 | B16: 6 | C16: 15 | D16: DEU | E16: STK | F16: 1 | G16: Birnen Abate Fetel | H16: Birnen Abate Fetel | I16: Offenverkauf | J16: Poires Abate Fetel | K16: Poires Abate Fetel | L16: en vrac | M16: Birnen Abate Fetel | N16: Birnen Abate Fetel | O16: vendita sfusa
A17: 800754 | B17: 6 | C17: 15 | D17: DEU | E17: STK | F17: 1 | G17: Äpfel Pink Lady | H17: Äpfel Pink Lady | I17: Offenverkauf | J17: Pommes Pink Lady | K17: Pommes Pink Lady | L17: en vrac | M17: Mele Pink Lady | N17: Mele Pink Lady | O17: vendita sfusa
A18: 800755 | B18: 6 | C18: 0 | D18: DEU | E18: STK | F18: 1 | G18: Äpfel rot offen Sorte sie kg | H18: Äpfel rot | I18: offen | J18: Pommes rouges en vrac Sor kg | K18: Pommes rouges | L18: en vrac | M18: Mele rosse vendita sfu va kg | N18: Mele rosse | O18: vendita sfusa
A19: 800785 | B19: 6 | C19: 15 | D19: DEU | E19: STK | F19: 1 | G19: Satsumas | H19: Satsumas | I19: Offenverkauf | J19: Mandarines | K19: Mandarines | L19: en vrac | M19: Mandarini | N19: Mandarini | O19: vendita sfusa
A20: 800806 | B20: 6 | C20: 7 | D20: DEU | E20: STK | F20: 1 | G20: Zwiebeln Offenverkauf kg | H20: Zwiebeln | J20: Oignons vrac kg | K20: Oignons | M20: Cipolle vendita sfusa kg | N20: Cipolle
A21: 800807 | B21: 6 | C21: 0 | D21: DEU | E21: STK | F21: 1 | G21: Birnen offen Sorte siehe kg | H21: Birnen | I21: offen | J21: Poires en vrac Sorte voir kg | K21: Poires | L21: en vrac | M21: Pere vendita sfusa variet kg | N21: Pere | O21: vendita sfusa
A22: 800816 | B22: 6 | C22: 15 | D22: DEU | E22: STK | F22: 1 | G22: Orangen | H22: Orangen | I22: Offenverkauf | J22: Oranges | K22: Oranges | L22: en vrac | M22: Arance | N22: Arance | O22: vendita sfusa
A23: 800822 | B23: 6 | C23: 0 | D23: DEU | E23: STK | F23: 1 | G23: Auberginen Offenverkauf kg | H23: Auberginen | J23: Aubergines en vrac kg | K23: Aubergines | M23: Melanzane vendita sfusa kg | N23: Melanzane
A24: 800826 | B24: 6 | C24: 15 | D24: DEU | E24: STK | F24: 1 | G24: Spitzpaprika rot Offenverka | H24: Sweet-Paprika Ramiro | I24: Offenverkauf | J24: Poivrons doux pointus vrac | K24: Poivrons doux pointus Ramiro | L24: en vrac | M24: Pepperoni Palermo rosso ven | N24: Peperoni dolci Ramiro | O24: vendita sfusa
A25: 800827 | B25: 6 | C25: 15 | D25: DEU | E25: STK | F25: 1 | G25: Lollo rot/grün | H25: Salat Gewicht | I25: Offenverkauf | J25: Lollo rot/grün | K25: Salade rouge/verte | L25: vrac | M25: Lollo rot/grün | N25: Insalata rosso / verde | O25: vendita sfusa
A26: 800828 | B26: 6 | C26: 92 | D26: DEU | E26: STK | F26: 1 | G26: Endiviensalat | H26: Endiviensalat | I26: Offenverkauf | J26: Scarole | K26: Scarole | L26: en vrac | M26: Indivia Scarola | N26: Indivia Scarola | O26: vendita sfusa
A27: 800834 | B27: 6 | C27: 7 | D27: DEU | E27: STK | F27: 1 | G27: Chiquita Bananen Offenver kg | H27: Chiquita | I27: Bananen | J27: Chiquita Bananes vrac kg | K27: Chiquita | L27: Bananes | M27: Chiquita banane vendita s kg | N27: Chiquita | O27: banane
A28: 800855 | B28: 6 | C28: 15 | D28: DEU | E28: STK | F28: 1 | G28: Flachpfirsiche | H28: Flachpfirsiche | I28: Offenverkauf | J28: Flachpfirsiche | K28: Pêches plates | L28: vrac | M28: Flachpfirsiche | N28: Pesche piatte | O28: vendita sfusa
A29: 800882 | B29: 6 | C29: 0 | D29: DEU | E29: STK | F29: 1 | G29: Tomaten Peretti Offenver kg | H29: Tomaten Peretti | J29: Tomates Peretti vrac kg | K29: Tomates Peretti | M29: Pomodori Peretti vendita kg | N29: Pomodori Peretti
A30: 800883 | B30: 6 | C30: 15 | D30: DEU | E30: STK | F30: 1 | G30: Nektarinen flach | H30: Nektarinen flach | I30: Offenverkauf | J30: Nectarines | K30: Nectarines | L30: en vrac | M30: Nettarine | N30: Nettarine | O30: vendita sfusa
A31: 800884 | B31: 6 | C31: 0 | D31: DEU | E31: STK | F31: 1 | G31: Trauben weiss Offenverka kg | H31: Trauben weiss | J31: Raisin blanc vrac kg | K31: Raisin | L31: blanc | M31: Uva bianca vendita di mer kg | N31: Uva | O31: bianca
A32: 800893 | B32: 6 | C32: 0 | D32: DEU | E32: STK | F32: 1 | G32: Trauben dunkel Offenverk kg | H32: Trauben dunkel | J32: Raisin noir vrac kg | K32: Raisin | L32: noir | M32: Uva scura Vendita sfusa kg | N32: Uva | O32: scura
A33: 800917 | B33: 6 | C33: 15 | D33: DEU | E33: STK | F33: 1 | G33: Blumenkohl | H33: Romanesco | I33: Offenverkauf | J33: Chou-fleur | K33: Romanesco | L33: en vrac | M33: Cavolfiori | N33: Romanesco | O33: vendita sfusa
A34: 800968 | B34: 6 | C34: 0 | D34: DEU | E34: STK | F34: 1 | G34: Rispentomaten Offenverka kg | H34: Rispentomaten | J34: Tomates grappes en vrac kg | K34: Tomates grappes | M34: Pomodori ramato vendita kg | N34: Pomodori ramato
A35: 800970 | B35: 6 | C35: 15 | D35: DEU | E35: STK | F35: 1 | G35: Äpfel Kl. I | H35: Äpfel Kl. I , Jonagold | I35: Offenverkauf | J35: Pommes Kl. I | K35: Pommes Cl. I , Jonagold | L35: en vrac | M35: Mele Kl. I | N35: Mele Cl I , Jonagold | O35: vendita di merce sfusa
A36: 800971 | B36: 6 | C36: 15 | D36: DEU | E36: STK | F36: 1 | G36: Birnen Kl. I | H36: Birnen Kl. I | I36: Offenverkauf | J36: Poires cl. I | K36: Poires cl. I | L36: vrac | M36: Pere Kl. I | N36: Pere Cl. I | O36: vendita sfusa
A37: 800972 | B37: 6 | C37: 15 | D37: DEU | E37: STK | F37: 1 | G37: Clementinen | H37: Clementinen | I37: Offenverkauf | J37: Clementines | K37: Clementines | L37: en vrac | M37: Clementine | N37: Clementine | O37: vendita sfusa
A38: 800975 | B38: 6 | C38: 0 | D38: DEU | E38: STK | F38: 1 | G38: Nektarinen Offenverkauf kg | H38: Nektarinen | J38: Nectarines en vrac kg | K38: Nectarines | M38: Nettarine vendita sfusa kg | N38: Nettarine
A39: 800976 | B39: 6 | C39: 15 | D39: DEU | E39: STK | F39: 1 | G39: Äpfel Kl. I | H39: Äpfel Kl. I | I39: Offenverkauf | J39: Pommes Kl. I | K39: Pommes Kl. I | L39: en vrac | M39: Mele Kl. I | N39: Mele Kl. I | O39: vendita di merce sfusa
A40: 800978 | B40: 6 | C40: 15 | D40: DEU | E40: STK | F40: 1 | G40: Lauch grün | H40: Lauch grün | I40: Offenverkauf | J40: Poireau | K40: Poireau | L40: vrac | M40: Porro | N40: Porro | O40: vendita sfusa
A41: 801071 | B41: 6 | C41: 7 | D41: DEU | E41: STK | F41: 1 | G41: Orangen Blond Offenverka kg | H41: Orangen Blond | J41: Oranges blondes en vrac kg | K41: Oranges blondes | M41: Arance bionde vendita sf kg | N41: Arance bionde
A42: 801072 | B42: 6 | C42: 15 | D42: DEU | E42: STK | F42: 1 | G42: Marroni | H42: Marroni | I42: Offenverkauf | J42: Marrons | K42: Marrons | L42: en vrac | M42: Maroni | N42: Marroni | O42: Vendita sfusa
A43: 801073 | B43: 6 | C43: 0 | D43: DEU | E43: STK | F43: 1 | G43: Broccoli Offenverkauf kg | H43: Broccoli | J43: Brocoli en vrac kg | K43: Brocoli | M43: Broccoletti vendita sfus kg | N43: Broccoletti
A44: 801074 | B44: 6 | C44: 0 | D44: DEU | E44: STK | F44: 1 | G44: Blumenkohl Offenverkauf kg | H44: Blumenkohl | J44: Chou-fleur en vrac kg | K44: Chou-fleur | M44: Cavolfiori vendita sfusa kg | N44: Cavolfiori
A45: 801075 | B45: 6 | C45: 15 | D45: DEU | E45: STK | F45: 1 | G45: Kaki Persimon | H45: Kaki Persimon | I45: Offenverkauf | J45: Kakis Persimon | K45: Kakis Persimon | L45: vrac | M45: Cachi Persimon | N45: Cachi Persimon | O45: vendita di merce sfusa
A46: 801088 | B46: 6 | C46: 15 | D46: DEU | E46: STK | F46: 1 | G46: RAINFOREST Bananen | H46: Rainforest Bananen | I46: Offenverkauf | J46: RAINFOREST Bananes | K46: Rainforest Bananes | L46: vrac | M46: RAINFOREST Bananes | N46: Rainforest banane | O46: vendita sfusa
A47: 801091 | B47: 6 | C47: 15 | D47: DEU | E47: STK | F47: 1 | G47: Orangen Tarocco | H47: Orangen Tarocco | I47: Offenverkauf | J47: Oranges Tarocco | K47: Oranges sanguines Tarocco | L47: en vrac | M47: Arance Tarocco | N47: Arance Tarocco | O47: vendita sfusa
A48: 801104 | B48: 6 | C48: 0 | D48: DEU | E48: STK | F48: 1 | G48: Fenchel Offenverkauf kg | H48: Fenchel | J48: Fenouil en vrac kg | K48: Fenouil | M48: Finocchi vendita sfusa kg | N48: Finocchi
A49: 801105 | B49: 6 | C49: 7 | D49: DEU | E49: STK | F49: 1 | G49: Peperoni rot Offenverkau kg | H49: Peperoni rot | J49: Poivrons rouges en vrac kg | K49: Poivrons rouges | M49: Peperoni rossi vendita s kg | N49: Peperoni rossi
A50: 801106 | B50: 6 | C50: 15 | D50: DEU | E50: STK | F50: 1 | G50: Peperoni gelb | H50: Peperoni gelb | I50: Offenverkauf | J50: Poivrons jaunes | K50: Poivrons jaunes | L50: en vrac | M50: Peperoni gialli | N50: Peperoni gialli | O50: vendita sfusa
A51: 801107 | B51: 6 | C51: 15 | D51: DEU | E51: STK | F51: 1 | G51: Fleischtomaten | H51: Tomaten rund | I51: Offenverkauf | J51: Tomates charnues | K51: Tomates | L51: en vrac | M51: Pomodori carnosi | N51: Pomodori | O51: vendita sfusa
A52: 801108 | B52: 6 | C52: 15 | D52: DEU | E52: STK | F52: 1 | G52: Karotten | H52: Karotten | I52: Offenverkauf | J52: Carottes en vrac kg | K52: Carottes | L52: en vrac | M52: Carote vendita sfusa kg | N52: Carote | O52: vendita sfusa
A53: 801109 | B53: 6 | C53: 0 | D53: DEU | E53: STK | F53: 1 | G53: Äpfel Golden Offenverkauf kg | H53: Äpfel | I53: Golden | J53: Pommes Golden en vrac kg | K53: Pommes | L53: Golden | M53: Mele Golden vendita sfusa kg | N53: Mele | O53: Golden
A54: 801110 | B54: 6 | C54: 0 | D54: DEU | E54: STK | F54: 1 | G54: Zucchetti Offenverkauf kg | H54: Zucchetti | J54: Courgettes en vrac kg | K54: Courgettes | M54: Zucchetti vendita sfusa kg | N54: Zucchetti
A55: 801111 | B55: 6 | C55: 7 | D55: DEU | E55: STK | F55: 1 | G55: Aprikosen Offenverkauf kg | H55: Aprikosen | J55: Abricots en vrac kg | K55: Abricots | M55: Albicocche vendita sfusa kg | N55: Albicocche
A56: 801292 | B56: 6 | C56: 15 | D56: DEU | E56: STK | F56: 1 | G56: Kohlraben Offenverkauf kg | H56: Kohlraben | I56: Offenverkauf | J56: Choux-raves en vrac kg | K56: Choux-raves | L56: en vrac | M56: Cavolo rapa Vendita sfus kg | N56: Cavolo rapa | O56: Vendita sfusa
A57: 801293 | B57: 6 | C57: 7 | D57: DEU | E57: STK | F57: 1 | G57: Kürbis Hokkaido ca. 1kg | H57: Kürbis | I57: Hokkaido | J57: Courge Hokkaido ca. 1kg | K57: Courge | L57: Hokkaido | M57: Zucca Hokkaido ca. 1kg | N57: Zucca | O57: Hokkaido
A58: 801307 | B58: 6 | C58: 7 | D58: DEU | E58: STK | F58: 1 | G58: Kürbis Butternuss ca.1kg | H58: Kürbis | I58: Butternuss | J58: Courge doubeurre ca.1kg | K58: Courge | L58: doubeurre | M58: Zucca Noce di burro ca.1kg | N58: Zucca | O58: Noce di burro
A59: 801365 | B59: 6 | C59: 15 | D59: DEU | E59: STK | F59: 1 | G59: Spanische Erdnüsse Offen kg | H59: Spanische Erdnüsse | I59: Offenverkauf | J59: Cacahuètes en vrac kg | K59: Cacahuètes | L59: en vrac | M59: Arachidi vendita sfusa kg | N59: Arachidi | O59: vendita sfusa
A60: 801366 | B60: 6 | C60: 15 | D60: DEU | E60: STK | F60: 1 | G60: Baumnüsse Offenverkauf kg | H60: Baumnüsse | I60: Offenverkauf | J60: Noix en vrac kg | K60: Noix | L60: en vrac | M60: Noci vendita sfusa kg | N60: Noci | O60: vendita sfusa
A61: 801546 | B61: 6 | C61: 7 | D61: DEU | E61: STK | F61: 1 | G61: Kabis Offenverkauf kg | H61: Kabis | J61: Chou vrac kg | K61: Chou | M61: Cavolo vendita sfusa kg | N61: Cavolo
A62: 801572 | B62: 6 | C62: 0 | D62: DEU | E62: STK | F62: 1 | G62: Bio Ingwer Offenverkau kg | H62: Bio Ingwer | I62: Offenverkauf | J62: Bio Gingembre en vrac kg | K62: Bio Gingembre | L62: en vrac | M62: Bio Zenzero vendita sf kg | N62: Bio Zenzero | O62: vendita sfusa
A63: 801578 | B63: 6 | C63: 0 | D63: DEU | E63: STK | F63: 1 | G63: Denner Bananen Offenverka kg | H63: Denner | I63: Bananen | J63: Denner Bananes vrac kg | K63: Denner | L63: Bananes | M63: Denner Banane vendita sfu kg | N63: Denner | O63: Banane
A64: 801702 | B64: 6 | C64: 15 | D64: DEU | E64: STK | F64: 1 | G64: Kirschen Offenverkauf kg | H64: Kirschen | I64: Offenverkauf | J64: Cerises en vrac kg | K64: Cerises | L64: en vrac | M64: Ciliegie vendita sfusa kg | N64: Ciliegie | O64: vendita sfusa
A65: 801746 | B65: 6 | C65: 15 | D65: DEU | E65: STK | F65: 1 | G65: IP Suisse Zwiebeln Offenver | H65: IP Suisse Zwiebeln | I65: Offenverkauf | J65: IP Suisse Oignons en vrac | K65: IP Suisse Oignons | L65: en vrac | M65: IP Suisse Cipolle vendita d | N65: IP Suisse Cipolle | O65: vendita di merce sfusa
A66: 801766 | B66: 6 | C66: 7 | D66: DEU | E66: STK | F66: 1 | G66: Zucchetti rund Offenverk kg | H66: Zucchetti rund | J66: Courgettes rondes en vra kg | K66: Courgettes rondes | M66: Zucchetti tondi vendita kg | N66: Zucchetti tondi
A67: 801773 | B67: 6 | C67: 7 | D67: DEU | E67: STK | F67: 1 | G67: Quitten kg | H67: Quitten | J67: Coings kg | K67: Coings | M67: Mele cotogne kg | N67: Mele cotogne
A68: 801793 | B68: 6 | C68: 0 | D68: DEU | E68: STK | F68: 1 | G68: IP-Suisse Zwiebeln Offenv kg | H68: IP-Suisse | I68: Zwiebeln | J68: IP-Suisse Oignons Oignons kg | K68: IP-Suisse | L68: Oignons | M68: IP-Suisse Cipolle vendita kg | N68: IP-Suisse | O68: Cipolle
A69: 801800 | B69: 6 | C69: 7 | D69: DEU | E69: STK | F69: 1 | G69: Bio Orangen Offenverkauf kg | H69: Bio Orangen | J69: Bio Oranges en vrac kg | K69: Bio Oranges | M69: Bio Arance vendita sfusa kg | N69: Bio Arance
A70: 801806 | B70: 6 | C70: 7 | D70: DEU | E70: STK | F70: 1 | G70: Spitzkabis Offenverkauf kg | H70: Spitzkabis | J70: Chou pointu vrac kg | K70: Chou pointu | M70: Verza vendita sfusa kg | N70: Verza
A71: 801911 | B71: 6 | C71: 0 | D71: DEU | E71: STK | F71: 1 | G71: Bio Bananen Offenverkauf kg | H71: Bio | I71: Bananen | J71: Bio Bananes vrac kg | K71: Bio | L71: Bananes | M71: Bio banane vendita sfusa kg | N71: Bio | O71: banane
A72: 802051 | B72: 6 | C72: 15 | D72: DEU | E72: STK | F72: 1 | G72: Peperoni diverse Offenv | H72: Peperoni diverse | I72: Offenverkauf | J72: Poivrons divers en vrac kg | K72: Poivrons divers | L72: en vrac | M72: Peperoni div. vendita s | N72: Peperoni div. | O72: vendita sfusa
A73: 802082 | B73: 6 | C73: 15 | D73: DEU | E73: STK | F73: 1 | G73: Spargeln weiss Offenve | H73: Spargeln weiss | I73: Offenverkauf | J73: Spargeln weiss Offenve | K73: Aspeges blanches | L73: en vrac | M73: Spargeln weiss Offenve | N73: Asparagi bianchi | O73: vendita sfusa
A74: 802083 | B74: 6 | C74: 7 | D74: DEU | E74: STK | F74: 1 | G74: Stangensellerie Offenver kg | H74: Stangensellerie | J74: Céleri en branche en vra kg | K74: Céleri en branche | M74: Sedano vendita sfusa kg | N74: Sedano
A75: 802171 | B75: 6 | C75: 15 | D75: DEU | E75: STK | F75: 1 | G75: Mini Bananen Offenverka | H75: Mini Bananen | I75: Offenverkauf | J75: Mini bananes vrac | K75: Mini bananes | L75: vrac | M75: Mini banane vendita sfu | N75: Mini banane | O75: vendita sfusa
A76: 802173 | B76: 6 | C76: 15 | D76: DEU | E76: STK | F76: 1 | G76: Kartoffeln Offenverkauf kg | H76: Kartoffeln | I76: Offenverkauf | J76: Pommes de terre en vra | K76: Pommes de terre | L76: en vrac | M76: Patate vendita sfusa kg | N76: Patate | O76: vendita sfusa
A77: 802175 | B77: 6 | C77: 0 | D77: DEU | E77: STK | F77: 1 | G77: Knoblauch frisch Offenver kg | H77: Knoblauch | I77: frisch | J77: Ail frais Offenverkauf kg | K77: Ail | L77: frais | M77: Aglio fresco Offenverkauf kg | N77: Aglio | O77: fresco
A78: 802189 | B78: 6 | C78: 7 | D78: DEU | E78: STK | F78: 1 | G78: Knollensellerie Offenv kg | H78: Knollensellerie | I78: Offenverkauf | J78: Céleri rave en vrac kg | K78: Céleri rave | L78: en vrac | M78: Sedano rapa vendita sf kg | N78: Sedano rapa | O78: vendita sfusa
A79: 802317 | B79: 6 | C79: 0 | D79: DEU | E79: STK | F79: 1 | G79: IP-Suisse Kürbis Butt ca.1kg | H79: IP-Suisse | I79: Kürbis | J79: IP-Suisse Courge doub ca.1kg | K79: IP-Suisse | L79: Courge | M79: IP-Suisse Zucca Butte ca.1kg | N79: IP-Suisse | O79: Zucca
A80: 802328 | B80: 6 | C80: 10 | D80: DEU | E80: STK | F80: 1 | G80: Bio Kürbis Butternuss ca.1kg | H80: Bio | I80: Kürbis | J80: Bio Courge doubeurre ca.1kg | K80: Bio | L80: Courge | M80: Bio Zucca Noce di bur ca.1kg | N80: Bio | O80: Zucca
A81: 802412 | B81: 6 | C81: 7 | D81: DEU | E81: STK | F81: 1 | G81: IP-Suisse Kürbis Butt ca.1kg | H81: IP-Suisse | I81: Kürbis | J81: IP-Suisse Courge Butt ca.1kg | K81: IP-Suisse | L81: Courge | M81: IP-Suisse Zucca Butte ca.1kg | N81: IP-Suisse | O81: Zucca
A82: 802515 | B82: 6 | C82: 7 | D82: DEU | E82: STK | F82: 1 | G82: IP Suisse Knollenselle Of kg | H82: IP Suisse | I82: Knollensellerie | J82: IP Suisse Céleri-rave en kg | K82: IP Suisse | L82: Céleri-rave | M82: IP Suisse Sedano rapa ven kg | N82: IP Suisse | O82: Sedano rapa
A83: 802780 | B83: 6 | C83: 15 | D83: DEU | E83: STK | F83: 1 | G83: IP-Suisse Lauch Offenverk kg | H83: IP-Suisse Lauch | I83: Offenverkauf | J83: IP-Suisse Poireau vrac kg | K83: IP-Suisse Poireau | L83: vrac | M83: IP-Suisse Porro vendita s kg | N83: IP-Suisse Porro | O83: vendita sfusa
A84: 802781 | B84: 6 | C84: 15 | D84: DEU | E84: STK | F84: 1 | G84: IP-Suisse Zucchetti Offen kg | H84: IP-Suisse Zucchetti | I84: Offenverkauf | J84: IP-Suisse Courgettes en v kg | K84: IP-Suisse Courgettes | L84: en vrac | M84: IP-Suisse Zucchine vendit kg | N84: IP-Suisse Zucchine | O84: vendita sfusa
A85: 802782 | B85: 6 | C85: 15 | D85: DEU | E85: STK | F85: 1 | G85: IP-Suisse Fenchel Offenve kg | H85: IP-Suisse Fenchel | I85: Offenverkauf | J85: IP-Suisse Fenouil en vrac kg | K85: IP-Suisse Fenouil | L85: en vrac | M85: IP-Suisse Finocchi vendit kg | N85: IP-Suisse Finocchi | O85: vendita sfusa
A86: 802783 | B86: 6 | C86: 15 | D86: DEU | E86: STK | F86: 1 | G86: IP-Suisse Kohlraben Offen kg | H86: IP-Suisse Kohlraben | I86: Offenverkauf | J86: IP-Suisse Choux-raves en kg | K86: IP-Suisse Choux-raves | L86: en vrac | M86: IP-Suisse Cavolo rapa Ven kg | N86: IP-Suisse Cavolo rapa | O86: Vendita sfusa
... A95: 803120 | B95: 6 | C95: 90 | D95: DEU | E95: STK | F95: 1 | G95: Champignons braun offen kg | H95: Champignons braun | I95: offen | J95: Champignons braun offen kg | K95: Champignons braun | L95: offen | M95: Champignons braun offen kg | N95: Champignons braun | O95: offen
A96: 803122 | B96: 6 | C96: 15 | D96: DEU | E96: STK | F96: 1 | G96: Äpfel Golden geschüttet kg | H96: Äpfel Golden | I96: geschüttet | J96: Äpfel Golden kg | K96: Äpfel Golden | M96: Mele Golden cassetta kg | N96: Mele Golden | O96: cassetta
A97: 803123 | B97: 6 | C97: 15 | D97: DEU | E97: STK | F97: 1 | G97: Äpfel Golden Kl.I geschüt kg | H97: Äpfel Golden | I97: Kl.I geschüttet | J97: Äpfel Golden Kl.I geschüt kg | K97: Äpfel Golden | L97: Kl.I geschüttet | M97: Mele Golden Cl. I cassett kg | N97: Mele Golden | O97: Cl. I cassetta
A98: 803124 | B98: 6 | C98: 15 | D98: DEU | E98: STK | F98: 1 | G98: Äpfel Granny Smith geschü kg | H98: Äpfel Granny Smith | I98: geschüttet | J98: Pommes Granny Smith cageo kg | K98: Pommes Granny Smith | L98: cageot | M98: Mele Granny Smith cassett kg | N98: Mele Granny Smith | O98: cassetta
A99: 803125 | B99: 6 | C99: 15 | D99: DEU | E99: STK | F99: 1 | G99: Äpfel Braeburn Kl 1 gesch kg | H99: Äpfel Braeburn Kl 1 geschüttet | I99: geschüttet | J99: Pommes Braeburn Cl 1 cage kg | K99: Pommes Braeburn Cl 1 cageot Br | L99: cageot | M99: Mele Braeburn Cl.l 1 cass kg | N99: Mele Braeburn Cl.l 1 cassetta | O99: cassetta
A100: 803126 | B100: 6 | C100: 15 | D100: DEU | E100: STK | F100: 1 | G100: Äpfel Granny Smith Kl.I m kg | H100: Äpfel Granny Smith | I100: Kl.I mehrlagig | J100: Pommes Granny Smith Cl. 1 kg | K100: Pommes Granny Smith | L100: Cl. 1 plusieurs couches | M100: Mele Granny Smith Cl. 1 p kg | N100: Mele Granny Smith | O100: Cl. 1 più strati
A101: 803127 | B101: 6 | C101: 15 | D101: DEU | E101: STK | F101: 1 | G101: Äpfel Granny Smith Kl.I L kg | H101: Äpfel Granny Smith | I101: Kl.I Lagen | J101: Pommes Granny Smith Cl. I kg | K101: Pommes Granny Smith | L101: Cl. I en couches | M101: Mele Granny Smith Cl.I st kg | N101: Mele Granny Smith | O101: Cl.I strati
A102: 803129 | B102: 6 | C102: 10 | D102: DEU | E102: STK | F102: 1 | G102: Birnen | H102: Birnen | J102: Poires | K102: Poires | M102: Pere | N102: Pere
A103: 803132 | B103: 6 | C103: 15 | D103: DEU | E103: STK | F103: 1 | G103: Äpfel Braeburn Kl.I gesch kg | H103: Äpfel Braeburn | I103: Kl.I geschüttet | J103: Pommes Braeburn Kl.I gesc kg | K103: Pommes Braeburn | L103: Kl.I geschüttet | M103: Mele Braeburn Cl. I casse kg | N103: Mele Braeburn | O103: Cl. I cassetta
A104: 803133 | B104: 6 | C104: 15 | D104: DEU | E104: STK | F104: 1 | G104: Äpfel Braeburn Kl.I Lage kg | H104: Äpfel Braeburn | I104: Kl.I Lage | J104: Pommes Braeburn Cl.I en c kg | K104: Pommes Braeburn | L104: Cl.I en couches | M104: Mele Braeburn Cl.I strati kg | N104: Mele Braeburn | O104: Cl.I strati
A105: 803155 | B105: 6 | C105: 0 | D105: DEU | E105: STK | F105: 1 | G105: Clementinen / Mandarin kg | H105: Clementinen / Mandarinen | I105: Offenverkauf | J105: Clémentines / Mandarin kg | K105: Clémentines / Mandarines | L105: en vrac | M105: Clementine / Mandarini kg | N105: Clementine / Mandarini | O105: vendita sfusa
A106: 803456 | B106: 6 | C106: 7 | D106: DEU | E106: STK | F106: 1 | G106: Nostrano Gurken kg | H106: Nostrano Gurken | J106: Concombre Nostrani kg | K106: Concombre Nostrani | M106: Cetrioli Nostrani kg | N106: Cetrioli Nostrani
A107: 999892 | B107: 87 | C107: 20 | D107: DEU | E107: COLIS | F107: 1 | G107: Sammelartikel Kassentaste F | H107: Sammelartikel Kassentaste Food | J107: Sammelartikel Kassentaste F | K107: Sammelartikel Kassentaste Food | M107: Sammelartikel Kassentaste F | N107: Sammelartikel Kassentaste Food
A108: 999893 | B108: 87 | C108: 90 | D108: DEU | E108: STK | F108: 1 | G108: Sammelartikel Kassentaste | H108: Sammelartikel Kassentaste Nonf | J108: Sammelartikel Kassentaste | K108: Sammelartikel Kassentaste Nonf | M108: Sammelartikel Kassentaste | N108: Sammelartikel Kassentaste Nonf
...
