Workbook
Name EntitiesCol: Entities!$SRS$2
Name EntitiesRow: Entities!$A$1000000
Name RelationshipsCol: [1]Relationships!$SSS$2
Name RelationshipsRow: [1]Relationships!$A$1000000
Name RSC__refxartikeltypsap: 'Reference Data'!$T$2:$T$5
Name RSC__refxbooleanalkoholhaltig: 'Reference Data'!$U$2:$U$5
Name RSC__refxboolen: 'Reference Data'!$V$2:$V$5
Name RSC__refxgtintyperegioartikel: 'Reference Data'!$AP$2:$AP$5
Name RSC__refxshopinshop: 'Reference Data'!$AO$2:$AO$5
Name RSC__refxsystemsap: 'Reference Data'!$AQ$2:$AQ$5
Name RSC_atxalkoholhaltig__de_DE: 'Reference Data'!$M$2:$M$2
Name RSC_atxalkoholhaltig__fr_FR: 'Reference Data'!$L$2:$L$2
Name RSC_atxalkoholhaltig__it_IT: 'Reference Data'!$G$2:$G$2
Name RSC_atxwarengruppesap__de_DE: 'Reference Data'!$B$2:$B$2
Name RSC_atxwarengruppesap__fr_FR: 'Reference Data'!$E$2:$E$2
Name RSC_atxwarengruppesap__it_IT: 'Reference Data'!$O$2:$O$2
Name RSC_axartikelslpmstruktur__de_DE: 'Reference Data'!$C$2:$C$2
Name RSC_axartikelslpmstruktur__fr_FR: 'Reference Data'!$H$2:$H$2
Name RSC_axartikelslpmstruktur__it_IT: 'Reference Data'!$A$2:$A$2
Name RSC_axartikeltypsap__de_DE: 'Reference Data'!$J$2:$J$2
Name RSC_axartikeltypsap__fr_FR: 'Reference Data'!$I$2:$I$2
Name RSC_axartikeltypsap__it_IT: 'Reference Data'!$P$2:$P$2
Name RSC_axmhdvorhanden__de_DE: 'Reference Data'!$N$2:$N$2
Name RSC_axmhdvorhanden__fr_FR: 'Reference Data'!$Q$2:$Q$2
Name RSC_axmhdvorhanden__it_IT: 'Reference Data'!$D$2:$D$2
Name RSC_axtaxdummyfilter__de_DE: 'Reference Data'!$K$2:$K$2
Name RSC_axtaxdummyfilter__fr_FR: 'Reference Data'!$R$2:$R$2
Name RSC_axtaxdummyfilter__it_IT: 'Reference Data'!$F$2:$F$2
Name RSC_de_DE_refxaltersbegrtyp: 'Reference Data'!$AL$2:$AL$9
Name RSC_de_DE_refxartikelartsap: 'Reference Data'!$W$2:$W$14
Name RSC_de_DE_refxmengeneinheit: 'Reference Data'!$AC$2:$AC$14
Name RSC_de_DE_refxsaisontypsap: 'Reference Data'!$Z$2:$Z$7
Name RSC_de_DE_refxtaxclass: 'Reference Data'!$AI$2:$AI$6
Name RSC_de_DE_refxvergleichspreiseinheit: 'Reference Data'!$AF$2:$AF$6
Name RSC_ENTITY_NAME: 'Reference Data'!$S$2:$S$2
Name RSC_fr_FR_refxaltersbegrtyp: 'Reference Data'!$AM$2:$AM$9
Name RSC_fr_FR_refxartikelartsap: 'Reference Data'!$X$2:$X$6
Name RSC_fr_FR_refxmengeneinheit: 'Reference Data'!$AD$2:$AD$14
Name RSC_fr_FR_refxsaisontypsap: 'Reference Data'!$AA$2:$AA$7
Name RSC_fr_FR_refxtaxclass: 'Reference Data'!$AJ$2:$AJ$6
Name RSC_fr_FR_refxvergleichspreiseinheit: 'Reference Data'!$AG$2:$AG$3
Name RSC_it_IT_refxaltersbegrtyp: 'Reference Data'!$AN$2:$AN$9
Name RSC_it_IT_refxartikelartsap: 'Reference Data'!$Y$2:$Y$6
Name RSC_it_IT_refxmengeneinheit: 'Reference Data'!$AE$2:$AE$14
Name RSC_it_IT_refxsaisontypsap: 'Reference Data'!$AB$2:$AB$7
Name RSC_it_IT_refxtaxclass: 'Reference Data'!$AK$2:$AK$6
Name RSC_it_IT_refxvergleichspreiseinheit: 'Reference Data'!$AH$2:$AH$3

Sheet Help
B3: These are all read only
A4: TEMPLATE NAME | B4: RS EXCEL
A5: TEMPLATE VERSION | B5: V1.0
A6: MULTI VALUES DELIMITER | B6: ||
A7: CONTEXT PATH DELIMITER | B7: >>
A8: LEGENDS | B8: INHERITED VALUE(S)
B9: GOVERNANCE ERROR(S)
A12: Type
A13: SYSTEM/RELATIONSHIPS | B13: COLLECTION | C13: MANDATORY | D13: MANDATORY COLLECTION
A14: GLOBAL | B14: COLLECTION | C14: MANDATORY | D14: MANDATORY COLLECTION
A15: GLOBAL ENHANCER | B15: COLLECTION | C15: MANDATORY | D15: MANDATORY COLLECTION
A16: CONTEXT | B16: COLLECTION | C16: MANDATORY | D16: MANDATORY COLLECTION
A17: CONTEXT ENHANCER | B17: COLLECTION | C17: MANDATORY | D17: MANDATORY COLLECTION

Sheet Entities
A1: System Attributes | E1: Enhancer Attribute(s) | G1: Matching Attribute(s) | H1: 01 - Rumpfinformationen | J1: 99 - intern | L1: 01 - Rumpfinformationen | O1: 03 - Texte | U1: 99 - intern | AA1: 01 - Rumpfinformationen | AG1: 05 - Kasse | AL1: 99 - intern
A2: Action | B2: Type | C2: ID | D2: Name | E2: Artikeltyp | F2: Warengruppe//de-DE | G2: MDM ID | H2: Artikelart//de-DE | I2: Saison Typ//de-DE | J2: GTIN Suche | K2: Ergänzte Regio-Artikel-GTIN | L2: Artikeltext//de-DE | M2: Artikeltext//fr-FR | N2: Artikeltext//it-IT | O2: Gestellbeschriftung 1//de-DE | P2: Gestellbeschriftung 1//fr-FR | Q2: Gestellbeschriftung 1//it-IT | R2: Gestellbeschriftung 2//de-DE | S2: Gestellbeschriftung 2//fr-FR | T2: Gestellbeschriftung 2//it-IT | U2: Gestellbeschriftung 3 Regio//de-DE | V2: Gestellbeschriftung 3 Regio//fr-FR | W2: Gestellbeschriftung 3 Regio//it-IT | X2: Cash receipt text Regio//de-DE | Y2: Cash receipt text Regio//fr-FR | Z2: Cash receipt text Regio//it-IT | AA2: Nettoinhalt | AB2: Inhaltsmengeneinheit Grundpreis//de-DE | AC2: Grundpreiseinheit//de-DE | AD2: Basismengeneinheit//de-DE | AE2: Steuerklassifikation//de-DE | AF2: Altersbegrenzungs-Typ//de-DE | AG2: Rabatt zugelassen | AH2: Rückgabe zugelassen | AI2: Preisänderung Kasse erlaubt | AJ2: Automatischer Bondruck | AK2: Shop-In-Shop | AL2: Ist Fremdartikel | AM2: GTIN-Typ Regioapp | AN2: Ist Regioartikel | AO2: SAP System Integration
B3: exartikel | C3: fb03a8a8-92fa-4327-9d81-07b476c5f202 | D3: 1602056 - 661812 - Importierter Artikeltext PLU | E3: 00 - Einzelartikel | F3: Warengruppe>>Getränke>>Tafelgetränke>>Säfte gekühlt | G3: 1602056 | H3: ZHAW - Handelsware ohne Charge | I3: In/Out | J3: 753 | L3: Importierter Artikeltext PLU | M3: Importierter Artikeltext PLU | N3: Importierter Artikeltext PLU | O3: Kirschsaft | P3: Kirschsaft | Q3: Kirschsaft | R3: frisch ab Presse | S3: frisch ab Presse | T3: frisch ab Presse | U3: ca. 250 ml | X3: Kirschsaft ca. 250 ml | AA3: 0.25 | AB3: Milliliter | AC3: 100 | AD3: (PCE) Stück | AE3: 1 - Normalsatz | AF3: Keine | AG3: false | AH3: false | AI3: false | AJ3: false | AL3: false | AM3: PLU | AN3: true | AO3: S4H
B4: exartikel | E4: 00 - Einzelartikel | F4: ="Warengruppe>>"&Migrationsartikel!V2&">>"&Migrationsartikel!W2&">>"&Migrationsartikel!X2 -> Warengruppe>>Backwaren & Convenience>>Brot und Backwaren>>Backwaren andere | H4: ZHAW - Handelsware ohne Charge | I4: In/Out | J4: =Migrationsartikel!B2 -> 700 | L4: =Migrationsartikel!F2&" "&Migrationsartikel!G2&" "&Migrationsartikel!H2 -> Baguette aus der Region 250g | M4: =Migrationsartikel!J2&" "&Migrationsartikel!K2&" "&Migrationsartikel!L2 -> Baguette de la région 250g | N4: =Migrationsartikel!N2&" "&Migrationsartikel!O2&" "&Migrationsartikel!P2 -> Baguette della regione 250g | O4: =Migrationsartikel!F2 -> Baguette | P4: =Migrationsartikel!J2 -> Baguette | Q4: =Migrationsartikel!N2 -> Baguette | R4: =Migrationsartikel!G2 -> aus der Region | S4: =Migrationsartikel!K2 -> de la région | T4: =Migrationsartikel!O2 -> della regione | U4: =Migrationsartikel!H2 -> 250g | V4: =Migrationsartikel!L2 -> 250g | W4: =Migrationsartikel!P2 -> 250g | X4: =Migrationsartikel!I2 -> Baguette 250g | Y4: =Migrationsartikel!M2 -> Baguette 250g | Z4: =Migrationsartikel!Q2 -> Baguette 250g | AA4: =Migrationsartikel!R2 -> 0.25 | AB4: =Migrationsartikel!T2 -> Gramm | AC4: =Migrationsartikel!S2 -> 100 | AD4: =Migrationsartikel!U2 -> (PCE) Stück | AE4: 1 - Normalsatz | AF4: Keine | AG4: =IF(Migrationsartikel!AB2="ja","true",FALSE) -> true | AH4: =IF(Migrationsartikel!AC2="ja","true",FALSE) -> true | AI4: =IF(Migrationsartikel!AD2="ja","true",FALSE) -> true | AJ4: =IF(Migrationsartikel!AE2="ja","true",FALSE) -> true | AK4: =IF(Migrationsartikel!AF2="ja","Denner Partner","") | AL4: =IF(Migrationsartikel!AG2="ja","true","false") -> false | AM4: =IF(J4<>"","PLU","Kassentastenbelegung (ohne GTIN/PLU)") -> PLU | AN4: true | AO4: S4H
B5: exartikel | E5: 1 - Einzelartikel | F5: ="Warengruppe>>"&Migrationsartikel!V3&">>"&Migrationsartikel!W3&">>"&Migrationsartikel!X3 -> Warengruppe>>Backwaren & Convenience>>Brot und Backwaren>>Backwaren andere | H5: ZHAW - Handelsware ohne Charge | I5: In/Out | J5: =Migrationsartikel!B3 -> 701 | L5: =Migrationsartikel!F3&" "&Migrationsartikel!G3&" "&Migrationsartikel!H3 -> Baslerbrot aus der Region 250g | M5: =Migrationsartikel!J3&" "&Migrationsartikel!K3&" "&Migrationsartikel!L3 -> Pain bâlois de la région 250g | N5: =Migrationsartikel!N3&" "&Migrationsartikel!O3&" "&Migrationsartikel!P3 -> Pane di Basilea della regione 250g | O5: =Migrationsartikel!F3 -> Baslerbrot | P5: =Migrationsartikel!J3 -> Pain bâlois | Q5: =Migrationsartikel!N3 -> Pane di Basilea | R5: =Migrationsartikel!G3 -> aus der Region | S5: =Migrationsartikel!K3 -> de la région | T5: =Migrationsartikel!O3 -> della regione | U5: =Migrationsartikel!H3 -> 250g | V5: =Migrationsartikel!L3 -> 250g | W5: =Migrationsartikel!P3 -> 250g | X5: =Migrationsartikel!I3 -> Baslerbrot 250g | Y5: =Migrationsartikel!M3 -> Pain bâlois 250g | Z5: =Migrationsartikel!Q3 -> Pane di Basilea 250g | AA5: =Migrationsartikel!R3 -> 0.25 | AB5: =Migrationsartikel!T3 -> Gramm | AC5: =Migrationsartikel!S3 -> 100 | AD5: =Migrationsartikel!U3 -> (PCE) Stück | AE5: 1 - Normalsatz | AF5: Keine | AG5: =IF(Migrationsartikel!AB3="ja","true",FALSE) -> true | AH5: =IF(Migrationsartikel!AC3="ja","true",FALSE) -> true | AI5: =IF(Migrationsartikel!AD3="ja","true",FALSE) -> true | AJ5: =IF(Migrationsartikel!AE3="ja","true",FALSE) -> true | AK5: =IF(Migrationsartikel!AF3="ja","Denner Partner","") | AL5: =IF(Migrationsartikel!AG3="ja","true","false") -> false | AM5: =IF(J5<>"","PLU","Kassentastenbelegung (ohne GTIN/PLU)") -> PLU | AN5: true | AO5: S4H
B6: exartikel | E6: 2 - Einzelartikel | F6: ="Warengruppe>>"&Migrationsartikel!V4&">>"&Migrationsartikel!W4&">>"&Migrationsartikel!X4 -> Warengruppe>>Backwaren & Convenience>>Brot und Backwaren>>Backwaren andere | H6: ZHAW - Handelsware ohne Charge | I6: In/Out | J6: =Migrationsartikel!B4 -> 702 | L6: =Migrationsartikel!F4&" "&Migrationsartikel!G4&" "&Migrationsartikel!H4 -> Baslerbrot aus der Region 500g | M6: =Migrationsartikel!J4&" "&Migrationsartikel!K4&" "&Migrationsartikel!L4 -> Pain bâlois de la région 500g | N6: =Migrationsartikel!N4&" "&Migrationsartikel!O4&" "&Migrationsartikel!P4 -> Pane di Basilea della regione 500g | O6: =Migrationsartikel!F4 -> Baslerbrot | P6: =Migrationsartikel!J4 -> Pain bâlois | Q6: =Migrationsartikel!N4 -> Pane di Basilea | R6: =Migrationsartikel!G4 -> aus der Region | S6: =Migrationsartikel!K4 -> de la région | T6: =Migrationsartikel!O4 -> della regione | U6: =Migrationsartikel!H4 -> 500g | V6: =Migrationsartikel!L4 -> 500g | W6: =Migrationsartikel!P4 -> 500g | X6: =Migrationsartikel!I4 -> Baslerbrot 500g | Y6: =Migrationsartikel!M4 -> Pain bâlois 500g | Z6: =Migrationsartikel!Q4 -> Pane di Basilea 500g | AA6: =Migrationsartikel!R4 -> 0.5 | AB6: =Migrationsartikel!T4 -> Gramm | AC6: =Migrationsartikel!S4 -> 100 | AD6: =Migrationsartikel!U4 -> (PCE) Stück | AE6: 1 - Normalsatz | AF6: Keine | AG6: =IF(Migrationsartikel!AB4="ja","true",FALSE) -> true | AH6: =IF(Migrationsartikel!AC4="ja","true",FALSE) -> true | AI6: =IF(Migrationsartikel!AD4="ja","true",FALSE) -> true | AJ6: =IF(Migrationsartikel!AE4="ja","true",FALSE) -> true | AK6: =IF(Migrationsartikel!AF4="ja","Denner Partner","") | AL6: =IF(Migrationsartikel!AG4="ja","true","false") -> false | AM6: =IF(J6<>"","PLU","Kassentastenbelegung (ohne GTIN/PLU)") -> PLU | AN6: true | AO6: S4H
B7: exartikel | E7: 3 - Einzelartikel | F7: ="Warengruppe>>"&Migrationsartikel!V5&">>"&Migrationsartikel!W5&">>"&Migrationsartikel!X5 -> Warengruppe>>Backwaren & Convenience>>Brot und Backwaren>>Backwaren andere | H7: ZHAW - Handelsware ohne Charge | I7: In/Out | J7: =Migrationsartikel!B5 -> 703 | L7: =Migrationsartikel!F5&" "&Migrationsartikel!G5&" "&Migrationsartikel!H5 -> Berliner aus der Region 1Stk | M7: =Migrationsartikel!J5&" "&Migrationsartikel!K5&" "&Migrationsartikel!L5 -> Boule de Berlin de la région 1pce | N7: =Migrationsartikel!N5&" "&Migrationsartikel!O5&" "&Migrationsartikel!P5 -> Berliner della regione 1pz | O7: =Migrationsartikel!F5 -> Berliner | P7: =Migrationsartikel!J5 -> Boule de Berlin | Q7: =Migrationsartikel!N5 -> Berliner | R7: =Migrationsartikel!G5 -> aus der Region | S7: =Migrationsartikel!K5 -> de la région | T7: =Migrationsartikel!O5 -> della regione | U7: =Migrationsartikel!H5 -> 1Stk | V7: =Migrationsartikel!L5 -> 1pce | W7: =Migrationsartikel!P5 -> 1pz | X7: =Migrationsartikel!I5 -> Berliner | Y7: =Migrationsartikel!M5 -> Boule de Berlin | Z7: =Migrationsartikel!Q5 -> Berliner | AA7: =Migrationsartikel!R5 -> 1 | AB7: =Migrationsartikel!T5 -> Stück | AC7: =Migrationsartikel!S5 -> 1 | AD7: =Migrationsartikel!U5 -> (PCE) Stück | AE7: 1 - Normalsatz | AF7: Keine | AG7: =IF(Migrationsartikel!AB5="ja","true",FALSE) -> true | AH7: =IF(Migrationsartikel!AC5="ja","true",FALSE) -> true | AI7: =IF(Migrationsartikel!AD5="ja","true",FALSE) -> true | AJ7: =IF(Migrationsartikel!AE5="ja","true",FALSE) -> true | AK7: =IF(Migrationsartikel!AF5="ja","Denner Partner","") | AL7: =IF(Migrationsartikel!AG5="ja","true","false") -> false | AM7: =IF(J7<>"","PLU","Kassentastenbelegung (ohne GTIN/PLU)") -> PLU | AN7: true | AO7: S4H
B8: exartikel | E8: 4 - Einzelartikel | F8: ="Warengruppe>>"&Migrationsartikel!V6&">>"&Migrationsartikel!W6&">>"&Migrationsartikel!X6 -> Warengruppe>>Backwaren & Convenience>>Brot und Backwaren>>Backwaren andere | H8: ZHAW - Handelsware ohne Charge | I8: In/Out | J8: =Migrationsartikel!B6 -> 704 | L8: =Migrationsartikel!F6&" "&Migrationsartikel!G6&" "&Migrationsartikel!H6 -> Birewegge aus der Region 1Stk | M8: =Migrationsartikel!J6&" "&Migrationsartikel!K6&" "&Migrationsartikel!L6 -> Birewegge de la région 1pce | N8: =Migrationsartikel!N6&" "&Migrationsartikel!O6&" "&Migrationsartikel!P6 -> Birewegge della regione 1pz | O8: =Migrationsartikel!F6 -> Birewegge | P8: =Migrationsartikel!J6 -> Birewegge | Q8: =Migrationsartikel!N6 -> Birewegge | R8: =Migrationsartikel!G6 -> aus der Region | S8: =Migrationsartikel!K6 -> de la région | T8: =Migrationsartikel!O6 -> della regione | U8: =Migrationsartikel!H6 -> 1Stk | V8: =Migrationsartikel!L6 -> 1pce | W8: =Migrationsartikel!P6 -> 1pz | X8: =Migrationsartikel!I6 -> Birewegge | Y8: =Migrationsartikel!M6 -> Birewegge | Z8: =Migrationsartikel!Q6 -> Birewegge | AA8: =Migrationsartikel!R6 -> 1 | AB8: =Migrationsartikel!T6 -> Stück | AC8: =Migrationsartikel!S6 -> 1 | AD8: =Migrationsartikel!U6 -> (PCE) Stück | AE8: 1 - Normalsatz | AF8: Keine | AG8: =IF(Migrationsartikel!AB6="ja","true",FALSE) -> true | AH8: =IF(Migrationsartikel!AC6="ja","true",FALSE) -> true | AI8: =IF(Migrationsartikel!AD6="ja","true",FALSE) -> true | AJ8: =IF(Migrationsartikel!AE6="ja","true",FALSE) -> true | AK8: =IF(Migrationsartikel!AF6="ja","Denner Partner","") | AL8: =IF(Migrationsartikel!AG6="ja","true","false") -> false | AM8: =IF(J8<>"","PLU","Kassentastenbelegung (ohne GTIN/PLU)") -> PLU | AN8: true | AO8: S4H
B9: exartikel | E9: 5 - Einzelartikel | F9: ="Warengruppe>>"&Migrationsartikel!V7&">>"&Migrationsartikel!W7&">>"&Migrationsartikel!X7 -> Warengruppe>>Backwaren & Convenience>>Brot und Backwaren>>Backwaren andere | H9: ZHAW - Handelsware ohne Charge | I9: In/Out | J9: =Migrationsartikel!B7 -> 705 | L9: =Migrationsartikel!F7&" "&Migrationsartikel!G7&" "&Migrationsartikel!H7 -> Bricelets aus der Region 1Stk | M9: =Migrationsartikel!J7&" "&Migrationsartikel!K7&" "&Migrationsartikel!L7 -> Bricelets de la région 1pce | N9: =Migrationsartikel!N7&" "&Migrationsartikel!O7&" "&Migrationsartikel!P7 -> Bricelets della regione 1pz | O9: =Migrationsartikel!F7 -> Bricelets | P9: =Migrationsartikel!J7 -> Bricelets | Q9: =Migrationsartikel!N7 -> Bricelets | R9: =Migrationsartikel!G7 -> aus der Region | S9: =Migrationsartikel!K7 -> de la région | T9: =Migrationsartikel!O7 -> della regione | U9: =Migrationsartikel!H7 -> 1Stk | V9: =Migrationsartikel!L7 -> 1pce | W9: =Migrationsartikel!P7 -> 1pz | X9: =Migrationsartikel!I7 -> Bricelets | Y9: =Migrationsartikel!M7 -> Bricelets | Z9: =Migrationsartikel!Q7 -> Bricelets | AA9: =Migrationsartikel!R7 -> 1 | AB9: =Migrationsartikel!T7 -> Stück | AC9: =Migrationsartikel!S7 -> 1 | AD9: =Migrationsartikel!U7 -> (PCE) Stück | AE9: 1 - Normalsatz | AF9: Keine | AG9: =IF(Migrationsartikel!AB7="ja","true",FALSE) -> true | AH9: =IF(Migrationsartikel!AC7="ja","true",FALSE) -> true | AI9: =IF(Migrationsartikel!AD7="ja","true",FALSE) -> true | AJ9: =IF(Migrationsartikel!AE7="ja","true",FALSE) -> true | AK9: =IF(Migrationsartikel!AF7="ja","Denner Partner","") | AL9: =IF(Migrationsartikel!AG7="ja","true","false") -> false | AM9: =IF(J9<>"","PLU","Kassentastenbelegung (ohne GTIN/PLU)") -> PLU | AN9: true | AO9: S4H
B10: exartikel | E10: 6 - Einzelartikel | F10: ="Warengruppe>>"&Migrationsartikel!V8&">>"&Migrationsartikel!W8&">>"&Migrationsartikel!X8 -> Warengruppe>>Backwaren & Convenience>>Brot und Backwaren>>Backwaren andere | H10: ZHAW - Handelsware ohne Charge | I10: In/Out | J10: =Migrationsartikel!B8 -> 706 | L10: =Migrationsartikel!F8&" "&Migrationsartikel!G8&" "&Migrationsartikel!H8 -> Brioche mit Füllung aus der Region 1Stk | M10: =Migrationsartikel!J8&" "&Migrationsartikel!K8&" "&Migrationsartikel!L8 -> Brioche fourée de la région 1pce | N10: =Migrationsartikel!N8&" "&Migrationsartikel!O8&" "&Migrationsartikel!P8 -> Brioche ripiena della regione 1pz | O10: =Migrationsartikel!F8 -> Brioche mit Füllung | P10: =Migrationsartikel!J8 -> Brioche fourée | Q10: =Migrationsartikel!N8 -> Brioche ripiena | R10: =Migrationsartikel!G8 -> aus der Region | S10: =Migrationsartikel!K8 -> de la région | T10: =Migrationsartikel!O8 -> della regione | U10: =Migrationsartikel!H8 -> 1Stk | V10: =Migrationsartikel!L8 -> 1pce | W10: =Migrationsartikel!P8 -> 1pz | X10: =Migrationsartikel!I8 -> Brioche mit Füllung | Y10: =Migrationsartikel!M8 -> Brioche fourée | Z10: =Migrationsartikel!Q8 -> Brioche ripiena | AA10: =Migrationsartikel!R8 -> 1 | AB10: =Migrationsartikel!T8 -> Stück | AC10: =Migrationsartikel!S8 -> 1 | AD10: =Migrationsartikel!U8 -> (PCE) Stück | AE10: 1 - Normalsatz | AF10: Keine | AG10: =IF(Migrationsartikel!AB8="ja","true",FALSE) -> true | AH10: =IF(Migrationsartikel!AC8="ja","true",FALSE) -> true | AI10: =IF(Migrationsartikel!AD8="ja","true",FALSE) -> true | AJ10: =IF(Migrationsartikel!AE8="ja","true",FALSE) -> true | AK10: =IF(Migrationsartikel!AF8="ja","Denner Partner","") | AL10: =IF(Migrationsartikel!AG8="ja","true","false") -> false | AM10: =IF(J10<>"","PLU","Kassentastenbelegung (ohne GTIN/PLU)") -> PLU | AN10: true | AO10: S4H
B11: exartikel | E11: 7 - Einzelartikel | F11: ="Warengruppe>>"&Migrationsartikel!V9&">>"&Migrationsartikel!W9&">>"&Migrationsartikel!X9 -> Warengruppe>>Backwaren & Convenience>>Brot und Backwaren>>Backwaren andere | H11: ZHAW - Handelsware ohne Charge | I11: In/Out | J11: =Migrationsartikel!B9 -> 707 | L11: =Migrationsartikel!F9&" "&Migrationsartikel!G9&" "&Migrationsartikel!H9 -> Brot vom Beck aus der Region 1Stk | M11: =Migrationsartikel!J9&" "&Migrationsartikel!K9&" "&Migrationsartikel!L9 -> Pain du boulanger de la région 1pce | N11: =Migrationsartikel!N9&" "&Migrationsartikel!O9&" "&Migrationsartikel!P9 -> Pane del panettiere della regione 1pz | O11: =Migrationsartikel!F9 -> Brot vom Beck | P11: =Migrationsartikel!J9 -> Pain du boulanger | Q11: =Migrationsartikel!N9 -> Pane del panettiere | R11: =Migrationsartikel!G9 -> aus der Region | S11: =Migrationsartikel!K9 -> de la région | T11: =Migrationsartikel!O9 -> della regione | U11: =Migrationsartikel!H9 -> 1Stk | V11: =Migrationsartikel!L9 -> 1pce | W11: =Migrationsartikel!P9 -> 1pz | X11: =Migrationsartikel!I9 -> Brot vom Beck | Y11: =Migrationsartikel!M9 -> Pain du boulanger | Z11: =Migrationsartikel!Q9 -> Pane del panettiere | AA11: =Migrationsartikel!R9 -> 1 | AB11: =Migrationsartikel!T9 -> Stück | AC11: =Migrationsartikel!S9 -> 1 | AD11: =Migrationsartikel!U9 -> (PCE) Stück | AE11: 1 - Normalsatz | AF11: Keine | AG11: =IF(Migrationsartikel!AB9="ja","true",FALSE) -> true | AH11: =IF(Migrationsartikel!AC9="ja","true",FALSE) -> true | AI11: =IF(Migrationsartikel!AD9="ja","true",FALSE) -> true | AJ11: =IF(Migrationsartikel!AE9="ja","true",FALSE) -> true | AK11: =IF(Migrationsartikel!AF9="ja","Denner Partner","") | AL11: =IF(Migrationsartikel!AG9="ja","true","false") -> false | AM11: =IF(J11<>"","PLU","Kassentastenbelegung (ohne GTIN/PLU)") -> PLU | AN11: true | AO11: S4H
B12: exartikel | E12: 8 - Einzelartikel | F12: ="Warengruppe>>"&Migrationsartikel!V10&">>"&Migrationsartikel!W10&">>"&Migrationsartikel!X10 -> Warengruppe>>Backwaren & Convenience>>Brot und Backwaren>>Backwaren andere | H12: ZHAW - Handelsware ohne Charge | I12: In/Out | J12: =Migrationsartikel!B10 -> 708 | L12: =Migrationsartikel!F10&" "&Migrationsartikel!G10&" "&Migrationsartikel!H10 -> Brottheke aus der Region 1Stk | M12: =Migrationsartikel!J10&" "&Migrationsartikel!K10&" "&Migrationsartikel!L10 -> Comptoir à pain de la région 1pce | N12: =Migrationsartikel!N10&" "&Migrationsartikel!O10&" "&Migrationsartikel!P10 -> Banco pane della regione 1pz | O12: =Migrationsartikel!F10 -> Brottheke | P12: =Migrationsartikel!J10 -> Comptoir à pain | Q12: =Migrationsartikel!N10 -> Banco pane | R12: =Migrationsartikel!G10 -> aus der Region | S12: =Migrationsartikel!K10 -> de la région | T12: =Migrationsartikel!O10 -> della regione | U12: =Migrationsartikel!H10 -> 1Stk | V12: =Migrationsartikel!L10 -> 1pce | W12: =Migrationsartikel!P10 -> 1pz | X12: =Migrationsartikel!I10 -> Brottheke | Y12: =Migrationsartikel!M10 -> Comptoir à pain | Z12: =Migrationsartikel!Q10 -> Banco pane | AA12: =Migrationsartikel!R10 -> 1 | AB12: =Migrationsartikel!T10 -> Stück | AC12: =Migrationsartikel!S10 -> 1 | AD12: =Migrationsartikel!U10 -> (PCE) Stück | AE12: 1 - Normalsatz | AF12: Keine | AG12: =IF(Migrationsartikel!AB10="ja","true",FALSE) -> true | AH12: =IF(Migrationsartikel!AC10="ja","true",FALSE) -> true | AI12: =IF(Migrationsartikel!AD10="ja","true",FALSE) -> true | AJ12: =IF(Migrationsartikel!AE10="ja","true",FALSE) -> true | AK12: =IF(Migrationsartikel!AF10="ja","Denner Partner","") | AL12: =IF(Migrationsartikel!AG10="ja","true","false") -> false | AM12: =IF(J12<>"","PLU","Kassentastenbelegung (ohne GTIN/PLU)") -> PLU | AN12: true | AO12: S4H
B13: exartikel | E13: 9 - Einzelartikel | F13: ="Warengruppe>>"&Migrationsartikel!V11&">>"&Migrationsartikel!W11&">>"&Migrationsartikel!X11 -> Warengruppe>>Backwaren & Convenience>>Brot und Backwaren>>Backwaren andere | H13: ZHAW - Handelsware ohne Charge | I13: In/Out | J13: =Migrationsartikel!B11 -> 709 | L13: =Migrationsartikel!F11&" "&Migrationsartikel!G11&" "&Migrationsartikel!H11 -> Bürli aus der Region 1Stk | M13: =Migrationsartikel!J11&" "&Migrationsartikel!K11&" "&Migrationsartikel!L11 -> Bürli de la région 1pce | N13: =Migrationsartikel!N11&" "&Migrationsartikel!O11&" "&Migrationsartikel!P11 -> Bürli della regione 1pz | O13: =Migrationsartikel!F11 -> Bürli | P13: =Migrationsartikel!J11 -> Bürli | Q13: =Migrationsartikel!N11 -> Bürli | R13: =Migrationsartikel!G11 -> aus der Region | S13: =Migrationsartikel!K11 -> de la région | T13: =Migrationsartikel!O11 -> della regione | U13: =Migrationsartikel!H11 -> 1Stk | V13: =Migrationsartikel!L11 -> 1pce | W13: =Migrationsartikel!P11 -> 1pz | X13: =Migrationsartikel!I11 -> Bürli | Y13: =Migrationsartikel!M11 -> Bürli | Z13: =Migrationsartikel!Q11 -> Bürli | AA13: =Migrationsartikel!R11 -> 1 | AB13: =Migrationsartikel!T11 -> Stück | AC13: =Migrationsartikel!S11 -> 1 | AD13: =Migrationsartikel!U11 -> (PCE) Stück | AE13: 1 - Normalsatz | AF13: Keine | AG13: =IF(Migrationsartikel!AB11="ja","true",FALSE) -> true | AH13: =IF(Migrationsartikel!AC11="ja","true",FALSE) -> true | AI13: =IF(Migrationsartikel!AD11="ja","true",FALSE) -> true | AJ13: =IF(Migrationsartikel!AE11="ja","true",FALSE) -> true | AK13: =IF(Migrationsartikel!AF11="ja","Denner Partner","") | AL13: =IF(Migrationsartikel!AG11="ja","true","false") -> false | AM13: =IF(J13<>"","PLU","Kassentastenbelegung (ohne GTIN/PLU)") -> PLU | AN13: true | AO13: S4H
B14: exartikel | E14: 10 - Einzelartikel | F14: ="Warengruppe>>"&Migrationsartikel!V12&">>"&Migrationsartikel!W12&">>"&Migrationsartikel!X12 -> Warengruppe>>Backwaren & Convenience>>Brot und Backwaren>>Backwaren andere | H14: ZHAW - Handelsware ohne Charge | I14: In/Out | J14: =Migrationsartikel!B12 -> 710 | L14: =Migrationsartikel!F12&" "&Migrationsartikel!G12&" "&Migrationsartikel!H12 -> Buttergipfel aus der Region 1Stk | M14: =Migrationsartikel!J12&" "&Migrationsartikel!K12&" "&Migrationsartikel!L12 -> Croissant au beurre de la région 1pce | N14: =Migrationsartikel!N12&" "&Migrationsartikel!O12&" "&Migrationsartikel!P12 -> Cornetto al burro della regione 1pz | O14: =Migrationsartikel!F12 -> Buttergipfel | P14: =Migrationsartikel!J12 -> Croissant au beurre | Q14: =Migrationsartikel!N12 -> Cornetto al burro | R14: =Migrationsartikel!G12 -> aus der Region | S14: =Migrationsartikel!K12 -> de la région | T14: =Migrationsartikel!O12 -> della regione | U14: =Migrationsartikel!H12 -> 1Stk | V14: =Migrationsartikel!L12 -> 1pce | W14: =Migrationsartikel!P12 -> 1pz | X14: =Migrationsartikel!I12 -> Buttergipfel | Y14: =Migrationsartikel!M12 -> Croissant au beurre | Z14: =Migrationsartikel!Q12 -> Cornetto al burro | AA14: =Migrationsartikel!R12 -> 1 | AB14: =Migrationsartikel!T12 -> Stück | AC14: =Migrationsartikel!S12 -> 1 | AD14: =Migrationsartikel!U12 -> (PCE) Stück | AE14: 1 - Normalsatz | AF14: Keine | AG14: =IF(Migrationsartikel!AB12="ja","true",FALSE) -> true | AH14: =IF(Migrationsartikel!AC12="ja","true",FALSE) -> true | AI14: =IF(Migrationsartikel!AD12="ja","true",FALSE) -> true | AJ14: =IF(Migrationsartikel!AE12="ja","true",FALSE) -> true | AK14: =IF(Migrationsartikel!AF12="ja","Denner Partner","") | AL14: =IF(Migrationsartikel!AG12="ja","true","false") -> false | AM14: =IF(J14<>"","PLU","Kassentastenbelegung (ohne GTIN/PLU)") -> PLU | AN14: true | AO14: S4H
B15: exartikel | E15: 11 - Einzelartikel | F15: ="Warengruppe>>"&Migrationsartikel!V13&">>"&Migrationsartikel!W13&">>"&Migrationsartikel!X13 -> Warengruppe>>Backwaren & Convenience>>Brot und Backwaren>>Backwaren andere | H15: ZHAW - Handelsware ohne Charge | I15: In/Out | J15: =Migrationsartikel!B13 -> 711 | L15: =Migrationsartikel!F13&" "&Migrationsartikel!G13&" "&Migrationsartikel!H13 -> Butterzopf aus der Region 300g | M15: =Migrationsartikel!J13&" "&Migrationsartikel!K13&" "&Migrationsartikel!L13 -> Tresse de la région 300g | N15: =Migrationsartikel!N13&" "&Migrationsartikel!O13&" "&Migrationsartikel!P13 -> Treccia della regione 300g | O15: =Migrationsartikel!F13 -> Butterzopf | P15: =Migrationsartikel!J13 -> Tresse | Q15: =Migrationsartikel!N13 -> Treccia | R15: =Migrationsartikel!G13 -> aus der Region | S15: =Migrationsartikel!K13 -> de la région | T15: =Migrationsartikel!O13 -> della regione | U15: =Migrationsartikel!H13 -> 300g | V15: =Migrationsartikel!L13 -> 300g | W15: =Migrationsartikel!P13 -> 300g | X15: =Migrationsartikel!I13 -> Butterzopf 300g | Y15: =Migrationsartikel!M13 -> Tresse 300g | Z15: =Migrationsartikel!Q13 -> Treccia 300g | AA15: =Migrationsartikel!R13 -> 0.3 | AB15: =Migrationsartikel!T13 -> Gramm | AC15: =Migrationsartikel!S13 -> 100 | AD15: =Migrationsartikel!U13 -> (PCE) Stück | AE15: 1 - Normalsatz | AF15: Keine | AG15: =IF(Migrationsartikel!AB13="ja","true",FALSE) -> true | AH15: =IF(Migrationsartikel!AC13="ja","true",FALSE) -> true | AI15: =IF(Migrationsartikel!AD13="ja","true",FALSE) -> true | AJ15: =IF(Migrationsartikel!AE13="ja","true",FALSE) -> true | AK15: =IF(Migrationsartikel!AF13="ja","Denner Partner","") | AL15: =IF(Migrationsartikel!AG13="ja","true","false") -> false | AM15: =IF(J15<>"","PLU","Kassentastenbelegung (ohne GTIN/PLU)") -> PLU | AN15: true | AO15: S4H
... B330: exartikel | E330: 326 - Einzelartikel | F330: ="Warengruppe>>"&Migrationsartikel!V328&">>"&Migrationsartikel!W328&">>"&Migrationsartikel!X328 -> Warengruppe>>>>>> | H330: ZHAW - Handelsware ohne Charge | I330: In/Out | J330: =Migrationsartikel!B328 -> 0 | L330: =Migrationsartikel!F328&" "&Migrationsartikel!G328&" "&Migrationsartikel!H328 | M330: =Migrationsartikel!J328&" "&Migrationsartikel!K328&" "&Migrationsartikel!L328 | N330: =Migrationsartikel!N328&" "&Migrationsartikel!O328&" "&Migrationsartikel!P328 | O330: =Migrationsartikel!F328 -> 0 | P330: =Migrationsartikel!J328 -> 0 | Q330: =Migrationsartikel!N328 -> 0 | R330: =Migrationsartikel!G328 -> 0 | S330: =Migrationsartikel!K328 -> 0 | T330: =Migrationsartikel!O328 -> 0 | U330: =Migrationsartikel!H328 -> 0 | V330: =Migrationsartikel!L328 -> 0 | W330: =Migrationsartikel!P328 -> 0 | X330: =Migrationsartikel!I328 -> 0 | Y330: =Migrationsartikel!M328 -> 0 | Z330: =Migrationsartikel!Q328 -> 0 | AA330: =Migrationsartikel!R328 -> 0 | AB330: =Migrationsartikel!T328 -> 0 | AC330: =Migrationsartikel!S328 -> 0 | AD330: =Migrationsartikel!U328 -> 0 | AE330: 1 - Normalsatz | AF330: Keine | AG330: =IF(Migrationsartikel!AB328="ja","true",FALSE) -> FALSE | AH330: =IF(Migrationsartikel!AC328="ja","true",FALSE) -> FALSE | AI330: =IF(Migrationsartikel!AD328="ja","true",FALSE) -> FALSE | AJ330: =IF(Migrationsartikel!AE328="ja","true",FALSE) -> FALSE | AK330: =IF(Migrationsartikel!AF328="ja","Denner Partner","") | AL330: =IF(Migrationsartikel!AG328="ja","true","false") -> false | AM330: =IF(J330<>"","PLU","Kassentastenbelegung (ohne GTIN/PLU)") -> PLU | AN330: true | AO330: S4H
B331: exartikel | E331: 327 - Einzelartikel | F331: ="Warengruppe>>"&Migrationsartikel!V329&">>"&Migrationsartikel!W329&">>"&Migrationsartikel!X329 -> Warengruppe>>>>>> | H331: ZHAW - Handelsware ohne Charge | I331: In/Out | J331: =Migrationsartikel!B329 -> 0 | O331: =Migrationsartikel!F329 -> 0 | P331: =Migrationsartikel!J329 -> 0 | Q331: =Migrationsartikel!N329 -> 0 | R331: =Migrationsartikel!G329 -> 0 | S331: =Migrationsartikel!K329 -> 0 | T331: =Migrationsartikel!O329 -> 0 | U331: =Migrationsartikel!H329 -> 0 | V331: =Migrationsartikel!L329 -> 0 | W331: =Migrationsartikel!P329 -> 0 | X331: =Migrationsartikel!I329 -> 0 | Y331: =Migrationsartikel!M329 -> 0 | Z331: =Migrationsartikel!Q329 -> 0 | AA331: =Migrationsartikel!R329 -> 0 | AB331: =Migrationsartikel!T329 -> 0 | AC331: =Migrationsartikel!S329 -> 0 | AD331: =Migrationsartikel!U329 -> 0 | AE331: 1 - Normalsatz | AF331: Keine | AG331: =IF(Migrationsartikel!AB329="ja","true",FALSE) -> FALSE | AH331: =IF(Migrationsartikel!AC329="ja","true",FALSE) -> FALSE | AI331: =IF(Migrationsartikel!AD329="ja","true",FALSE) -> FALSE | AJ331: =IF(Migrationsartikel!AE329="ja","true",FALSE) -> FALSE | AK331: =IF(Migrationsartikel!AF329="ja","Denner Partner","") | AL331: =IF(Migrationsartikel!AG329="ja","true","false") -> false | AM331: =IF(J331<>"","PLU","Kassentastenbelegung (ohne GTIN/PLU)") -> PLU | AN331: true | AO331: S4H
B332: exartikel | E332: 328 - Einzelartikel | F332: ="Warengruppe>>"&Migrationsartikel!V330&">>"&Migrationsartikel!W330&">>"&Migrationsartikel!X330 -> Warengruppe>>>>>> | H332: ZHAW - Handelsware ohne Charge | I332: In/Out | J332: =Migrationsartikel!B330 -> 0 | O332: =Migrationsartikel!F330 -> 0 | P332: =Migrationsartikel!J330 -> 0 | Q332: =Migrationsartikel!N330 -> 0 | R332: =Migrationsartikel!G330 -> 0 | S332: =Migrationsartikel!K330 -> 0 | T332: =Migrationsartikel!O330 -> 0 | U332: =Migrationsartikel!H330 -> 0 | V332: =Migrationsartikel!L330 -> 0 | W332: =Migrationsartikel!P330 -> 0 | X332: =Migrationsartikel!I330 -> 0 | Y332: =Migrationsartikel!M330 -> 0 | Z332: =Migrationsartikel!Q330 -> 0 | AA332: =Migrationsartikel!R330 -> 0 | AB332: =Migrationsartikel!T330 -> 0 | AC332: =Migrationsartikel!S330 -> 0 | AD332: =Migrationsartikel!U330 -> 0 | AE332: 1 - Normalsatz | AF332: Keine | AG332: =IF(Migrationsartikel!AB330="ja","true",FALSE) -> FALSE | AH332: =IF(Migrationsartikel!AC330="ja","true",FALSE) -> FALSE | AI332: =IF(Migrationsartikel!AD330="ja","true",FALSE) -> FALSE | AJ332: =IF(Migrationsartikel!AE330="ja","true",FALSE) -> FALSE | AK332: =IF(Migrationsartikel!AF330="ja","Denner Partner","") | AL332: =IF(Migrationsartikel!AG330="ja","true","false") -> false | AM332: =IF(J332<>"","PLU","Kassentastenbelegung (ohne GTIN/PLU)") -> PLU | AN332: true | AO332: S4H
B333: exartikel | E333: 329 - Einzelartikel | F333: ="Warengruppe>>"&Migrationsartikel!V331&">>"&Migrationsartikel!W331&">>"&Migrationsartikel!X331 -> Warengruppe>>>>>> | H333: ZHAW - Handelsware ohne Charge | I333: In/Out | J333: =Migrationsartikel!B331 -> 0 | O333: =Migrationsartikel!F331 -> 0 | P333: =Migrationsartikel!J331 -> 0 | Q333: =Migrationsartikel!N331 -> 0 | R333: =Migrationsartikel!G331 -> 0 | S333: =Migrationsartikel!K331 -> 0 | T333: =Migrationsartikel!O331 -> 0 | U333: =Migrationsartikel!H331 -> 0 | V333: =Migrationsartikel!L331 -> 0 | W333: =Migrationsartikel!P331 -> 0 | X333: =Migrationsartikel!I331 -> 0 | Y333: =Migrationsartikel!M331 -> 0 | Z333: =Migrationsartikel!Q331 -> 0 | AA333: =Migrationsartikel!R331 -> 0 | AB333: =Migrationsartikel!T331 -> 0 | AC333: =Migrationsartikel!S331 -> 0 | AD333: =Migrationsartikel!U331 -> 0 | AE333: 1 - Normalsatz | AF333: Keine | AG333: =IF(Migrationsartikel!AB331="ja","true",FALSE) -> FALSE | AH333: =IF(Migrationsartikel!AC331="ja","true",FALSE) -> FALSE | AI333: =IF(Migrationsartikel!AD331="ja","true",FALSE) -> FALSE | AJ333: =IF(Migrationsartikel!AE331="ja","true",FALSE) -> FALSE | AK333: =IF(Migrationsartikel!AF331="ja","Denner Partner","") | AL333: =IF(Migrationsartikel!AG331="ja","true","false") -> false | AM333: =IF(J333<>"","PLU","Kassentastenbelegung (ohne GTIN/PLU)") -> PLU | AN333: true | AO333: S4H
B334: exartikel | E334: 330 - Einzelartikel | F334: ="Warengruppe>>"&Migrationsartikel!V332&">>"&Migrationsartikel!W332&">>"&Migrationsartikel!X332 -> Warengruppe>>>>>> | H334: ZHAW - Handelsware ohne Charge | I334: In/Out | J334: =Migrationsartikel!B332 -> 0 | O334: =Migrationsartikel!F332 -> 0 | P334: =Migrationsartikel!J332 -> 0 | Q334: =Migrationsartikel!N332 -> 0 | R334: =Migrationsartikel!G332 -> 0 | S334: =Migrationsartikel!K332 -> 0 | T334: =Migrationsartikel!O332 -> 0 | U334: =Migrationsartikel!H332 -> 0 | V334: =Migrationsartikel!L332 -> 0 | W334: =Migrationsartikel!P332 -> 0 | X334: =Migrationsartikel!I332 -> 0 | Y334: =Migrationsartikel!M332 -> 0 | Z334: =Migrationsartikel!Q332 -> 0 | AA334: =Migrationsartikel!R332 -> 0 | AB334: =Migrationsartikel!T332 -> 0 | AC334: =Migrationsartikel!S332 -> 0 | AD334: =Migrationsartikel!U332 -> 0 | AE334: 1 - Normalsatz | AF334: Keine | AG334: =IF(Migrationsartikel!AB332="ja","true",FALSE) -> FALSE | AH334: =IF(Migrationsartikel!AC332="ja","true",FALSE) -> FALSE | AI334: =IF(Migrationsartikel!AD332="ja","true",FALSE) -> FALSE | AJ334: =IF(Migrationsartikel!AE332="ja","true",FALSE) -> FALSE | AK334: =IF(Migrationsartikel!AF332="ja","Denner Partner","") | AL334: =IF(Migrationsartikel!AG332="ja","true","false") -> false | AM334: =IF(J334<>"","PLU","Kassentastenbelegung (ohne GTIN/PLU)") -> PLU | AN334: true | AO334: S4H
B335: exartikel | E335: 331 - Einzelartikel | F335: ="Warengruppe>>"&Migrationsartikel!V333&">>"&Migrationsartikel!W333&">>"&Migrationsartikel!X333 -> Warengruppe>>>>>> | H335: ZHAW - Handelsware ohne Charge | I335: In/Out | J335: =Migrationsartikel!B333 -> 0 | O335: =Migrationsartikel!F333 -> 0 | P335: =Migrationsartikel!J333 -> 0 | Q335: =Migrationsartikel!N333 -> 0 | R335: =Migrationsartikel!G333 -> 0 | S335: =Migrationsartikel!K333 -> 0 | T335: =Migrationsartikel!O333 -> 0 | U335: =Migrationsartikel!H333 -> 0 | V335: =Migrationsartikel!L333 -> 0 | W335: =Migrationsartikel!P333 -> 0 | X335: =Migrationsartikel!I333 -> 0 | Y335: =Migrationsartikel!M333 -> 0 | Z335: =Migrationsartikel!Q333 -> 0 | AA335: =Migrationsartikel!R333 -> 0 | AB335: =Migrationsartikel!T333 -> 0 | AC335: =Migrationsartikel!S333 -> 0 | AD335: =Migrationsartikel!U333 -> 0 | AE335: 1 - Normalsatz | AF335: Keine | AG335: =IF(Migrationsartikel!AB333="ja","true",FALSE) -> FALSE | AH335: =IF(Migrationsartikel!AC333="ja","true",FALSE) -> FALSE | AI335: =IF(Migrationsartikel!AD333="ja","true",FALSE) -> FALSE | AJ335: =IF(Migrationsartikel!AE333="ja","true",FALSE) -> FALSE | AK335: =IF(Migrationsartikel!AF333="ja","Denner Partner","") | AL335: =IF(Migrationsartikel!AG333="ja","true","false") -> false | AM335: =IF(J335<>"","PLU","Kassentastenbelegung (ohne GTIN/PLU)") -> PLU | AN335: true | AO335: S4H
B336: exartikel | E336: 332 - Einzelartikel | F336: ="Warengruppe>>"&Migrationsartikel!V334&">>"&Migrationsartikel!W334&">>"&Migrationsartikel!X334 -> Warengruppe>>>>>> | H336: ZHAW - Handelsware ohne Charge | I336: In/Out | J336: =Migrationsartikel!B334 -> 0 | O336: =Migrationsartikel!F334 -> 0 | P336: =Migrationsartikel!J334 -> 0 | Q336: =Migrationsartikel!N334 -> 0 | R336: =Migrationsartikel!G334 -> 0 | S336: =Migrationsartikel!K334 -> 0 | T336: =Migrationsartikel!O334 -> 0 | U336: =Migrationsartikel!H334 -> 0 | V336: =Migrationsartikel!L334 -> 0 | W336: =Migrationsartikel!P334 -> 0 | X336: =Migrationsartikel!I334 -> 0 | Y336: =Migrationsartikel!M334 -> 0 | Z336: =Migrationsartikel!Q334 -> 0 | AA336: =Migrationsartikel!R334 -> 0 | AB336: =Migrationsartikel!T334 -> 0 | AC336: =Migrationsartikel!S334 -> 0 | AD336: =Migrationsartikel!U334 -> 0 | AE336: 1 - Normalsatz | AF336: Keine | AG336: =IF(Migrationsartikel!AB334="ja","true",FALSE) -> FALSE | AH336: =IF(Migrationsartikel!AC334="ja","true",FALSE) -> FALSE | AI336: =IF(Migrationsartikel!AD334="ja","true",FALSE) -> FALSE | AJ336: =IF(Migrationsartikel!AE334="ja","true",FALSE) -> FALSE | AK336: =IF(Migrationsartikel!AF334="ja","Denner Partner","") | AL336: =IF(Migrationsartikel!AG334="ja","true","false") -> false | AM336: =IF(J336<>"","PLU","Kassentastenbelegung (ohne GTIN/PLU)") -> PLU | AN336: true | AO336: S4H
B337: exartikel | E337: 333 - Einzelartikel | F337: ="Warengruppe>>"&Migrationsartikel!V335&">>"&Migrationsartikel!W335&">>"&Migrationsartikel!X335 -> Warengruppe>>>>>> | H337: ZHAW - Handelsware ohne Charge | I337: In/Out | J337: =Migrationsartikel!B335 -> 0 | O337: =Migrationsartikel!F335 -> 0 | P337: =Migrationsartikel!J335 -> 0 | Q337: =Migrationsartikel!N335 -> 0 | R337: =Migrationsartikel!G335 -> 0 | S337: =Migrationsartikel!K335 -> 0 | T337: =Migrationsartikel!O335 -> 0 | U337: =Migrationsartikel!H335 -> 0 | V337: =Migrationsartikel!L335 -> 0 | W337: =Migrationsartikel!P335 -> 0 | X337: =Migrationsartikel!I335 -> 0 | Y337: =Migrationsartikel!M335 -> 0 | Z337: =Migrationsartikel!Q335 -> 0 | AA337: =Migrationsartikel!R335 -> 0 | AB337: =Migrationsartikel!T335 -> 0 | AC337: =Migrationsartikel!S335 -> 0 | AD337: =Migrationsartikel!U335 -> 0 | AE337: 1 - Normalsatz | AF337: Keine | AG337: =IF(Migrationsartikel!AB335="ja","true",FALSE) -> FALSE | AH337: =IF(Migrationsartikel!AC335="ja","true",FALSE) -> FALSE | AI337: =IF(Migrationsartikel!AD335="ja","true",FALSE) -> FALSE | AJ337: =IF(Migrationsartikel!AE335="ja","true",FALSE) -> FALSE | AK337: =IF(Migrationsartikel!AF335="ja","Denner Partner","") | AL337: =IF(Migrationsartikel!AG335="ja","true","false") -> false | AM337: =IF(J337<>"","PLU","Kassentastenbelegung (ohne GTIN/PLU)") -> PLU | AN337: true | AO337: S4H
B338: exartikel | E338: 334 - Einzelartikel | F338: ="Warengruppe>>"&Migrationsartikel!V336&">>"&Migrationsartikel!W336&">>"&Migrationsartikel!X336 -> Warengruppe>>>>>> | H338: ZHAW - Handelsware ohne Charge | I338: In/Out | J338: =Migrationsartikel!B336 -> 0 | O338: =Migrationsartikel!F336 -> 0 | P338: =Migrationsartikel!J336 -> 0 | Q338: =Migrationsartikel!N336 -> 0 | R338: =Migrationsartikel!G336 -> 0 | S338: =Migrationsartikel!K336 -> 0 | T338: =Migrationsartikel!O336 -> 0 | U338: =Migrationsartikel!H336 -> 0 | V338: =Migrationsartikel!L336 -> 0 | W338: =Migrationsartikel!P336 -> 0 | X338: =Migrationsartikel!I336 -> 0 | Y338: =Migrationsartikel!M336 -> 0 | Z338: =Migrationsartikel!Q336 -> 0 | AA338: =Migrationsartikel!R336 -> 0 | AB338: =Migrationsartikel!T336 -> 0 | AC338: =Migrationsartikel!S336 -> 0 | AD338: =Migrationsartikel!U336 -> 0 | AE338: 1 - Normalsatz | AF338: Keine | AG338: =IF(Migrationsartikel!AB336="ja","true",FALSE) -> FALSE | AH338: =IF(Migrationsartikel!AC336="ja","true",FALSE) -> FALSE | AI338: =IF(Migrationsartikel!AD336="ja","true",FALSE) -> FALSE | AJ338: =IF(Migrationsartikel!AE336="ja","true",FALSE) -> FALSE | AK338: =IF(Migrationsartikel!AF336="ja","Denner Partner","") | AL338: =IF(Migrationsartikel!AG336="ja","true","false") -> false | AM338: =IF(J338<>"","PLU","Kassentastenbelegung (ohne GTIN/PLU)") -> PLU | AN338: true | AO338: S4H
B339: exartikel | E339: 335 - Einzelartikel | F339: ="Warengruppe>>"&Migrationsartikel!V337&">>"&Migrationsartikel!W337&">>"&Migrationsartikel!X337 -> Warengruppe>>>>>> | H339: ZHAW - Handelsware ohne Charge | I339: In/Out | J339: =Migrationsartikel!B337 -> 0 | O339: =Migrationsartikel!F337 -> 0 | P339: =Migrationsartikel!J337 -> 0 | Q339: =Migrationsartikel!N337 -> 0 | R339: =Migrationsartikel!G337 -> 0 | S339: =Migrationsartikel!K337 -> 0 | T339: =Migrationsartikel!O337 -> 0 | U339: =Migrationsartikel!H337 -> 0 | V339: =Migrationsartikel!L337 -> 0 | W339: =Migrationsartikel!P337 -> 0 | X339: =Migrationsartikel!I337 -> 0 | Y339: =Migrationsartikel!M337 -> 0 | Z339: =Migrationsartikel!Q337 -> 0 | AA339: =Migrationsartikel!R337 -> 0 | AB339: =Migrationsartikel!T337 -> 0 | AC339: =Migrationsartikel!S337 -> 0 | AD339: =Migrationsartikel!U337 -> 0 | AE339: 1 - Normalsatz | AF339: Keine | AG339: =IF(Migrationsartikel!AB337="ja","true",FALSE) -> FALSE | AH339: =IF(Migrationsartikel!AC337="ja","true",FALSE) -> FALSE | AI339: =IF(Migrationsartikel!AD337="ja","true",FALSE) -> FALSE | AJ339: =IF(Migrationsartikel!AE337="ja","true",FALSE) -> FALSE | AK339: =IF(Migrationsartikel!AF337="ja","Denner Partner","") | AL339: =IF(Migrationsartikel!AG337="ja","true","false") -> false | AM339: =IF(J339<>"","PLU","Kassentastenbelegung (ohne GTIN/PLU)") -> PLU | AN339: true | AO339: S4H
B340: exartikel | E340: 336 - Einzelartikel | F340: ="Warengruppe>>"&Migrationsartikel!V338&">>"&Migrationsartikel!W338&">>"&Migrationsartikel!X338 -> Warengruppe>>>>>> | H340: ZHAW - Handelsware ohne Charge | I340: In/Out | J340: =Migrationsartikel!B338 -> 0 | O340: =Migrationsartikel!F338 -> 0 | P340: =Migrationsartikel!J338 -> 0 | Q340: =Migrationsartikel!N338 -> 0 | R340: =Migrationsartikel!G338 -> 0 | S340: =Migrationsartikel!K338 -> 0 | T340: =Migrationsartikel!O338 -> 0 | U340: =Migrationsartikel!H338 -> 0 | V340: =Migrationsartikel!L338 -> 0 | W340: =Migrationsartikel!P338 -> 0 | X340: =Migrationsartikel!I338 -> 0 | Y340: =Migrationsartikel!M338 -> 0 | Z340: =Migrationsartikel!Q338 -> 0 | AA340: =Migrationsartikel!R338 -> 0 | AB340: =Migrationsartikel!T338 -> 0 | AC340: =Migrationsartikel!S338 -> 0 | AD340: =Migrationsartikel!U338 -> 0 | AE340: 1 - Normalsatz | AF340: Keine | AG340: =IF(Migrationsartikel!AB338="ja","true",FALSE) -> FALSE | AH340: =IF(Migrationsartikel!AC338="ja","true",FALSE) -> FALSE | AI340: =IF(Migrationsartikel!AD338="ja","true",FALSE) -> FALSE | AJ340: =IF(Migrationsartikel!AE338="ja","true",FALSE) -> FALSE | AK340: =IF(Migrationsartikel!AF338="ja","Denner Partner","") | AL340: =IF(Migrationsartikel!AG338="ja","true","false") -> false | AM340: =IF(J340<>"","PLU","Kassentastenbelegung (ohne GTIN/PLU)") -> PLU | AN340: true | AO340: S4H
B341: exartikel | E341: 337 - Einzelartikel | F341: ="Warengruppe>>"&Migrationsartikel!V339&">>"&Migrationsartikel!W339&">>"&Migrationsartikel!X339 -> Warengruppe>>>>>> | H341: ZHAW - Handelsware ohne Charge | I341: In/Out | J341: =Migrationsartikel!B339 -> 0 | O341: =Migrationsartikel!F339 -> 0 | P341: =Migrationsartikel!J339 -> 0 | Q341: =Migrationsartikel!N339 -> 0 | R341: =Migrationsartikel!G339 -> 0 | S341: =Migrationsartikel!K339 -> 0 | T341: =Migrationsartikel!O339 -> 0 | U341: =Migrationsartikel!H339 -> 0 | V341: =Migrationsartikel!L339 -> 0 | W341: =Migrationsartikel!P339 -> 0 | X341: =Migrationsartikel!I339 -> 0 | Y341: =Migrationsartikel!M339 -> 0 | Z341: =Migrationsartikel!Q339 -> 0 | AA341: =Migrationsartikel!R339 -> 0 | AB341: =Migrationsartikel!T339 -> 0 | AC341: =Migrationsartikel!S339 -> 0 | AD341: =Migrationsartikel!U339 -> 0 | AE341: 1 - Normalsatz | AF341: Keine | AG341: =IF(Migrationsartikel!AB339="ja","true",FALSE) -> FALSE | AH341: =IF(Migrationsartikel!AC339="ja","true",FALSE) -> FALSE | AI341: =IF(Migrationsartikel!AD339="ja","true",FALSE) -> FALSE | AJ341: =IF(Migrationsartikel!AE339="ja","true",FALSE) -> FALSE | AK341: =IF(Migrationsartikel!AF339="ja","Denner Partner","") | AL341: =IF(Migrationsartikel!AG339="ja","true","false") -> false | AM341: =IF(J341<>"","PLU","Kassentastenbelegung (ohne GTIN/PLU)") -> PLU | AN341: true | AO341: S4H
B342: exartikel | E342: 338 - Einzelartikel | F342: ="Warengruppe>>"&Migrationsartikel!V340&">>"&Migrationsartikel!W340&">>"&Migrationsartikel!X340 -> Warengruppe>>>>>> | H342: ZHAW - Handelsware ohne Charge | I342: In/Out | J342: =Migrationsartikel!B340 -> 0 | O342: =Migrationsartikel!F340 -> 0 | P342: =Migrationsartikel!J340 -> 0 | Q342: =Migrationsartikel!N340 -> 0 | R342: =Migrationsartikel!G340 -> 0 | S342: =Migrationsartikel!K340 -> 0 | T342: =Migrationsartikel!O340 -> 0 | U342: =Migrationsartikel!H340 -> 0 | V342: =Migrationsartikel!L340 -> 0 | W342: =Migrationsartikel!P340 -> 0 | X342: =Migrationsartikel!I340 -> 0 | Y342: =Migrationsartikel!M340 -> 0 | Z342: =Migrationsartikel!Q340 -> 0 | AA342: =Migrationsartikel!R340 -> 0 | AB342: =Migrationsartikel!T340 -> 0 | AC342: =Migrationsartikel!S340 -> 0 | AD342: =Migrationsartikel!U340 -> 0 | AE342: 1 - Normalsatz | AF342: Keine | AG342: =IF(Migrationsartikel!AB340="ja","true",FALSE) -> FALSE | AH342: =IF(Migrationsartikel!AC340="ja","true",FALSE) -> FALSE | AI342: =IF(Migrationsartikel!AD340="ja","true",FALSE) -> FALSE | AJ342: =IF(Migrationsartikel!AE340="ja","true",FALSE) -> FALSE | AK342: =IF(Migrationsartikel!AF340="ja","Denner Partner","") | AL342: =IF(Migrationsartikel!AG340="ja","true","false") -> false | AM342: =IF(J342<>"","PLU","Kassentastenbelegung (ohne GTIN/PLU)") -> PLU | AN342: true | AO342: S4H
... B488: exartikel | E488: 484 - Einzelartikel | F488: ="Warengruppe>>"&Migrationsartikel!V486&">>"&Migrationsartikel!W486&">>"&Migrationsartikel!X486 -> Warengruppe>>>>>> | H488: ZHAW - Handelsware ohne Charge | I488: In/Out | J488: =Migrationsartikel!B486 -> 0 | O488: =Migrationsartikel!F486 -> 0 | P488: =Migrationsartikel!J486 -> 0 | Q488: =Migrationsartikel!N486 -> 0 | R488: =Migrationsartikel!G486 -> 0 | S488: =Migrationsartikel!K486 -> 0 | T488: =Migrationsartikel!O486 -> 0 | U488: =Migrationsartikel!H486 -> 0 | V488: =Migrationsartikel!L486 -> 0 | W488: =Migrationsartikel!P486 -> 0 | X488: =Migrationsartikel!I486 -> 0 | Y488: =Migrationsartikel!M486 -> 0 | Z488: =Migrationsartikel!Q486 -> 0 | AA488: =Migrationsartikel!R486 -> 0 | AB488: =Migrationsartikel!T486 -> 0 | AC488: =Migrationsartikel!S486 -> 0 | AD488: =Migrationsartikel!U486 -> 0 | AE488: 1 - Normalsatz | AF488: Keine | AG488: =IF(Migrationsartikel!AB486="ja","true",FALSE) -> FALSE | AH488: =IF(Migrationsartikel!AC486="ja","true",FALSE) -> FALSE | AI488: =IF(Migrationsartikel!AD486="ja","true",FALSE) -> FALSE | AJ488: =IF(Migrationsartikel!AE486="ja","true",FALSE) -> FALSE | AK488: =IF(Migrationsartikel!AF486="ja","Denner Partner","") | AL488: =IF(Migrationsartikel!AG486="ja","true","false") -> false | AM488: =IF(J488<>"","PLU","Kassentastenbelegung (ohne GTIN/PLU)") -> PLU | AN488: true | AO488: S4H
B489: exartikel | E489: 485 - Einzelartikel | F489: ="Warengruppe>>"&Migrationsartikel!V487&">>"&Migrationsartikel!W487&">>"&Migrationsartikel!X487 -> Warengruppe>>>>>> | H489: ZHAW - Handelsware ohne Charge | I489: In/Out | O489: =Migrationsartikel!F487 -> 0 | P489: =Migrationsartikel!J487 -> 0 | Q489: =Migrationsartikel!N487 -> 0 | R489: =Migrationsartikel!G487 -> 0 | S489: =Migrationsartikel!K487 -> 0 | T489: =Migrationsartikel!O487 -> 0 | U489: =Migrationsartikel!H487 -> 0 | V489: =Migrationsartikel!L487 -> 0 | W489: =Migrationsartikel!P487 -> 0 | X489: =Migrationsartikel!I487 -> 0 | Y489: =Migrationsartikel!M487 -> 0 | Z489: =Migrationsartikel!Q487 -> 0 | AA489: =Migrationsartikel!R487 -> 0 | AB489: =Migrationsartikel!T487 -> 0 | AC489: =Migrationsartikel!S487 -> 0 | AD489: =Migrationsartikel!U487 -> 0 | AE489: 1 - Normalsatz | AF489: Keine | AG489: =IF(Migrationsartikel!AB487="ja","true",FALSE) -> FALSE | AH489: =IF(Migrationsartikel!AC487="ja","true",FALSE) -> FALSE | AI489: =IF(Migrationsartikel!AD487="ja","true",FALSE) -> FALSE | AJ489: =IF(Migrationsartikel!AE487="ja","true",FALSE) -> FALSE | AK489: =IF(Migrationsartikel!AF487="ja","Denner Partner","") | AL489: =IF(Migrationsartikel!AG487="ja","true","false") -> false | AM489: =IF(J489<>"","PLU","Kassentastenbelegung (ohne GTIN/PLU)") -> Kassentastenbelegung (ohne GTIN/PLU) | AN489: true | AO489: S4H
B490: exartikel | E490: 486 - Einzelartikel | F490: ="Warengruppe>>"&Migrationsartikel!V488&">>"&Migrationsartikel!W488&">>"&Migrationsartikel!X488 -> Warengruppe>>>>>> | H490: ZHAW - Handelsware ohne Charge | I490: In/Out | O490: =Migrationsartikel!F488 -> 0 | P490: =Migrationsartikel!J488 -> 0 | Q490: =Migrationsartikel!N488 -> 0 | R490: =Migrationsartikel!G488 -> 0 | S490: =Migrationsartikel!K488 -> 0 | T490: =Migrationsartikel!O488 -> 0 | U490: =Migrationsartikel!H488 -> 0 | V490: =Migrationsartikel!L488 -> 0 | W490: =Migrationsartikel!P488 -> 0 | X490: =Migrationsartikel!I488 -> 0 | Y490: =Migrationsartikel!M488 -> 0 | Z490: =Migrationsartikel!Q488 -> 0 | AA490: =Migrationsartikel!R488 -> 0 | AB490: =Migrationsartikel!T488 -> 0 | AC490: =Migrationsartikel!S488 -> 0 | AD490: =Migrationsartikel!U488 -> 0 | AE490: 1 - Normalsatz | AF490: Keine | AG490: =IF(Migrationsartikel!AB488="ja","true",FALSE) -> FALSE | AH490: =IF(Migrationsartikel!AC488="ja","true",FALSE) -> FALSE | AI490: =IF(Migrationsartikel!AD488="ja","true",FALSE) -> FALSE | AJ490: =IF(Migrationsartikel!AE488="ja","true",FALSE) -> FALSE | AK490: =IF(Migrationsartikel!AF488="ja","Denner Partner","") | AL490: =IF(Migrationsartikel!AG488="ja","true","false") -> false | AM490: =IF(J490<>"","PLU","Kassentastenbelegung (ohne GTIN/PLU)") -> Kassentastenbelegung (ohne GTIN/PLU) | AN490: true | AO490: S4H
B491: exartikel | E491: 487 - Einzelartikel | F491: ="Warengruppe>>"&Migrationsartikel!V489&">>"&Migrationsartikel!W489&">>"&Migrationsartikel!X489 -> Warengruppe>>>>>> | H491: ZHAW - Handelsware ohne Charge | I491: In/Out | O491: =Migrationsartikel!F489 -> 0 | P491: =Migrationsartikel!J489 -> 0 | Q491: =Migrationsartikel!N489 -> 0 | R491: =Migrationsartikel!G489 -> 0 | S491: =Migrationsartikel!K489 -> 0 | T491: =Migrationsartikel!O489 -> 0 | U491: =Migrationsartikel!H489 -> 0 | V491: =Migrationsartikel!L489 -> 0 | W491: =Migrationsartikel!P489 -> 0 | X491: =Migrationsartikel!I489 -> 0 | Y491: =Migrationsartikel!M489 -> 0 | Z491: =Migrationsartikel!Q489 -> 0 | AA491: =Migrationsartikel!R489 -> 0 | AB491: =Migrationsartikel!T489 -> 0 | AC491: =Migrationsartikel!S489 -> 0 | AD491: =Migrationsartikel!U489 -> 0 | AE491: 1 - Normalsatz | AF491: Keine | AG491: =IF(Migrationsartikel!AB489="ja","true",FALSE) -> FALSE | AH491: =IF(Migrationsartikel!AC489="ja","true",FALSE) -> FALSE | AI491: =IF(Migrationsartikel!AD489="ja","true",FALSE) -> FALSE | AJ491: =IF(Migrationsartikel!AE489="ja","true",FALSE) -> FALSE | AK491: =IF(Migrationsartikel!AF489="ja","Denner Partner","") | AL491: =IF(Migrationsartikel!AG489="ja","true","false") -> false | AM491: =IF(J491<>"","PLU","Kassentastenbelegung (ohne GTIN/PLU)") -> Kassentastenbelegung (ohne GTIN/PLU) | AN491: true | AO491: S4H
B492: exartikel | E492: 488 - Einzelartikel | F492: ="Warengruppe>>"&Migrationsartikel!V490&">>"&Migrationsartikel!W490&">>"&Migrationsartikel!X490 -> Warengruppe>>>>>> | H492: ZHAW - Handelsware ohne Charge | I492: In/Out | O492: =Migrationsartikel!F490 -> 0 | P492: =Migrationsartikel!J490 -> 0 | Q492: =Migrationsartikel!N490 -> 0 | R492: =Migrationsartikel!G490 -> 0 | S492: =Migrationsartikel!K490 -> 0 | T492: =Migrationsartikel!O490 -> 0 | U492: =Migrationsartikel!H490 -> 0 | V492: =Migrationsartikel!L490 -> 0 | W492: =Migrationsartikel!P490 -> 0 | X492: =Migrationsartikel!I490 -> 0 | Y492: =Migrationsartikel!M490 -> 0 | Z492: =Migrationsartikel!Q490 -> 0 | AA492: =Migrationsartikel!R490 -> 0 | AB492: =Migrationsartikel!T490 -> 0 | AC492: =Migrationsartikel!S490 -> 0 | AD492: =Migrationsartikel!U490 -> 0 | AE492: 1 - Normalsatz | AF492: Keine | AG492: =IF(Migrationsartikel!AB490="ja","true",FALSE) -> FALSE | AH492: =IF(Migrationsartikel!AC490="ja","true",FALSE) -> FALSE | AI492: =IF(Migrationsartikel!AD490="ja","true",FALSE) -> FALSE | AJ492: =IF(Migrationsartikel!AE490="ja","true",FALSE) -> FALSE | AK492: =IF(Migrationsartikel!AF490="ja","Denner Partner","") | AL492: =IF(Migrationsartikel!AG490="ja","true","false") -> false | AM492: =IF(J492<>"","PLU","Kassentastenbelegung (ohne GTIN/PLU)") -> Kassentastenbelegung (ohne GTIN/PLU) | AN492: true | AO492: S4H
B493: exartikel | E493: 489 - Einzelartikel | F493: ="Warengruppe>>"&Migrationsartikel!V491&">>"&Migrationsartikel!W491&">>"&Migrationsartikel!X491 -> Warengruppe>>>>>> | H493: ZHAW - Handelsware ohne Charge | I493: In/Out | O493: =Migrationsartikel!F491 -> 0 | P493: =Migrationsartikel!J491 -> 0 | Q493: =Migrationsartikel!N491 -> 0 | R493: =Migrationsartikel!G491 -> 0 | S493: =Migrationsartikel!K491 -> 0 | T493: =Migrationsartikel!O491 -> 0 | U493: =Migrationsartikel!H491 -> 0 | V493: =Migrationsartikel!L491 -> 0 | W493: =Migrationsartikel!P491 -> 0 | X493: =Migrationsartikel!I491 -> 0 | Y493: =Migrationsartikel!M491 -> 0 | Z493: =Migrationsartikel!Q491 -> 0 | AA493: =Migrationsartikel!R491 -> 0 | AB493: =Migrationsartikel!T491 -> 0 | AC493: =Migrationsartikel!S491 -> 0 | AD493: =Migrationsartikel!U491 -> 0 | AE493: 1 - Normalsatz | AF493: Keine | AG493: =IF(Migrationsartikel!AB491="ja","true",FALSE) -> FALSE | AH493: =IF(Migrationsartikel!AC491="ja","true",FALSE) -> FALSE | AI493: =IF(Migrationsartikel!AD491="ja","true",FALSE) -> FALSE | AJ493: =IF(Migrationsartikel!AE491="ja","true",FALSE) -> FALSE | AK493: =IF(Migrationsartikel!AF491="ja","Denner Partner","") | AL493: =IF(Migrationsartikel!AG491="ja","true","false") -> false | AM493: =IF(J493<>"","PLU","Kassentastenbelegung (ohne GTIN/PLU)") -> Kassentastenbelegung (ohne GTIN/PLU) | AN493: true | AO493: S4H
B494: exartikel | E494: 490 - Einzelartikel | F494: ="Warengruppe>>"&Migrationsartikel!V492&">>"&Migrationsartikel!W492&">>"&Migrationsartikel!X492 -> Warengruppe>>>>>> | H494: ZHAW - Handelsware ohne Charge | I494: In/Out | O494: =Migrationsartikel!F492 -> 0 | P494: =Migrationsartikel!J492 -> 0 | Q494: =Migrationsartikel!N492 -> 0 | R494: =Migrationsartikel!G492 -> 0 | S494: =Migrationsartikel!K492 -> 0 | T494: =Migrationsartikel!O492 -> 0 | U494: =Migrationsartikel!H492 -> 0 | V494: =Migrationsartikel!L492 -> 0 | W494: =Migrationsartikel!P492 -> 0 | X494: =Migrationsartikel!I492 -> 0 | Y494: =Migrationsartikel!M492 -> 0 | Z494: =Migrationsartikel!Q492 -> 0 | AA494: =Migrationsartikel!R492 -> 0 | AB494: =Migrationsartikel!T492 -> 0 | AC494: =Migrationsartikel!S492 -> 0 | AD494: =Migrationsartikel!U492 -> 0 | AE494: 1 - Normalsatz | AF494: Keine | AG494: =IF(Migrationsartikel!AB492="ja","true",FALSE) -> FALSE | AH494: =IF(Migrationsartikel!AC492="ja","true",FALSE) -> FALSE | AI494: =IF(Migrationsartikel!AD492="ja","true",FALSE) -> FALSE | AJ494: =IF(Migrationsartikel!AE492="ja","true",FALSE) -> FALSE | AK494: =IF(Migrationsartikel!AF492="ja","Denner Partner","") | AL494: =IF(Migrationsartikel!AG492="ja","true","false") -> false | AM494: =IF(J494<>"","PLU","Kassentastenbelegung (ohne GTIN/PLU)") -> Kassentastenbelegung (ohne GTIN/PLU) | AN494: true | AO494: S4H

Sheet Migrationsartikel
A1: Lf Nr. | B1: PLU-Nr. neu | C1: Stk / kg | D1: PAZ | E1: EAN | F1: Gestellbeschriftung 1 Max. 22 Zeichen (d) | G1: Gestellbeschriftung 2 Max. 22 Zeichen (d) | H1: Gestellbeschriftung 3 Max. 4-8 Zeichen (d) | I1: Kassenbontext Max. 28 Zeichen (d) | J1: Gestellbeschriftung 1 Max. 22 Zeichen (f) | K1: Gestellbeschriftung 2 Max. 22 Zeichen (f) | L1: Gestellbeschriftung 3 Max. 4-8 Zeichen (f) | M1: Kassenbontext Max. 28 Zeichen (f) | N1: Gestellbeschriftung 1 Max. 22 Zeichen (i) | O1: Gestellbeschriftung 2 Max. 22 Zeichen (i) | P1: Gestellbeschriftung 3 Max. 4-8 Zeichen (i) | Q1: Kassenbontext Max. 28 Zeichen (i) | R1: Nettoinhalt | S1: Grundpreismenge Feld 1 | T1: Grundpreismenge Feld 2 | U1: Basismengeneinheit Waage = Kg Verkauf = Stk = Stk Relevant für Berechnungen im MDM/SAP | V1: Warengruppe 1. Feld | W1: Warengruppe 2. Feld | X1: Warengruppe 3. Feld | Y1: Steuerklassifikation | Z1: Altersbegrenzung | AA1: Depot | AB1: Rabatt zugelassen | AC1: Rückgabe zugelassen | AD1: Preisänderung zugelassen | AE1: Etiketten-druck | AF1: Shop-in-Shop | AG1: Fremdartikel | AH1: Qualitätsanforderung geprüft | AI1: Verkaufskonditionen | AJ1: Lieferant
A2: 1 | B2: 700 | C2: Stk | D2: Nein | F2: Baguette | G2: aus der Region | H2: 250g | I2: Baguette 250g | J2: Baguette | K2: de la région | L2: 250g | M2: Baguette 250g | N2: Baguette | O2: della regione | P2: 250g | Q2: Baguette 250g | R2: 0.25 | S2: 100 | T2: Gramm | U2: (PCE) Stück | V2: Backwaren & Convenience | W2: Brot und Backwaren | X2: Backwaren andere | AB2: ja | AC2: ja | AD2: ja | AE2: ja | AF2: - | AG2: - | AH2: ja | AI2: 0.05 | AJ2: -
A3: 2 | B3: 701 | C3: Stk | D3: Nein | F3: Baslerbrot | G3: aus der Region | H3: 250g | I3: Baslerbrot 250g | J3: Pain bâlois | K3: de la région | L3: 250g | M3: Pain bâlois 250g | N3: Pane di Basilea | O3: della regione | P3: 250g | Q3: Pane di Basilea 250g | R3: 0.25 | S3: 100 | T3: Gramm | U3: (PCE) Stück | V3: Backwaren & Convenience | W3: Brot und Backwaren | X3: Backwaren andere | AB3: ja | AC3: ja | AD3: ja | AE3: ja | AF3: - | AG3: - | AH3: ja | AI3: 0.05 | AJ3: -
A4: 3 | B4: 702 | C4: Stk | D4: Nein | F4: Baslerbrot | G4: aus der Region | H4: 500g | I4: Baslerbrot 500g | J4: Pain bâlois | K4: de la région | L4: 500g | M4: Pain bâlois 500g | N4: Pane di Basilea | O4: della regione | P4: 500g | Q4: Pane di Basilea 500g | R4: 0.5 | S4: 100 | T4: Gramm | U4: (PCE) Stück | V4: Backwaren & Convenience | W4: Brot und Backwaren | X4: Backwaren andere | AB4: ja | AC4: ja | AD4: ja | AE4: ja | AF4: - | AG4: - | AH4: ja | AI4: 0.05 | AJ4: -
A5: 4 | B5: 703 | C5: Stk | D5: Nein | F5: Berliner | G5: aus der Region | H5: 1Stk | I5: Berliner | J5: Boule de Berlin | K5: de la région | L5: 1pce | M5: Boule de Berlin | N5: Berliner | O5: della regione | P5: 1pz | Q5: Berliner | R5: 1 | S5: 1 | T5: Stück | U5: (PCE) Stück | V5: Backwaren & Convenience | W5: Brot und Backwaren | X5: Backwaren andere | AB5: ja | AC5: ja | AD5: ja | AE5: ja | AF5: - | AG5: - | AH5: ja | AI5: 0.05 | AJ5: -
A6: 5 | B6: 704 | C6: Stk | D6: Nein | F6: Birewegge | G6: aus der Region | H6: 1Stk | I6: Birewegge | J6: Birewegge | K6: de la région | L6: 1pce | M6: Birewegge | N6: Birewegge | O6: della regione | P6: 1pz | Q6: Birewegge | R6: 1 | S6: 1 | T6: Stück | U6: (PCE) Stück | V6: Backwaren & Convenience | W6: Brot und Backwaren | X6: Backwaren andere | AB6: ja | AC6: ja | AD6: ja | AE6: ja | AF6: - | AG6: - | AH6: ja | AI6: 0.05 | AJ6: -
A7: 6 | B7: 705 | C7: Stk | D7: Nein | F7: Bricelets | G7: aus der Region | H7: 1Stk | I7: Bricelets | J7: Bricelets | K7: de la région | L7: 1pce | M7: Bricelets | N7: Bricelets | O7: della regione | P7: 1pz | Q7: Bricelets | R7: 1 | S7: 1 | T7: Stück | U7: (PCE) Stück | V7: Backwaren & Convenience | W7: Brot und Backwaren | X7: Backwaren andere | AB7: ja | AC7: ja | AD7: ja | AE7: ja | AF7: - | AG7: - | AH7: ja | AI7: 0.05 | AJ7: -
A8: 7 | B8: 706 | C8: Stk | D8: Nein | F8: Brioche mit Füllung | G8: aus der Region | H8: 1Stk | I8: Brioche mit Füllung | J8: Brioche fourée | K8: de la région | L8: 1pce | M8: Brioche fourée | N8: Brioche ripiena | O8: della regione | P8: 1pz | Q8: Brioche ripiena | R8: 1 | S8: 1 | T8: Stück | U8: (PCE) Stück | V8: Backwaren & Convenience | W8: Brot und Backwaren | X8: Backwaren andere | AB8: ja | AC8: ja | AD8: ja | AE8: ja | AF8: - | AG8: - | AH8: ja | AI8: 0 | AJ8: -
A9: 8 | B9: 707 | C9: Stk | D9: Nein | F9: Brot vom Beck | G9: aus der Region | H9: 1Stk | I9: Brot vom Beck | J9: Pain du boulanger | K9: de la région | L9: 1pce | M9: Pain du boulanger | N9: Pane del panettiere | O9: della regione | P9: 1pz | Q9: Pane del panettiere | R9: 1 | S9: 1 | T9: Stück | U9: (PCE) Stück | V9: Backwaren & Convenience | W9: Brot und Backwaren | X9: Backwaren andere | AB9: ja | AC9: ja | AD9: ja | AE9: ja | AF9: - | AG9: - | AH9: ja | AI9: 0 | AJ9: -
A10: 9 | B10: 708 | C10: Stk | D10: Nein | F10: Brottheke | G10: aus der Region | H10: 1Stk | I10: Brottheke | J10: Comptoir à pain | K10: de la région | L10: 1pce | M10: Comptoir à pain | N10: Banco pane | O10: della regione | P10: 1pz | Q10: Banco pane | R10: 1 | S10: 1 | T10: Stück | U10: (PCE) Stück | V10: Backwaren & Convenience | W10: Brot und Backwaren | X10: Backwaren andere | AB10: ja | AC10: ja | AD10: ja | AE10: ja | AF10: - | AG10: - | AH10: ja | AI10: 0 | AJ10: -
A11: 10 | B11: 709 | C11: Stk | D11: Nein | F11: Bürli | G11: aus der Region | H11: 1Stk | I11: Bürli | J11: Bürli | K11: de la région | L11: 1pce | M11: Bürli | N11: Bürli | O11: della regione | P11: 1pz | Q11: Bürli | R11: 1 | S11: 1 | T11: Stück | U11: (PCE) Stück | V11: Backwaren & Convenience | W11: Brot und Backwaren | X11: Backwaren andere | AB11: ja | AC11: ja | AD11: ja | AE11: ja | AF11: - | AG11: - | AH11: ja | AI11: 0.05 | AJ11: -
A12: 11 | B12: 710 | C12: Stk | D12: Nein | F12: Buttergipfel | G12: aus der Region | H12: 1Stk | I12: Buttergipfel | J12: Croissant au beurre | K12: de la région | L12: 1pce | M12: Croissant au beurre | N12: Cornetto al burro | O12: della regione | P12: 1pz | Q12: Cornetto al burro | R12: 1 | S12: 1 | T12: Stück | U12: (PCE) Stück | V12: Backwaren & Convenience | W12: Brot und Backwaren | X12: Backwaren andere | AB12: ja | AC12: ja | AD12: ja | AE12: ja | AF12: - | AG12: - | AH12: ja | AI12: 0.05 | AJ12: -
A13: 12 | B13: 711 | C13: Stk | D13: Nein | F13: Butterzopf | G13: aus der Region | H13: 300g | I13: Butterzopf 300g | J13: Tresse | K13: de la région | L13: 300g | M13: Tresse 300g | N13: Treccia | O13: della regione | P13: 300g | Q13: Treccia 300g | R13: 0.3 | S13: 100 | T13: Gramm | U13: (PCE) Stück | V13: Backwaren & Convenience | W13: Brot und Backwaren | X13: Backwaren andere | AB13: ja | AC13: ja | AD13: ja | AE13: ja | AF13: - | AG13: - | AH13: ja | AI13: 0.05 | AJ13: -
... A165: 123 | B165: 915 | C165: Stk | D165: Nein | F165: Tee | G165: aus der Region | H165: 1Stk | I165: Tee | J165: Thé | K165: de la région | L165: 1pce | M165: Thé | N165: Tè | O165: della regione | P165: 1pz | Q165: Tè | R165: 1 | S165: 1 | T165: Stück | U165: (PCE) Stück | V165: Getränke | W165: Kaffee und Tee | X165: Tee | AB165: ja | AC165: ja | AD165: ja | AE165: ja | AF165: - | AG165: - | AH165: ja | AI165: 0 | AJ165: -
A166: 129 | B166: 950 | C166: Stk | D166: Nein | F166: Gasflasche | H166: 10.5kg | I166: Gasflasche 10.5kg | J166: Bouteille de gaz | L166: 10.5kg | M166: Bouteille gaz 10.5kg | N166: Bombola di gas | P166: 10.5kg | Q166: Bombola gas 10.5kg | R166: 10.5 | S166: 1 | T166: Kilogramm | U166: (PCE) Stück | V166: Near Food | W166: Gebrauchsartikel | X166: Gebrauchsartikel | AB166: ja | AC166: ja | AD166: ja | AE166: ja | AF166: - | AG166: ja | AH166: ja | AI166: 0.05 | AJ166: -
A167: 130 | B167: 951 | C167: Stk | D167: Nein | F167: Gasflasche | H167: 5kg | I167: Gasflasche 5kg | J167: Bouteille de gaz | L167: 5kg | M167: Bouteille gaz 5kg | N167: Bombola di gas | P167: 5kg | Q167: Bombola gas 5kg | R167: 5 | S167: 1 | T167: Kilogramm | U167: (PCE) Stück | V167: Near Food | W167: Gebrauchsartikel | X167: Gebrauchsartikel | AB167: ja | AC167: ja | AD167: ja | AE167: ja | AF167: - | AG167: ja | AH167: ja | AI167: 0.05 | AJ167: -
A168: 131 | B168: 952 | C168: Stk | D168: Nein | F168: Gasflasche | H168: 33kg | I168: Gasflasche 33kg | J168: Bouteille de gaz | L168: 33kg | M168: Bouteille gaz 33kg | N168: Bombola di gas | P168: 33kg | Q168: Bombola gas 33kg | R168: 33 | S168: 1 | T168: Kilogramm | U168: (PCE) Stück | V168: Near Food | W168: Gebrauchsartikel | X168: Gebrauchsartikel | AB168: ja | AC168: ja | AD168: ja | AE168: ja | AF168: - | AG168: ja | AH168: ja | AI168: 0.05 | AJ168: -
A169: 132 | B169: 953 | C169: Stk | D169: Nein | F169: Gasflasche | H169: 35kg | I169: Gasflasche 35kg | J169: Bouteille de gaz | L169: 35kg | M169: Bouteille gaz 35kg | N169: Bombola di gas | P169: 35kg | Q169: Bombola gas 35kg | R169: 35 | S169: 1 | T169: Kilogramm | U169: (PCE) Stück | V169: Near Food | W169: Gebrauchsartikel | X169: Gebrauchsartikel | AB169: ja | AC169: ja | AD169: ja | AE169: ja | AF169: - | AG169: ja | AH169: ja | AI169: 0.05 | AJ169: -
A170: 133 | B170: 954 | C170: Stk | D170: Nein | F170: Gasflasche | H170: 7.5kg | I170: Gasflasche 7.5kg | J170: Bouteille de gaz | L170: 7.5kg | M170: Bouteille gaz 7.5kg | N170: Bombola di gas | P170: 7.5kg | Q170: Bombola gas 7.5kg | R170: 7.5 | S170: 1 | T170: Kilogramm | U170: (PCE) Stück | V170: Near Food | W170: Gebrauchsartikel | X170: Gebrauchsartikel | AB170: ja | AC170: ja | AD170: ja | AE170: ja | AF170: - | AG170: ja | AH170: ja | AI170: 0.05 | AJ170: -
A171: 139 | B171: 955 | C171: Stk | D171: Nein | F171: Holz | H171: 1Stk | I171: Holz | J171: Bois de chauffage | L171: 1pce | M171: Bois de chauffage | N171: Legna da ardere | P171: 1pz | Q171: Legna da ardere | R171: 1 | S171: 1 | T171: Stück | U171: (PCE) Stück | V171: Near Food | W171: Gebrauchsartikel | X171: Gebrauchsartikel | AB171: ja | AC171: ja | AD171: ja | AE171: ja | AF171: - | AG171: ja | AH171: ja | AI171: 0.05 | AJ171: -
A172: 140 | B172: 956 | C172: Stk | D172: Nein | F172: Holzkohle | H172: 1Stk | I172: Holzkohle | J172: Charbon de bois | L172: 1pce | M172: Charbon de bois | N172: Carbone | P172: 1pz | Q172: Carbone | R172: 1 | S172: 1 | T172: Stück | U172: (PCE) Stück | V172: Near Food | W172: Gebrauchsartikel | X172: Gebrauchsartikel | AB172: ja | AC172: ja | AD172: ja | AE172: ja | AF172: - | AG172: ja | AH172: ja | AI172: 0.05 | AJ172: -
A173: 141 | B173: 957 | C173: Stk | D173: Nein | F173: Karten | H173: 1Stk | I173: Karten | J173: Cartes | L173: 1pce | M173: Cartes | N173: Cartoline | P173: 1pz | Q173: Cartoline | R173: 1 | S173: 1 | T173: Stück | U173: (PCE) Stück | V173: Near Food | W173: Gebrauchsartikel | X173: Gebrauchsartikel | AB173: ja | AC173: ja | AD173: ja | AE173: ja | AF173: - | AG173: ja | AH173: ja | AI173: 0.05 | AJ173: -
A174: 142 | B174: 958 | C174: Stk | D174: Nein | F174: Pellets | H174: 1Stk | I174: Pellets | J174: Pellets | L174: 1pce | M174: Pellets | N174: Pellet | P174: 1pz | Q174: Pellet | R174: 1 | S174: 1 | T174: Stück | U174: (PCE) Stück | V174: Near Food | W174: Gebrauchsartikel | X174: Gebrauchsartikel | AB174: ja | AC174: ja | AD174: ja | AE174: ja | AF174: - | AG174: ja | AH174: ja | AI174: 0.05 | AJ174: -
A175: 144 | B175: 959 | C175: Stk | D175: Nein | F175: Zeitschriften | H175: 1Stk | I175: Zeitschriften | J175: Magazines | L175: 1pce | M175: Magazines | N175: Riviste | P175: 1pz | Q175: Riviste | R175: 1 | S175: 1 | T175: Stück | U175: (PCE) Stück | V175: Near Food | W175: Gebrauchsartikel | X175: Gebrauchsartikel | AB175: ja | AC175: ja | AD175: ja | AE175: ja | AF175: - | AG175: ja | AH175: ja | AI175: 0 | AJ175: -
A176: 124 | B176: 960 | C176: Stk | D176: Nein | F176: Bündelmarke | H176: 1Stk | I176: Bündelmarke | J176: Marque de regroupement | L176: 1pce | M176: Marque de regroupement | N176: Tagliando tarif. fasci | P176: 1pz | Q176: Tagliando tarif. fasci | R176: 1 | S176: 1 | T176: Stück | U176: (PCE) Stück | V176: Near Food | W176: Gebrauchsartikel | X176: Gebührensäcke und Marken | AB176: ja | AC176: ja | AD176: ja | AE176: ja | AF176: - | AG176: - | AH176: ja | AI176: 0.05 | AJ176: -
A177: 125 | B177: 961 | C177: Stk | D177: Nein | F177: Container Band | H177: 1Stk | I177: Container Band 1Stk | J177: Bande de conteneur | L177: 1pce | M177: Bande conteneur 1pce | N177: Fascia per contenitore | P177: 1pz | Q177: Fascia contenitore 1pz | R177: 1 | S177: 1 | T177: Stück | U177: (PCE) Stück | V177: Near Food | W177: Gebrauchsartikel | X177: Gebührensäcke und Marken | AB177: ja | AC177: ja | AD177: ja | AE177: ja | AF177: - | AG177: - | AH177: ja | AI177: 0.05 | AJ177: -
... A188: 145 | B188: 972 | C188: Stk | D188: Nein | F188: Gutschein | H188: 1Stk | I188: Gutschein | J188: Bon cadeau | L188: 1pce | M188: Bon cadeau | N188: Buono regalo | P188: 1pz | Q188: Buono regalo | R188: 1 | S188: 1 | T188: Stück | U188: (PCE) Stück | V188: Nicht-Handelsware | W188: Kasse | X188: Gutschein, Voucher | AB188: ja | AC188: ja | AD188: ja | AE188: ja | AF188: - | AG188: ja | AH188: ja | AI188: 0 | AJ188: -
A189: 147 | B189: 916 | C189: Stk | D189: Nein | F189: Vin cuit | G189: aus der Region | H189: 50cl | I189: Vin cuit 50cl | J189: Vin cuit | K189: de la région | L189: 50cl | M189: Vin cuit 50cl | N189: Vin cuit | O189: della regione | P189: 50cl | Q189: Vin cuit 50cl | R189: 0.5 | S189: 1 | T189: Stück | U189: (PCE) Stück | V189: Wein | W189: Weine | X189: Wein andere | AB189: ja | AC189: ja | AD189: ja | AE189: ja | AF189: - | AG189: - | AH189: ja | AI189: 0.05 | AJ189: -
A190: 147 | B190: 917 | C190: Stk | D190: Nein | F190: Vin cuit | G190: aus der Region | H190: 75cl | I190: Vin cuit 75cl | J190: Vin cuit | K190: de la région | L190: 75cl | M190: Vin cuit 75cl | N190: Vin cuit | O190: della regione | P190: 75cl | Q190: Vin cuit 75cl | R190: 0.75 | S190: 1 | T190: Stück | U190: (PCE) Stück | V190: Wein | W190: Weine | X190: Wein andere | AB190: ja | AC190: ja | AD190: ja | AE190: ja | AF190: - | AG190: - | AH190: ja | AI190: 0.05 | AJ190: -
A191: 147 | B191: 918 | C191: Stk | D191: Nein | F191: Vin cuit | G191: aus der Region | H191: 1l | I191: Vin cuit 1l | J191: Vin cuit | K191: de la région | L191: 1l | M191: Vin cuit 1l | N191: Vin cuit | O191: della regione | P191: 1l | Q191: Vin cuit 1l | R191: 1 | S191: 1 | T191: Stück | U191: (PCE) Stück | V191: Wein | W191: Weine | X191: Wein andere | AB191: ja | AC191: ja | AD191: ja | AE191: ja | AF191: - | AG191: - | AH191: ja | AI191: 0.05 | AJ191: -
A192: 148 | B192: 919 | C192: Stk | D192: Nein | F192: Wein | G192: aus der Region | H192: 1l | I192: Wein 1l | J192: Vin | K192: de la région | L192: 1l | M192: Vin 1l | N192: Vino | O192: della regione | P192: 1l | Q192: Vino 1l | R192: 1 | S192: 1 | T192: Stück | U192: (PCE) Stück | V192: Wein | W192: Weine | X192: Wein andere | AB192: ja | AC192: ja | AD192: ja | AE192: ja | AF192: - | AG192: - | AH192: ja | AI192: 0 | AJ192: -
A193: 148 | B193: 920 | C193: Stk | D193: Nein | F193: Wein | G193: aus der Region | H193: 25cl | I193: Wein 25cl | J193: Vin | K193: de la région | L193: 25cl | M193: Vin 25cl | N193: Vino | O193: della regione | P193: 25cl | Q193: Vino 25cl | R193: 0.25 | S193: 1 | T193: Stück | U193: (PCE) Stück | V193: Wein | W193: Weine | X193: Wein andere | AB193: ja | AC193: ja | AD193: ja | AE193: ja | AF193: - | AG193: - | AH193: ja | AI193: 0 | AJ193: -
A194: 148 | B194: 921 | C194: Stk | D194: Nein | F194: Wein | G194: aus der Region | H194: 50cl | I194: Wein 50cl | J194: Vin | K194: de la région | L194: 50cl | M194: Vin 50cl | N194: Vino | O194: della regione | P194: 50cl | Q194: Vino 50cl | R194: 0.5 | S194: 1 | T194: Stück | U194: (PCE) Stück | V194: Wein | W194: Weine | X194: Wein andere | AB194: ja | AC194: ja | AD194: ja | AE194: ja | AF194: - | AG194: - | AH194: ja | AI194: 0 | AJ194: -
A195: 148 | B195: 922 | C195: Stk | D195: Nein | F195: Wein | G195: aus der Region | H195: 75cl | I195: Wein 75cl | J195: Vin | K195: de la région | L195: 75cl | M195: Vin 75cl | N195: Vino | O195: della regione | P195: 75cl | Q195: Vino 75cl | R195: 0.75 | S195: 1 | T195: Stück | U195: (PCE) Stück | V195: Wein | W195: Weine | X195: Wein andere | AB195: ja | AC195: ja | AD195: ja | AE195: ja | AF195: - | AG195: - | AH195: ja | AI195: 0 | AJ195: -
A196: 200 | B196: 135 | C196: kg | D196: Nein | F196: Birnen Büscheli | G196: Offen Kl. 1 | I196: Birnen Büscheli Offen Kl. 1 | J196: Poires Büscheli | K196: En vrac, cl. 1 | M196: Poires Büscheli | N196: Pere Büscheli | O196: Cl. 1 vendita sfusa | Q196: Pere Büscheli Cl. 1 v.s. | R196: 1 | S196: 1 | T196: Kilogramm | U196: (KGM) KG | V196: Früchte und Gemüse | W196: Früchte und Gemüse | X196: Früchte | AB196: ja | AC196: ja | AD196: ja | AE196: ja | AF196: - | AG196: - | AH196: ja | AI196: 0.05 | AJ196: -
A197: 201 | B197: 180 | C197: Stk | D197: Nein | F197: Ananas | G197: Baby | H197: 1Stk | I197: Ananas Baby Stk | J197: Ananas | K197: Baby | L197: 1pce | M197: Ananas Baby | N197: Ananas | O197: Baby | P197: 1pz | Q197: Ananas Baby 1 pz | R197: 1 | S197: 1 | T197: Stück | U197: (PCE) Stück | V197: Früchte und Gemüse | W197: Früchte und Gemüse | X197: Früchte | AB197: ja | AC197: ja | AD197: ja | AE197: ja | AF197: - | AG197: - | AH197: ja | AI197: 0.05 | AJ197: -
A198: 202 | C198: Stk | D198: Nein | E198: 7613399001270 | F198: Ananas | G198: Becher | H198: 200g | I198: Ananas Becher 200g | J198: Ananas | K198: Gobelet | L198: 200g | M198: Ananas gobelet 200g | N198: Ananas | O198: bicchiere | P198: 200g | Q198: Ananas bicchiere 200g | R198: 0.2 | S198: 100 | T198: Gramm | U198: (PCE) Stück | V198: Früchte und Gemüse | W198: Früchte und Gemüse | X198: Früchte | AB198: ja | AC198: ja | AD198: ja | AE198: ja | AF198: - | AG198: - | AH198: ja | AI198: 0.05 | AJ198: -
A199: 203 | C199: Stk | E199: 2008002220011 | F199: Äpfel Granny Smith | G199: gepackt | I199: Äpfel Granny Smith gepackt | J199: Pommes Granny Smith | K199: Emballé | M199: Pommes Granny Smith, emballé | N199: Mele Granny Smith | O199: confezionato | Q199: Mele Granny Smith confez. | R199: 1 | S199: 1 | T199: Kilogramm | U199: (PCE) Stück | V199: Früchte und Gemüse | W199: Früchte und Gemüse | X199: Früchte | AB199: ja | AC199: ja | AD199: ja | AE199: ja | AF199: - | AG199: - | AH199: ja | AI199: 0.05 | AJ199: -
A200: 204 | C200: Stk | D200: Nein | E200: 7613399021476 | F200: Aprikosen | H200: 2kg | I200: Aprikosen 2kg | J200: Abricots | L200: 2kg | M200: Abricots 2kg | N200: Albicocche | P200: 2kg | Q200: Albicocche 2kg | R200: 2 | S200: 1 | T200: Kilogramm | U200: (PCE) Stück | V200: Früchte und Gemüse | W200: Früchte und Gemüse | X200: Früchte | AB200: ja | AC200: ja | AD200: ja | AE200: ja | AF200: - | AG200: - | AH200: ja | AI200: 0.05 | AJ200: -
A201: 205 | B201: 122 | C201: kg | D201: Nein | F201: Aprikosen | G201: Offen AAA | I201: Aprikosen Offen AAA | J201: Abricots | K201: En vrac AAA | M201: Abricosts en vrac AAA | N201: Albicocche | O201: vendita sfusa AAA | Q201: Albicocche vend. sfus. AAA | R201: 1 | S201: 1 | T201: Kilogramm | U201: (KGM) KG | V201: Früchte und Gemüse | W201: Früchte und Gemüse | X201: Früchte | AB201: ja | AC201: ja | AD201: ja | AE201: ja | AF201: - | AG201: - | AH201: ja | AI201: 0.05 | AJ201: -
A202: 206 | C202: kg | D202: Ja | E202: 2203231000000 | F202: Aprikosen | H202: ca. 800g | I202: Aprikosen ca. 800g | J202: Abricots | L202: env. 800g | M202: Abricots env. 800g | N202: Albicocche | P202: ca. 800g | Q202: Albicocche ca. 800g | R202: 0.8 | S202: 1 | T202: Kilogramm | U202: (PCE) Stück | V202: Früchte und Gemüse | W202: Früchte und Gemüse | X202: Früchte | AB202: ja | AC202: ja | AD202: ja | AE202: ja | AF202: - | AG202: - | AH202: ja | AI202: 0.05 | AJ202: -
A203: 207 | B203: 124 | C203: kg | F203: Aprikosen Offen | I203: Aprikosen Offen | J203: Abrivots | K203: En Vrac | M203: Abricots en vrac | N203: Albicocche | O203: vendita sfusa | Q203: Albicocche vend. sfusa | R203: 1 | S203: 1 | T203: Kilogramm | U203: (KGM) KG | V203: Früchte und Gemüse | W203: Früchte und Gemüse | X203: Früchte | AB203: ja | AC203: ja | AD203: ja | AE203: ja | AF203: - | AG203: - | AH203: ja | AI203: 0.05 | AJ203: -
A204: 208 | C204: kg | D204: Ja | E204: 2203231000000 | F204: Aprikosen | G204: Schale | H204: 650g | I204: Aprikosen Schale 650g | J204: Abricots | K204: Barquette | L204: 650g | M204: Abricots barquette 650g | N204: Albicocche | O204: vaschetta | P204: 650g | Q204: Albicocche vasch. 650g | R204: 0.65 | S204: 1 | T204: Kilogramm | U204: (PCE) Stück | V204: Früchte und Gemüse | W204: Früchte und Gemüse | X204: Früchte | AB204: ja | AC204: ja | AD204: ja | AE204: ja | AF204: - | AG204: - | AH204: ja | AI204: 0.05 | AJ204: -
A205: 209 | C205: Stk | D205: Nein | E205: 7613399047834 | F205: Aprikosen getrocknet | H205: 200g | I205: Aprikosen getrocknet 200g | J205: Abricots secs | L205: 200g | M205: Abricots secs 200g | N205: Albicocche secche | P205: 200g | Q205: Albicocche secche 200g | R205: 0.2 | S205: 100 | T205: Gramm | U205: (PCE) Stück | V205: Früchte und Gemüse | W205: Früchte und Gemüse | X205: Früchte | AB205: ja | AC205: ja | AD205: ja | AE205: ja | AF205: - | AG205: - | AH205: ja | AI205: 0.05 | AJ205: -
A206: 210 | B206: 126 | C206: kg | D206: Nein | F206: Bananen Fyffes | G206: Offen | I206: Bananen Fyffes Offen | J206: Bananes Fyffes | K206: En vrac | M206: Bananes Fyffes en vrac | N206: Banane Fyffes | O206: vendita sfusa | Q206: Banane Fyffes vend. sfusa | R206: 1 | S206: 1 | T206: Kilogramm | U206: (KGM) KG | V206: Früchte und Gemüse | W206: Früchte und Gemüse | X206: Früchte | AB206: ja | AC206: ja | AD206: ja | AE206: ja | AF206: - | AG206: - | AH206: ja | AI206: 0.05 | AJ206: -
A207: 211 | C207: kg | D207: Ja | E207: 2201581000000 | F207: Bananen | G207: gepackt | I207: Bananen gepackt | J207: Bananes | K207: Emballé | M207: Bananes emballé | N207: Banane | O207: confezionato | Q207: Banane confezionato | R207: 1 | S207: 1 | T207: Kilogramm | U207: (PCE) Stück | V207: Früchte und Gemüse | W207: Früchte und Gemüse | X207: Früchte | AB207: ja | AC207: ja | AD207: ja | AE207: ja | AF207: - | AG207: - | AH207: ja | AI207: 0.05 | AJ207: -
A208: 212 | C208: Stk | D208: Nein | E208: 7610632050514 | F208: Beerenmischung | G208: Schale | H208: 250g | I208: Beerenmischung Schale 250g | J208: Mélange de baies | K208: Barquette | L208: 250g | M208: Melange de baies 250g | N208: Bacche miste | O208: vaschetta | P208: 250g | Q208: Bacche miste 250g | R208: 0.25 | S208: 100 | T208: Gramm | U208: (PCE) Stück | V208: Früchte und Gemüse | W208: Früchte und Gemüse | X208: Früchte | AB208: ja | AC208: ja | AD208: ja | AE208: ja | AF208: - | AG208: - | AH208: ja | AI208: 0.05 | AJ208: -
A209: 213 | B209: 128 | C209: kg | F209: Bio Bananen Offen | I209: Bio Bananen Offen | J209: Bio Bananes | K209: En vrac | M209: Bio Bananes en vrac | N209: Bio Banane | O209: vendita sfusa | Q209: Bio Banane vendita sfusa | R209: 1 | S209: 1 | T209: Kilogramm | U209: (KGM) KG | V209: Früchte und Gemüse | W209: Früchte und Gemüse | X209: Früchte | AB209: ja | AC209: ja | AD209: ja | AE209: ja | AF209: - | AG209: - | AH209: ja | AI209: 0.05 | AJ209: -
A210: 214 | B210: 171 | C210: kg | F210: Bio Wassermelone Mini | I210: Bio Wassermelone Mini | J210: Bio Pastèques | K210: Mini | M210: Bio Pastèques Mini | N210: Bio Angurie mini | Q210: Bio Angurie mini | R210: 1 | S210: 1 | T210: Kilogramm | U210: (KGM) KG | V210: Früchte und Gemüse | W210: Früchte und Gemüse | X210: Früchte | AB210: ja | AC210: ja | AD210: ja | AE210: ja | AF210: - | AG210: - | AH210: ja | AI210: 0.05 | AJ210: -
A211: 215 | B211: 159 | C211: kg | F211: Bio Orangen Offen | I211: Bio Orangen Offen | J211: Bio Oranges | K211: En vrac | M211: Bio Oranges en vrac | N211: Bio Arance | O211: vendita sfusa | Q211: Bio Arance vendita sfusa | R211: 1 | S211: 1 | T211: Kilogramm | U211: (KGM) KG | V211: Früchte und Gemüse | W211: Früchte und Gemüse | X211: Früchte | AB211: ja | AC211: ja | AD211: ja | AE211: ja | AF211: - | AG211: - | AH211: ja | AI211: 0.05 | AJ211: -
A212: 216 | B212: 137 | C212: kg | F212: Birnen Ercolini | G212: Offen Kl. 1 | I212: Birnen Ercolini Offen Kl. 1 | J212: Poires Ercolini | K212: En vrac, cl. 1 | M212: Poire Ercolini en vrac cl. 1 | N212: Pere Ercolini | O212: Cl. 1 vendita sfusa | Q212: Pere Ercolini cl.1 vend. Sf. | R212: 1 | S212: 1 | T212: Kilogramm | U212: (KGM) KG | V212: Früchte und Gemüse | W212: Früchte und Gemüse | X212: Früchte | AB212: ja | AC212: ja | AD212: ja | AE212: ja | AF212: - | AG212: - | AH212: ja | AI212: 0.05 | AJ212: -
A213: 217 | B213: 142 | C213: kg | F213: Birnen Kaiser | G213: Offen Kl. 1 | I213: Birnen Kaiser Offen Kl.1 | J213: Poires Beurré Bosc | K213: En vrac, cl. 1 | M213: Poire Beurré Bosc en v. cl1 | N213: Pere Kaiser | O213: Cl. 1 vendita sfusa | Q213: Pere Kaiser cl. 1 vendta sf. | R213: 1 | S213: 1 | T213: Kilogramm | U213: (KGM) KG | V213: Früchte und Gemüse | W213: Früchte und Gemüse | X213: Früchte | AB213: ja | AC213: ja | AD213: ja | AE213: ja | AF213: - | AG213: - | AH213: ja | AI213: 0.05 | AJ213: -
A214: 218 | C214: kg | D214: Ja | E214: 2203071000000 | F214: Birnen Abate | G214: Kl. 1 gepackt | I214: Birnen Abate Kl. 1 gepackt | J214: Poires Abate | K214: Cl. 1 emballé | M214: Poires Abate cl. 1 emballé | N214: Pere Abate | O214: Cl. 1 confezionato | Q214: Pere Abate cl.1 confezionato | R214: 1 | S214: 1 | T214: Kilogramm | U214: (PCE) Stück | V214: Früchte und Gemüse | W214: Früchte und Gemüse | X214: Früchte | AB214: ja | AC214: ja | AD214: ja | AE214: ja | AF214: - | AG214: - | AH214: ja | AI214: 0.05 | AJ214: -
A215: 219 | C215: kg | D215: Ja | E215: 2215861000009 | F215: Bio Birnen Abate | G215: Kl. 1 gepackt | I215: Bio Birnen Abate Kl. 1 gep. | J215: Bio Poires Abate | K215: Cl. 1 emballé | M215: Bio Poires Abate cl1 emballé | N215: Bio Pere Abate | O215: Cl. 1 confezionato | Q215: Bio Pere Abate cl. 1 confez. | R215: 1 | S215: 1 | T215: Kilogramm | U215: (PCE) Stück | V215: Früchte und Gemüse | W215: Früchte und Gemüse | X215: Früchte | AB215: ja | AC215: ja | AD215: ja | AE215: ja | AF215: - | AG215: - | AH215: ja | AI215: 0.05 | AJ215: -
A216: 220 | B216: 134 | C216: kg | D216: Nein | F216: Birnen Boscop | G216: Offen Kl. 1 | I216: Birnen Boscop Offen Kl. 1 | J216: Poires Boscop | K216: En vrac, cl. 1 | M216: Poires Boscop en vrac cl. 1 | N216: Pere Boscop | O216: Cl. 1 vendita sfusa | Q216: Pere Boscop cl.1 vend. sfusa | R216: 1 | S216: 1 | T216: Kilogramm | U216: (KGM) KG | V216: Früchte und Gemüse | W216: Früchte und Gemüse | X216: Früchte | AB216: ja | AC216: ja | AD216: ja | AE216: ja | AF216: - | AG216: - | AH216: ja | AI216: 0.05 | AJ216: -
A217: 221 | C217: kg | D217: Ja | E217: 2260561000002 | F217: Birnen Boscop | G217: Kl. 1 gepackt | I217: Birnen Boscop Kl. 1 gepackt | J217: Poires Boscop | K217: Cl. 1 emballé | M217: Poires Boscop cl. 1 emballé | N217: Pere Boscop | O217: Cl. 1 confezionato | Q217: Pere Boscop cl. 1 confez. | R217: 1 | S217: 1 | T217: Kilogramm | U217: (PCE) Stück | V217: Früchte und Gemüse | W217: Früchte und Gemüse | X217: Früchte | AB217: ja | AC217: ja | AD217: ja | AE217: ja | AF217: - | AG217: - | AH217: ja | AI217: 0.05 | AJ217: -
A218: 222 | C218: kg | D218: Ja | E218: 2287572000000 | F218: Birnen Carmen | G218: Kl. 1 gepackt | I218: Birnen Carmen Kl. 1 gepackt | J218: Poires Carmen | K218: Cl. 1 emballé | M218: Poires Carmen cl. 1 emballé | N218: Pere Carmen | O218: Cl. 1 confezionato | Q218: Pere Carmen cl. 1 confez. | R218: 1 | S218: 1 | T218: Kilogramm | U218: (PCE) Stück | V218: Früchte und Gemüse | W218: Früchte und Gemüse | X218: Früchte | AB218: ja | AC218: ja | AD218: ja | AE218: ja | AF218: - | AG218: - | AH218: ja | AI218: 0.05 | AJ218: -
A219: 223 | B219: 136 | C219: kg | D219: Nein | F219: Birnen Conférence | G219: Offen Kl. 1 | I219: Birnen Conférence Offen Kl.1 | J219: Poires Conférence | K219: En vrac, cl. 1 | M219: Poires Conférence cl.1 en vr | N219: Pere Conférence | O219: Cl. 1 vendita sfusa | Q219: Pere Conférence cl. 1 ve. Sf | R219: 1 | S219: 1 | T219: Kilogramm | U219: (KGM) KG | V219: Früchte und Gemüse | W219: Früchte und Gemüse | X219: Früchte | AB219: ja | AC219: ja | AD219: ja | AE219: ja | AF219: - | AG219: - | AH219: ja | AI219: 0.05 | AJ219: -
A220: 224 | C220: kg | D220: Ja | E220: 2216831000005 | F220: Birnen Conférence | G220: Kl. 1 gepackt | I220: Birnen Conférence Kl. 2 gep. | J220: Poires Conférence | K220: Cl. 1 emballé | M220: Poires Conférence cl. 1 emb. | N220: Pere Conférence | O220: Cl. 1 confezionato | Q220: Pere Conférence cl. 1 conf | R220: 1 | S220: 1 | T220: Kilogramm | U220: (PCE) Stück | V220: Früchte und Gemüse | W220: Früchte und Gemüse | X220: Früchte | AB220: ja | AC220: ja | AD220: ja | AE220: ja | AF220: - | AG220: - | AH220: ja | AI220: 0.05 | AJ220: -
A221: 225 | C221: kg | D221: Ja | E221: 2216799000000 | F221: Bio Birnen Conférence | G221: Kl. 1 gepackt | I221: Bio Birnen Conf. Kl.1 gep. | J221: Bio Poires Conférence | K221: Cl. 1 emballé | M221: Bio Poires Confér. cl.1 emb. | N221: Bio Pere Conférence | O221: Cl. 1 confezionato | Q221: Bio Pere Conf. cl. 1 conf. | R221: 1 | S221: 1 | T221: Kilogramm | U221: (PCE) Stück | V221: Früchte und Gemüse | W221: Früchte und Gemüse | X221: Früchte | AB221: ja | AC221: ja | AD221: ja | AE221: ja | AF221: - | AG221: - | AH221: ja | AI221: 0.05 | AJ221: -
A222: 226 | B222: 138 | C222: kg | D222: Nein | F222: Birnen Forellen | G222: Offen Kl. 1 | I222: Birnen Forellen Offen Kl. 1 | J222: Poires Forelle | K222: En vrac, cl. 1 | M222: Poires Forelle cl. 1 en vrac | N222: Pere Forelle | O222: Cl. 1 vendita sfusa | Q222: Pere Forelle cl. 1 vend. Sf. | R222: 1 | S222: 1 | T222: Kilogramm | U222: (KGM) KG | V222: Früchte und Gemüse | W222: Früchte und Gemüse | X222: Früchte | AB222: ja | AC222: ja | AD222: ja | AE222: ja | AF222: - | AG222: - | AH222: ja | AI222: 0.05 | AJ222: -
A223: 227 | C223: kg | D223: Ja | E223: 2287571000006 | F223: Birnen Forellen | G223: Kl. 1 gepackt | I223: Birnen Forellen Kl.1 gepackt | J223: Poires Forelle | K223: Cl. 1 emballé | M223: Poires Forelle cl. 1 emballé | N223: Pere Forelle | O223: Cl. 1 confezionato | Q223: Pere Forelle cl. 1 confez. | R223: 1 | S223: 1 | T223: Kilogramm | U223: (PCE) Stück | V223: Früchte und Gemüse | W223: Früchte und Gemüse | X223: Früchte | AB223: ja | AC223: ja | AD223: ja | AE223: ja | AF223: - | AG223: - | AH223: ja | AI223: 0.05 | AJ223: -
A224: 228 | B224: 139 | C224: kg | D224: Nein | F224: Birnen Fred | G224: Offen Kl. 1 | I224: Birnen Fred Offen Kl. 1 | J224: Poires Fred | K224: En vrac, cl. 1 | M224: Poires Fred cl. 1 en vrac | N224: Pere Fred | O224: Cl. 1 vendita sfusa | Q224: Pere Fred cl. 1 vend sfusa | R224: 1 | S224: 1 | T224: Kilogramm | U224: (KGM) KG | V224: Früchte und Gemüse | W224: Früchte und Gemüse | X224: Früchte | AB224: ja | AC224: ja | AD224: ja | AE224: ja | AF224: - | AG224: - | AH224: ja | AI224: 0.05 | AJ224: -
A225: 229 | C225: kg | D225: Ja | E225: 2287571000006 | F225: Birnen Fred | G225: Kl. 1 gepackt | I225: Birnen Fred Kl. 1 gepackt | J225: Poires Fred | K225: Cl. 1 emballé | M225: Poires Fred cl. 1 emballé | N225: Pere Fred | O225: Cl. 1 confezionato | Q225: Pere Fred cl. 1 confez. | R225: 1 | S225: 1 | T225: Kilogramm | U225: (PCE) Stück | V225: Früchte und Gemüse | W225: Früchte und Gemüse | X225: Früchte | AB225: ja | AC225: ja | AD225: ja | AE225: ja | AF225: - | AG225: - | AH225: ja | AI225: 0.05 | AJ225: -
A226: 230 | B226: 140 | C226: kg | D226: Nein | F226: Birnen Gute Louise | G226: Offen Kl. 1 | I226: Birnen Gute Louise Off. Kl.1 | J226: Poires Bonne Louise | K226: En vrac, cl. 1 | M226: Poires Bonn. Lou. cl.1 en v. | N226: Pere Gute Luise | O226: Cl. 1 vendita sfusa | Q226: Pere Gute Luise cl. 1 v. sf. | R226: 1 | S226: 1 | T226: Kilogramm | U226: (KGM) KG | V226: Früchte und Gemüse | W226: Früchte und Gemüse | X226: Früchte | AB226: ja | AC226: ja | AD226: ja | AE226: ja | AF226: - | AG226: - | AH226: ja | AI226: 0.05 | AJ226: -
A227: 231 | C227: kg | D227: Ja | E227: 2216791000008 | F227: Birnen Gute Louise | G227: Kl. 1 gepackt | I227: Birnen Gute Louise Kl.1 gep. | J227: Poires Bonne Louise | K227: Cl. 1 emballé | M227: Poires Bonn. Lou. cl.1 emb. | N227: Pere Gute Luise | O227: Cl. 1 confezionato | Q227: Pere Gute Luise cl. 1 confez | R227: 1 | S227: 1 | T227: Kilogramm | U227: (PCE) Stück | V227: Früchte und Gemüse | W227: Früchte und Gemüse | X227: Früchte | AB227: ja | AC227: ja | AD227: ja | AE227: ja | AF227: - | AG227: - | AH227: ja | AI227: 0.05 | AJ227: -
A228: 232 | B228: 141 | C228: kg | D228: Nein | F228: Birnen Guyot | G228: Offen Kl. 1 | I228: Birnen Guyot Offen Kl. 1 | J228: Poires Guyot | K228: En vrac, cl. 1 | M228: Poires Guyot cl. 1 en vrac | N228: Pere Guyot | O228: Cl. 1 vendita sfusa | Q228: Pere Guyot cl. 1 vend. sfusa | R228: 1 | S228: 1 | T228: Kilogramm | U228: (KGM) KG | V228: Früchte und Gemüse | W228: Früchte und Gemüse | X228: Früchte | AB228: ja | AC228: ja | AD228: ja | AE228: ja | AF228: - | AG228: - | AH228: ja | AI228: 0.05 | AJ228: -
A229: 233 | C229: kg | D229: Ja | E229: 2213811000000 | F229: Birnen Guyot | G229: Kl. 1 gepackt | I229: Birnen Guyot Kl. 1 gepackt | J229: Poires Guyot | K229: Cl. 1 emballé | M229: Poires Guyot cl. 1 emballé | N229: Pere Guyot | O229: Cl. 1 confezionato | Q229: Pere Guyot cl. 1 confez. | R229: 1 | S229: 1 | T229: Kilogramm | U229: (PCE) Stück | V229: Früchte und Gemüse | W229: Früchte und Gemüse | X229: Früchte | AB229: ja | AC229: ja | AD229: ja | AE229: ja | AF229: - | AG229: - | AH229: ja | AI229: 0.05 | AJ229: -
A230: 234 | B230: 147 | C230: kg | F230: Birnen Offen | I230: Birnen Offen | J230: Poires | K230: En vrac | M230: Poires en vrac | N230: Pere | O230: vendita sfusa | Q230: Pere vendita sfusa | R230: 1 | S230: 1 | T230: Kilogramm | U230: (KGM) KG | V230: Früchte und Gemüse | W230: Früchte und Gemüse | X230: Früchte | AB230: ja | AC230: ja | AD230: ja | AE230: ja | AF230: - | AG230: - | AH230: ja | AI230: 0.05 | AJ230: -
A231: 235 | B231: 144 | C231: kg | D231: Nein | F231: Birnen Packhams | G231: Offen Kl. 1 | I231: Birnen Packhams Offen Kl. 1 | J231: Poires Packhams | K231: En vrac, cl. 1 | M231: Poires Packhams cl.1 en vrac | N231: Pere Packhams | O231: Cl. 1 vendita sfusa | Q231: Pere Packhams cl. 1 v.sfusa | R231: 1 | S231: 1 | T231: Kilogramm | U231: (KGM) KG | V231: Früchte und Gemüse | W231: Früchte und Gemüse | X231: Früchte | AB231: ja | AC231: ja | AD231: ja | AE231: ja | AF231: - | AG231: - | AH231: ja | AI231: 0.05 | AJ231: -
A232: 236 | C232: kg | D232: Ja | E232: 2216921000007 | F232: Birnen Packhams | G232: Kl. 1 gepackt | I232: Birnen Packhams Kl.1 gepackt | J232: Poires Packhams | K232: Cl. 1 emballé | M232: Poires Packhams cl. 1 emb. | N232: Pere Packhams | O232: Cl. 1 confezionato | Q232: Pere Packhams cl. 1 convez. | R232: 1 | S232: 1 | T232: Kilogramm | U232: (PCE) Stück | V232: Früchte und Gemüse | W232: Früchte und Gemüse | X232: Früchte | AB232: ja | AC232: ja | AD232: ja | AE232: ja | AF232: - | AG232: - | AH232: ja | AI232: 0.05 | AJ232: -
A233: 237 | B233: 145 | C233: kg | D233: Nein | F233: Birnen Rocha | G233: Offen Kl. 1 | I233: Birnen Rocha Offen Kl. 1 | J233: Poires Rocha | K233: En vrac, cl. 1 | M233: Poires Rocha cl.1 en vrac | N233: Pere Rocha | O233: Cl. 1 vendita sfusa | Q233: Pere Rocha cl. 1 v. sfusa | R233: 1 | S233: 1 | T233: Kilogramm | U233: (KGM) KG | V233: Früchte und Gemüse | W233: Früchte und Gemüse | X233: Früchte | AB233: ja | AC233: ja | AD233: ja | AE233: ja | AF233: - | AG233: - | AH233: ja | AI233: 0.05 | AJ233: -
A234: 238 | C234: kg | D234: Ja | E234: 2287571000006 | F234: Birnen Rosmarie | G234: Kl. 1 gepackt | I234: Birnen Rosmarei Kl.1 gepackt | J234: Poires Rosemarie | K234: Cl. 1 emballé | M234: Poires Rosemarie cl. 1 emb. | N234: Pere Rosmarie | O234: Cl. 1 confezionato | Q234: Pere Rosmarie cl. 1 confez. | R234: 1 | S234: 1 | T234: Kilogramm | U234: (PCE) Stück | V234: Früchte und Gemüse | W234: Früchte und Gemüse | X234: Früchte | AB234: ja | AC234: ja | AD234: ja | AE234: ja | AF234: - | AG234: - | AH234: ja | AI234: 0.05 | AJ234: -
A235: 239 | C235: kg | D235: Ja | E235: 2215881000000 | F235: Birnen Trévoux | G235: Kl. 1 gepackt | I235: Birnen Trévoux Kl. 1 gepackt | J235: Poires Trévoux | K235: Cl. 1 emballé | M235: Poires Trévoux cl. 1 emballé | N235: Pere Trévoux | O235: Cl. 1 confezionato | Q235: Pere Trévoux cl. 1 confez. | R235: 1 | S235: 1 | T235: Kilogramm | U235: (PCE) Stück | V235: Früchte und Gemüse | W235: Früchte und Gemüse | X235: Früchte | AB235: ja | AC235: ja | AD235: ja | AE235: ja | AF235: - | AG235: - | AH235: ja | AI235: 0.05 | AJ235: -
A236: 240 | B236: 146 | C236: kg | D236: Nein | F236: Birnen Williams | G236: Offen Kl. 1 | I236: Birnen Williams Offen Kl. 1 | J236: Poires Williams | K236: En vrac, cl. 1 | M236: Poires Williams cl.1 en vrac | N236: Pere Williams | O236: Cl. 1 vendita sfusa | Q236: Pere Williams cl. 1 v. sfusa | R236: 1 | S236: 1 | T236: Kilogramm | U236: (KGM) KG | V236: Früchte und Gemüse | W236: Früchte und Gemüse | X236: Früchte | AB236: ja | AC236: ja | AD236: ja | AE236: ja | AF236: - | AG236: - | AH236: ja | AI236: 0.05 | AJ236: -
A237: 241 | C237: kg | D237: Ja | E237: 2215861000009 | F237: Birnen Williams | G237: Kl. 1 gepackt | I237: Birnen Williams Kl.1 gepackt | J237: Poires Williams | K237: Cl. 1 emballé | M237: Poires Williams cl.1 emballé | N237: Pere Williams | O237: Cl. 1 confezionato | Q237: Pere Williams cl. 1 confez. | R237: 1 | S237: 1 | T237: Kilogramm | U237: (PCE) Stück | V237: Früchte und Gemüse | W237: Früchte und Gemüse | X237: Früchte | AB237: ja | AC237: ja | AD237: ja | AE237: ja | AF237: - | AG237: - | AH237: ja | AI237: 0.05 | AJ237: -
A238: 242 | C238: Stk | D238: Ja | E238: 2215861000009 | F238: Bio Birnen Williams | G238: Offen Kl. 1 | H238: 500g | I238: Bio Birne Will. Off Kl1 500g | J238: Bio Poires Williams | K238: En vrac, cl. 1 | L238: 500g | M238: Bio Poires Will. cl1 en vrac | N238: Bio Pere Williams | O238: Cl. 1 vendita sfusa | P238: 500g | Q238: Bio Pere Williams cl. 1 500g | R238: 0.5 | S238: 1 | T238: Kilogramm | U238: (PCE) Stück | V238: Früchte und Gemüse | W238: Früchte und Gemüse | X238: Früchte | AB238: ja | AC238: ja | AD238: ja | AE238: ja | AF238: - | AG238: - | AH238: ja | AI238: 0.05 | AJ238: -
A239: 243 | B239: 158 | C239: kg | F239: Orangen Tarocco | G239: Offen | I239: Orangen Tarocco Offen | J239: Oranges Tarocco | K239: En vrac | M239: Oranges Tarocco en vrac | N239: Arance Tarocco | O239: vendita sfusa | Q239: Arance Tarocco vendita sfusa | R239: 1 | S239: 1 | T239: Kilogramm | U239: (KGM) KG | V239: Früchte und Gemüse | W239: Früchte und Gemüse | X239: Früchte | AB239: ja | AC239: ja | AD239: ja | AE239: ja | AF239: - | AG239: - | AH239: ja | AI239: 0.05 | AJ239: -
A240: 244 | B240: 100 | C240: kg | D240: Nein | F240: Äpfel Boskoop | G240: Offen Kl. 1 | I240: Äpel Boskoop Offen Kl. 1 | J240: Pommes Boskoop | K240: En vrac, cl. 1 | M240: Pommes Boskoop cl.1 en vrac | N240: Mele Boskoop | O240: Cl. 1 vendita sfusa | Q240: Mele Boskoop cl. 1 v. sfusa | R240: 1 | S240: 1 | T240: Kilogramm | U240: (KGM) KG | V240: Früchte und Gemüse | W240: Früchte und Gemüse | X240: Früchte | AB240: ja | AC240: ja | AD240: ja | AE240: ja | AF240: - | AG240: - | AH240: ja | AI240: 0.05 | AJ240: -
A241: 245 | C241: kg | D241: Ja | E241: 2216961000005 | F241: Äpfel Boskoop | G241: Kl. 1 gepackt | I241: Äpfel Boskoop Kl. 1 gepackt | J241: Pommes Boskoop | K241: Cl. 1 emballé | M241: Pommes Boskoop cl.1 emball. | N241: Mele Boskoop | O241: Cl. 1 confezionato | Q241: Mele Boskoop cl. 1 confez. | R241: 1 | S241: 1 | T241: Kilogramm | U241: (PCE) Stück | V241: Früchte und Gemüse | W241: Früchte und Gemüse | X241: Früchte | AB241: ja | AC241: ja | AD241: ja | AE241: ja | AF241: - | AG241: - | AH241: ja | AI241: 0.05 | AJ241: -
A242: 246 | B242: 101 | C242: kg | D242: Nein | F242: Äpfel Braeburn | G242: Offen Kl. 1 | I242: Äpfel Braeburn Offen Kl. 1 | J242: Pommes Braeburn | K242: En vrac, cl. 1 | M242: Pommes Braeburn cl.1 en vrac | N242: Mele Braeburn | O242: Cl. 1 vendita sfusa | Q242: Mele Braeburn cl. 1 v. sfusa | R242: 1 | S242: 1 | T242: Kilogramm | U242: (KGM) KG | V242: Früchte und Gemüse | W242: Früchte und Gemüse | X242: Früchte | AB242: ja | AC242: ja | AD242: ja | AE242: ja | AF242: - | AG242: - | AH242: ja | AI242: 0.05 | AJ242: -
A243: 247 | C243: kg | D243: Ja | E243: 2274484000001 | F243: Äpfel Braeburn | G243: Kl. 1 gepackt | I243: Äpfel Braeburn Kl. 1 gepackt | J243: Pommes Braeburn | K243: Cl. 1 emballé | M243: Pommes Braeburn cl.1 emball. | N243: Mele Braeburn | O243: Cl. 1 confezionato | Q243: Mele Braeburn cl. 1 confez. | R243: 1 | S243: 1 | T243: Kilogramm | U243: (PCE) Stück | V243: Früchte und Gemüse | W243: Früchte und Gemüse | X243: Früchte | AB243: ja | AC243: ja | AD243: ja | AE243: ja | AF243: - | AG243: - | AH243: ja | AI243: 0.05 | AJ243: -
A244: 248 | B244: 102 | C244: kg | D244: Nein | F244: Äpfel Braeburn | G244: Offen Kl. 2 | I244: Äpfel Braeburn Offen Kl. 2 | J244: Pommes Braeburn | K244: En vrac, cl. 2 | M244: Pommes Braeburn cl.2 en vrac | N244: Mele Braeburn | O244: Cl. 2 vendita sfusa | Q244: Mele Braeburn cl. 2 v. sfusa | R244: 1 | S244: 1 | T244: Kilogramm | U244: (KGM) KG | V244: Früchte und Gemüse | W244: Früchte und Gemüse | X244: Früchte | AB244: ja | AC244: ja | AD244: ja | AE244: ja | AF244: - | AG244: - | AH244: ja | AI244: 0.05 | AJ244: -
A245: 249 | C245: Stk | D245: Nein | E245: 7610632010280 | F245: Brombeeren | G245: Schale | H245: 125g | I245: Brombeeren Schale 125g | J245: Mûres | K245: Barquette | L245: 125g | M245: Mûres barquette 125g | N245: More | O245: vaschetta | P245: 125g | Q245: More vaschetta 125g | R245: 0.125 | S245: 100 | T245: Gramm | U245: (PCE) Stück | V245: Früchte und Gemüse | W245: Früchte und Gemüse | X245: Früchte | AB245: ja | AC245: ja | AD245: ja | AE245: ja | AF245: - | AG245: - | AH245: ja | AI245: 0.05 | AJ245: -
A246: 250 | C246: Stk | D246: Nein | E246: 7610632050064 | F246: Brombeeren | G246: Schale | H246: 250g | I246: Brombeeren Schale 250g | J246: Mûres | K246: Barquette | L246: 250g | M246: Mûres barquette 250g | N246: More | O246: vaschetta | P246: 250g | Q246: More vaschetta 250g | R246: 0.25 | S246: 100 | T246: Gramm | U246: (PCE) Stück | V246: Früchte und Gemüse | W246: Früchte und Gemüse | X246: Früchte | AB246: ja | AC246: ja | AD246: ja | AE246: ja | AF246: - | AG246: - | AH246: ja | AI246: 0.05 | AJ246: -
A247: 251 | B247: 127 | C247: kg | F247: Bananen Chiquita Offen | I247: Bananen Chiquita Offen | J247: Bananes Chiquita | K247: En vrac | M247: Bananes Chiquita en vrac | N247: Banane Chiquita | O247: vendita sfusa | Q247: Banane Chiquita v. sfusa | R247: 1 | S247: 1 | T247: Kilogramm | U247: (KGM) KG | V247: Früchte und Gemüse | W247: Früchte und Gemüse | X247: Früchte | AB247: ja | AC247: ja | AD247: ja | AE247: ja | AF247: - | AG247: - | AH247: ja | AI247: 0.05 | AJ247: -
A248: 252 | B248: 129 | C248: kg | D248: Nein | F248: Bio Clementinen | G248: Offen | I248: Bio Clementinen Offen | J248: Bio Clémentines | K248: En vrac | M248: Bio Clémentines en vrac | N248: Bio Clementine | O248: vendita sfusa | Q248: Bio Clementine vendita sfusa | R248: 1 | S248: 1 | T248: Kilogramm | U248: (KGM) KG | V248: Früchte und Gemüse | W248: Früchte und Gemüse | X248: Früchte | AB248: ja | AC248: ja | AD248: ja | AE248: ja | AF248: - | AG248: - | AH248: ja | AI248: 0.05 | AJ248: -
A249: 253 | B249: 131 | C249: kg | D249: Nein | F249: Clementinen mit Blatt | G249: Offen | I249: Clementinen mit Blatt Offen | J249: Clémentines + feuilles | K249: En vrac | M249: Clémentines feuilles en vrac | N249: Clementine con foglia | O249: vendita sfusa | Q249: Clementine con foglia v.s. | R249: 1 | S249: 1 | T249: Kilogramm | U249: (KGM) KG | V249: Früchte und Gemüse | W249: Früchte und Gemüse | X249: Früchte | AB249: ja | AC249: ja | AD249: ja | AE249: ja | AF249: - | AG249: - | AH249: ja | AI249: 0.05 | AJ249: -
A250: 254 | B250: 132 | C250: kg | D250: Nein | F250: Clementinen | G250: Rotkehlchen Offen | I250: Clementinen Rothehlchen Off. | J250: Clémentines Rotkehlchen | K250: En vrac | M250: Clémentines Rotkehl en vrac | N250: Clementine Rotkehlchen | O250: vendita sfusa | Q250: Clementine Rotk. v. sfusa | R250: 1 | S250: 1 | T250: Kilogramm | U250: (KGM) KG | V250: Früchte und Gemüse | W250: Früchte und Gemüse | X250: Früchte | AB250: ja | AC250: ja | AD250: ja | AE250: ja | AF250: - | AG250: - | AH250: ja | AI250: 0.05 | AJ250: -
A251: 255 | B251: 130 | C251: kg | F251: Clementinen/Mandarinen Offen | I251: Clementeinen/Mandarinen Offen | J251: Clémentines/Mandarines | K251: En vrac | M251: Clément/Mandarines en vrac | N251: Clementine/mandarini | O251: vendita sfusa | Q251: Clementine/mandarini v.s. | R251: 1 | S251: 1 | T251: Kilogramm | U251: (KGM) KG | V251: Früchte und Gemüse | W251: Früchte und Gemüse | X251: Früchte | AB251: ja | AC251: ja | AD251: ja | AE251: ja | AF251: - | AG251: - | AH251: ja | AI251: 0.05 | AJ251: -
A252: 256 | B252: 103 | C252: kg | D252: Nein | F252: Äpfel Cox Orange | G252: Offen Kl. 1 | I252: Äpfel Cox Orange Offen Kl. 1 | J252: Pommes Cox Orange | K252: En vrac, cl. 1 | M252: Pommes Cox Orange cl.1 en v. | N252: Mele Cox Orange | O252: Cl. 1 vendita sfusa | Q252: Mele Cox Orange cl. 1 v.s. | R252: 1 | S252: 1 | T252: Kilogramm | U252: (KGM) KG | V252: Früchte und Gemüse | W252: Früchte und Gemüse | X252: Früchte | AB252: ja | AC252: ja | AD252: ja | AE252: ja | AF252: - | AG252: - | AH252: ja | AI252: 0.05 | AJ252: -
A253: 257 | C253: kg | D253: Ja | E253: 2202261000005 | F253: Äpfel Cox Orange | G253: Kl. 1 gepackt | I253: Äpfel Cox Orange Kl. 1 gep. | J253: Pommes Cox Orange | K253: Cl. 1 emballé | M253: Pommes Cox Orange cl.1 emb. | N253: Mele Cox Orange | O253: Cl. 1 confezionato | Q253: Mele Cox Orange cl. 1 confez | R253: 1 | S253: 1 | T253: Kilogramm | U253: (PCE) Stück | V253: Früchte und Gemüse | W253: Früchte und Gemüse | X253: Früchte | AB253: ja | AC253: ja | AD253: ja | AE253: ja | AF253: - | AG253: - | AH253: ja | AI253: 0.05 | AJ253: -
A254: 258 | B254: 125 | C254: kg | F254: Bananen Denner Offen | I254: Bananen Denner Offen | J254: Bananes Denner | K254: en vrac | M254: Bananes Denner en vrac | N254: Banane Denner | O254: vendita sfusa | Q254: Banane Denner vendita sfusa | R254: 1 | S254: 1 | T254: Kilogramm | U254: (KGM) KG | V254: Früchte und Gemüse | W254: Früchte und Gemüse | X254: Früchte | AB254: ja | AC254: ja | AD254: ja | AE254: ja | AF254: - | AG254: - | AH254: ja | AI254: 0.05 | AJ254: -
A255: 259 | B255: 105 | C255: kg | D255: Nein | F255: Äpfel Elstar | G255: Offen Kl. 1 | I255: Äpfel Elstar Offen Kl. 1 | J255: Pommes Elstar | K255: En vrac, cl. 1 | M255: Pommes Elstar cl. 1 en vrac | N255: Mele Elstar | O255: Cl. 1 vendita sfusa | Q255: Mele Elstar cl. 1 ven. sfusa | R255: 1 | S255: 1 | T255: Kilogramm | U255: (KGM) KG | V255: Früchte und Gemüse | W255: Früchte und Gemüse | X255: Früchte | AB255: ja | AC255: ja | AD255: ja | AE255: ja | AF255: - | AG255: - | AH255: ja | AI255: 0.05 | AJ255: -
A256: 260 | C256: kg | D256: Ja | E256: 2202291000006 | F256: Äpfel Elstar | G256: Kl. 1 gepackt | I256: Äpfel Elstar Kl. 1 gepackt | J256: Pommes Elstar | K256: Cl. 1 emballé | M256: Pommes Elstar cl. 1 emballé | N256: Mele Elstar | O256: Cl. 1 confezionato | Q256: Mele Elstar cl. 1 confez. | R256: 1 | S256: 1 | T256: Kilogramm | U256: (PCE) Stück | V256: Früchte und Gemüse | W256: Früchte und Gemüse | X256: Früchte | AB256: ja | AC256: ja | AD256: ja | AE256: ja | AF256: - | AG256: - | AH256: ja | AI256: 0.05 | AJ256: -
A257: 261 | B257: 150 | C257: kg | D257: Nein | F257: Flachpfirsiche | G257: Offen | I257: Flachpfirsiche Offen | J257: Pêches plates | K257: En vrac | M257: Pêches plartes en vrac | N257: Pesche tabacchiera | O257: vendita sfusa | Q257: Pesche tabacchiera v. sfusa | R257: 1 | S257: 1 | T257: Kilogramm | U257: (KGM) KG | V257: Früchte und Gemüse | W257: Früchte und Gemüse | X257: Früchte | AB257: ja | AC257: ja | AD257: ja | AE257: ja | AF257: - | AG257: - | AH257: ja | AI257: 0.05 | AJ257: -
A258: 262 | C258: Stk | D258: Nein | E258: 7613399001287 | F258: Fruchtbecher | H258: 200g | I258: Fruchtbecher 200g | J258: Gobelet de fruits | L258: 200g | M258: Gobelet de fruits 200g | N258: Bicchiere di frutta | P258: 200g | Q258: Bicchiere di frutta 200g | R258: 0.2 | S258: 100 | T258: Gramm | U258: (PCE) Stück | V258: Früchte und Gemüse | W258: Früchte und Gemüse | X258: Früchte | AB258: ja | AC258: ja | AD258: ja | AE258: ja | AF258: - | AG258: - | AH258: ja | AI258: 0.05 | AJ258: -
A259: 263 | C259: kg | D259: Ja | E259: 2296291000005 | F259: Früchtemix | G259: Äpfel/Orangen/Bananen | I259: Früchtemix Äpfel/Orange/Ban. | J259: Mélange de fruits | K259: Pommes/oranges/bananes | M259: Mélange fruits pom/oran/ban | N259: Mix di frutta | O259: Mele/arance/banane | Q259: Mix di frutta mele/aran./ban | R259: 1 | S259: 1 | T259: Kilogramm | U259: (PCE) Stück | V259: Früchte und Gemüse | W259: Früchte und Gemüse | X259: Früchte | AB259: ja | AC259: ja | AD259: ja | AE259: ja | AF259: - | AG259: - | AH259: ja | AI259: 0.05 | AJ259: -
A260: 264 | B260: 107 | C260: kg | D260: Nein | F260: Äpfel Gala | G260: Offen Kl. 1 | I260: Äpfel Gala Offen Kl. 1 | J260: Pommes Gala | K260: En vrac, cl. 1 | M260: Pommes Gala cl. 1 en vrac | N260: Mele Gala | O260: Cl. 1 vendita sfusa | Q260: Mele Gala cl.1 vendita sfusa | R260: 1 | S260: 1 | T260: Kilogramm | U260: (KGM) KG | V260: Früchte und Gemüse | W260: Früchte und Gemüse | X260: Früchte | AB260: ja | AC260: ja | AD260: ja | AE260: ja | AF260: - | AG260: - | AH260: ja | AI260: 0.05 | AJ260: -
A261: 265 | C261: kg | D261: Ja | E261: 2202381000008 | F261: Äpfel Gala | G261: Kl. 1 gepackt | I261: Äpfel Gala Kl. 1 gepackt | J261: Pommes Gala | K261: Cl. 1 emballé | M261: Pommes Gala cl. 1 emballé | N261: Mele Gala | O261: Cl. 1 confezionato | Q261: Mele Gala cl. 1 confezionato | R261: 1 | S261: 1 | T261: Kilogramm | U261: (PCE) Stück | V261: Früchte und Gemüse | W261: Früchte und Gemüse | X261: Früchte | AB261: ja | AC261: ja | AD261: ja | AE261: ja | AF261: - | AG261: - | AH261: ja | AI261: 0.05 | AJ261: -

Sheet Model
A1: Sheet Name | B1: Data | D1: Attribute Name | E1: isCollection
A2: Entities | B2: Data | D2: GTIN-Typ Regioapp | E2: true

Sheet Reference Data
A1: axartikelslpmstruktur__it_IT | B1: atxwarengruppesap__de_DE | C1: axartikelslpmstruktur__de_DE | D1: axmhdvorhanden__it_IT | E1: atxwarengruppesap__fr_FR | F1: axtaxdummyfilter__it_IT | G1: atxalkoholhaltig__it_IT | H1: axartikelslpmstruktur__fr_FR | I1: axartikeltypsap__fr_FR | J1: axartikeltypsap__de_DE | K1: axtaxdummyfilter__de_DE | L1: atxalkoholhaltig__fr_FR | M1: atxalkoholhaltig__de_DE | N1: axmhdvorhanden__de_DE | O1: atxwarengruppesap__it_IT | P1: axartikeltypsap__it_IT | Q1: axmhdvorhanden__fr_FR | R1: axtaxdummyfilter__fr_FR | S1: ENTITY_NAME | T1: refxartikeltypsap | U1: refxbooleanalkoholhaltig | V1: refxboolen | W1: refxartikelartsap de-DE | X1: refxartikelartsap fr-FR | Y1: refxartikelartsap it-IT | Z1: refxsaisontypsap de-DE | AA1: refxsaisontypsap fr-FR | AB1: refxsaisontypsap it-IT | AC1: refxmengeneinheit de-DE | AD1: refxmengeneinheit fr-FR | AE1: refxmengeneinheit it-IT | AF1: refxvergleichspreiseinheit de-DE | AG1: refxvergleichspreiseinheit fr-FR | AH1: refxvergleichspreiseinheit it-IT | AI1: refxtaxclass de-DE | AJ1: refxtaxclass fr-FR | AK1: refxtaxclass it-IT | AL1: refxaltersbegrtyp de-DE | AM1: refxaltersbegrtyp fr-FR | AN1: refxaltersbegrtyp it-IT | AO1: refxshopinshop | AP1: refxgtintyperegioartikel | AQ1: refxsystemsap
A2: SLPM Struktur>>3 Getränke>>30 Getränke>>3025 Tafelgetränke>>30251010 Säfte gekühlt | B2: Warengruppe>>Getränke>>Tafelgetränke>>Säfte gekühlt | C2: SLPM Struktur>>3 Getränke>>30 Getränke>>3025 Tafelgetränke>>30251010 Säfte gekühlt | D2: Ja | E2: Groupe de produits>>Boissons>>Boissons de table>>Jus de fruits réfrigérés | F2: Dummy for Attribute Filtering | G2: Nein | H2: SLPM Struktur>>3 Getränke>>30 Getränke>>3025 Tafelgetränke>>30251010 Säfte gekühlt | I2: 00 - Einzelartikel | J2: 00 - Einzelartikel | K2: Dummy for Attribute Filtering | L2: Nein | M2: Nein | N2: Ja | O2: Gruppo di prodotti>>Bevande>>Bevande da tavola>>Succhi refrigerati | P2: 00 - Einzelartikel | Q2: Ja | R2: Dummy for Attribute Filtering | S2: exartikel | T2: 00 - Einzelartikel | U2: Ja | V2: Ja | W2: ZAUS - Display In/Out Artikel | X2: ZAUS - Display In/Out Artikel | Y2: ZAUS - Display In/Out Artikel | Z2: In/Out | AA2: In/Out | AB2: In/Out | AC2: Centiliter | AD2: Caisse | AE2: Borsa | AF2: 1 | AG2: [DELETE] | AH2: [DELETE] | AI2: 0 - Ohne MWST | AJ2: 0 - Sans TVA | AK2: 0 - Senza IVA | AL2: Alcopops | AM2: Alcopop | AN2: Alcolpop | AO2: Denner Partner | AP2: GTIN | AQ2: S4H
T3: 12 - Display | U3: Nein | V3: Nein | W3: ZEGS - Externe Gutscheine | X3: ZHAW - Handelsware ohne Charge | Y3: ZHAW - Handelsware ohne Charge | Z3: Permanent | AA3: Permanent | AB3: Permanent | AC3: Each | AD3: Centilitre | AE3: Cassa | AF3: 10 | AG3: [NULL] | AH3: [NULL] | AI3: 1 - Normalsatz | AJ3: 1 - Taux normal | AK3: 1 - Tariffa standard | AL3: Bier | AM3: Aucune | AN3: Birra | AO3: Postartikel | AP3: _EMPTY | AQ3: S4HP
T4: [DELETE] | U4: [DELETE] | V4: [DELETE] | W4: ZHAW - Handelsware ohne Charge | X4: ZWEI - Wein mit Charge | Y4: ZWEI - Wein mit Charge | Z4: Saison | AA4: Saison | AB4: Saison | AC4: Gramm | AD4: Chaque | AE4: Centilitro | AF4: 100 | AI4: 3 - Reduzierter Satz | AJ4: 3 - Taux réduit | AK4: 3 - Tariffa ridotta | AL4: Keine | AM4: Bière | AN4: Nessuna | AO4: [DELETE] | AP4: [DELETE] | AQ4: [DELETE]
T5: [NULL] | U5: [NULL] | V5: [NULL] | W5: ZHIB - Hilfs-/Betriebsstoffe aus VZ | X5: [DELETE] | Y5: [DELETE] | Z5: Saison/Promo | AA5: Saison/Promo | AB5: Saison/Promo | AC5: Kilogramm | AD5: Gramme | AE5: Chilogrammo | AF5: [DELETE] | AI5: [DELETE] | AJ5: [DELETE] | AK5: [DELETE] | AL5: Rauchwaren | AM5: Spiriteux | AN5: Superalcolici | AO5: [NULL] | AP5: [NULL] | AQ5: [NULL]
W6: ZIGS - Denner Gutschein | X6: [NULL] | Y6: [NULL] | Z6: [DELETE] | AA6: [DELETE] | AB6: [DELETE] | AC6: Kiste | AD6: Kilogramme | AE6: Confezione | AF6: [NULL] | AI6: [NULL] | AJ6: [NULL] | AK6: [NULL] | AL6: Spirituosen | AM6: Tabac | AN6: Tabacchi
W7: ZLEE - Leergut | Z7: [NULL] | AA7: [NULL] | AB7: [NULL] | AC7: Liter | AD7: Litre | AE7: Each | AL7: Wein | AM7: Vin | AN7: Vino
W8: ZLOS - Lose | AC8: Milliliter | AD8: Millilitre | AE8: Grammo | AL8: [DELETE] | AM8: [DELETE] | AN8: [DELETE]
W9: ZRWE - Wein in Tanks | AC9: Pack | AD9: Paquet | AE9: Litro | AL9: [NULL] | AM9: [NULL] | AN9: [NULL]
W10: ZVBR - Verbrauchsmat. aus Antalis | AC10: Rolle | AD10: Pièce | AE10: Millilitro
W11: ZVOL - Vollgut | AC11: Stück | AD11: Rouleau | AE11: Pezzo
W12: ZWEI - Wein mit Charge | AC12: Tüte | AD12: Sachet | AE12: Rotolo
W13: [DELETE] | AC13: [DELETE] | AD13: [DELETE] | AE13: [DELETE]
W14: [NULL] | AC14: [NULL] | AD14: [NULL] | AE14: [NULL]

Sheet dedea_axba2387
A1: ZIGS - Denner Gutschein | B1: ZWEI - Wein mit Charge | C1: [EMPTY] | D1: ZVOL - Vollgut | E1: ZAUS - Display In/Out Artikel | F1: ZLEE - Leergut | G1: ZEGS - Externe Gutscheine | H1: ZHAW - Handelsware ohne Charge | I1: ZRWE - Wein in Tanks | J1: ZHIB - Hilfs-/Betriebsstoffe aus VZ | K1: ZLOS - Lose
A2: (KGM) KG | B2: (PCE) Stück | C2: (KGM) KG | D2: (KGM) KG | E2: (KGM) KG | F2: (KGM) KG | G2: (KGM) KG | H2: (KGM) KG | I2: (LTR) Liter | J2: (KGM) KG | K2: (KGM) KG
A3: (PCE) Stück | B3: [DELETE] | C3: (LTR) Liter | D3: (PCE) Stück | E3: (PCE) Stück | F3: (PCE) Stück | G3: (PCE) Stück | H3: (PCE) Stück | I3: [DELETE] | J3: (PCE) Stück | K3: (PCE) Stück
A4: [DELETE] | B4: [NULL] | C4: (PCE) Stück | D4: [DELETE] | E4: [DELETE] | F4: [DELETE] | G4: [DELETE] | H4: [DELETE] | I4: [NULL] | J4: [DELETE] | K4: [DELETE]
A5: [NULL] | C5: [DELETE] | D5: [NULL] | E5: [NULL] | F5: [NULL] | G5: [NULL] | H5: [NULL] | J5: [NULL] | K5: [NULL]
C6: [NULL]

Sheet frfra_axba1516
A1: ZWEI - Wein mit Charge | B1: [EMPTY] | C1: ZAUS - Display In/Out Artikel | D1: ZHAW - Handelsware ohne Charge
A2: (PCE) Pièce | B2: (KGM) kg | C2: (KGM) kg | D2: (KGM) kg
A3: [DELETE] | B3: (L) Litre | C3: (PCE) Pièce | D3: (PCE) Pièce
A4: [NULL] | B4: (PCE) Pièce | C4: [DELETE] | D4: [DELETE]
B5: [DELETE] | C5: [NULL] | D5: [NULL]
B6: [NULL]

Sheet itita_axba3948
A1: ZWEI - Wein mit Charge | B1: [EMPTY] | C1: ZAUS - Display In/Out Artikel | D1: ZHAW - Handelsware ohne Charge
A2: (PCE) Pezzo | B2: (KGM) KG | C2: (KGM) KG | D2: (KGM) KG
A3: [DELETE] | B3: (L) Litro | C3: (PCE) Pezzo | D3: (PCE) Pezzo
A4: [NULL] | B4: (PCE) Pezzo | C4: [DELETE] | D4: [DELETE]
B5: [DELETE] | C5: [NULL] | D5: [NULL]
B6: [NULL]
