Workbook
Name EntitiesCol: Entities!$SRI$2
Name EntitiesRow: Entities!$A$999454
Name RelationshipsCol: [1]Relationships!$SSS$2
Name RelationshipsRow: [1]Relationships!$A$1000000
Name RSC__refxartikeltypsap: 'Reference Data'!$T$2:$T$5
Name RSC__refxbooleanalkoholhaltig: 'Reference Data'!$U$2:$U$5
Name RSC__refxboolen: 'Reference Data'!$V$2:$V$5
Name RSC__refxgtintyperegioartikel: 'Reference Data'!$AP$2:$AP$5
Name RSC__refxshopinshop: 'Reference Data'!$AO$2:$AO$5
Name RSC__refxsystemsap: 'Reference Data'!$AQ$2:$AQ$5
Name RSC_atxalkoholhaltig__de_DE: 'Reference Data'!$M$2:$M$2
Name RSC_atxalkoholhaltig__fr_FR: 'Reference Data'!$L$2:$L$2
Name RSC_atxalkoholhaltig__it_IT: 'Reference Data'!$G$2:$G$2
Name RSC_atxwarengruppesap__de_DE: 'Reference Data'!$B$2:$B$2
Name RSC_atxwarengruppesap__fr_FR: 'Reference Data'!$E$2:$E$2
Name RSC_atxwarengruppesap__it_IT: 'Reference Data'!$O$2:$O$2
Name RSC_axartikelslpmstruktur__de_DE: 'Reference Data'!$C$2:$C$2
Name RSC_axartikelslpmstruktur__fr_FR: 'Reference Data'!$H$2:$H$2
Name RSC_axartikelslpmstruktur__it_IT: 'Reference Data'!$A$2:$A$2
Name RSC_axartikeltypsap__de_DE: 'Reference Data'!$J$2:$J$2
Name RSC_axartikeltypsap__fr_FR: 'Reference Data'!$I$2:$I$2
Name RSC_axartikeltypsap__it_IT: 'Reference Data'!$P$2:$P$2
Name RSC_axmhdvorhanden__de_DE: 'Reference Data'!$N$2:$N$2
Name RSC_axmhdvorhanden__fr_FR: 'Reference Data'!$Q$2:$Q$2
Name RSC_axmhdvorhanden__it_IT: 'Reference Data'!$D$2:$D$2
Name RSC_axtaxdummyfilter__de_DE: 'Reference Data'!$K$2:$K$2
Name RSC_axtaxdummyfilter__fr_FR: 'Reference Data'!$R$2:$R$2
Name RSC_axtaxdummyfilter__it_IT: 'Reference Data'!$F$2:$F$2
Name RSC_de_DE_refxaltersbegrtyp: 'Reference Data'!$AL$2:$AL$9
Name RSC_de_DE_refxartikelartsap: 'Reference Data'!$W$2:$W$14
Name RSC_de_DE_refxmengeneinheit: 'Reference Data'!$AC$2:$AC$14
Name RSC_de_DE_refxsaisontypsap: 'Reference Data'!$Z$2:$Z$7
Name RSC_de_DE_refxtaxclass: 'Reference Data'!$AI$2:$AI$6
Name RSC_de_DE_refxvergleichspreiseinheit: 'Reference Data'!$AF$2:$AF$6
Name RSC_ENTITY_NAME: 'Reference Data'!$S$2:$S$2
Name RSC_fr_FR_refxaltersbegrtyp: 'Reference Data'!$AM$2:$AM$9
Name RSC_fr_FR_refxartikelartsap: 'Reference Data'!$X$2:$X$6
Name RSC_fr_FR_refxmengeneinheit: 'Reference Data'!$AD$2:$AD$14
Name RSC_fr_FR_refxsaisontypsap: 'Reference Data'!$AA$2:$AA$7
Name RSC_fr_FR_refxtaxclass: 'Reference Data'!$AJ$2:$AJ$6
Name RSC_fr_FR_refxvergleichspreiseinheit: 'Reference Data'!$AG$2:$AG$3
Name RSC_it_IT_refxaltersbegrtyp: 'Reference Data'!$AN$2:$AN$9
Name RSC_it_IT_refxartikelartsap: 'Reference Data'!$Y$2:$Y$6
Name RSC_it_IT_refxmengeneinheit: 'Reference Data'!$AE$2:$AE$14
Name RSC_it_IT_refxsaisontypsap: 'Reference Data'!$AB$2:$AB$7
Name RSC_it_IT_refxtaxclass: 'Reference Data'!$AK$2:$AK$6
Name RSC_it_IT_refxvergleichspreiseinheit: 'Reference Data'!$AH$2:$AH$3

Sheet Help
B3: These are all read only
A4: TEMPLATE NAME | B4: RS EXCEL
A5: TEMPLATE VERSION | B5: V1.0
A6: MULTI VALUES DELIMITER | B6: ||
A7: CONTEXT PATH DELIMITER | B7: >>
A8: LEGENDS | B8: INHERITED VALUE(S)
B9: GOVERNANCE ERROR(S)
A12: Type
A13: SYSTEM/RELATIONSHIPS | B13: COLLECTION | C13: MANDATORY | D13: MANDATORY COLLECTION
A14: GLOBAL | B14: COLLECTION | C14: MANDATORY | D14: MANDATORY COLLECTION
A15: GLOBAL ENHANCER | B15: COLLECTION | C15: MANDATORY | D15: MANDATORY COLLECTION
A16: CONTEXT | B16: COLLECTION | C16: MANDATORY | D16: MANDATORY COLLECTION
A17: CONTEXT ENHANCER | B17: COLLECTION | C17: MANDATORY | D17: MANDATORY COLLECTION

Sheet Entities
A1: System Attributes | E1: Enhancer Attribute(s) | G1: Matching Attribute(s) | H1: 01 - Rumpfinformationen | J1: 99 - intern | L1: 01 - Rumpfinformationen | O1: 03 - Texte | U1: 99 - intern | AA1: 01 - Rumpfinformationen | AH1: 05 - Kasse | AM1: 99 - intern
A2: Action | B2: Type | C2: ID | D2: Name | E2: Artikeltyp | F2: Warengruppe//de-DE | G2: MDM ID | H2: Artikelart//de-DE | I2: Saison Typ//de-DE | J2: GTIN Suche | K2: Ergänzte Regio-Artikel-GTIN | L2: Artikeltext//de-DE | M2: Artikeltext//fr-FR | N2: Artikeltext//it-IT | O2: Gestellbeschriftung 1//de-DE | P2: Gestellbeschriftung 1//fr-FR | Q2: Gestellbeschriftung 1//it-IT | R2: Gestellbeschriftung 2//de-DE | S2: Gestellbeschriftung 2//fr-FR | T2: Gestellbeschriftung 2//it-IT | U2: Gestellbeschriftung 3 Regio//de-DE | V2: Gestellbeschriftung 3 Regio//fr-FR | W2: Gestellbeschriftung 3 Regio//it-IT | X2: Cash receipt text Regio//de-DE | Y2: Cash receipt text Regio//fr-FR | Z2: Cash receipt text Regio//it-IT | AA2: Nettoinhalt | AB2: Inhaltsmengeneinheit Grundpreis//de-DE | AC2: Grundpreiseinheit//de-DE | AD2: Basismengeneinheit//de-DE | AE2: Steuerklassifikation//de-DE | AF2: Leergut | AG2: Altersbegrenzungs-Typ//de-DE | AH2: Rabatt zugelassen | AI2: Rückgabe zugelassen | AJ2: Preisänderung Kasse erlaubt | AK2: Automatischer Bondruck | AL2: Shop-In-Shop | AM2: Ist Fremdartikel | AN2: GTIN-Typ Regioapp | AO2: Ist Regioartikel | AP2: Source | AQ2: SAP System Integration | AR2: Ist Vordefiniert
B3: exartikel | E3: 00 - Einzelartikel | F3: ="Warengruppe>>"&_xlfn.TEXTJOIN(">>",TRUE,Migrationsartikel!V2:X2) -> Warengruppe>>Früchte und Gemüse>>Früchte und Gemüse>>Früchte | H3: ZHAW - Handelsware ohne Charge | J3: =_xlfn.TEXTJOIN(" ",TRUE,Migrationsartikel!B2,Migrationsartikel!E2) -> 7610029177671 | L3: =_xlfn.TEXTJOIN(" ",TRUE,Migrationsartikel!F2:H2) -> Marroni gekocht 400g | M3: =_xlfn.TEXTJOIN(" ",TRUE,Migrationsartikel!J2:L2) -> Marrons cuits 400g | N3: =_xlfn.TEXTJOIN(" ",TRUE,Migrationsartikel!N2:P2) -> Castagne cotte 400g | O3: =Migrationsartikel!F2 -> Marroni gekocht | P3: =Migrationsartikel!J2 -> Marrons cuits | Q3: =Migrationsartikel!N2 -> Castagne cotte | R3: =_xlfn.TEXTJOIN(" ",TRUE,Migrationsartikel!G2) | S3: =_xlfn.TEXTJOIN(" ",TRUE,Migrationsartikel!K2) | T3: =_xlfn.TEXTJOIN(" ",TRUE,Migrationsartikel!O2) | U3: =_xlfn.TEXTJOIN(" ",TRUE,Migrationsartikel!H2) -> 400g | V3: =_xlfn.TEXTJOIN(" ",TRUE,Migrationsartikel!L2) -> 400g | W3: =_xlfn.TEXTJOIN(" ",TRUE,Migrationsartikel!P2) -> 400g | X3: =Migrationsartikel!I2 -> Marroni gekocht | Y3: =Migrationsartikel!M2 -> Marrons cuits | Z3: =Migrationsartikel!Q2 -> Castagne cotte | AA3: =Migrationsartikel!R2 -> 1 | AB3: =Migrationsartikel!T2 -> Kilogramm | AC3: =Migrationsartikel!S2 -> 1 | AD3: =Migrationsartikel!U2 -> (PCE) Stück | AE3: =Migrationsartikel!Y2 -> 3 - Reduzierter Satz | AF3: =IF(Migrationsartikel!AA2="Kein Depotartikel","",Migrationsartikel!AA2) | AG3: =Migrationsartikel!Z2 -> Keine | AH3: =IF(Migrationsartikel!AB2="ja","true",FALSE) -> true | AI3: =IF(Migrationsartikel!AC2="ja","true",FALSE) -> true | AJ3: =IF(Migrationsartikel!AD2="ja","true",FALSE) -> true | AK3: =IF(Migrationsartikel!AE2="ja","true",FALSE) -> true | AL3: =IF(Migrationsartikel!AF2="ja","Denner Partner","") | AM3: =IF(Migrationsartikel!AG2="ja","true","false") -> false | AN3: =IF(AND(ISNUMBER(J3),J3>=100,J3<=999),"PLU",IF(AND(ISNUMBER(J3),J3>999),"GTIN","Kassentastenbelegung (ohne GTIN/PLU)")) -> Kassentastenbelegung (ohne GTIN/PLU) | AO3: true | AP3: Imp. Regio 3 - 3003 | AQ3: S4H | AR3: true
B4: exartikel | E4: 00 - Einzelartikel | F4: ="Warengruppe>>"&_xlfn.TEXTJOIN(">>",TRUE,Migrationsartikel!V3:X3) -> Warengruppe>>Früchte und Gemüse>>Früchte und Gemüse>>Früchte | H4: ZHAW - Handelsware ohne Charge | J4: =_xlfn.TEXTJOIN(" ",TRUE,Migrationsartikel!B3,Migrationsartikel!E3) | L4: =_xlfn.TEXTJOIN(" ",TRUE,Migrationsartikel!F3:H3) -> Aprikosen 1kg | M4: =_xlfn.TEXTJOIN(" ",TRUE,Migrationsartikel!J3:L3) -> Abricots 1kg | N4: =_xlfn.TEXTJOIN(" ",TRUE,Migrationsartikel!N3:P3) -> Albicocche 1kg | O4: =Migrationsartikel!F3 -> Aprikosen | P4: =Migrationsartikel!J3 -> Abricots | Q4: =Migrationsartikel!N3 -> Albicocche | R4: =_xlfn.TEXTJOIN(" ",TRUE,Migrationsartikel!G3) | S4: =_xlfn.TEXTJOIN(" ",TRUE,Migrationsartikel!K3) | T4: =_xlfn.TEXTJOIN(" ",TRUE,Migrationsartikel!O3) | U4: =_xlfn.TEXTJOIN(" ",TRUE,Migrationsartikel!H3) -> 1kg | V4: =_xlfn.TEXTJOIN(" ",TRUE,Migrationsartikel!L3) -> 1kg | W4: =_xlfn.TEXTJOIN(" ",TRUE,Migrationsartikel!P3) -> 1kg | X4: =Migrationsartikel!I3 -> Aprikosen 1kg | Y4: =Migrationsartikel!M3 -> Abricots 1g | Z4: =Migrationsartikel!Q3 -> Albicocche 1kg | AA4: =Migrationsartikel!R3 -> 1 | AB4: =Migrationsartikel!T3 -> Kilogramm | AC4: =Migrationsartikel!S3 -> 1 | AD4: =Migrationsartikel!U3 -> (PCE) Stück | AE4: =Migrationsartikel!Y3 -> 3 - Reduzierter Satz | AF4: =IF(Migrationsartikel!AA3="Kein Depotartikel","",Migrationsartikel!AA3) | AG4: =Migrationsartikel!Z3 -> Keine | AH4: =IF(Migrationsartikel!AB3="ja","true",FALSE) -> true | AI4: =IF(Migrationsartikel!AC3="ja","true",FALSE) -> true | AJ4: =IF(Migrationsartikel!AD3="ja","true",FALSE) -> true | AK4: =IF(Migrationsartikel!AE3="ja","true",FALSE) -> true | AL4: =IF(Migrationsartikel!AF3="ja","Denner Partner","") | AM4: =IF(Migrationsartikel!AG3="ja","true","false") -> false | AN4: =IF(AND(ISNUMBER(J4),J4>=100,J4<=999),"PLU",IF(AND(ISNUMBER(J4),J4>999),"GTIN","Kassentastenbelegung (ohne GTIN/PLU)")) -> Kassentastenbelegung (ohne GTIN/PLU) | AO4: true | AP4: Imp. Regio 3 - 3004 | AQ4: S4H | AR4: true
B5: exartikel | E5: 00 - Einzelartikel | F5: ="Warengruppe>>"&_xlfn.TEXTJOIN(">>",TRUE,Migrationsartikel!V4:X4) -> Warengruppe>>Früchte und Gemüse>>Früchte und Gemüse>>Früchte | H5: ZHAW - Handelsware ohne Charge | J5: =_xlfn.TEXTJOIN(" ",TRUE,Migrationsartikel!B4,Migrationsartikel!E4) -> 7613399055839 | L5: =_xlfn.TEXTJOIN(" ",TRUE,Migrationsartikel!F4:H4) -> Bio Datteln Frisch Medjoul 200g | M5: =_xlfn.TEXTJOIN(" ",TRUE,Migrationsartikel!J4:L4) -> Bio Dattes fraîches Medjoul 200g | N5: =_xlfn.TEXTJOIN(" ",TRUE,Migrationsartikel!N4:P4) -> Bio datteri freschi Medjoul 200g | O5: =Migrationsartikel!F4 -> Bio Datteln Frisch | P5: =Migrationsartikel!J4 -> Bio Dattes fraîches | Q5: =Migrationsartikel!N4 -> Bio datteri freschi | R5: =_xlfn.TEXTJOIN(" ",TRUE,Migrationsartikel!G4) -> Medjoul | S5: =_xlfn.TEXTJOIN(" ",TRUE,Migrationsartikel!K4) -> Medjoul | T5: =_xlfn.TEXTJOIN(" ",TRUE,Migrationsartikel!O4) -> Medjoul | U5: =_xlfn.TEXTJOIN(" ",TRUE,Migrationsartikel!H4) -> 200g | V5: =_xlfn.TEXTJOIN(" ",TRUE,Migrationsartikel!L4) -> 200g | W5: =_xlfn.TEXTJOIN(" ",TRUE,Migrationsartikel!P4) -> 200g | X5: =Migrationsartikel!I4 -> Bio Datteln Medjoul 200g | Y5: =Migrationsartikel!M4 -> Bio Dattes fr. Medjoul 200g | Z5: =Migrationsartikel!Q4 -> Bio datteri fre Medjoul 200g | AA5: =Migrationsartikel!R4 -> 0.2 | AB5: =Migrationsartikel!T4 -> Gramm | AC5: =Migrationsartikel!S4 -> 100 | AD5: =Migrationsartikel!U4 -> (PCE) Stück | AE5: =Migrationsartikel!Y4 -> 3 - Reduzierter Satz | AF5: =IF(Migrationsartikel!AA4="Kein Depotartikel","",Migrationsartikel!AA4) | AG5: =Migrationsartikel!Z4 -> Keine | AH5: =IF(Migrationsartikel!AB4="ja","true",FALSE) -> true | AI5: =IF(Migrationsartikel!AC4="ja","true",FALSE) -> true | AJ5: =IF(Migrationsartikel!AD4="ja","true",FALSE) -> true | AK5: =IF(Migrationsartikel!AE4="ja","true",FALSE) -> true | AL5: =IF(Migrationsartikel!AF4="ja","Denner Partner","") | AM5: =IF(Migrationsartikel!AG4="ja","true","false") -> false | AN5: =IF(AND(ISNUMBER(J5),J5>=100,J5<=999),"PLU",IF(AND(ISNUMBER(J5),J5>999),"GTIN","Kassentastenbelegung (ohne GTIN/PLU)")) -> Kassentastenbelegung (ohne GTIN/PLU) | AO5: true | AP5: Imp. Regio 3 - 3005 | AQ5: S4H | AR5: true
B6: exartikel | E6: 00 - Einzelartikel | F6: ="Warengruppe>>"&_xlfn.TEXTJOIN(">>",TRUE,Migrationsartikel!V5:X5) -> Warengruppe>>Früchte und Gemüse>>Früchte und Gemüse>>Früchte | H6: ZHAW - Handelsware ohne Charge | J6: =_xlfn.TEXTJOIN(" ",TRUE,Migrationsartikel!B5,Migrationsartikel!E5) | L6: =_xlfn.TEXTJOIN(" ",TRUE,Migrationsartikel!F5:H5) -> Feigen Pulled 400g | M6: =_xlfn.TEXTJOIN(" ",TRUE,Migrationsartikel!J5:L5) -> Figues Pulled 400g | N6: =_xlfn.TEXTJOIN(" ",TRUE,Migrationsartikel!N5:P5) -> Fichi Pulled 400g | O6: =Migrationsartikel!F5 -> Feigen Pulled | P6: =Migrationsartikel!J5 -> Figues Pulled | Q6: =Migrationsartikel!N5 -> Fichi Pulled | R6: =_xlfn.TEXTJOIN(" ",TRUE,Migrationsartikel!G5) | S6: =_xlfn.TEXTJOIN(" ",TRUE,Migrationsartikel!K5) | T6: =_xlfn.TEXTJOIN(" ",TRUE,Migrationsartikel!O5) | U6: =_xlfn.TEXTJOIN(" ",TRUE,Migrationsartikel!H5) -> 400g | V6: =_xlfn.TEXTJOIN(" ",TRUE,Migrationsartikel!L5) -> 400g | W6: =_xlfn.TEXTJOIN(" ",TRUE,Migrationsartikel!P5) -> 400g | X6: =Migrationsartikel!I5 -> Feigen Pulled 400g | Y6: =Migrationsartikel!M5 -> Figues Pulled 400g | Z6: =Migrationsartikel!Q5 -> Fichi Pulled 40g | AA6: =Migrationsartikel!R5 -> 0.4 | AB6: =Migrationsartikel!T5 -> Kilogramm | AC6: =Migrationsartikel!S5 -> 1 | AD6: =Migrationsartikel!U5 -> (PCE) Stück | AE6: =Migrationsartikel!Y5 -> 3 - Reduzierter Satz | AF6: =IF(Migrationsartikel!AA5="Kein Depotartikel","",Migrationsartikel!AA5) | AG6: =Migrationsartikel!Z5 -> Keine | AH6: =IF(Migrationsartikel!AB5="ja","true",FALSE) -> true | AI6: =IF(Migrationsartikel!AC5="ja","true",FALSE) -> true | AJ6: =IF(Migrationsartikel!AD5="ja","true",FALSE) -> true | AK6: =IF(Migrationsartikel!AE5="ja","true",FALSE) -> true | AL6: =IF(Migrationsartikel!AF5="ja","Denner Partner","") | AM6: =IF(Migrationsartikel!AG5="ja","true","false") -> false | AN6: =IF(AND(ISNUMBER(J6),J6>=100,J6<=999),"PLU",IF(AND(ISNUMBER(J6),J6>999),"GTIN","Kassentastenbelegung (ohne GTIN/PLU)")) -> Kassentastenbelegung (ohne GTIN/PLU) | AO6: true | AP6: Imp. Regio 3 - 3006 | AQ6: S4H | AR6: true
B7: exartikel | E7: 00 - Einzelartikel | F7: ="Warengruppe>>"&_xlfn.TEXTJOIN(">>",TRUE,Migrationsartikel!V6:X6) -> Warengruppe>>Früchte und Gemüse>>Früchte und Gemüse>>Früchte | H7: ZHAW - Handelsware ohne Charge | J7: =_xlfn.TEXTJOIN(" ",TRUE,Migrationsartikel!B6,Migrationsartikel!E6) -> 7613399055365 | L7: =_xlfn.TEXTJOIN(" ",TRUE,Migrationsartikel!F6:H6) -> Haselnüsse 500g | M7: =_xlfn.TEXTJOIN(" ",TRUE,Migrationsartikel!J6:L6) -> Noisettes 500g | N7: =_xlfn.TEXTJOIN(" ",TRUE,Migrationsartikel!N6:P6) -> Nocciole 500g | O7: =Migrationsartikel!F6 -> Haselnüsse | P7: =Migrationsartikel!J6 -> Noisettes | Q7: =Migrationsartikel!N6 -> Nocciole | R7: =_xlfn.TEXTJOIN(" ",TRUE,Migrationsartikel!G6) | S7: =_xlfn.TEXTJOIN(" ",TRUE,Migrationsartikel!K6) | T7: =_xlfn.TEXTJOIN(" ",TRUE,Migrationsartikel!O6) | U7: =_xlfn.TEXTJOIN(" ",TRUE,Migrationsartikel!H6) -> 500g | V7: =_xlfn.TEXTJOIN(" ",TRUE,Migrationsartikel!L6) -> 500g | W7: =_xlfn.TEXTJOIN(" ",TRUE,Migrationsartikel!P6) -> 500g | X7: =Migrationsartikel!I6 -> Haselnüsse 500g | Y7: =Migrationsartikel!M6 -> Noisettes 500g | Z7: =Migrationsartikel!Q6 -> Nocciole 500g | AA7: =Migrationsartikel!R6 -> 0.5 | AB7: =Migrationsartikel!T6 -> Kilogramm | AC7: =Migrationsartikel!S6 -> 1 | AD7: =Migrationsartikel!U6 -> (PCE) Stück | AE7: =Migrationsartikel!Y6 -> 3 - Reduzierter Satz | AF7: =IF(Migrationsartikel!AA6="Kein Depotartikel","",Migrationsartikel!AA6) | AG7: =Migrationsartikel!Z6 -> Keine | AH7: =IF(Migrationsartikel!AB6="ja","true",FALSE) -> true | AI7: =IF(Migrationsartikel!AC6="ja","true",FALSE) -> true | AJ7: =IF(Migrationsartikel!AD6="ja","true",FALSE) -> true | AK7: =IF(Migrationsartikel!AE6="ja","true",FALSE) -> true | AL7: =IF(Migrationsartikel!AF6="ja","Denner Partner","") | AM7: =IF(Migrationsartikel!AG6="ja","true","false") -> false | AN7: =IF(AND(ISNUMBER(J7),J7>=100,J7<=999),"PLU",IF(AND(ISNUMBER(J7),J7>999),"GTIN","Kassentastenbelegung (ohne GTIN/PLU)")) -> Kassentastenbelegung (ohne GTIN/PLU) | AO7: true | AP7: Imp. Regio 3 - 3007 | AQ7: S4H | AR7: true
B8: exartikel | E8: 00 - Einzelartikel | F8: ="Warengruppe>>"&_xlfn.TEXTJOIN(">>",TRUE,Migrationsartikel!V7:X7) -> Warengruppe>>Früchte und Gemüse>>Früchte und Gemüse>>Früchte | H8: ZHAW - Handelsware ohne Charge | J8: =_xlfn.TEXTJOIN(" ",TRUE,Migrationsartikel!B7,Migrationsartikel!E7) -> 143 | L8: =_xlfn.TEXTJOIN(" ",TRUE,Migrationsartikel!F7:H7) -> Birnen Büscheli Offen Kl. 1 | M8: =_xlfn.TEXTJOIN(" ",TRUE,Migrationsartikel!J7:L7) -> Poires Büscheli En vrac, cl. 1 | N8: =_xlfn.TEXTJOIN(" ",TRUE,Migrationsartikel!N7:P7) -> Pere Büscheli Cl. 1 vendita sfusa | O8: =Migrationsartikel!F7 -> Birnen Büscheli | P8: =Migrationsartikel!J7 -> Poires Büscheli | Q8: =Migrationsartikel!N7 -> Pere Büscheli | R8: =_xlfn.TEXTJOIN(" ",TRUE,Migrationsartikel!G7) -> Offen Kl. 1 | S8: =_xlfn.TEXTJOIN(" ",TRUE,Migrationsartikel!K7) -> En vrac, cl. 1 | T8: =_xlfn.TEXTJOIN(" ",TRUE,Migrationsartikel!O7) -> Cl. 1 vendita sfusa | U8: =_xlfn.TEXTJOIN(" ",TRUE,Migrationsartikel!H7) | V8: =_xlfn.TEXTJOIN(" ",TRUE,Migrationsartikel!L7) | W8: =_xlfn.TEXTJOIN(" ",TRUE,Migrationsartikel!P7) | X8: =Migrationsartikel!I7 -> Birnen Büscheli Offen Kl. 1 | Y8: =Migrationsartikel!M7 -> Poires Büscheli | Z8: =Migrationsartikel!Q7 -> Pere Büscheli Cl. 1 v.s. | AA8: =Migrationsartikel!R7 -> 1 | AB8: =Migrationsartikel!T7 -> Kilogramm | AC8: =Migrationsartikel!S7 -> 1 | AD8: =Migrationsartikel!U7 -> (KGM) KG | AE8: =Migrationsartikel!Y7 -> 3 - Reduzierter Satz | AF8: =IF(Migrationsartikel!AA7="Kein Depotartikel","",Migrationsartikel!AA7) | AG8: =Migrationsartikel!Z7 -> Keine | AH8: =IF(Migrationsartikel!AB7="ja","true",FALSE) -> true | AI8: =IF(Migrationsartikel!AC7="ja","true",FALSE) -> true | AJ8: =IF(Migrationsartikel!AD7="ja","true",FALSE) -> true | AK8: =IF(Migrationsartikel!AE7="ja","true",FALSE) -> true | AL8: =IF(Migrationsartikel!AF7="ja","Denner Partner","") | AM8: =IF(Migrationsartikel!AG7="ja","true","false") -> false | AN8: =IF(AND(ISNUMBER(J8),J8>=100,J8<=999),"PLU",IF(AND(ISNUMBER(J8),J8>999),"GTIN","Kassentastenbelegung (ohne GTIN/PLU)")) -> Kassentastenbelegung (ohne GTIN/PLU) | AO8: true | AP8: Imp. Regio 3 - 3008 | AQ8: S4H | AR8: true
B9: exartikel | E9: 00 - Einzelartikel | F9: ="Warengruppe>>"&_xlfn.TEXTJOIN(">>",TRUE,Migrationsartikel!V8:X8) -> Warengruppe>>Früchte und Gemüse>>Früchte und Gemüse>>Früchte | H9: ZHAW - Handelsware ohne Charge | J9: =_xlfn.TEXTJOIN(" ",TRUE,Migrationsartikel!B8,Migrationsartikel!E8) -> 7613399039945 | L9: =_xlfn.TEXTJOIN(" ",TRUE,Migrationsartikel!F8:H8) -> Granatapfelkerne Becher 125g | M9: =_xlfn.TEXTJOIN(" ",TRUE,Migrationsartikel!J8:L8) -> Graines de grenade Gobelet 125g | N9: =_xlfn.TEXTJOIN(" ",TRUE,Migrationsartikel!N8:P8) -> Melagrana chicchi bicchiere 125g | O9: =Migrationsartikel!F8 -> Granatapfelkerne | P9: =Migrationsartikel!J8 -> Graines de grenade | Q9: =Migrationsartikel!N8 -> Melagrana chicchi | R9: =_xlfn.TEXTJOIN(" ",TRUE,Migrationsartikel!G8) -> Becher | S9: =_xlfn.TEXTJOIN(" ",TRUE,Migrationsartikel!K8) -> Gobelet | T9: =_xlfn.TEXTJOIN(" ",TRUE,Migrationsartikel!O8) -> bicchiere | U9: =_xlfn.TEXTJOIN(" ",TRUE,Migrationsartikel!H8) -> 125g | V9: =_xlfn.TEXTJOIN(" ",TRUE,Migrationsartikel!L8) -> 125g | W9: =_xlfn.TEXTJOIN(" ",TRUE,Migrationsartikel!P8) -> 125g | X9: =Migrationsartikel!I8 -> Granatapfelkerne Becher | Y9: =Migrationsartikel!M8 -> Graines de grenade 125g | Z9: =Migrationsartikel!Q8 -> Melagrana chicchi 125g | AA9: =Migrationsartikel!R8 -> 0.125 | AB9: =Migrationsartikel!T8 -> Gramm | AC9: =Migrationsartikel!S8 -> 100 | AD9: =Migrationsartikel!U8 -> (PCE) Stück | AE9: =Migrationsartikel!Y8 -> 3 - Reduzierter Satz | AF9: =IF(Migrationsartikel!AA8="Kein Depotartikel","",Migrationsartikel!AA8) | AG9: =Migrationsartikel!Z8 -> Keine | AH9: =IF(Migrationsartikel!AB8="ja","true",FALSE) -> true | AI9: =IF(Migrationsartikel!AC8="ja","true",FALSE) -> true | AJ9: =IF(Migrationsartikel!AD8="ja","true",FALSE) -> true | AK9: =IF(Migrationsartikel!AE8="ja","true",FALSE) -> true | AL9: =IF(Migrationsartikel!AF8="ja","Denner Partner","") | AM9: =IF(Migrationsartikel!AG8="ja","true","false") -> false | AN9: =IF(AND(ISNUMBER(J9),J9>=100,J9<=999),"PLU",IF(AND(ISNUMBER(J9),J9>999),"GTIN","Kassentastenbelegung (ohne GTIN/PLU)")) -> Kassentastenbelegung (ohne GTIN/PLU) | AO9: true | AP9: Imp. Regio 3 - 3009 | AQ9: S4H | AR9: true
B10: exartikel | E10: 00 - Einzelartikel | F10: ="Warengruppe>>"&_xlfn.TEXTJOIN(">>",TRUE,Migrationsartikel!V9:X9) -> Warengruppe>>Früchte und Gemüse>>Früchte und Gemüse>>Früchte | H10: ZHAW - Handelsware ohne Charge | J10: =_xlfn.TEXTJOIN(" ",TRUE,Migrationsartikel!B9,Migrationsartikel!E9) | L10: =_xlfn.TEXTJOIN(" ",TRUE,Migrationsartikel!F9:H9) -> Ananas Baby 1Stk | M10: =_xlfn.TEXTJOIN(" ",TRUE,Migrationsartikel!J9:L9) -> Ananas Baby 1pce | N10: =_xlfn.TEXTJOIN(" ",TRUE,Migrationsartikel!N9:P9) -> Ananas Baby 1pz | O10: =Migrationsartikel!F9 -> Ananas | P10: =Migrationsartikel!J9 -> Ananas | Q10: =Migrationsartikel!N9 -> Ananas | R10: =_xlfn.TEXTJOIN(" ",TRUE,Migrationsartikel!G9) -> Baby | S10: =_xlfn.TEXTJOIN(" ",TRUE,Migrationsartikel!K9) -> Baby | T10: =_xlfn.TEXTJOIN(" ",TRUE,Migrationsartikel!O9) -> Baby | U10: =_xlfn.TEXTJOIN(" ",TRUE,Migrationsartikel!H9) -> 1Stk | V10: =_xlfn.TEXTJOIN(" ",TRUE,Migrationsartikel!L9) -> 1pce | W10: =_xlfn.TEXTJOIN(" ",TRUE,Migrationsartikel!P9) -> 1pz | X10: =Migrationsartikel!I9 -> Ananas Baby Stk | Y10: =Migrationsartikel!M9 -> Ananas Baby | Z10: =Migrationsartikel!Q9 -> Ananas Baby 1 pz | AA10: =Migrationsartikel!R9 -> 1 | AB10: =Migrationsartikel!T9 -> Stück | AC10: =Migrationsartikel!S9 -> 1 | AD10: =Migrationsartikel!U9 -> (PCE) Stück | AE10: =Migrationsartikel!Y9 -> 3 - Reduzierter Satz | AF10: =IF(Migrationsartikel!AA9="Kein Depotartikel","",Migrationsartikel!AA9) | AG10: =Migrationsartikel!Z9 -> Keine | AH10: =IF(Migrationsartikel!AB9="ja","true",FALSE) -> true | AI10: =IF(Migrationsartikel!AC9="ja","true",FALSE) -> true | AJ10: =IF(Migrationsartikel!AD9="ja","true",FALSE) -> true | AK10: =IF(Migrationsartikel!AE9="ja","true",FALSE) -> true | AL10: =IF(Migrationsartikel!AF9="ja","Denner Partner","") | AM10: =IF(Migrationsartikel!AG9="ja","true","false") -> false | AN10: =IF(AND(ISNUMBER(J10),J10>=100,J10<=999),"PLU",IF(AND(ISNUMBER(J10),J10>999),"GTIN","Kassentastenbelegung (ohne GTIN/PLU)")) -> Kassentastenbelegung (ohne GTIN/PLU) | AO10: true | AP10: Imp. Regio 3 - 3010 | AQ10: S4H | AR10: true
B11: exartikel | E11: 00 - Einzelartikel | F11: ="Warengruppe>>"&_xlfn.TEXTJOIN(">>",TRUE,Migrationsartikel!V10:X10) -> Warengruppe>>Früchte und Gemüse>>Früchte und Gemüse>>Früchte | H11: ZHAW - Handelsware ohne Charge | J11: =_xlfn.TEXTJOIN(" ",TRUE,Migrationsartikel!B10,Migrationsartikel!E10) -> 7613399001270 | L11: =_xlfn.TEXTJOIN(" ",TRUE,Migrationsartikel!F10:H10) -> Ananas Becher 200g | M11: =_xlfn.TEXTJOIN(" ",TRUE,Migrationsartikel!J10:L10) -> Ananas Gobelet 200g | N11: =_xlfn.TEXTJOIN(" ",TRUE,Migrationsartikel!N10:P10) -> Ananas bicchiere 200g | O11: =Migrationsartikel!F10 -> Ananas | P11: =Migrationsartikel!J10 -> Ananas | Q11: =Migrationsartikel!N10 -> Ananas | R11: =_xlfn.TEXTJOIN(" ",TRUE,Migrationsartikel!G10) -> Becher | S11: =_xlfn.TEXTJOIN(" ",TRUE,Migrationsartikel!K10) -> Gobelet | T11: =_xlfn.TEXTJOIN(" ",TRUE,Migrationsartikel!O10) -> bicchiere | U11: =_xlfn.TEXTJOIN(" ",TRUE,Migrationsartikel!H10) -> 200g | V11: =_xlfn.TEXTJOIN(" ",TRUE,Migrationsartikel!L10) -> 200g | W11: =_xlfn.TEXTJOIN(" ",TRUE,Migrationsartikel!P10) -> 200g | X11: =Migrationsartikel!I10 -> Ananas Becher 200g | Y11: =Migrationsartikel!M10 -> Ananas gobelet 200g | Z11: =Migrationsartikel!Q10 -> Ananas bicchiere 200g | AA11: =Migrationsartikel!R10 -> 0.2 | AB11: =Migrationsartikel!T10 -> Gramm | AC11: =Migrationsartikel!S10 -> 100 | AD11: =Migrationsartikel!U10 -> (PCE) Stück | AE11: =Migrationsartikel!Y10 -> 3 - Reduzierter Satz | AF11: =IF(Migrationsartikel!AA10="Kein Depotartikel","",Migrationsartikel!AA10) | AG11: =Migrationsartikel!Z10 -> Keine | AH11: =IF(Migrationsartikel!AB10="ja","true",FALSE) -> true | AI11: =IF(Migrationsartikel!AC10="ja","true",FALSE) -> true | AJ11: =IF(Migrationsartikel!AD10="ja","true",FALSE) -> true | AK11: =IF(Migrationsartikel!AE10="ja","true",FALSE) -> true | AL11: =IF(Migrationsartikel!AF10="ja","Denner Partner","") | AM11: =IF(Migrationsartikel!AG10="ja","true","false") -> false | AN11: =IF(AND(ISNUMBER(J11),J11>=100,J11<=999),"PLU",IF(AND(ISNUMBER(J11),J11>999),"GTIN","Kassentastenbelegung (ohne GTIN/PLU)")) -> Kassentastenbelegung (ohne GTIN/PLU) | AO11: true | AP11: Imp. Regio 3 - 3011 | AQ11: S4H | AR11: true
B12: exartikel | E12: 00 - Einzelartikel | F12: ="Warengruppe>>"&_xlfn.TEXTJOIN(">>",TRUE,Migrationsartikel!V11:X11) -> Warengruppe>>Früchte und Gemüse>>Früchte und Gemüse>>Früchte | H12: ZHAW - Handelsware ohne Charge | J12: =_xlfn.TEXTJOIN(" ",TRUE,Migrationsartikel!B11,Migrationsartikel!E11) -> 104 | L12: =_xlfn.TEXTJOIN(" ",TRUE,Migrationsartikel!F11:H11) -> Äpfel Diwa Offen Kl. 1 | M12: =_xlfn.TEXTJOIN(" ",TRUE,Migrationsartikel!J11:L11) -> Pommes Diwa En vrac, cl. 1 | N12: =_xlfn.TEXTJOIN(" ",TRUE,Migrationsartikel!N11:P11) -> Mele Diwa Cl. 1 vendita sfusa | O12: =Migrationsartikel!F11 -> Äpfel Diwa | P12: =Migrationsartikel!J11 -> Pommes Diwa | Q12: =Migrationsartikel!N11 -> Mele Diwa | R12: =_xlfn.TEXTJOIN(" ",TRUE,Migrationsartikel!G11) -> Offen Kl. 1 | S12: =_xlfn.TEXTJOIN(" ",TRUE,Migrationsartikel!K11) -> En vrac, cl. 1 | T12: =_xlfn.TEXTJOIN(" ",TRUE,Migrationsartikel!O11) -> Cl. 1 vendita sfusa | U12: =_xlfn.TEXTJOIN(" ",TRUE,Migrationsartikel!H11) | V12: =_xlfn.TEXTJOIN(" ",TRUE,Migrationsartikel!L11) | W12: =_xlfn.TEXTJOIN(" ",TRUE,Migrationsartikel!P11) | X12: =Migrationsartikel!I11 -> Äpfel Diwa Offen Kl. 1 | Y12: =Migrationsartikel!M11 -> Pommes Diwa en vrac cl. 1 | Z12: =Migrationsartikel!Q11 -> Mele Diwa cl. 1 vend. sfusa | AA12: =Migrationsartikel!R11 -> 1 | AB12: =Migrationsartikel!T11 -> Kilogramm | AC12: =Migrationsartikel!S11 -> 1 | AD12: =Migrationsartikel!U11 -> (KGM) KG | AE12: =Migrationsartikel!Y11 -> 3 - Reduzierter Satz | AF12: =IF(Migrationsartikel!AA11="Kein Depotartikel","",Migrationsartikel!AA11) | AG12: =Migrationsartikel!Z11 -> Keine | AH12: =IF(Migrationsartikel!AB11="ja","true",FALSE) -> true | AI12: =IF(Migrationsartikel!AC11="ja","true",FALSE) -> true | AJ12: =IF(Migrationsartikel!AD11="ja","true",FALSE) -> true | AK12: =IF(Migrationsartikel!AE11="ja","true",FALSE) -> true | AL12: =IF(Migrationsartikel!AF11="ja","Denner Partner","") | AM12: =IF(Migrationsartikel!AG11="ja","true","false") -> false | AN12: =IF(AND(ISNUMBER(J12),J12>=100,J12<=999),"PLU",IF(AND(ISNUMBER(J12),J12>999),"GTIN","Kassentastenbelegung (ohne GTIN/PLU)")) -> Kassentastenbelegung (ohne GTIN/PLU) | AO12: true | AP12: Imp. Regio 3 - 3012 | AQ12: S4H | AR12: true
B13: exartikel | E13: 00 - Einzelartikel | F13: ="Warengruppe>>"&_xlfn.TEXTJOIN(">>",TRUE,Migrationsartikel!V12:X12) -> Warengruppe>>Früchte und Gemüse>>Früchte und Gemüse>>Früchte | H13: ZHAW - Handelsware ohne Charge | J13: =_xlfn.TEXTJOIN(" ",TRUE,Migrationsartikel!B12,Migrationsartikel!E12) -> 134 | L13: =_xlfn.TEXTJOIN(" ",TRUE,Migrationsartikel!F12:H12) -> IP-Suisse Äpfel Gala Kl. 1 | M13: =_xlfn.TEXTJOIN(" ",TRUE,Migrationsartikel!J12:L12) -> IP-Suisse Pommes Gala Cl. 1 | N13: =_xlfn.TEXTJOIN(" ",TRUE,Migrationsartikel!N12:P12) -> IP-Suisse Mele Gala Cl. 1 | O13: =Migrationsartikel!F12 -> IP-Suisse Äpfel Gala | P13: =Migrationsartikel!J12 -> IP-Suisse Pommes Gala | Q13: =Migrationsartikel!N12 -> IP-Suisse Mele Gala | R13: =_xlfn.TEXTJOIN(" ",TRUE,Migrationsartikel!G12) -> Kl. 1 | S13: =_xlfn.TEXTJOIN(" ",TRUE,Migrationsartikel!K12) -> Cl. 1 | T13: =_xlfn.TEXTJOIN(" ",TRUE,Migrationsartikel!O12) -> Cl. 1 | U13: =_xlfn.TEXTJOIN(" ",TRUE,Migrationsartikel!H12) | V13: =_xlfn.TEXTJOIN(" ",TRUE,Migrationsartikel!L12) | W13: =_xlfn.TEXTJOIN(" ",TRUE,Migrationsartikel!P12) | X13: =Migrationsartikel!I12 -> IP-Suisse Äpfel Gala Kl. 1 | Y13: =Migrationsartikel!M12 -> IP-Suisse Pommes Gala cl. 1 | Z13: =Migrationsartikel!Q12 -> IP-Suisse Mele Gala cl. 1 | AA13: =Migrationsartikel!R12 -> 1 | AB13: =Migrationsartikel!T12 -> Kilogramm | AC13: =Migrationsartikel!S12 -> 1 | AD13: =Migrationsartikel!U12 -> (KGM) KG | AE13: =Migrationsartikel!Y12 -> 3 - Reduzierter Satz | AF13: =IF(Migrationsartikel!AA12="Kein Depotartikel","",Migrationsartikel!AA12) | AG13: =Migrationsartikel!Z12 -> Keine | AH13: =IF(Migrationsartikel!AB12="ja","true",FALSE) -> true | AI13: =IF(Migrationsartikel!AC12="ja","true",FALSE) -> true | AJ13: =IF(Migrationsartikel!AD12="ja","true",FALSE) -> true | AK13: =IF(Migrationsartikel!AE12="ja","true",FALSE) -> true | AL13: =IF(Migrationsartikel!AF12="ja","Denner Partner","") | AM13: =IF(Migrationsartikel!AG12="ja","true","false") -> false | AN13: =IF(AND(ISNUMBER(J13),J13>=100,J13<=999),"PLU",IF(AND(ISNUMBER(J13),J13>999),"GTIN","Kassentastenbelegung (ohne GTIN/PLU)")) -> Kassentastenbelegung (ohne GTIN/PLU) | AO13: true | AP13: Imp. Regio 3 - 3013 | AQ13: S4H | AR13: true
B14: exartikel | E14: 00 - Einzelartikel | F14: ="Warengruppe>>"&_xlfn.TEXTJOIN(">>",TRUE,Migrationsartikel!V13:X13) -> Warengruppe>>Früchte und Gemüse>>Früchte und Gemüse>>Früchte | H14: ZHAW - Handelsware ohne Charge | J14: =_xlfn.TEXTJOIN(" ",TRUE,Migrationsartikel!B13,Migrationsartikel!E13) -> 112 | L14: =_xlfn.TEXTJOIN(" ",TRUE,Migrationsartikel!F13:H13) -> Äpfel Gala Offen Kl. 2 | M14: =_xlfn.TEXTJOIN(" ",TRUE,Migrationsartikel!J13:L13) -> Pommes Gala En vrac, cl. 2 | N14: =_xlfn.TEXTJOIN(" ",TRUE,Migrationsartikel!N13:P13) -> Mele Gala Cl. 2 vendita sfusa | O14: =Migrationsartikel!F13 -> Äpfel Gala | P14: =Migrationsartikel!J13 -> Pommes Gala | Q14: =Migrationsartikel!N13 -> Mele Gala | R14: =_xlfn.TEXTJOIN(" ",TRUE,Migrationsartikel!G13) -> Offen Kl. 2 | S14: =_xlfn.TEXTJOIN(" ",TRUE,Migrationsartikel!K13) -> En vrac, cl. 2 | T14: =_xlfn.TEXTJOIN(" ",TRUE,Migrationsartikel!O13) -> Cl. 2 vendita sfusa | U14: =_xlfn.TEXTJOIN(" ",TRUE,Migrationsartikel!H13) | V14: =_xlfn.TEXTJOIN(" ",TRUE,Migrationsartikel!L13) | W14: =_xlfn.TEXTJOIN(" ",TRUE,Migrationsartikel!P13) | X14: =Migrationsartikel!I13 -> Äpfel Gala Offen Kl. 2 | Y14: =Migrationsartikel!M13 -> Pommes Gala en vrac cl. 2 | Z14: =Migrationsartikel!Q13 -> Mele Gala cl. 2 vend. afusa | AA14: =Migrationsartikel!R13 -> 1 | AB14: =Migrationsartikel!T13 -> Kilogramm | AC14: =Migrationsartikel!S13 -> 1 | AD14: =Migrationsartikel!U13 -> (KGM) KG | AE14: =Migrationsartikel!Y13 -> 3 - Reduzierter Satz | AF14: =IF(Migrationsartikel!AA13="Kein Depotartikel","",Migrationsartikel!AA13) | AG14: =Migrationsartikel!Z13 -> Keine | AH14: =IF(Migrationsartikel!AB13="ja","true",FALSE) -> true | AI14: =IF(Migrationsartikel!AC13="ja","true",FALSE) -> true | AJ14: =IF(Migrationsartikel!AD13="ja","true",FALSE) -> true | AK14: =IF(Migrationsartikel!AE13="ja","true",FALSE) -> true | AL14: =IF(Migrationsartikel!AF13="ja","Denner Partner","") | AM14: =IF(Migrationsartikel!AG13="ja","true","false") -> false | AN14: =IF(AND(ISNUMBER(J14),J14>=100,J14<=999),"PLU",IF(AND(ISNUMBER(J14),J14>999),"GTIN","Kassentastenbelegung (ohne GTIN/PLU)")) -> Kassentastenbelegung (ohne GTIN/PLU) | AO14: true | AP14: Imp. Regio 3 - 3014 | AQ14: S4H | AR14: true
... B375: exartikel | E375: 00 - Einzelartikel | F375: ="Warengruppe>>"&_xlfn.TEXTJOIN(">>",TRUE,Migrationsartikel!V374:X374) -> Warengruppe>>Food>>Öl/Essig/Salatsaucen>>Öl/Essig/Salatsaucen | H375: ZHAW - Handelsware ohne Charge | J375: =_xlfn.TEXTJOIN(" ",TRUE,Migrationsartikel!B374,Migrationsartikel!E374) | L375: =_xlfn.TEXTJOIN(" ",TRUE,Migrationsartikel!F374:H374) -> Salatsauce Mama's 500ml | M375: =_xlfn.TEXTJOIN(" ",TRUE,Migrationsartikel!J374:L374) -> Sauce à salade Mama’s 500ml | N375: =_xlfn.TEXTJOIN(" ",TRUE,Migrationsartikel!N374:P374) -> Mama's Condimento insalata 500ml | O375: =Migrationsartikel!F374 -> Salatsauce Mama's | P375: =Migrationsartikel!J374 -> Sauce à salade Mama’s | Q375: =Migrationsartikel!N374 -> Mama's Condimento | R375: =_xlfn.TEXTJOIN(" ",TRUE,Migrationsartikel!G374) | S375: =_xlfn.TEXTJOIN(" ",TRUE,Migrationsartikel!K374) | T375: =_xlfn.TEXTJOIN(" ",TRUE,Migrationsartikel!O374) -> insalata | U375: =_xlfn.TEXTJOIN(" ",TRUE,Migrationsartikel!H374) -> 500ml | V375: =_xlfn.TEXTJOIN(" ",TRUE,Migrationsartikel!L374) -> 500ml | W375: =_xlfn.TEXTJOIN(" ",TRUE,Migrationsartikel!P374) -> 500ml | X375: =Migrationsartikel!I374 -> Salatsauce Mama's | Y375: =Migrationsartikel!M374 -> Sauce à salade Mama's 500ml | Z375: =Migrationsartikel!Q374 -> Mama's Cond. insal. 500ml | AA375: =Migrationsartikel!R374 -> 0.5 | AB375: =Migrationsartikel!T374 -> Liter | AC375: =Migrationsartikel!S374 -> 1 | AD375: =Migrationsartikel!U374 -> (LTR) Liter | AE375: =Migrationsartikel!Y374 -> 3 - Reduzierter Satz | AF375: =IF(Migrationsartikel!AA374="Kein Depotartikel","",Migrationsartikel!AA374) | AG375: =Migrationsartikel!Z374 -> Keine | AH375: =IF(Migrationsartikel!AB374="ja","true",FALSE) -> true | AI375: =IF(Migrationsartikel!AC374="ja","true",FALSE) -> true | AJ375: =IF(Migrationsartikel!AD374="ja","true",FALSE) -> true | AK375: =IF(Migrationsartikel!AE374="ja","true",FALSE) -> true | AL375: =IF(Migrationsartikel!AF374="ja","Denner Partner","") | AM375: =IF(Migrationsartikel!AG374="ja","true","false") -> false | AN375: =IF(AND(ISNUMBER(J375),J375>=100,J375<=999),"PLU",IF(AND(ISNUMBER(J375),J375>999),"GTIN","Kassentastenbelegung (ohne GTIN/PLU)")) -> Kassentastenbelegung (ohne GTIN/PLU) | AO375: true | AP375: Imp. Regio 3 - 3375 | AQ375: S4H | AR375: true

Sheet Migrationsartikel
A1: Lf Nr. | B1: PLU-Nr. neu | C1: Stk / kg | D1: PAZ | E1: EAN | F1: Gestellbeschriftung 1 Max. 22 Zeichen (d) | G1: Gestellbeschriftung 2 Max. 22 Zeichen (d) | H1: Gestellbeschriftung 3 Max. 4-8 Zeichen (d) | I1: Kassenbontext Max. 28 Zeichen (d) | J1: Gestellbeschriftung 1 Max. 22 Zeichen (f) | K1: Gestellbeschriftung 2 Max. 22 Zeichen (f) | L1: Gestellbeschriftung 3 Max. 4-8 Zeichen (f) | M1: Kassenbontext Max. 28 Zeichen (f) | N1: Gestellbeschriftung 1 Max. 22 Zeichen (i) | O1: Gestellbeschriftung 2 Max. 22 Zeichen (i) | P1: Gestellbeschriftung 3 Max. 4-8 Zeichen (i) | Q1: Kassenbontext Max. 28 Zeichen (i) | R1: Nettoinhalt | S1: Grundpreismenge Feld 1 | T1: Grundpreismenge Feld 2 | U1: Basismengeneinheit Waage = Kg Verkauf = Stk = Stk Relevant für Berechnungen im MDM/SAP | V1: Warengruppe 1. Feld | W1: Warengruppe 2. Feld | X1: Warengruppe 3. Feld | Y1: Steuerklassifikation | Z1: Altersbegrenzung | AA1: Depot | AB1: Rabatt zugelassen | AC1: Rückgabe zugelassen | AD1: Preisänderung zugelassen | AE1: Etiketten-druck | AF1: Shop-in-Shop | AG1: Fremdartikel | AH1: Qualitätsanforderung geprüft | AI1: Verkaufskonditionen | AJ1: Lieferant
A2: 162 | C2: Stk | D2: Nein | E2: 7610029177671 | F2: Marroni gekocht | H2: 400g | I2: Marroni gekocht | J2: Marrons cuits | L2: 400g | M2: Marrons cuits | N2: Castagne cotte | P2: 400g | Q2: Castagne cotte | R2: 1 | S2: 1 | T2: Kilogramm | U2: (PCE) Stück | V2: Früchte und Gemüse | W2: Früchte und Gemüse | X2: Früchte | Y2: 3 - Reduzierter Satz | Z2: Keine | AA2: Kein Depotartikel | AB2: ja | AC2: ja | AD2: ja | AE2: ja | AF2: - | AG2: - | AH2: ja | AI2: 0.05 | AJ2: -
A3: 163 | C3: Stk | F3: Aprikosen | H3: 1kg | I3: Aprikosen 1kg | J3: Abricots | L3: 1kg | M3: Abricots 1g | N3: Albicocche | P3: 1kg | Q3: Albicocche 1kg | R3: 1 | S3: 1 | T3: Kilogramm | U3: (PCE) Stück | V3: Früchte und Gemüse | W3: Früchte und Gemüse | X3: Früchte | Y3: 3 - Reduzierter Satz | Z3: Keine | AA3: Kein Depotartikel | AB3: ja | AC3: ja | AD3: ja | AE3: ja | AF3: - | AG3: - | AH3: ja | AI3: 0.05 | AJ3: -
A4: 169 | C4: Stk | D4: Nein | E4: 7613399055839 | F4: Bio Datteln Frisch | G4: Medjoul | H4: 200g | I4: Bio Datteln Medjoul 200g | J4: Bio Dattes fraîches | K4: Medjoul | L4: 200g | M4: Bio Dattes fr. Medjoul 200g | N4: Bio datteri freschi | O4: Medjoul | P4: 200g | Q4: Bio datteri fre Medjoul 200g | R4: 0.2 | S4: 100 | T4: Gramm | U4: (PCE) Stück | V4: Früchte und Gemüse | W4: Früchte und Gemüse | X4: Früchte | Y4: 3 - Reduzierter Satz | Z4: Keine | AA4: Kein Depotartikel | AB4: ja | AC4: ja | AD4: ja | AE4: ja | AF4: - | AG4: - | AH4: ja | AI4: 0.05 | AJ4: -
A5: 170 | C5: Stk | F5: Feigen Pulled | H5: 400g | I5: Feigen Pulled 400g | J5: Figues Pulled | L5: 400g | M5: Figues Pulled 400g | N5: Fichi Pulled | P5: 400g | Q5: Fichi Pulled 40g | R5: 0.4 | S5: 1 | T5: Kilogramm | U5: (PCE) Stück | V5: Früchte und Gemüse | W5: Früchte und Gemüse | X5: Früchte | Y5: 3 - Reduzierter Satz | Z5: Keine | AA5: Kein Depotartikel | AB5: ja | AC5: ja | AD5: ja | AE5: ja | AF5: - | AG5: - | AH5: ja | AI5: 0.05 | AJ5: -
A6: 195 | C6: Stk | D6: Nein | E6: 7613399055365 | F6: Haselnüsse | H6: 500g | I6: Haselnüsse 500g | J6: Noisettes | L6: 500g | M6: Noisettes 500g | N6: Nocciole | P6: 500g | Q6: Nocciole 500g | R6: 0.5 | S6: 1 | T6: Kilogramm | U6: (PCE) Stück | V6: Früchte und Gemüse | W6: Früchte und Gemüse | X6: Früchte | Y6: 3 - Reduzierter Satz | Z6: Keine | AA6: Kein Depotartikel | AB6: ja | AC6: ja | AD6: ja | AE6: ja | AF6: - | AG6: - | AH6: ja | AI6: 0.05 | AJ6: -
A7: 200 | B7: 143 | C7: kg | D7: Nein | F7: Birnen Büscheli | G7: Offen Kl. 1 | I7: Birnen Büscheli Offen Kl. 1 | J7: Poires Büscheli | K7: En vrac, cl. 1 | M7: Poires Büscheli | N7: Pere Büscheli | O7: Cl. 1 vendita sfusa | Q7: Pere Büscheli Cl. 1 v.s. | R7: 1 | S7: 1 | T7: Kilogramm | U7: (KGM) KG | V7: Früchte und Gemüse | W7: Früchte und Gemüse | X7: Früchte | Y7: 3 - Reduzierter Satz | Z7: Keine | AA7: Kein Depotartikel | AB7: ja | AC7: ja | AD7: ja | AE7: ja | AF7: - | AG7: - | AH7: ja | AI7: 0.05 | AJ7: -
A8: 204 | C8: Stk | D8: Nein | E8: 7613399039945 | F8: Granatapfelkerne | G8: Becher | H8: 125g | I8: Granatapfelkerne Becher | J8: Graines de grenade | K8: Gobelet | L8: 125g | M8: Graines de grenade 125g | N8: Melagrana chicchi | O8: bicchiere | P8: 125g | Q8: Melagrana chicchi 125g | R8: 0.125 | S8: 100 | T8: Gramm | U8: (PCE) Stück | V8: Früchte und Gemüse | W8: Früchte und Gemüse | X8: Früchte | Y8: 3 - Reduzierter Satz | Z8: Keine | AA8: Kein Depotartikel | AB8: ja | AC8: ja | AD8: ja | AE8: ja | AF8: - | AG8: - | AH8: ja | AI8: 0.05 | AJ8: -
A9: 214 | C9: Stk | D9: Nein | F9: Ananas | G9: Baby | H9: 1Stk | I9: Ananas Baby Stk | J9: Ananas | K9: Baby | L9: 1pce | M9: Ananas Baby | N9: Ananas | O9: Baby | P9: 1pz | Q9: Ananas Baby 1 pz | R9: 1 | S9: 1 | T9: Stück | U9: (PCE) Stück | V9: Früchte und Gemüse | W9: Früchte und Gemüse | X9: Früchte | Y9: 3 - Reduzierter Satz | Z9: Keine | AA9: Kein Depotartikel | AB9: ja | AC9: ja | AD9: ja | AE9: ja | AF9: - | AG9: - | AH9: ja | AI9: 0.05 | AJ9: -
A10: 215 | C10: Stk | D10: Nein | E10: 7613399001270 | F10: Ananas | G10: Becher | H10: 200g | I10: Ananas Becher 200g | J10: Ananas | K10: Gobelet | L10: 200g | M10: Ananas gobelet 200g | N10: Ananas | O10: bicchiere | P10: 200g | Q10: Ananas bicchiere 200g | R10: 0.2 | S10: 100 | T10: Gramm | U10: (PCE) Stück | V10: Früchte und Gemüse | W10: Früchte und Gemüse | X10: Früchte | Y10: 3 - Reduzierter Satz | Z10: Keine | AA10: Kein Depotartikel | AB10: ja | AC10: ja | AD10: ja | AE10: ja | AF10: - | AG10: - | AH10: ja | AI10: 0.05 | AJ10: -
A11: 230 | B11: 104 | C11: kg | F11: Äpfel Diwa | G11: Offen Kl. 1 | I11: Äpfel Diwa Offen Kl. 1 | J11: Pommes Diwa | K11: En vrac, cl. 1 | M11: Pommes Diwa en vrac cl. 1 | N11: Mele Diwa | O11: Cl. 1 vendita sfusa | Q11: Mele Diwa cl. 1 vend. sfusa | R11: 1 | S11: 1 | T11: Kilogramm | U11: (KGM) KG | V11: Früchte und Gemüse | W11: Früchte und Gemüse | X11: Früchte | Y11: 3 - Reduzierter Satz | Z11: Keine | AA11: Kein Depotartikel | AB11: ja | AC11: ja | AD11: ja | AE11: ja | AF11: - | AG11: - | AH11: ja | AI11: 0.05 | AJ11: -
A12: 243 | B12: 134 | C12: kg | F12: IP-Suisse Äpfel Gala | G12: Kl. 1 | I12: IP-Suisse Äpfel Gala Kl. 1 | J12: IP-Suisse Pommes Gala | K12: Cl. 1 | M12: IP-Suisse Pommes Gala cl. 1 | N12: IP-Suisse Mele Gala | O12: Cl. 1 | Q12: IP-Suisse Mele Gala cl. 1 | R12: 1 | S12: 1 | T12: Kilogramm | U12: (KGM) KG | V12: Früchte und Gemüse | W12: Früchte und Gemüse | X12: Früchte | Y12: 3 - Reduzierter Satz | Z12: Keine | AA12: Kein Depotartikel | AB12: ja | AC12: ja | AD12: ja | AE12: ja | AF12: - | AG12: - | AH12: ja | AI12: 0.05 | AJ12: -
A13: 245 | B13: 112 | C13: kg | F13: Äpfel Gala | G13: Offen Kl. 2 | I13: Äpfel Gala Offen Kl. 2 | J13: Pommes Gala | K13: En vrac, cl. 2 | M13: Pommes Gala en vrac cl. 2 | N13: Mele Gala | O13: Cl. 2 vendita sfusa | Q13: Mele Gala cl. 2 vend. afusa | R13: 1 | S13: 1 | T13: Kilogramm | U13: (KGM) KG | V13: Früchte und Gemüse | W13: Früchte und Gemüse | X13: Früchte | Y13: 3 - Reduzierter Satz | Z13: Keine | AA13: Kein Depotartikel | AB13: ja | AC13: ja | AD13: ja | AE13: ja | AF13: - | AG13: - | AH13: ja | AI13: 0.05 | AJ13: -
A14: 254 | B14: 125 | C14: kg | F14: Äpfel Pink Lady | G14: Offen Kl. 1 | I14: Äpfel Pink Lady Offen Kl. 1 | J14: Pommes Pink Lady | K14: En vrac, cl. 1 | M14: Pomm Pink Lady en vrac cl.1 | N14: Mele Pink Lady | O14: Cl. 1 vendita sfusa | Q14: Mele Pink Lady cl. 1 vend. s | R14: 1 | S14: 1 | T14: Kilogramm | U14: (KGM) KG | V14: Früchte und Gemüse | W14: Früchte und Gemüse | X14: Früchte | Y14: 3 - Reduzierter Satz | Z14: Keine | AA14: Kein Depotartikel | AB14: ja | AC14: ja | AD14: ja | AE14: ja | AF14: - | AG14: - | AH14: ja | AI14: 0.05 | AJ14: -
A15: 265 | C15: Stk | F15: Aprikosen | H15: 500g | I15: Aprikosen 500g | J15: Abricots | L15: 500g | M15: Abricos 500g | N15: Albicocche | P15: 500g | Q15: Albicocche 500g | R15: 0.5 | S15: 1 | T15: Kilogramm | U15: (PCE) Stück | V15: Früchte und Gemüse | W15: Früchte und Gemüse | X15: Früchte | Y15: 3 - Reduzierter Satz | Z15: Keine | AA15: Kein Depotartikel | AB15: ja | AC15: ja | AD15: ja | AE15: ja | AF15: - | AG15: - | AH15: ja | AI15: 0.05 | AJ15: -
A16: 269 | C16: Stk | D16: Nein | E16: 7613399021476 | F16: Aprikosen | H16: 2kg | I16: Aprikosen 2kg | J16: Abricots | L16: 2kg | M16: Abricots 2kg | N16: Albicocche | P16: 2kg | Q16: Albicocche 2kg | R16: 2 | S16: 1 | T16: Kilogramm | U16: (PCE) Stück | V16: Früchte und Gemüse | W16: Früchte und Gemüse | X16: Früchte | Y16: 3 - Reduzierter Satz | Z16: Keine | AA16: Kein Depotartikel | AB16: ja | AC16: ja | AD16: ja | AE16: ja | AF16: - | AG16: - | AH16: ja | AI16: 0.05 | AJ16: -
A17: 276 | B17: 135 | C17: kg | D17: Nein | F17: Aprikosen | G17: Offen AAA | I17: Aprikosen Offen AAA | J17: Abricots | K17: En vrac AAA | M17: Abricosts en vrac AAA | N17: Albicocche | O17: vendita sfusa AAA | Q17: Albicocche vend. sfus. AAA | R17: 1 | S17: 1 | T17: Kilogramm | U17: (KGM) KG | V17: Früchte und Gemüse | W17: Früchte und Gemüse | X17: Früchte | Y17: 3 - Reduzierter Satz | Z17: Keine | AA17: Kein Depotartikel | AB17: ja | AC17: ja | AD17: ja | AE17: ja | AF17: - | AG17: - | AH17: ja | AI17: 0.05 | AJ17: -
A18: 298 | C18: Stk | D18: Ja | E18: 2202158000000 | F18: Aprikosen | H18: ca. 800g | I18: Aprikosen ca. 800g | J18: Abricots | L18: env. 800g | M18: Abricots env. 800g | N18: Albicocche | P18: ca. 800g | Q18: Albicocche ca. 800g | R18: 0.8 | S18: 1 | T18: Kilogramm | U18: (PCE) Stück | V18: Früchte und Gemüse | W18: Früchte und Gemüse | X18: Früchte | Y18: 3 - Reduzierter Satz | Z18: Keine | AA18: Kein Depotartikel | AB18: ja | AC18: ja | AD18: ja | AE18: ja | AF18: - | AG18: - | AH18: ja | AI18: 0.05 | AJ18: -
A19: 317 | C19: Stk | D19: Ja | E19: 2205672000000 | F19: Aprikosen | G19: Schale | H19: 650g | I19: Aprikosen Schale 650g | J19: Abricots | K19: Barquette | L19: 650g | M19: Abricots barquette 650g | N19: Albicocche | O19: vaschetta | P19: 650g | Q19: Albicocche vasch. 650g | R19: 0.65 | S19: 1 | T19: Kilogramm | U19: (PCE) Stück | V19: Früchte und Gemüse | W19: Früchte und Gemüse | X19: Früchte | Y19: 3 - Reduzierter Satz | Z19: Keine | AA19: Kein Depotartikel | AB19: ja | AC19: ja | AD19: ja | AE19: ja | AF19: - | AG19: - | AH19: ja | AI19: 0.05 | AJ19: -
A20: 318 | C20: Stk | D20: Nein | E20: 7613399047834 | F20: Aprikosen getrocknet | H20: 200g | I20: Aprikosen getrocknet 200g | J20: Abricots secs | L20: 200g | M20: Abricots secs 200g | N20: Albicocche secche | P20: 200g | Q20: Albicocche secche 200g | R20: 0.2 | S20: 100 | T20: Gramm | U20: (PCE) Stück | V20: Früchte und Gemüse | W20: Früchte und Gemüse | X20: Früchte | Y20: 3 - Reduzierter Satz | Z20: Keine | AA20: Kein Depotartikel | AB20: ja | AC20: ja | AD20: ja | AE20: ja | AF20: - | AG20: - | AH20: ja | AI20: 0.05 | AJ20: -
A21: 327 | B21: 138 | C21: kg | D21: Nein | F21: Bananen Fyffes | G21: Offen | I21: Bananen Fyffes Offen | J21: Bananes Fyffes | K21: En vrac | M21: Bananes Fyffes en vrac | N21: Banane Fyffes | O21: vendita sfusa | Q21: Banane Fyffes vend. sfusa | R21: 1 | S21: 1 | T21: Kilogramm | U21: (KGM) KG | V21: Früchte und Gemüse | W21: Früchte und Gemüse | X21: Früchte | Y21: 3 - Reduzierter Satz | Z21: Keine | AA21: Kein Depotartikel | AB21: ja | AC21: ja | AD21: ja | AE21: ja | AF21: - | AG21: - | AH21: ja | AI21: 0.05 | AJ21: -
A22: 328 | C22: Stk | D22: Ja | E22: 2201581000000 | F22: Bananen | G22: gepackt | I22: Bananen gepackt | J22: Bananes | K22: Emballé | M22: Bananes emballé | N22: Banane | O22: confezionato | Q22: Banane confezionato | R22: 1 | S22: 1 | T22: Kilogramm | U22: (PCE) Stück | V22: Früchte und Gemüse | W22: Früchte und Gemüse | X22: Früchte | Y22: 3 - Reduzierter Satz | Z22: Keine | AA22: Kein Depotartikel | AB22: ja | AC22: ja | AD22: ja | AE22: ja | AF22: - | AG22: - | AH22: ja | AI22: 0.05 | AJ22: -
A23: 346 | C23: Stk | D23: Nein | E23: 7610632050514 | F23: Beerenmischung | G23: Schale | H23: 250g | I23: Beerenmischung Schale 250g | J23: Mélange de baies | K23: Barquette | L23: 250g | M23: Melange de baies 250g | N23: Bacche miste | O23: vaschetta | P23: 250g | Q23: Bacche miste 250g | R23: 0.25 | S23: 100 | T23: Gramm | U23: (PCE) Stück | V23: Früchte und Gemüse | W23: Früchte und Gemüse | X23: Früchte | Y23: 3 - Reduzierter Satz | Z23: Keine | AA23: Kein Depotartikel | AB23: ja | AC23: ja | AD23: ja | AE23: ja | AF23: - | AG23: - | AH23: ja | AI23: 0.05 | AJ23: -
A24: 369 | B24: 145 | C24: kg | F24: Birnen Ercolini | G24: Offen Kl. 1 | I24: Birnen Ercolini Offen Kl. 1 | J24: Poires Ercolini | K24: En vrac, cl. 1 | M24: Poire Ercolini en vrac cl. 1 | N24: Pere Ercolini | O24: Cl. 1 vendita sfusa | Q24: Pere Ercolini cl.1 vend. Sf. | R24: 1 | S24: 1 | T24: Kilogramm | U24: (KGM) KG | V24: Früchte und Gemüse | W24: Früchte und Gemüse | X24: Früchte | Y24: 3 - Reduzierter Satz | Z24: Keine | AA24: Kein Depotartikel | AB24: ja | AC24: ja | AD24: ja | AE24: ja | AF24: - | AG24: - | AH24: ja | AI24: 0.05 | AJ24: -
A25: 371 | B25: 151 | C25: kg | F25: Birnen Kaiser | G25: Offen Kl. 1 | I25: Birnen Kaiser Offen Kl.1 | J25: Poires Beurré Bosc | K25: En vrac, cl. 1 | M25: Poire Beurré Bosc en v. cl1 | N25: Pere Kaiser | O25: Cl. 1 vendita sfusa | Q25: Pere Kaiser cl. 1 vendta sf. | R25: 1 | S25: 1 | T25: Kilogramm | U25: (KGM) KG | V25: Früchte und Gemüse | W25: Früchte und Gemüse | X25: Früchte | Y25: 3 - Reduzierter Satz | Z25: Keine | AA25: Kein Depotartikel | AB25: ja | AC25: ja | AD25: ja | AE25: ja | AF25: - | AG25: - | AH25: ja | AI25: 0.05 | AJ25: -
A26: 375 | C26: Stk | D26: Ja | E26: 2203071000000 | F26: Birnen Abate | G26: Kl. 1 gepackt | I26: Birnen Abate Kl. 1 gepackt | J26: Poires Abate | K26: Cl. 1 emballé | M26: Poires Abate cl. 1 emballé | N26: Pere Abate | O26: Cl. 1 confezionato | Q26: Pere Abate cl.1 confezionato | R26: 1 | S26: 1 | T26: Kilogramm | U26: (PCE) Stück | V26: Früchte und Gemüse | W26: Früchte und Gemüse | X26: Früchte | Y26: 3 - Reduzierter Satz | Z26: Keine | AA26: Kein Depotartikel | AB26: ja | AC26: ja | AD26: ja | AE26: ja | AF26: - | AG26: - | AH26: ja | AI26: 0.05 | AJ26: -
A27: 376 | C27: Stk | D27: Ja | E27: 2205627000000 | F27: Bio Birnen Abate | G27: Kl. 1 gepackt | I27: Bio Birnen Abate Kl. 1 gep. | J27: Bio Poires Abate | K27: Cl. 1 emballé | M27: Bio Poires Abate cl1 emballé | N27: Bio Pere Abate | O27: Cl. 1 confezionato | Q27: Bio Pere Abate cl. 1 confez. | R27: 1 | S27: 1 | T27: Kilogramm | U27: (PCE) Stück | V27: Früchte und Gemüse | W27: Früchte und Gemüse | X27: Früchte | Y27: 3 - Reduzierter Satz | Z27: Keine | AA27: Kein Depotartikel | AB27: ja | AC27: ja | AD27: ja | AE27: ja | AF27: - | AG27: - | AH27: ja | AI27: 0.05 | AJ27: -
A28: 378 | B28: 142 | C28: kg | D28: Nein | F28: Birnen Boscop | G28: Offen Kl. 1 | I28: Birnen Boscop Offen Kl. 1 | J28: Poires Boscop | K28: En vrac, cl. 1 | M28: Poires Boscop en vrac cl. 1 | N28: Pere Boscop | O28: Cl. 1 vendita sfusa | Q28: Pere Boscop cl.1 vend. sfusa | R28: 1 | S28: 1 | T28: Kilogramm | U28: (KGM) KG | V28: Früchte und Gemüse | W28: Früchte und Gemüse | X28: Früchte | Y28: 3 - Reduzierter Satz | Z28: Keine | AA28: Kein Depotartikel | AB28: ja | AC28: ja | AD28: ja | AE28: ja | AF28: - | AG28: - | AH28: ja | AI28: 0.05 | AJ28: -
A29: 381 | C29: Stk | D29: Ja | E29: 2260561000002 | F29: Birnen Boscop | G29: Kl. 1 gepackt | I29: Birnen Boscop Kl. 1 gepackt | J29: Poires Boscop | K29: Cl. 1 emballé | M29: Poires Boscop cl. 1 emballé | N29: Pere Boscop | O29: Cl. 1 confezionato | Q29: Pere Boscop cl. 1 confez. | R29: 1 | S29: 1 | T29: Kilogramm | U29: (PCE) Stück | V29: Früchte und Gemüse | W29: Früchte und Gemüse | X29: Früchte | Y29: 3 - Reduzierter Satz | Z29: Keine | AA29: Kein Depotartikel | AB29: ja | AC29: ja | AD29: ja | AE29: ja | AF29: - | AG29: - | AH29: ja | AI29: 0.05 | AJ29: -
A30: 383 | C30: Stk | D30: Ja | E30: 2287572000000 | F30: Birnen Carmen | G30: Kl. 1 gepackt | I30: Birnen Carmen Kl. 1 gepackt | J30: Poires Carmen | K30: Cl. 1 emballé | M30: Poires Carmen cl. 1 emballé | N30: Pere Carmen | O30: Cl. 1 confezionato | Q30: Pere Carmen cl. 1 confez. | R30: 1 | S30: 1 | T30: Kilogramm | U30: (PCE) Stück | V30: Früchte und Gemüse | W30: Früchte und Gemüse | X30: Früchte | Y30: 3 - Reduzierter Satz | Z30: Keine | AA30: Kein Depotartikel | AB30: ja | AC30: ja | AD30: ja | AE30: ja | AF30: - | AG30: - | AH30: ja | AI30: 0.05 | AJ30: -
A31: 386 | B31: 144 | C31: kg | D31: Nein | F31: Birnen Conférence | G31: Offen Kl. 1 | I31: Birnen Conférence Offen Kl.1 | J31: Poires Conférence | K31: En vrac, cl. 1 | M31: Poires Conférence cl.1 en vr | N31: Pere Conférence | O31: Cl. 1 vendita sfusa | Q31: Pere Conférence cl. 1 ve. Sf | R31: 1 | S31: 1 | T31: Kilogramm | U31: (KGM) KG | V31: Früchte und Gemüse | W31: Früchte und Gemüse | X31: Früchte | Y31: 3 - Reduzierter Satz | Z31: Keine | AA31: Kein Depotartikel | AB31: ja | AC31: ja | AD31: ja | AE31: ja | AF31: - | AG31: - | AH31: ja | AI31: 0.05 | AJ31: -
A32: 387 | C32: Stk | D32: Ja | E32: 2216831000005 | F32: Birnen Conférence | G32: Kl. 1 gepackt | I32: Birnen Conférence Kl. 1 gep. | J32: Poires Conférence | K32: Cl. 1 emballé | M32: Poires Conférence cl. 1 emb. | N32: Pere Conférence | O32: Cl. 1 confezionato | Q32: Pere Conférence cl. 1 conf | R32: 1 | S32: 1 | T32: Kilogramm | U32: (PCE) Stück | V32: Früchte und Gemüse | W32: Früchte und Gemüse | X32: Früchte | Y32: 3 - Reduzierter Satz | Z32: Keine | AA32: Kein Depotartikel | AB32: ja | AC32: ja | AD32: ja | AE32: ja | AF32: - | AG32: - | AH32: ja | AI32: 0.05 | AJ32: -
A33: 388 | C33: Stk | D33: Ja | E33: 2216799000000 | F33: Bio Birnen Conférence | G33: Kl. 1 gepackt | I33: Bio Birnen Conf. Kl.1 gep. | J33: Bio Poires Conférence | K33: Cl. 1 emballé | M33: Bio Poires Confér. cl.1 emb. | N33: Bio Pere Conférence | O33: Cl. 1 confezionato | Q33: Bio Pere Conf. cl. 1 conf. | R33: 1 | S33: 1 | T33: Kilogramm | U33: (PCE) Stück | V33: Früchte und Gemüse | W33: Früchte und Gemüse | X33: Früchte | Y33: 3 - Reduzierter Satz | Z33: Keine | AA33: Kein Depotartikel | AB33: ja | AC33: ja | AD33: ja | AE33: ja | AF33: - | AG33: - | AH33: ja | AI33: 0.05 | AJ33: -
A34: 389 | B34: 146 | C34: kg | D34: Nein | F34: Birnen Forellen | G34: Offen Kl. 1 | I34: Birnen Forellen Offen Kl. 1 | J34: Poires Forelle | K34: En vrac, cl. 1 | M34: Poires Forelle cl. 1 en vrac | N34: Pere Forelle | O34: Cl. 1 vendita sfusa | Q34: Pere Forelle cl. 1 vend. Sf. | R34: 1 | S34: 1 | T34: Kilogramm | U34: (KGM) KG | V34: Früchte und Gemüse | W34: Früchte und Gemüse | X34: Früchte | Y34: 3 - Reduzierter Satz | Z34: Keine | AA34: Kein Depotartikel | AB34: ja | AC34: ja | AD34: ja | AE34: ja | AF34: - | AG34: - | AH34: ja | AI34: 0.05 | AJ34: -
A35: 391 | C35: Stk | D35: Ja | E35: 2201108000000 | F35: Birnen Forellen | G35: Kl. 1 gepackt | I35: Birnen Forellen Kl.1 gepackt | J35: Poires Forelle | K35: Cl. 1 emballé | M35: Poires Forelle cl. 1 emballé | N35: Pere Forelle | O35: Cl. 1 confezionato | Q35: Pere Forelle cl. 1 confez. | R35: 1 | S35: 1 | T35: Kilogramm | U35: (PCE) Stück | V35: Früchte und Gemüse | W35: Früchte und Gemüse | X35: Früchte | Y35: 3 - Reduzierter Satz | Z35: Keine | AA35: Kein Depotartikel | AB35: ja | AC35: ja | AD35: ja | AE35: ja | AF35: - | AG35: - | AH35: ja | AI35: 0.05 | AJ35: -
A36: 394 | B36: 147 | C36: kg | D36: Nein | F36: Birnen Fred | G36: Offen Kl. 1 | I36: Birnen Fred Offen Kl. 1 | J36: Poires Fred | K36: En vrac, cl. 1 | M36: Poires Fred cl. 1 en vrac | N36: Pere Fred | O36: Cl. 1 vendita sfusa | Q36: Pere Fred cl. 1 vend sfusa | R36: 1 | S36: 1 | T36: Kilogramm | U36: (KGM) KG | V36: Früchte und Gemüse | W36: Früchte und Gemüse | X36: Früchte | Y36: 3 - Reduzierter Satz | Z36: Keine | AA36: Kein Depotartikel | AB36: ja | AC36: ja | AD36: ja | AE36: ja | AF36: - | AG36: - | AH36: ja | AI36: 0.05 | AJ36: -
A37: 395 | C37: Stk | D37: Ja | E37: 2205556000000 | F37: Birnen Fred | G37: Kl. 1 gepackt | I37: Birnen Fred Kl. 1 gepackt | J37: Poires Fred | K37: Cl. 1 emballé | M37: Poires Fred cl. 1 emballé | N37: Pere Fred | O37: Cl. 1 confezionato | Q37: Pere Fred cl. 1 confez. | R37: 1 | S37: 1 | T37: Kilogramm | U37: (PCE) Stück | V37: Früchte und Gemüse | W37: Früchte und Gemüse | X37: Früchte | Y37: 3 - Reduzierter Satz | Z37: Keine | AA37: Kein Depotartikel | AB37: ja | AC37: ja | AD37: ja | AE37: ja | AF37: - | AG37: - | AH37: ja | AI37: 0.05 | AJ37: -
A38: 398 | B38: 148 | C38: kg | D38: Nein | F38: Birnen Gute Louise | G38: Offen Kl. 1 | I38: Birnen Gute Louise Off. Kl.1 | J38: Poires Bonne Louise | K38: En vrac, cl. 1 | M38: Poires Bonn. Lou. cl.1 en v. | N38: Pere Gute Luise | O38: Cl. 1 vendita sfusa | Q38: Pere Gute Luise cl. 1 v. sf. | R38: 1 | S38: 1 | T38: Kilogramm | U38: (KGM) KG | V38: Früchte und Gemüse | W38: Früchte und Gemüse | X38: Früchte | Y38: 3 - Reduzierter Satz | Z38: Keine | AA38: Kein Depotartikel | AB38: ja | AC38: ja | AD38: ja | AE38: ja | AF38: - | AG38: - | AH38: ja | AI38: 0.05 | AJ38: -
A39: 400 | C39: Stk | D39: Ja | E39: 2216791000008 | F39: Birnen Gute Louise | G39: Kl. 1 gepackt | I39: Birnen Gute Louise Kl.1 gep. | J39: Poires Bonne Louise | K39: Cl. 1 emballé | M39: Poires Bonn. Lou. cl.1 emb. | N39: Pere Gute Luise | O39: Cl. 1 confezionato | Q39: Pere Gute Luise cl. 1 confez | R39: 1 | S39: 1 | T39: Kilogramm | U39: (PCE) Stück | V39: Früchte und Gemüse | W39: Früchte und Gemüse | X39: Früchte | Y39: 3 - Reduzierter Satz | Z39: Keine | AA39: Kein Depotartikel | AB39: ja | AC39: ja | AD39: ja | AE39: ja | AF39: - | AG39: - | AH39: ja | AI39: 0.05 | AJ39: -
A40: 403 | B40: 150 | C40: kg | D40: Nein | F40: Birnen Guyot | G40: Offen Kl. 1 | I40: Birnen Guyot Offen Kl. 1 | J40: Poires Guyot | K40: En vrac, cl. 1 | M40: Poires Guyot cl. 1 en vrac | N40: Pere Guyot | O40: Cl. 1 vendita sfusa | Q40: Pere Guyot cl. 1 vend. sfusa | R40: 1 | S40: 1 | T40: Kilogramm | U40: (KGM) KG | V40: Früchte und Gemüse | W40: Früchte und Gemüse | X40: Früchte | Y40: 3 - Reduzierter Satz | Z40: Keine | AA40: Kein Depotartikel | AB40: ja | AC40: ja | AD40: ja | AE40: ja | AF40: - | AG40: - | AH40: ja | AI40: 0.05 | AJ40: -
A41: 404 | C41: Stk | D41: Ja | E41: 2213811000000 | F41: Birnen Guyot | G41: Kl. 1 gepackt | I41: Birnen Guyot Kl. 1 gepackt | J41: Poires Guyot | K41: Cl. 1 emballé | M41: Poires Guyot cl. 1 emballé | N41: Pere Guyot | O41: Cl. 1 confezionato | Q41: Pere Guyot cl. 1 confez. | R41: 1 | S41: 1 | T41: Kilogramm | U41: (PCE) Stück | V41: Früchte und Gemüse | W41: Früchte und Gemüse | X41: Früchte | Y41: 3 - Reduzierter Satz | Z41: Keine | AA41: Kein Depotartikel | AB41: ja | AC41: ja | AD41: ja | AE41: ja | AF41: - | AG41: - | AH41: ja | AI41: 0.05 | AJ41: -
A42: 409 | B42: 160 | C42: kg | D42: Nein | F42: Birnen Packhams | G42: Offen Kl. 1 | I42: Birnen Packhams Offen Kl. 1 | J42: Poires Packhams | K42: En vrac, cl. 1 | M42: Poires Packhams cl.1 en vrac | N42: Pere Packhams | O42: Cl. 1 vendita sfusa | Q42: Pere Packhams cl. 1 v.sfusa | R42: 1 | S42: 1 | T42: Kilogramm | U42: (KGM) KG | V42: Früchte und Gemüse | W42: Früchte und Gemüse | X42: Früchte | Y42: 3 - Reduzierter Satz | Z42: Keine | AA42: Kein Depotartikel | AB42: ja | AC42: ja | AD42: ja | AE42: ja | AF42: - | AG42: - | AH42: ja | AI42: 0.05 | AJ42: -
A43: 411 | C43: Stk | D43: Ja | E43: 2216921000007 | F43: Birnen Packhams | G43: Kl. 1 gepackt | I43: Birnen Packhams Kl.1 gepackt | J43: Poires Packhams | K43: Cl. 1 emballé | M43: Poires Packhams cl. 1 emb. | N43: Pere Packhams | O43: Cl. 1 confezionato | Q43: Pere Packhams cl. 1 convez. | R43: 1 | S43: 1 | T43: Kilogramm | U43: (PCE) Stück | V43: Früchte und Gemüse | W43: Früchte und Gemüse | X43: Früchte | Y43: 3 - Reduzierter Satz | Z43: Keine | AA43: Kein Depotartikel | AB43: ja | AC43: ja | AD43: ja | AE43: ja | AF43: - | AG43: - | AH43: ja | AI43: 0.05 | AJ43: -
A44: 413 | B44: 161 | C44: kg | D44: Nein | F44: Birnen Rocha | G44: Offen Kl. 1 | I44: Birnen Rocha Offen Kl. 1 | J44: Poires Rocha | K44: En vrac, cl. 1 | M44: Poires Rocha cl.1 en vrac | N44: Pere Rocha | O44: Cl. 1 vendita sfusa | Q44: Pere Rocha cl. 1 v. sfusa | R44: 1 | S44: 1 | T44: Kilogramm | U44: (KGM) KG | V44: Früchte und Gemüse | W44: Früchte und Gemüse | X44: Früchte | Y44: 3 - Reduzierter Satz | Z44: Keine | AA44: Kein Depotartikel | AB44: ja | AC44: ja | AD44: ja | AE44: ja | AF44: - | AG44: - | AH44: ja | AI44: 0.05 | AJ44: -
A45: 414 | C45: Stk | D45: Ja | E45: 2205363000000 | F45: Birnen Rosmarie | G45: Kl. 1 gepackt | I45: Birnen Rosmarei Kl.1 gepackt | J45: Poires Rosemarie | K45: Cl. 1 emballé | M45: Poires Rosemarie cl. 1 emb. | N45: Pere Rosmarie | O45: Cl. 1 confezionato | Q45: Pere Rosmarie cl. 1 confez. | R45: 1 | S45: 1 | T45: Kilogramm | U45: (PCE) Stück | V45: Früchte und Gemüse | W45: Früchte und Gemüse | X45: Früchte | Y45: 3 - Reduzierter Satz | Z45: Keine | AA45: Kein Depotartikel | AB45: ja | AC45: ja | AD45: ja | AE45: ja | AF45: - | AG45: - | AH45: ja | AI45: 0.05 | AJ45: -
A46: 434 | C46: Stk | D46: Ja | E46: 2215881000000 | F46: Birnen Trévoux | G46: Kl. 1 gepackt | I46: Birnen Trévoux Kl. 1 gepackt | J46: Poires Trévoux | K46: Cl. 1 emballé | M46: Poires Trévoux cl. 1 emballé | N46: Pere Trévoux | O46: Cl. 1 confezionato | Q46: Pere Trévoux cl. 1 confez. | R46: 1 | S46: 1 | T46: Kilogramm | U46: (PCE) Stück | V46: Früchte und Gemüse | W46: Früchte und Gemüse | X46: Früchte | Y46: 3 - Reduzierter Satz | Z46: Keine | AA46: Kein Depotartikel | AB46: ja | AC46: ja | AD46: ja | AE46: ja | AF46: - | AG46: - | AH46: ja | AI46: 0.05 | AJ46: -
A47: 435 | B47: 162 | C47: kg | D47: Nein | F47: Birnen Williams | G47: Offen Kl. 1 | I47: Birnen Williams Offen Kl. 1 | J47: Poires Williams | K47: En vrac, cl. 1 | M47: Poires Williams cl.1 en vrac | N47: Pere Williams | O47: Cl. 1 vendita sfusa | Q47: Pere Williams cl. 1 v. sfusa | R47: 1 | S47: 1 | T47: Kilogramm | U47: (KGM) KG | V47: Früchte und Gemüse | W47: Früchte und Gemüse | X47: Früchte | Y47: 3 - Reduzierter Satz | Z47: Keine | AA47: Kein Depotartikel | AB47: ja | AC47: ja | AD47: ja | AE47: ja | AF47: - | AG47: - | AH47: ja | AI47: 0.05 | AJ47: -
A48: 437 | C48: Stk | D48: Ja | E48: 2201661000000 | F48: Birnen Williams | G48: Kl. 1 gepackt | I48: Birnen Williams Kl.1 gepackt | J48: Poires Williams | K48: Cl. 1 emballé | M48: Poires Williams cl.1 emballé | N48: Pere Williams | O48: Cl. 1 confezionato | Q48: Pere Williams cl. 1 confez. | R48: 1 | S48: 1 | T48: Kilogramm | U48: (PCE) Stück | V48: Früchte und Gemüse | W48: Früchte und Gemüse | X48: Früchte | Y48: 3 - Reduzierter Satz | Z48: Keine | AA48: Kein Depotartikel | AB48: ja | AC48: ja | AD48: ja | AE48: ja | AF48: - | AG48: - | AH48: ja | AI48: 0.05 | AJ48: -
A49: 440 | C49: Stk | D49: Ja | E49: 2205617000000 | F49: Bio Birnen Williams | G49: Offen Kl. 1 | H49: 500g | I49: Bio Birne Will. Off Kl1 500g | J49: Bio Poires Williams | K49: En vrac, cl. 1 | L49: 500g | M49: Bio Poires Will. cl1 en vrac | N49: Bio Pere Williams | O49: Cl. 1 vendita sfusa | P49: 500g | Q49: Bio Pere Williams cl. 1 500g | R49: 0.5 | S49: 1 | T49: Kilogramm | U49: (PCE) Stück | V49: Früchte und Gemüse | W49: Früchte und Gemüse | X49: Früchte | Y49: 3 - Reduzierter Satz | Z49: Keine | AA49: Kein Depotartikel | AB49: ja | AC49: ja | AD49: ja | AE49: ja | AF49: - | AG49: - | AH49: ja | AI49: 0.05 | AJ49: -
A50: 442 | B50: 168 | C50: kg | F50: Orangen Tarocco | G50: Offen | I50: Orangen Tarocco Offen | J50: Oranges Tarocco | K50: En vrac | M50: Oranges Tarocco en vrac | N50: Arance Tarocco | O50: vendita sfusa | Q50: Arance Tarocco vendita sfusa | R50: 1 | S50: 1 | T50: Kilogramm | U50: (KGM) KG | V50: Früchte und Gemüse | W50: Früchte und Gemüse | X50: Früchte | Y50: 3 - Reduzierter Satz | Z50: Keine | AA50: Kein Depotartikel | AB50: ja | AC50: ja | AD50: ja | AE50: ja | AF50: - | AG50: - | AH50: ja | AI50: 0.05 | AJ50: -
A51: 443 | B51: 100 | C51: kg | D51: Nein | F51: Äpfel Boskoop | G51: Offen Kl. 1 | I51: Äpel Boskoop Offen Kl. 1 | J51: Pommes Boskoop | K51: En vrac, cl. 1 | M51: Pommes Boskoop cl.1 en vrac | N51: Mele Boskoop | O51: Cl. 1 vendita sfusa | Q51: Mele Boskoop cl. 1 v. sfusa | R51: 1 | S51: 1 | T51: Kilogramm | U51: (KGM) KG | V51: Früchte und Gemüse | W51: Früchte und Gemüse | X51: Früchte | Y51: 3 - Reduzierter Satz | Z51: Keine | AA51: Kein Depotartikel | AB51: ja | AC51: ja | AD51: ja | AE51: ja | AF51: - | AG51: - | AH51: ja | AI51: 0.05 | AJ51: -
A52: 448 | C52: Stk | D52: Ja | E52: 2216961000005 | F52: Äpfel Boskoop | G52: Kl. 1 gepackt | I52: Äpfel Boskoop Kl. 1 gepackt | J52: Pommes Boskoop | K52: Cl. 1 emballé | M52: Pommes Boskoop cl.1 emball. | N52: Mele Boskoop | O52: Cl. 1 confezionato | Q52: Mele Boskoop cl. 1 confez. | R52: 1 | S52: 1 | T52: Kilogramm | U52: (PCE) Stück | V52: Früchte und Gemüse | W52: Früchte und Gemüse | X52: Früchte | Y52: 3 - Reduzierter Satz | Z52: Keine | AA52: Kein Depotartikel | AB52: ja | AC52: ja | AD52: ja | AE52: ja | AF52: - | AG52: - | AH52: ja | AI52: 0.05 | AJ52: -
A53: 449 | B53: 101 | C53: kg | D53: Nein | F53: Äpfel Braeburn | G53: Offen Kl. 1 | I53: Äpfel Braeburn Offen Kl. 1 | J53: Pommes Braeburn | K53: En vrac, cl. 1 | M53: Pommes Braeburn cl.1 en vrac | N53: Mele Braeburn | O53: Cl. 1 vendita sfusa | Q53: Mele Braeburn cl. 1 v. sfusa | R53: 1 | S53: 1 | T53: Kilogramm | U53: (KGM) KG | V53: Früchte und Gemüse | W53: Früchte und Gemüse | X53: Früchte | Y53: 3 - Reduzierter Satz | Z53: Keine | AA53: Kein Depotartikel | AB53: ja | AC53: ja | AD53: ja | AE53: ja | AF53: - | AG53: - | AH53: ja | AI53: 0.05 | AJ53: -
A54: 453 | C54: Stk | D54: Ja | E54: 2274484000001 | F54: Äpfel Braeburn | G54: Kl. 1 gepackt | I54: Äpfel Braeburn Kl. 1 gepackt | J54: Pommes Braeburn | K54: Cl. 1 emballé | M54: Pommes Braeburn cl.1 emball. | N54: Mele Braeburn | O54: Cl. 1 confezionato | Q54: Mele Braeburn cl. 1 confez. | R54: 1 | S54: 1 | T54: Kilogramm | U54: (PCE) Stück | V54: Früchte und Gemüse | W54: Früchte und Gemüse | X54: Früchte | Y54: 3 - Reduzierter Satz | Z54: Keine | AA54: Kein Depotartikel | AB54: ja | AC54: ja | AD54: ja | AE54: ja | AF54: - | AG54: - | AH54: ja | AI54: 0.05 | AJ54: -
A55: 467 | B55: 102 | C55: kg | D55: Nein | F55: Äpfel Braeburn | G55: Offen Kl. 2 | I55: Äpfel Braeburn Offen Kl. 2 | J55: Pommes Braeburn | K55: En vrac, cl. 2 | M55: Pommes Braeburn cl.2 en vrac | N55: Mele Braeburn | O55: Cl. 2 vendita sfusa | Q55: Mele Braeburn cl. 2 v. sfusa | R55: 1 | S55: 1 | T55: Kilogramm | U55: (KGM) KG | V55: Früchte und Gemüse | W55: Früchte und Gemüse | X55: Früchte | Y55: 3 - Reduzierter Satz | Z55: Keine | AA55: Kein Depotartikel | AB55: ja | AC55: ja | AD55: ja | AE55: ja | AF55: - | AG55: - | AH55: ja | AI55: 0.05 | AJ55: -
A56: 476 | C56: Stk | D56: Nein | E56: 7610632010280 | F56: Brombeeren | G56: Schale | H56: 125g | I56: Brombeeren Schale 125g | J56: Mûres | K56: Barquette | L56: 125g | M56: Mûres barquette 125g | N56: More | O56: vaschetta | P56: 125g | Q56: More vaschetta 125g | R56: 0.125 | S56: 100 | T56: Gramm | U56: (PCE) Stück | V56: Früchte und Gemüse | W56: Früchte und Gemüse | X56: Früchte | Y56: 3 - Reduzierter Satz | Z56: Keine | AA56: Kein Depotartikel | AB56: ja | AC56: ja | AD56: ja | AE56: ja | AF56: - | AG56: - | AH56: ja | AI56: 0.05 | AJ56: -
A57: 479 | C57: Stk | D57: Nein | E57: 7610632050064 | F57: Brombeeren | G57: Schale | H57: 250g | I57: Brombeeren Schale 250g | J57: Mûres | K57: Barquette | L57: 250g | M57: Mûres barquette 250g | N57: More | O57: vaschetta | P57: 250g | Q57: More vaschetta 250g | R57: 0.25 | S57: 100 | T57: Gramm | U57: (PCE) Stück | V57: Früchte und Gemüse | W57: Früchte und Gemüse | X57: Früchte | Y57: 3 - Reduzierter Satz | Z57: Keine | AA57: Kein Depotartikel | AB57: ja | AC57: ja | AD57: ja | AE57: ja | AF57: - | AG57: - | AH57: ja | AI57: 0.05 | AJ57: -
A58: 482 | B58: 139 | C58: kg | D58: Nein | F58: Bio Clementinen | G58: Offen | I58: Bio Clementinen Offen | J58: Bio Clémentines | K58: En vrac | M58: Bio Clémentines en vrac | N58: Bio Clementine | O58: vendita sfusa | Q58: Bio Clementine vendita sfusa | R58: 1 | S58: 1 | T58: Kilogramm | U58: (KGM) KG | V58: Früchte und Gemüse | W58: Früchte und Gemüse | X58: Früchte | Y58: 3 - Reduzierter Satz | Z58: Keine | AA58: Kein Depotartikel | AB58: ja | AC58: ja | AD58: ja | AE58: ja | AF58: - | AG58: - | AH58: ja | AI58: 0.05 | AJ58: -
A59: 484 | B59: 140 | C59: kg | D59: Nein | F59: Clementinen mit Blatt | G59: Offen | I59: Clementinen mit Blatt Offen | J59: Clémentines + feuilles | K59: En vrac | M59: Clémentines feuilles en vrac | N59: Clementine con foglia | O59: vendita sfusa | Q59: Clementine con foglia v.s. | R59: 1 | S59: 1 | T59: Kilogramm | U59: (KGM) KG | V59: Früchte und Gemüse | W59: Früchte und Gemüse | X59: Früchte | Y59: 3 - Reduzierter Satz | Z59: Keine | AA59: Kein Depotartikel | AB59: ja | AC59: ja | AD59: ja | AE59: ja | AF59: - | AG59: - | AH59: ja | AI59: 0.05 | AJ59: -
A60: 485 | B60: 141 | C60: kg | D60: Nein | F60: Clementinen | G60: Rotkehlchen Offen | I60: Clement. Rothehlchen Off. | J60: Clément. Rotkehlchen | K60: En vrac | M60: Clémentines Rotkehl en vrac | N60: Clementine Rotkehlchen | O60: vendita sfusa | Q60: Clementine Rotk. v. sfusa | R60: 1 | S60: 1 | T60: Kilogramm | U60: (KGM) KG | V60: Früchte und Gemüse | W60: Früchte und Gemüse | X60: Früchte | Y60: 3 - Reduzierter Satz | Z60: Keine | AA60: Kein Depotartikel | AB60: ja | AC60: ja | AD60: ja | AE60: ja | AF60: - | AG60: - | AH60: ja | AI60: 0.05 | AJ60: -
A61: 505 | B61: 103 | C61: kg | D61: Nein | F61: Äpfel Cox Orange | G61: Offen Kl. 1 | I61: Äpfel Cox Orange Offen Kl. 1 | J61: Pommes Cox Orange | K61: En vrac, cl. 1 | M61: Pommes Cox Orange cl.1 en v. | N61: Mele Cox Orange | O61: Cl. 1 vendita sfusa | Q61: Mele Cox Orange cl. 1 v.s. | R61: 1 | S61: 1 | T61: Kilogramm | U61: (KGM) KG | V61: Früchte und Gemüse | W61: Früchte und Gemüse | X61: Früchte | Y61: 3 - Reduzierter Satz | Z61: Keine | AA61: Kein Depotartikel | AB61: ja | AC61: ja | AD61: ja | AE61: ja | AF61: - | AG61: - | AH61: ja | AI61: 0.05 | AJ61: -
A62: 506 | C62: Stk | D62: Ja | E62: 2202261000005 | F62: Äpfel Cox Orange | G62: Kl. 1 gepackt | I62: Äpfel Cox Orange Kl. 1 gep. | J62: Pommes Cox Orange | K62: Cl. 1 emballé | M62: Pommes Cox Orange cl.1 emb. | N62: Mele Cox Orange | O62: Cl. 1 confezionato | Q62: Mele Cox Orange cl. 1 confez | R62: 1 | S62: 1 | T62: Kilogramm | U62: (PCE) Stück | V62: Früchte und Gemüse | W62: Früchte und Gemüse | X62: Früchte | Y62: 3 - Reduzierter Satz | Z62: Keine | AA62: Kein Depotartikel | AB62: ja | AC62: ja | AD62: ja | AE62: ja | AF62: - | AG62: - | AH62: ja | AI62: 0.05 | AJ62: -
A63: 508 | C63: Stk | D63: Nein | E63: 7613399008774 | F63: Cranberries | G63: Beutel | H63: 340g | I63: Cranberries Beutel 340g | J63: Cranberries | K63: Sac | L63: 340g | M63: Cranberries sac 340g | N63: Cranberries | O63: sacchetto | P63: 340g | Q63: Cranberries sacchetto 340g | R63: 0.34 | S63: 100 | T63: Gramm | U63: (PCE) Stück | V63: Früchte und Gemüse | W63: Früchte und Gemüse | X63: Früchte | Y63: 3 - Reduzierter Satz | Z63: Keine | AA63: Kein Depotartikel | AB63: ja | AC63: ja | AD63: ja | AE63: ja | AF63: - | AG63: - | AH63: ja | AI63: 0.05 | AJ63: -
A64: 546 | B64: 110 | C64: kg | D64: Nein | F64: Äpfel Elstar | G64: Offen Kl. 1 | I64: Äpfel Elstar Offen Kl. 1 | J64: Pommes Elstar | K64: En vrac, cl. 1 | M64: Pommes Elstar cl. 1 en vrac | N64: Mele Elstar | O64: Cl. 1 vendita sfusa | Q64: Mele Elstar cl. 1 ven. sfusa | R64: 1 | S64: 1 | T64: Kilogramm | U64: (KGM) KG | V64: Früchte und Gemüse | W64: Früchte und Gemüse | X64: Früchte | Y64: 3 - Reduzierter Satz | Z64: Keine | AA64: Kein Depotartikel | AB64: ja | AC64: ja | AD64: ja | AE64: ja | AF64: - | AG64: - | AH64: ja | AI64: 0.05 | AJ64: -
A65: 563 | C65: Stk | D65: Ja | E65: 2202291000006 | F65: Äpfel Elstar | G65: Kl. 1 gepackt | I65: Äpfel Elstar Kl. 1 gepackt | J65: Pommes Elstar | K65: Cl. 1 emballé | M65: Pommes Elstar cl. 1 emballé | N65: Mele Elstar | O65: Cl. 1 confezionato | Q65: Mele Elstar cl. 1 confez. | R65: 1 | S65: 1 | T65: Kilogramm | U65: (PCE) Stück | V65: Früchte und Gemüse | W65: Früchte und Gemüse | X65: Früchte | Y65: 3 - Reduzierter Satz | Z65: Keine | AA65: Kein Depotartikel | AB65: ja | AC65: ja | AD65: ja | AE65: ja | AF65: - | AG65: - | AH65: ja | AI65: 0.05 | AJ65: -
A66: 564 | B66: 123 | C66: kg | D66: Nein | F66: Flachpfirsiche | G66: Offen | I66: Flachpfirsiche Offen | J66: Pêches plates | K66: En vrac | M66: Pêches plartes en vrac | N66: Pesche tabacchiera | O66: vendita sfusa | Q66: Pesche tabacchiera v. sfusa | R66: 1 | S66: 1 | T66: Kilogramm | U66: (KGM) KG | V66: Früchte und Gemüse | W66: Früchte und Gemüse | X66: Früchte | Y66: 3 - Reduzierter Satz | Z66: Keine | AA66: Kein Depotartikel | AB66: ja | AC66: ja | AD66: ja | AE66: ja | AF66: - | AG66: - | AH66: ja | AI66: 0.05 | AJ66: -
A67: 565 | C67: Stk | D67: Nein | E67: 7613399001287 | F67: Fruchtbecher | H67: 200g | I67: Fruchtbecher 200g | J67: Gobelet de fruits | L67: 200g | M67: Gobelet de fruits 200g | N67: Bicchiere di frutta | P67: 200g | Q67: Bicchiere di frutta 200g | R67: 0.2 | S67: 100 | T67: Gramm | U67: (PCE) Stück | V67: Früchte und Gemüse | W67: Früchte und Gemüse | X67: Früchte | Y67: 3 - Reduzierter Satz | Z67: Keine | AA67: Kein Depotartikel | AB67: ja | AC67: ja | AD67: ja | AE67: ja | AF67: - | AG67: - | AH67: ja | AI67: 0.05 | AJ67: -
A68: 567 | C68: Stk | D68: Ja | E68: 2296291000005 | F68: Früchtemix | G68: Äpfel/Orangen/Bananen | I68: Früchtemix Äpfel/Orange/Ban. | J68: Mélange de fruits | K68: Pommes/oranges/bananes | M68: Mélange fruits pom/oran/ban | N68: Mix di frutta | O68: Mele/arance/banane | Q68: Mix di frutta mele/aran./ban | R68: 1 | S68: 1 | T68: Kilogramm | U68: (PCE) Stück | V68: Früchte und Gemüse | W68: Früchte und Gemüse | X68: Früchte | Y68: 3 - Reduzierter Satz | Z68: Keine | AA68: Kein Depotartikel | AB68: ja | AC68: ja | AD68: ja | AE68: ja | AF68: - | AG68: - | AH68: ja | AI68: 0.05 | AJ68: -
A69: 571 | B69: 113 | C69: kg | D69: Nein | F69: Äpfel Gala | G69: Offen Kl. 1 | I69: Äpfel Gala Offen Kl. 1 | J69: Pommes Gala | K69: En vrac, cl. 1 | M69: Pommes Gala cl. 1 en vrac | N69: Mele Gala | O69: Cl. 1 vendita sfusa | Q69: Mele Gala cl.1 vendita sfusa | R69: 1 | S69: 1 | T69: Kilogramm | U69: (KGM) KG | V69: Früchte und Gemüse | W69: Früchte und Gemüse | X69: Früchte | Y69: 3 - Reduzierter Satz | Z69: Keine | AA69: Kein Depotartikel | AB69: ja | AC69: ja | AD69: ja | AE69: ja | AF69: - | AG69: - | AH69: ja | AI69: 0.05 | AJ69: -
A70: 572 | C70: Stk | D70: Ja | E70: 2202611000000 | F70: Äpfel Gala | G70: Kl. 1 gepackt | I70: Äpfel Gala Kl. 1 gepackt | J70: Pommes Gala | K70: Cl. 1 emballé | M70: Pommes Gala cl. 1 emballé | N70: Mele Gala | O70: Cl. 1 confezionato | Q70: Mele Gala cl. 1 confezionato | R70: 1 | S70: 1 | T70: Kilogramm | U70: (PCE) Stück | V70: Früchte und Gemüse | W70: Früchte und Gemüse | X70: Früchte | Y70: 3 - Reduzierter Satz | Z70: Keine | AA70: Kein Depotartikel | AB70: ja | AC70: ja | AD70: ja | AE70: ja | AF70: - | AG70: - | AH70: ja | AI70: 0.05 | AJ70: -
A71: 575 | C71: Stk | D71: Ja | E71: 2202391000005 | F71: Äpfel Gala TT | G71: Kl. 1 | H71: 1.5kg | I71: Äpfel Gala TT Kl. 1, 1.5 kg | J71: Pommes Gala | K71: Cl. 1 | L71: 1.5kg | M71: Pommes Gala cl. 1 1.5kg | N71: Mele Gala TT | O71: Cl. 1 | P71: 1.5kg | Q71: Mele Gala TT cl. 1 1.5kg | R71: 1.5 | S71: 1 | T71: Kilogramm | U71: (PCE) Stück | V71: Früchte und Gemüse | W71: Früchte und Gemüse | X71: Früchte | Y71: 3 - Reduzierter Satz | Z71: Keine | AA71: Kein Depotartikel | AB71: ja | AC71: ja | AD71: ja | AE71: ja | AF71: - | AG71: - | AH71: ja | AI71: 0.05 | AJ71: -
A72: 576 | C72: Stk | D72: Ja | E72: 2202633000000 | F72: Äpfel Gala TT | G72: Kl. 2 | H72: 1.5kg | I72: Äpfel Gala TT Kl. 2, 1.5 kg | J72: Pommes Gala | K72: Cl. 2 | L72: 1.5kg | M72: Pommes Gala cl. 2 1.5kg | N72: Mele Gala TT | O72: Cl. 2 | P72: 1.5kg | Q72: Mele Gala TT cl. 2 1.5kg | R72: 1.5 | S72: 1 | T72: Kilogramm | U72: (PCE) Stück | V72: Früchte und Gemüse | W72: Früchte und Gemüse | X72: Früchte | Y72: 3 - Reduzierter Satz | Z72: Keine | AA72: Kein Depotartikel | AB72: ja | AC72: ja | AD72: ja | AE72: ja | AF72: - | AG72: - | AH72: ja | AI72: 0.05 | AJ72: -
A73: 578 | C73: Stk | D73: Ja | E73: 2202389000000 | F73: Bio Äpfel Gala | G73: Kl. 1 gepackt | I73: Bio Äpfel Gala Kl. 1 gepackt | J73: Bio Pommes Golden | K73: Cl. 1 emballé | M73: Bio Pommes Gala cl. 1 emb. | N73: Bio Mele Gala | O73: Cl. 1 confezionato | Q73: Bio Mele Gala cl. 1 confez. | R73: 1 | S73: 1 | T73: Kilogramm | U73: (PCE) Stück | V73: Früchte und Gemüse | W73: Früchte und Gemüse | X73: Früchte | Y73: 3 - Reduzierter Satz | Z73: Keine | AA73: Kein Depotartikel | AB73: ja | AC73: ja | AD73: ja | AE73: ja | AF73: - | AG73: - | AH73: ja | AI73: 0.05 | AJ73: -
A74: 580 | B74: 114 | C74: kg | D74: Nein | F74: Äpfel Galmac | G74: Offen Kl. 1 | I74: Äpfel Galmac Offen Kl. 1 | J74: Pommes Galmac | K74: En vrac, cl. 1 | M74: Pommes Galmac cl. 1 en vrac | N74: Mele Galmac | O74: Cl. 1 vendita sfusa | Q74: Mele Galmac chl. 1 v. sfusa | R74: 1 | S74: 1 | T74: Kilogramm | U74: (KGM) KG | V74: Früchte und Gemüse | W74: Früchte und Gemüse | X74: Früchte | Y74: 3 - Reduzierter Satz | Z74: Keine | AA74: Kein Depotartikel | AB74: ja | AC74: ja | AD74: ja | AE74: ja | AF74: - | AG74: - | AH74: ja | AI74: 0.05 | AJ74: -
A75: 586 | C75: Stk | D75: Ja | E75: 2201354000000 | F75: Äpfel Galmac | G75: Kl. 1 gepackt | I75: Äpfel Galmac Kl. 1 gepackt | J75: Pommes Galmac | K75: Cl. 1 emballé | M75: Pommes Galmac cl. 1 emballé | N75: Mele Galmac | O75: Cl. 1 confezionato | Q75: Mele Galmac cl. 1 confez. | R75: 1 | S75: 1 | T75: Kilogramm | U75: (PCE) Stück | V75: Früchte und Gemüse | W75: Früchte und Gemüse | X75: Früchte | Y75: 3 - Reduzierter Satz | Z75: Keine | AA75: Kein Depotartikel | AB75: ja | AC75: ja | AD75: ja | AE75: ja | AF75: - | AG75: - | AH75: ja | AI75: 0.05 | AJ75: -
A76: 587 | C76: Stk | D76: Ja | E76: 2202663000000 | F76: Äpfel Golden | G76: Kl. 1 gepackt | I76: Äpfel Golden Kl. 1 gepackt | J76: Pommes Golden | K76: Cl. 1 emballé | M76: Pommes Golden cl. 1 emballé | N76: Mele Golden | O76: Cl. 1 confezionato | Q76: Mele Golden cl. 1 confez | R76: 1 | S76: 1 | T76: Kilogramm | U76: (PCE) Stück | V76: Früchte und Gemüse | W76: Früchte und Gemüse | X76: Früchte | Y76: 3 - Reduzierter Satz | Z76: Keine | AA76: Kein Depotartikel | AB76: ja | AC76: ja | AD76: ja | AE76: ja | AF76: - | AG76: - | AH76: ja | AI76: 0.05 | AJ76: -
A77: 588 | B77: 115 | C77: kg | D77: Nein | F77: Äpfel Golden | G77: Offen Kl. 2 | I77: Äpfel Golden Offen Kl. 2 | J77: Pommes Golden | K77: En vrac, cl. 2 | M77: Pommes Golden cl. 2 en vrac | N77: Mele Golden | O77: Cl. 2 vendita sfusa | Q77: Mele Golden cl. 2 v. sfusa | R77: 1 | S77: 1 | T77: Kilogramm | U77: (KGM) KG | V77: Früchte und Gemüse | W77: Früchte und Gemüse | X77: Früchte | Y77: 3 - Reduzierter Satz | Z77: Keine | AA77: Kein Depotartikel | AB77: ja | AC77: ja | AD77: ja | AE77: ja | AF77: - | AG77: - | AH77: ja | AI77: 0.05 | AJ77: -
A78: 600 | C78: Stk | D78: Ja | E78: 2202621000003 | F78: Äpfel Golden TT | H78: 1.5kg | I78: Äpfel Golden TT 1.5 kg | J78: Pommes Golden sac | L78: 1.5kg | M78: Pomes Golden sac 1.5kg | N78: Mele Golden TT | P78: 1.5kg | Q78: Mele Golden TT 1.5kg | R78: 1.5 | S78: 1 | T78: Kilogramm | U78: (PCE) Stück | V78: Früchte und Gemüse | W78: Früchte und Gemüse | X78: Früchte | Y78: 3 - Reduzierter Satz | Z78: Keine | AA78: Kein Depotartikel | AB78: ja | AC78: ja | AD78: ja | AE78: ja | AF78: - | AG78: - | AH78: ja | AI78: 0.05 | AJ78: -
A79: 605 | B79: 116 | C79: kg | D79: Nein | F79: Äpfel Granny Smith | G79: Offen Kl. 1 | I79: Äpfel Granny Smith Off. Kl.1 | J79: Pommes Granny Smith | K79: En vrac, cl. 1 | M79: Pommes Gran. Smith cl.1 en.v | N79: Mele Granny Smith | O79: Cl. 1 vendita sfusa | Q79: Mele Granny Smith cl. 1 v.s. | R79: 1 | S79: 1 | T79: Kilogramm | U79: (KGM) KG | V79: Früchte und Gemüse | W79: Früchte und Gemüse | X79: Früchte | Y79: 3 - Reduzierter Satz | Z79: Keine | AA79: Kein Depotartikel | AB79: ja | AC79: ja | AD79: ja | AE79: ja | AF79: - | AG79: - | AH79: ja | AI79: 0.05 | AJ79: -
A80: 610 | C80: Stk | D80: Ja | E80: 2202901000006 | F80: Äpfel Granny Smith | G80: Kl. 1 gepackt | I80: Äpfel Granny Smith Kl.1 gep. | J80: Pommes Granny Smith | K80: Cl. 1 emballé | M80: Pommes Gran. Smith cl.1 emb. | N80: Mele Granny Smith | O80: Cl. 1 confezionato | Q80: Mele Granny Smith cl.1 conf. | R80: 1 | S80: 1 | T80: Kilogramm | U80: (PCE) Stück | V80: Früchte und Gemüse | W80: Früchte und Gemüse | X80: Früchte | Y80: 3 - Reduzierter Satz | Z80: Keine | AA80: Kein Depotartikel | AB80: ja | AC80: ja | AD80: ja | AE80: ja | AF80: - | AG80: - | AH80: ja | AI80: 0.05 | AJ80: -
A81: 611 | C81: Stk | D81: Ja | E81: 2216811000001 | F81: Grapefruits rot | G81: Netz | H81: 2Stk | I81: Grapefruits rot Netz 2 Stk | J81: Pamplemousses rouges | K81: Filet | L81: 2pces | M81: Pamplemousses rouges 2 pces | N81: Pompelmi rossi | O81: retina | P81: 2pz | Q81: Pompelmi rossi retina 2 pz | R81: 2 | S81: 1 | T81: Stück | U81: (PCE) Stück | V81: Früchte und Gemüse | W81: Früchte und Gemüse | X81: Früchte | Y81: 3 - Reduzierter Satz | Z81: Keine | AA81: Kein Depotartikel | AB81: ja | AC81: ja | AD81: ja | AE81: ja | AF81: - | AG81: - | AH81: ja | AI81: 0.05 | AJ81: -
A82: 612 | C82: Stk | D82: Nein | F82: Grapefruits weiss | H82: Stk | I82: Grapefruits weiss Stk | J82: Pamplemousses jaune | L82: pce | M82: Pampelmousses jaune pce | N82: Pompelmi bianchi | P82: pz | Q82: Pompelmi bianchi pz | R82: 1 | S82: 1 | T82: Stück | U82: (PCE) Stück | V82: Früchte und Gemüse | W82: Früchte und Gemüse | X82: Früchte | Y82: 3 - Reduzierter Satz | Z82: Keine | AA82: Kein Depotartikel | AB82: ja | AC82: ja | AD82: ja | AE82: ja | AF82: - | AG82: - | AH82: ja | AI82: 0.05 | AJ82: -
A83: 615 | B83: 117 | C83: kg | D83: Nein | F83: Äpfel Gravensteiner | G83: Offen Kl. 1 | I83: Äpfel Gravensteiner Off. Kl1 | J83: Pommes Gravensteiner | K83: En vrac, cl. 1 | M83: Pommes Gravenstr. cl.1 en v. | N83: Mele Gravensteiner | O83: Cl. 1 vendita sfusa | Q83: Mele Gravensteiner cl.1 v.s. | R83: 1 | S83: 1 | T83: Kilogramm | U83: (KGM) KG | V83: Früchte und Gemüse | W83: Früchte und Gemüse | X83: Früchte | Y83: 3 - Reduzierter Satz | Z83: Keine | AA83: Kein Depotartikel | AB83: ja | AC83: ja | AD83: ja | AE83: ja | AF83: - | AG83: - | AH83: ja | AI83: 0.05 | AJ83: -
A84: 616 | C84: Stk | D84: Ja | E84: 2202021000009 | F84: Äpfel Gravensteiner | G84: Kl. 1 gepackt | I84: Äpfel Gravenst. Kl.1 gep. | J84: Pommes Gravensteiner | K84: Cl. 1 emballé | M84: Pommes Gravenstr. cl.1 emb. | N84: Mele Gravensteiner | O84: Cl. 1 confezionato | Q84: Mele Gravensteiner cl.1 conf | R84: 1 | S84: 1 | T84: Kilogramm | U84: (PCE) Stück | V84: Früchte und Gemüse | W84: Früchte und Gemüse | X84: Früchte | Y84: 3 - Reduzierter Satz | Z84: Keine | AA84: Kein Depotartikel | AB84: ja | AC84: ja | AD84: ja | AE84: ja | AF84: - | AG84: - | AH84: ja | AI84: 0.05 | AJ84: -
A85: 641 | B85: 121 | C85: kg | D85: Nein | F85: Äpfel Jazz | G85: Offen Kl. 1 | I85: Äpfel Jazz Offen Kl. 1 | J85: Pommes Jazz | K85: En vrac, cl. 1 | M85: Pommes Jazz cl. 1 en vrac | N85: Mele Jazz | O85: Cl. 1 vendita sfusa | Q85: Mele Jazz cl.1 vendita sfusa | R85: 1 | S85: 1 | T85: Kilogramm | U85: (KGM) KG | V85: Früchte und Gemüse | W85: Früchte und Gemüse | X85: Früchte | Y85: 3 - Reduzierter Satz | Z85: Keine | AA85: Kein Depotartikel | AB85: ja | AC85: ja | AD85: ja | AE85: ja | AF85: - | AG85: - | AH85: ja | AI85: 0.05 | AJ85: -
A86: 642 | C86: Stk | D86: Ja | E86: 2245251000005 | F86: Äpfel Jazz | G86: Kl. 1 gepackt | I86: Äpfel Jazz Kl. 1 gepackt | J86: Pommes Jazz | K86: Cl. 1 emballé | M86: Pommes Jazz cl. 1 emballé | N86: Mele Jazz | O86: Cl. 1 confezionato | Q86: Mele Jazz cl.1 confezionato | R86: 1 | S86: 1 | T86: Kilogramm | U86: (PCE) Stück | V86: Früchte und Gemüse | W86: Früchte und Gemüse | X86: Früchte | Y86: 3 - Reduzierter Satz | Z86: Keine | AA86: Kein Depotartikel | AB86: ja | AC86: ja | AD86: ja | AE86: ja | AF86: - | AG86: - | AH86: ja | AI86: 0.05 | AJ86: -
A87: 649 | C87: Stk | D87: Nein | E87: 7628072012627 | F87: Johannisbeeren | G87: Schale | H87: 250g | I87: Johannisbeeren Schale 250g | J87: Raisinets | K87: Barquette | L87: 250g | M87: Raisinets barquette 250g | N87: Ribes | O87: vaschetta | P87: 250g | Q87: Ribes vaschetta 250g | R87: 0.25 | S87: 100 | T87: Gramm | U87: (PCE) Stück | V87: Früchte und Gemüse | W87: Früchte und Gemüse | X87: Früchte | Y87: 3 - Reduzierter Satz | Z87: Keine | AA87: Kein Depotartikel | AB87: ja | AC87: ja | AD87: ja | AE87: ja | AF87: - | AG87: - | AH87: ja | AI87: 0.05 | AJ87: -
A88: 650 | B88: 124 | C88: kg | D88: Nein | F88: Äpfel Jonagold | G88: Offen Kl. 2 | I88: Äpfel Jonagold Offen Kl. 2 | J88: Pommes Jonagold | K88: En vrac, cl. 2 | M88: Pommes Jonagold cl.2 en v. | N88: Mele Jonagold | O88: Cl. 2 vendita sfusa | Q88: Mele Jonagold cl. 2 v. sfusa | R88: 1 | S88: 1 | T88: Kilogramm | U88: (KGM) KG | V88: Früchte und Gemüse | W88: Früchte und Gemüse | X88: Früchte | Y88: 3 - Reduzierter Satz | Z88: Keine | AA88: Kein Depotartikel | AB88: ja | AC88: ja | AD88: ja | AE88: ja | AF88: - | AG88: - | AH88: ja | AI88: 0.05 | AJ88: -
A89: 653 | C89: Stk | D89: Nein | E89: 2201761000003 | F89: Kaki | G89: gepackt | I89: Kaki gepackt | J89: Kakis | K89: Emballé | M89: Kakis emballé | N89: Cachi | O89: confezionato | Q89: Cachi confezionato | R89: 1 | S89: 1 | T89: Kilogramm | U89: (PCE) Stück | V89: Früchte und Gemüse | W89: Früchte und Gemüse | X89: Früchte | Y89: 3 - Reduzierter Satz | Z89: Keine | AA89: Kein Depotartikel | AB89: ja | AC89: ja | AD89: ja | AE89: ja | AF89: - | AG89: - | AH89: ja | AI89: 0.05 | AJ89: -
A90: 661 | C90: Stk | D90: Nein | F90: Kaki Sharon | I90: Kaki Sharon | J90: Kakis Sharon | M90: Kakis Sharon | N90: Cachi Sharon | Q90: Cachi Sharon | R90: 1 | S90: 1 | T90: Stück | U90: (PCE) Stück | V90: Früchte und Gemüse | W90: Früchte und Gemüse | X90: Früchte | Y90: 3 - Reduzierter Satz | Z90: Keine | AA90: Kein Depotartikel | AB90: ja | AC90: ja | AD90: ja | AE90: ja | AF90: - | AG90: - | AH90: ja | AI90: 0.05 | AJ90: -
A91: 671 | B91: 149 | C91: kg | D91: Nein | F91: Kirschen | G91: Offen | I91: Kirschen Offen | J91: Cerises | K91: En vrac | M91: Cerises en vrac | N91: Ciliegie | O91: vendita sfusa | Q91: Ciliegie vendita sfusa | R91: 1 | S91: 1 | T91: Kilogramm | U91: (KGM) KG | V91: Früchte und Gemüse | W91: Früchte und Gemüse | X91: Früchte | Y91: 3 - Reduzierter Satz | Z91: Keine | AA91: Kein Depotartikel | AB91: ja | AC91: ja | AD91: ja | AE91: ja | AF91: - | AG91: - | AH91: ja | AI91: 0.05 | AJ91: -
A92: 689 | C92: Stk | D92: Ja | E92: 2215771000007 | F92: Kiwi grün | G92: gepackt | I92: Kiwi grün gepackt | J92: Kiwi vert | K92: Emballé | M92: Kiwi vert emballé | N92: Kiwi verdi | O92: confezionato | Q92: Kiwi verdi confezionato | R92: 1 | S92: 1 | T92: Kilogramm | U92: (PCE) Stück | V92: Früchte und Gemüse | W92: Früchte und Gemüse | X92: Früchte | Y92: 3 - Reduzierter Satz | Z92: Keine | AA92: Kein Depotartikel | AB92: ja | AC92: ja | AD92: ja | AE92: ja | AF92: - | AG92: - | AH92: ja | AI92: 0.05 | AJ92: -
A93: 714 | C93: Stk | D93: Nein | F93: Kokosnuss | H93: 1Stk | I93: Kokosnuss 1 Stk | J93: Noix de coco | L93: 1pce | M93: Noix de coco 1 pce | N93: Noce di cocco | P93: 1pz | Q93: Noce di cocco 1 pz | R93: 1 | S93: 1 | T93: Stück | U93: (PCE) Stück | V93: Früchte und Gemüse | W93: Früchte und Gemüse | X93: Früchte | Y93: 3 - Reduzierter Satz | Z93: Keine | AA93: Kein Depotartikel | AB93: ja | AC93: ja | AD93: ja | AE93: ja | AF93: - | AG93: - | AH93: ja | AI93: 0.05 | AJ93: -
A94: 715 | C94: Stk | D94: Nein | E94: 7613399002598 | F94: Kokosnuss | G94: Becher | H94: 80g | I94: Kokosnuss Becher 80g | J94: Noix de coco | K94: Gobelet | L94: 80g | M94: Noix de coco 80g | N94: Noce di cocco | O94: bicchiere | P94: 80g | Q94: Noce di cocco bichiere 80g | R94: 0.08 | S94: 100 | T94: Gramm | U94: (PCE) Stück | V94: Früchte und Gemüse | W94: Früchte und Gemüse | X94: Früchte | Y94: 3 - Reduzierter Satz | Z94: Keine | AA94: Kein Depotartikel | AB94: ja | AC94: ja | AD94: ja | AE94: ja | AF94: - | AG94: - | AH94: ja | AI94: 0.05 | AJ94: -
A95: 726 | C95: Stk | D95: Ja | E95: 2205051000001 | F95: Limetten | G95: gepackt | I95: Limetten gepackt | J95: Citrons verts | K95: Emballé | M95: Citrons verts emballé | N95: Lime | O95: confezionato | Q95: Lime confezionato | R95: 1 | S95: 1 | T95: Kilogramm | U95: (PCE) Stück | V95: Früchte und Gemüse | W95: Früchte und Gemüse | X95: Früchte | Y95: 3 - Reduzierter Satz | Z95: Keine | AA95: Kein Depotartikel | AB95: ja | AC95: ja | AD95: ja | AE95: ja | AF95: - | AG95: - | AH95: ja | AI95: 0.05 | AJ95: -
A96: 734 | C96: Stk | D96: Ja | E96: 2205548000000 | F96: Äpfel Mairac | G96: Kl. 1 gepackt | I96: Äpfel Mairac Kl. 1 gepackt | J96: Pommes Mairac | K96: Cl. 1 emballé | M96: Pommes Mairac cl. 1 emballé | N96: Mele Mairac | O96: Cl. 1 confezionato | Q96: Mele Mairac cl. 1 confez. | R96: 1 | S96: 1 | T96: Kilogramm | U96: (PCE) Stück | V96: Früchte und Gemüse | W96: Früchte und Gemüse | X96: Früchte | Y96: 3 - Reduzierter Satz | Z96: Keine | AA96: Kein Depotartikel | AB96: ja | AC96: ja | AD96: ja | AE96: ja | AF96: - | AG96: - | AH96: ja | AI96: 0.05 | AJ96: -
A97: 764 | C97: Stk | D97: Ja | E97: 2201401000004 | F97: Marroni | G97: Netz | H97: 750g | I97: Marroni Netz 750g | J97: Marrons | K97: Filet | L97: 750g | M97: Marrons filet 750g | N97: Castagne | O97: retina | P97: 750g | Q97: Castagne retina 750g | R97: 0.75 | S97: 1 | T97: Kilogramm | U97: (PCE) Stück | V97: Früchte und Gemüse | W97: Früchte und Gemüse | X97: Früchte | Y97: 3 - Reduzierter Satz | Z97: Keine | AA97: Kein Depotartikel | AB97: ja | AC97: ja | AD97: ja | AE97: ja | AF97: - | AG97: - | AH97: ja | AI97: 0.05 | AJ97: -
A98: 785 | C98: Stk | D98: Ja | E98: 2264431000000 | F98: Melonen Charentais | H98: 1Stk | I98: Melonen Charentais 1 Stk | J98: Melons charentais | L98: 1pce | M98: Melons charentais 1 pce | N98: Meloni Charentais | P98: 1pz | Q98: Meloni Charentais 1 pz | R98: 1 | S98: 1 | T98: Stück | U98: (PCE) Stück | V98: Früchte und Gemüse | W98: Früchte und Gemüse | X98: Früchte | Y98: 3 - Reduzierter Satz | Z98: Keine | AA98: Kein Depotartikel | AB98: ja | AC98: ja | AD98: ja | AE98: ja | AF98: - | AG98: - | AH98: ja | AI98: 0.05 | AJ98: -
A99: 809 | C99: Stk | D99: Ja | E99: 2217202000006 | F99: Melonen Jolly | H99: 1Stk | I99: Melonen Jolly 1 Stk | J99: Melons Jolly | L99: 1pce | M99: Melons Jolly 1 pce | N99: Meloni Jolly | P99: 1pz | Q99: Meloni Jolly 1 pz | R99: 1 | S99: 1 | T99: Stück | U99: (PCE) Stück | V99: Früchte und Gemüse | W99: Früchte und Gemüse | X99: Früchte | Y99: 3 - Reduzierter Satz | Z99: Keine | AA99: Kein Depotartikel | AB99: ja | AC99: ja | AD99: ja | AE99: ja | AF99: - | AG99: - | AH99: ja | AI99: 0.05 | AJ99: -
A100: 810 | C100: Stk | D100: Ja | E100: 2205673000000 | F100: Melonen Limelon | H100: 1Stk | I100: Melonen Limelon 1 Stk | J100: Melons Limelon | L100: 1pce | M100: Melons Limelon 1 pce | N100: Meloni Limelon | P100: 1pz | Q100: Meloni Limelon 1 pz | R100: 1 | S100: 1 | T100: Stück | U100: (PCE) Stück | V100: Früchte und Gemüse | W100: Früchte und Gemüse | X100: Früchte | Y100: 3 - Reduzierter Satz | Z100: Keine | AA100: Kein Depotartikel | AB100: ja | AC100: ja | AD100: ja | AE100: ja | AF100: - | AG100: - | AH100: ja | AI100: 0.05 | AJ100: -
...

Sheet Leergutliste
A1: System Attributes | E1: Matching Attribute(s) | F1: Reference Data Attributes
A2: Action | B2: Type | C2: ID | D2: Name | E2: Artikelnummer | F2: Artikeltext//de-DE | G2: Artikeltext//fr-FR | H2: Artikeltext//it-IT | I2: Konditionsbetrag | J2: GTIN
B3: refxdepotartikel | C3: 24a46c0f-a771-41e2-93ed-cb0c3fab73bd | D3: 1031091 - Flasche Depot Fr. 0.30 1Stk | E3: 1031091 | F3: 1031091 - Flasche Depot Fr. 0.30 1Stk | G3: 1031091 - Bouteille Dépôt Fr. 0.30 1pce | H3: 1031091 - Bottiglia deposito CHF 0.30 1pz | I3: 0.3 | J3: 2009990300013 | L3: PROD
B4: refxdepotartikel | C4: cb0f8f2a-b148-4463-8ea6-f724fe195806 | D4: 1031091 - Flasche Depot Fr. 0.30 1Stk | E4: 1031091 | F4: 1031091 - Flasche Depot Fr. 0.30 1Stk | G4: 1031091 - Bouteille Dépôt Fr. 0.30 1pc | H4: 1031091 - Bottiglia 0.30 Deposito Fr. 1pz | I4: 0.3 | J4: 2009990300013 | L4: FS
B5: refxdepotartikel | C5: ab6d040c-8203-4e0b-b175-1994c4972eae | D5: 1031092 - Zylinder Soda Pfand Lieferung 1Stk CHF 10.00 | E5: 1031092 | F5: 1031092 - Zylinder Soda Pfand Lieferung 1Stk CHF 10.00 | G5: 1031092 - Cylindre Soda consigne 1pc CHF 10.00 | H5: 1031092 - Zylinder Soda cilindro consegna 1pz CHF 10.00 | I5: 10 | J5: 2009990400010 | L5: PROD
B6: refxdepotartikel | C6: fbc0f523-d3b6-47ba-81d4-f929ccdf1d54 | D6: 1031092 - Zylinder Soda Pfand Lieferung 1Stk | E6: 1031092 | F6: 1031092 - Zylinder Soda Pfand Lieferung 1Stk | G6: 1031092 - Cylindre Soda consigne 1pc | H6: 1031092 - Zylinder Soda cilindro consegna 1pz | I6: 10 | J6: 2009990400010 | L6: FS
B7: refxdepotartikel | C7: eff3978d-7324-4585-9715-cc4ffba09c37 | D7: 1031093 - Soda Lieferkarton 1Stk CHF 0.01 | E7: 1031093 | F7: 1031093 - Soda Lieferkarton 1Stk CHF 0.01 | G7: 1031093 - Carton de livraison Soda 1pc CHF 0.01 | H7: 1031093 - Soda Cartone consegna 1pz CHF 0.01 | I7: 0.01 | J7: 2009990410019 | L7: PROD
B8: refxdepotartikel | C8: bbd5d45f-1d71-4630-8c19-a80359c65efc | D8: 1031095 - Bierharass Depot 20er Fr. 5.00 1Stk | E8: 1031095 | F8: 1031095 - Bierharass Depot 20er Fr. 5.00 1Stk | G8: 1031095 - Caisse de bière dépôt 20 bt Fr. 5.00 1pc | H8: 1031095 - Cassa di birra da 20 deposi Fr. 5.00 1pz | I8: 5 | J8: 2009995530019 | L8: PROD
B9: refxdepotartikel | C9: efc07f6e-9d05-4740-8c39-a909a84956a5 | D9: 1031095 - Bierharass Depot 20er Fr. 5.00 1Stk | E9: 1031095 | F9: 1031095 - Bierharass Depot 20er Fr. 5.00 1Stk | G9: 1031095 - Caisse de bière Depot 20 Fr. 5.00 1pc | H9: 1031095 - Cassa di birra da 20 Depot Fr. 5.00 1pz | I9: 5 | J9: 2009995530019 | L9: FS
B10: refxdepotartikel | C10: 4ef93831-6d2b-4ecf-b453-90d4c225e3c6 | D10: 1035856 - Depot Harasse mit 20 Fl. CHF 11.00 | E10: 1035856 | F10: 1035856 - Depot Harasse mit 20 Fl. CHF 11.00 | G10: 1035856 - Depot Caisse avec 20 btlles CHF 11.00 | H10: 1035856 - Depot Cassa 20 bottiglie CHF 11.00 | I10: 11 | J10: 2009992010019 | L10: PROD
B11: refxdepotartikel | C11: aefcdd96-edf3-4763-8537-23b468197a31 | D11: 1035857 - Soda Zylinder Gebinde Rückgabe 1Stk CHF 10.00 | E11: 1035857 | F11: 1035857 - Soda Zylinder Gebinde Rückgabe 1Stk CHF 10.00 | G11: 1035857 - Soda Cylindre vide reprise 1 pce CHF 10.00 | H11: 1035857 - Soda Cilindri Contenitore resi 1pz CHF 10.00 | I11: 10 | J11: 2009995950015 | L11: PROD
B12: refxdepotartikel | C12: 39869ad3-bb9d-4f50-b44d-875afa9af2d4 | D12: 1035857 - Soda Zylinder Gebinde Rückgabe 1Stk | E12: 1035857 | F12: 1035857 - Soda Zylinder Gebinde Rückgabe 1Stk | G12: 1035857 - Soda Cylindre vide reprise 1 pce | H12: 1035857 - Soda Cilindri Contenitore resi 1pz | I12: 10 | J12: 2009995950015 | L12: FS
B13: refxdepotartikel | C13: 3cacbdbc-b134-402c-adba-636c19439a49 | D13: 1035858 - Gebinderücknahme DSD | E13: 1035858 | F13: 1035858 - Gebinderücknahme DSD | G13: 1035858 - restitution consigne DSD | H13: 1035858 - Restituzione contenitori, DSD | I13: 0.01 | J13: 2009995990011 | L13: FS
B14: refxdepotartikel | C14: f43d1af9-c103-4073-8a92-0c7379dd1446 | D14: 1102242 - Depot CHF 0.10 | E14: 1102242 | F14: 1102242 - Depot CHF 0.10 | G14: 1102242 - Depot CHF 0.10 | H14: 1102242 - Depot CHF 0.10 | I14: 0.1 | J14: 2011022420019 | L14: PROD
... B32: refxdepotartikel | C32: ers2vCq6ZaKBFib | D32: 1601772 - Depot Gasflasche Composite CHF 65.00 | E32: 1601772 | F32: 1601772 - Depot Gasflasche Composite CHF 65.00 | G32: 1102318 - Dépot Bouteille gaz Composite Vito 65.00 | H32: 1102318 - Bombole di gas deposito Vito CHF 65.00 | I32: 65 | J32: 2016017720013 | L32: FS

Sheet Model
A1: Sheet Name | B1: Data | D1: Attribute Name | E1: isCollection
A2: Entities | B2: Data | D2: GTIN-Typ Regioapp | E2: true

Sheet Reference Data
A1: axartikelslpmstruktur__it_IT | B1: atxwarengruppesap__de_DE | C1: axartikelslpmstruktur__de_DE | D1: axmhdvorhanden__it_IT | E1: atxwarengruppesap__fr_FR | F1: axtaxdummyfilter__it_IT | G1: atxalkoholhaltig__it_IT | H1: axartikelslpmstruktur__fr_FR | I1: axartikeltypsap__fr_FR | J1: axartikeltypsap__de_DE | K1: axtaxdummyfilter__de_DE | L1: atxalkoholhaltig__fr_FR | M1: atxalkoholhaltig__de_DE | N1: axmhdvorhanden__de_DE | O1: atxwarengruppesap__it_IT | P1: axartikeltypsap__it_IT | Q1: axmhdvorhanden__fr_FR | R1: axtaxdummyfilter__fr_FR | S1: ENTITY_NAME | T1: refxartikeltypsap | U1: refxbooleanalkoholhaltig | V1: refxboolen | W1: refxartikelartsap de-DE | X1: refxartikelartsap fr-FR | Y1: refxartikelartsap it-IT | Z1: refxsaisontypsap de-DE | AA1: refxsaisontypsap fr-FR | AB1: refxsaisontypsap it-IT | AC1: refxmengeneinheit de-DE | AD1: refxmengeneinheit fr-FR | AE1: refxmengeneinheit it-IT | AF1: refxvergleichspreiseinheit de-DE | AG1: refxvergleichspreiseinheit fr-FR | AH1: refxvergleichspreiseinheit it-IT | AI1: refxtaxclass de-DE | AJ1: refxtaxclass fr-FR | AK1: refxtaxclass it-IT | AL1: refxaltersbegrtyp de-DE | AM1: refxaltersbegrtyp fr-FR | AN1: refxaltersbegrtyp it-IT | AO1: refxshopinshop | AP1: refxgtintyperegioartikel | AQ1: refxsystemsap
A2: SLPM Struktur>>3 Getränke>>30 Getränke>>3025 Tafelgetränke>>30251010 Säfte gekühlt | B2: Warengruppe>>Getränke>>Tafelgetränke>>Säfte gekühlt | C2: SLPM Struktur>>3 Getränke>>30 Getränke>>3025 Tafelgetränke>>30251010 Säfte gekühlt | D2: Ja | E2: Groupe de produits>>Boissons>>Boissons de table>>Jus de fruits réfrigérés | F2: Dummy for Attribute Filtering | G2: Nein | H2: SLPM Struktur>>3 Getränke>>30 Getränke>>3025 Tafelgetränke>>30251010 Säfte gekühlt | I2: 00 - Einzelartikel | J2: 00 - Einzelartikel | K2: Dummy for Attribute Filtering | L2: Nein | M2: Nein | N2: Ja | O2: Gruppo di prodotti>>Bevande>>Bevande da tavola>>Succhi refrigerati | P2: 00 - Einzelartikel | Q2: Ja | R2: Dummy for Attribute Filtering | S2: exartikel | T2: 00 - Einzelartikel | U2: Ja | V2: Ja | W2: ZAUS - Display In/Out Artikel | X2: ZAUS - Display In/Out Artikel | Y2: ZAUS - Display In/Out Artikel | Z2: In/Out | AA2: In/Out | AB2: In/Out | AC2: Centiliter | AD2: Caisse | AE2: Borsa | AF2: 1 | AG2: [DELETE] | AH2: [DELETE] | AI2: 0 - Ohne MWST | AJ2: 0 - Sans TVA | AK2: 0 - Senza IVA | AL2: Alcopops | AM2: Alcopop | AN2: Alcolpop | AO2: Denner Partner | AP2: GTIN | AQ2: S4H
T3: 12 - Display | U3: Nein | V3: Nein | W3: ZEGS - Externe Gutscheine | X3: ZHAW - Handelsware ohne Charge | Y3: ZHAW - Handelsware ohne Charge | Z3: Permanent | AA3: Permanent | AB3: Permanent | AC3: Each | AD3: Centilitre | AE3: Cassa | AF3: 10 | AG3: [NULL] | AH3: [NULL] | AI3: 1 - Normalsatz | AJ3: 1 - Taux normal | AK3: 1 - Tariffa standard | AL3: Bier | AM3: Aucune | AN3: Birra | AO3: Postartikel | AP3: _EMPTY | AQ3: S4HP
T4: [DELETE] | U4: [DELETE] | V4: [DELETE] | W4: ZHAW - Handelsware ohne Charge | X4: ZWEI - Wein mit Charge | Y4: ZWEI - Wein mit Charge | Z4: Saison | AA4: Saison | AB4: Saison | AC4: Gramm | AD4: Chaque | AE4: Centilitro | AF4: 100 | AI4: 3 - Reduzierter Satz | AJ4: 3 - Taux réduit | AK4: 3 - Tariffa ridotta | AL4: Keine | AM4: Bière | AN4: Nessuna | AO4: [DELETE] | AP4: [DELETE] | AQ4: [DELETE]
T5: [NULL] | U5: [NULL] | V5: [NULL] | W5: ZHIB - Hilfs-/Betriebsstoffe aus VZ | X5: [DELETE] | Y5: [DELETE] | Z5: Saison/Promo | AA5: Saison/Promo | AB5: Saison/Promo | AC5: Kilogramm | AD5: Gramme | AE5: Chilogrammo | AF5: [DELETE] | AI5: [DELETE] | AJ5: [DELETE] | AK5: [DELETE] | AL5: Rauchwaren | AM5: Spiriteux | AN5: Superalcolici | AO5: [NULL] | AP5: [NULL] | AQ5: [NULL]
W6: ZIGS - Denner Gutschein | X6: [NULL] | Y6: [NULL] | Z6: [DELETE] | AA6: [DELETE] | AB6: [DELETE] | AC6: Kiste | AD6: Kilogramme | AE6: Confezione | AF6: [NULL] | AI6: [NULL] | AJ6: [NULL] | AK6: [NULL] | AL6: Spirituosen | AM6: Tabac | AN6: Tabacchi
W7: ZLEE - Leergut | Z7: [NULL] | AA7: [NULL] | AB7: [NULL] | AC7: Liter | AD7: Litre | AE7: Each | AL7: Wein | AM7: Vin | AN7: Vino
W8: ZLOS - Lose | AC8: Milliliter | AD8: Millilitre | AE8: Grammo | AL8: [DELETE] | AM8: [DELETE] | AN8: [DELETE]
W9: ZRWE - Wein in Tanks | AC9: Pack | AD9: Paquet | AE9: Litro | AL9: [NULL] | AM9: [NULL] | AN9: [NULL]
W10: ZVBR - Verbrauchsmat. aus Antalis | AC10: Rolle | AD10: Pièce | AE10: Millilitro
W11: ZVOL - Vollgut | AC11: Stück | AD11: Rouleau | AE11: Pezzo
W12: ZWEI - Wein mit Charge | AC12: Tüte | AD12: Sachet | AE12: Rotolo
W13: [DELETE] | AC13: [DELETE] | AD13: [DELETE] | AE13: [DELETE]
W14: [NULL] | AC14: [NULL] | AD14: [NULL] | AE14: [NULL]

Sheet dedea_axba2387
A1: ZIGS - Denner Gutschein | B1: ZWEI - Wein mit Charge | C1: [EMPTY] | D1: ZVOL - Vollgut | E1: ZAUS - Display In/Out Artikel | F1: ZLEE - Leergut | G1: ZEGS - Externe Gutscheine | H1: ZHAW - Handelsware ohne Charge | I1: ZRWE - Wein in Tanks | J1: ZHIB - Hilfs-/Betriebsstoffe aus VZ | K1: ZLOS - Lose
A2: (KGM) KG | B2: (PCE) Stück | C2: (KGM) KG | D2: (KGM) KG | E2: (KGM) KG | F2: (KGM) KG | G2: (KGM) KG | H2: (KGM) KG | I2: (LTR) Liter | J2: (KGM) KG | K2: (KGM) KG
A3: (PCE) Stück | B3: [DELETE] | C3: (LTR) Liter | D3: (PCE) Stück | E3: (PCE) Stück | F3: (PCE) Stück | G3: (PCE) Stück | H3: (PCE) Stück | I3: [DELETE] | J3: (PCE) Stück | K3: (PCE) Stück
A4: [DELETE] | B4: [NULL] | C4: (PCE) Stück | D4: [DELETE] | E4: [DELETE] | F4: [DELETE] | G4: [DELETE] | H4: [DELETE] | I4: [NULL] | J4: [DELETE] | K4: [DELETE]
A5: [NULL] | C5: [DELETE] | D5: [NULL] | E5: [NULL] | F5: [NULL] | G5: [NULL] | H5: [NULL] | J5: [NULL] | K5: [NULL]
C6: [NULL]

Sheet frfra_axba1516
A1: ZWEI - Wein mit Charge | B1: [EMPTY] | C1: ZAUS - Display In/Out Artikel | D1: ZHAW - Handelsware ohne Charge
A2: (PCE) Pièce | B2: (KGM) kg | C2: (KGM) kg | D2: (KGM) kg
A3: [DELETE] | B3: (L) Litre | C3: (PCE) Pièce | D3: (PCE) Pièce
A4: [NULL] | B4: (PCE) Pièce | C4: [DELETE] | D4: [DELETE]
B5: [DELETE] | C5: [NULL] | D5: [NULL]
B6: [NULL]

Sheet itita_axba3948
A1: ZWEI - Wein mit Charge | B1: [EMPTY] | C1: ZAUS - Display In/Out Artikel | D1: ZHAW - Handelsware ohne Charge
A2: (PCE) Pezzo | B2: (KGM) KG | C2: (KGM) KG | D2: (KGM) KG
A3: [DELETE] | B3: (L) Litro | C3: (PCE) Pezzo | D3: (PCE) Pezzo
A4: [NULL] | B4: (PCE) Pezzo | C4: [DELETE] | D4: [DELETE]
B5: [DELETE] | C5: [NULL] | D5: [NULL]
B6: [NULL]
